Workbook

Sheet Dashboard (2)
A1: ISZE — FY2027 GPS Extended Target | K1: GPS stretch FY27 (pt) | N1: 0.018 | O1: Cap at 100%? YES/NO | Q1: NO | R1: Price FY28-31 / yr | T1: 0.03 | V1: Blue / yellow = input. Q1 = NO: the same stretch for every distributor. Q1 = YES: stretch capped so no GPS share passes 100%.
A2: ISZE to distributor level. Stretch inputs on Dashboard (2) row 1. Every number on this sheet is live. | K2: GPS stretch FY28-31 / yr (pt) | N2: 0.01 | V2: FY27 stretch must stay >= ~1.1% to cover the EUR 952K the waterfall needs (Dashboard C25).
K3: 2025年度 | L3: FY2026 | Q3: 販社 = distributor sales to its dealers. Amounts only: KPI sales-to-dealer run 2.2-3.7x ISZE billing, so a share would read above 100%. | U3: 2026年度 | V3: FY2027 | AE3: 2027年度 | AF3: FY2028 | AO3: 2028年度 | AP3: FY2029 | AY3: 2029年度 | AZ3: FY2030 | BI3: 2030年度 | BJ3: FY2031
A4: DB | B4: Segment | C4: BP FY27 | D4: Max spend | E4: GPS % | F4: Stretch% | G4: Stretch EUR | H4: New GPS | I4: EXT TARGET | J4: Note | K4: ISZE台当たり単価 | M4: UIO | N4: ISZE部品販売 ポテンシャル | O4: ISZE部品売上実績 | P4: ISZE部品カバー率 (実績) | Q4: 販社台当たり単価 | R4: 販社部品販売ポテンシャル | S4: 販社部品販売 (実績) | T4: 販社部品カバー率 (実績) | U4: ISZE台当たり単価 | W4: UIO | X4: ISZE 部品販売 ポテンシャル | Y4: ISZE 部品カバー率 (目標) | Z4: ISZE部品売上目標 | AA4: 販社台当たり単価 | AB4: 販社部品販売ポテンシャル | AC4: 販社部品販売目標 | AD4: 販社部品カバー率(目標) | AE4: ISZE台当たり単価 | AG4: UIO | AH4: ISZE 部品販売 ポテンシャル | AI4: ISZE 部品カバー率 (目標) | AJ4: ISZE部品売上目標 | AK4: 販社台当たり単価 | AL4: 販社部品販売ポテンシャル | AM4: 販社部品販売目標 | AN4: 販社部品カバー率(目標) | AO4: ISZE台当たり単価 | AQ4: UIO | AR4: ISZE 部品販売 ポテンシャル | AS4: ISZE 部品カバー率 (目標) | AT4: ISZE部品売上目標 | AU4: 販社台当たり単価 | AV4: 販社部品販売ポテンシャル | AW4: 販社部品販売目標 | AX4: 販社部品カバー率(目標) | AY4: ISZE台当たり単価 | BA4: UIO | BB4: ISZE 部品販売 ポテンシャル | BC4: ISZE 部品カバー率 (目標) | BD4: ISZE部品売上目標 | BE4: 販社台当たり単価 | BF4: 販社部品販売ポテンシャル | BG4: 販社部品販売目標 | BH4: 販社部品カバー率(目標) | BI4: ISZE台当たり単価 | BK4: UIO | BL4: ISZE 部品販売 ポテンシャル | BM4: ISZE 部品カバー率 (目標) | BN4: ISZE部品売上目標 | BO4: 販社台当たり単価 | BP4: 販社部品販売ポテンシャル | BQ4: 販社部品販売目標 | BR4: 販社部品カバー率(目標)
K5: ISZE Parts Sales per Unit | N5: ISZE Parts Sles Potential | O5: ISZE Parts Sales Actual | P5: ISZE Share Actual | Q5: Distributor's Parts Sales per Unit | R5: Distributor's Parts Sales Potential | S5: Distributor Parts Sales Actual | T5: Dist Parts Share Actual | U5: ISZE Parts Sales per Unit | X5: ISZE Parts Sles Potential | Y5: ISZE Target Share | Z5: ISZE Parts Sales Target | AA5: Distributor's Parts Sales per Unit | AB5: Distributor's Parts Sales Potential | AC5: Distributor Parts Sales Target | AD5: Distributor Parts Share target | AE5: ISZE Parts Sales per Unit | AH5: ISZE Parts Sles Potential | AI5: ISZE Target Share | AJ5: ISZE Parts Sales Target | AK5: Distributor's Parts Sales per Unit | AL5: Distributor's Parts Sales Potential | AM5: Distributor Parts Sales Target | AN5: Distributor Parts Share target | AO5: ISZE Parts Sales per Unit | AR5: ISZE Parts Sles Potential | AS5: ISZE Target Share | AT5: ISZE Parts Sales Target | AU5: Distributor's Parts Sales per Unit | AV5: Distributor's Parts Sales Potential | AW5: Distributor Parts Sales Target | AX5: Distributor Parts Share target | AY5: ISZE Parts Sales per Unit | BB5: ISZE Parts Sles Potential | BC5: ISZE Target Share | BD5: ISZE Parts Sales Target | BE5: Distributor's Parts Sales per Unit | BF5: Distributor's Parts Sales Potential | BG5: Distributor Parts Sales Target | BH5: Distributor Parts Share target | BI5: ISZE Parts Sales per Unit | BL5: ISZE Parts Sles Potential | BM5: ISZE Target Share | BN5: ISZE Parts Sales Target | BO5: Distributor's Parts Sales per Unit | BP5: Distributor's Parts Sales Potential | BQ5: Distributor Parts Sales Target | BR5: Distributor Parts Share target
A6: ITUK | B6: presented | C6: =Dashboard!C5 -> 6974170.1 | D6: =Dashboard!D5 -> 12535797 | E6: =Dashboard!E5 -> 0.55634037 | F6: =Dashboard!F5 -> 0 | G6: =Dashboard!G5 -> 376073.91 | H6: =Dashboard!H5 -> 0 | I6: =Dashboard!I5 -> 7350244 | J6: Max spend on IML data (2026 vehicles, +5%); target as presented in July | K6: N35 | L6: 281.6 | M6: 11444 | N6: =L6*M6 -> 3222630.4 | Q6: =Inputs!$C$13 -> 448 | R6: =Q6*M6 -> 5126912 | U6: N35 | V6: =L6*(1+Inputs!$B$9) -> 295.68 | W6: 12345 | X6: =V6*W6 -> 3650169.6 | AA6: =Q6*(1+Inputs!$B$11) -> 461.44 | AB6: =AA6*W6 -> 5696476.8 | AE6: N35 | AF6: =V6*(1+'Dashboard (2)'!$T$1) -> 304.5504 | AG6: =ROUND(Inputs!E26*($W$6/($W$6+$W$7)),0) -> 12944 | AH6: =AF6*AG6 -> 3942100.4 | AK6: =AA6*(1+'Dashboard (2)'!$T$1) -> 475.2832 | AL6: =AK6*AG6 -> 6152065.7 | AO6: N35 | AP6: =AF6*(1+'Dashboard (2)'!$T$1) -> 313.68691 | AQ6: =ROUND(Inputs!F26*($W$6/($W$6+$W$7)),0) -> 13453 | AR6: =AP6*AQ6 -> 4220030 | AU6: =AK6*(1+'Dashboard (2)'!$T$1) -> 489.5417 | AV6: =AU6*AQ6 -> 6585804.4 | AY6: N35 | AZ6: =AP6*(1+'Dashboard (2)'!$T$1) -> 323.09752 | BA6: =ROUND(Inputs!G26*($W$6/($W$6+$W$7)),0) -> 13907 | BB6: =AZ6*BA6 -> 4493317.2 | BE6: =AU6*(1+'Dashboard (2)'!$T$1) -> 504.22795 | BF6: =BE6*BA6 -> 7012298.1 | BI6: N35 | BJ6: =AZ6*(1+'Dashboard (2)'!$T$1) -> 332.79044 | BK6: =ROUND(Inputs!H26*($W$6/($W$6+$W$7)),0) -> 14320 | BL6: =BJ6*BK6 -> 4765559.2 | BO6: =BE6*(1+'Dashboard (2)'!$T$1) -> 519.35479 | BP6: =BO6*BK6 -> 7437160.5
K7: N75 | L7: 704 | M7: 10747 | N7: =L7*M7 -> 7565888 | Q7: =Inputs!$C$14 -> 1120 | R7: =Q7*M7 -> 12036640 | U7: N75 | V7: =L7*(1+Inputs!$B$9) -> 739.2 | W7: 10865 | X7: =V7*W7 -> 8031408 | AA7: =Q7*(1+Inputs!$B$11) -> 1153.6 | AB7: =AA7*W7 -> 12533864 | AE7: N75 | AF7: =V7*(1+'Dashboard (2)'!$T$1) -> 761.376 | AG7: =Inputs!E26-AG6 -> 11392 | AH7: =AF7*AG7 -> 8673595.4 | AK7: =AA7*(1+'Dashboard (2)'!$T$1) -> 1188.208 | AL7: =AK7*AG7 -> 13536066 | AO7: N75 | AP7: =AF7*(1+'Dashboard (2)'!$T$1) -> 784.21728 | AQ7: =Inputs!F26-AQ6 -> 11841 | AR7: =AP7*AQ7 -> 9285916.8 | AU7: =AK7*(1+'Dashboard (2)'!$T$1) -> 1223.8542 | AV7: =AU7*AQ7 -> 14491658 | AY7: N75 | AZ7: =AP7*(1+'Dashboard (2)'!$T$1) -> 807.7438 | BA7: =Inputs!G26-BA6 -> 12239 | BB7: =AZ7*BA7 -> 9885976.3 | BE7: =AU7*(1+'Dashboard (2)'!$T$1) -> 1260.5699 | BF7: =BE7*BA7 -> 15428115 | BI7: N75 | BJ7: =AZ7*(1+'Dashboard (2)'!$T$1) -> 831.97611 | BK7: =Inputs!H26-BK6 -> 12603 | BL7: =BJ7*BK7 -> 10485395 | BO7: =BE7*(1+'Dashboard (2)'!$T$1) -> 1298.387 | BP7: =BO7*BK7 -> 16363571
K8: F | L8: 844.8 | M8: 877 | N8: =L8*M8 -> 740889.6 | Q8: =Inputs!$C$15 -> 1344 | R8: =Q8*M8 -> 1178688 | U8: F | V8: =L8*(1+Inputs!$B$9) -> 887.04 | W8: 963 | X8: =V8*W8 -> 854219.52 | AA8: =Q8*(1+Inputs!$B$11) -> 1384.32 | AB8: =AA8*W8 -> 1333100.2 | AE8: F | AF8: =V8*(1+'Dashboard (2)'!$T$1) -> 913.6512 | AG8: =Inputs!E27 -> 1055 | AH8: =AF8*AG8 -> 963902.02 | AK8: =AA8*(1+'Dashboard (2)'!$T$1) -> 1425.8496 | AL8: =AK8*AG8 -> 1504271.3 | AO8: F | AP8: =AF8*(1+'Dashboard (2)'!$T$1) -> 941.06074 | AQ8: =Inputs!F27 -> 1141 | AR8: =AP8*AQ8 -> 1073750.3 | AU8: =AK8*(1+'Dashboard (2)'!$T$1) -> 1468.6251 | AV8: =AU8*AQ8 -> 1675701.2 | AY8: F | AZ8: =AP8*(1+'Dashboard (2)'!$T$1) -> 969.29256 | BA8: =Inputs!G27 -> 1218 | BB8: =AZ8*BA8 -> 1180598.3 | BE8: =AU8*(1+'Dashboard (2)'!$T$1) -> 1512.6838 | BF8: =BE8*BA8 -> 1842448.9 | BI8: F | BJ8: =AZ8*(1+'Dashboard (2)'!$T$1) -> 998.37133 | BK8: =Inputs!H27 -> 1286 | BL8: =BJ8*BK8 -> 1283905.5 | BO8: =BE8*(1+'Dashboard (2)'!$T$1) -> 1558.0644 | BP8: =BO8*BK8 -> 2003670.8
M9: =SUM(M6:M8) -> 23068 | N9: =SUM(N6:N8) -> 11529408 | O9: 6805719.6 | P9: =O9/N9 -> 0.5902922 | R9: =SUM(R6:R8) -> 18342240 | S9: =Inputs!$B$34*Inputs!$B$16 -> 14418877 | T9: =S9/R9 -> 0.78610232 | W9: =SUM(W6:W8) -> 24173 | X9: =SUM(X6:X8) -> 12535797 | Y9: =Z9/X9 -> 0.58634037 | Z9: =Dashboard!I5 -> 7350244 | AB9: =SUM(AB6:AB8) -> 19563441 | AC9: =AB9*AD9 -> 15731008 | AD9: =IF(T9>=Inputs!$B$38,T9,MIN(T9+'Dashboard (2)'!$N$1,Inputs!$B$38)) -> 0.80410232 | AG9: =SUM(AG6:AG8) -> 25391 | AH9: =SUM(AH6:AH8) -> 13579598 | AI9: =IF(Y9>=Inputs!$B$38,Y9,MIN(Y9+'Dashboard (2)'!$N$2,Inputs!$B$38)) -> 0.59634037 | AJ9: =AH9*AI9 -> 8098062.4 | AL9: =SUM(AL6:AL8) -> 21192403 | AM9: =AL9*AN9 -> 17252784 | AN9: =IF(AD9>=Inputs!$B$38,AD9,MIN(AD9+'Dashboard (2)'!$N$2,Inputs!$B$38)) -> 0.81410232 | AQ9: =SUM(AQ6:AQ8) -> 26435 | AR9: =SUM(AR6:AR8) -> 14579697 | AS9: =IF(AI9>=Inputs!$B$38,AI9,MIN(AI9+'Dashboard (2)'!$N$2,Inputs!$B$38)) -> 0.60634037 | AT9: =AR9*AS9 -> 8840259 | AV9: =SUM(AV6:AV8) -> 22753164 | AW9: =AV9*AX9 -> 18750935 | AX9: =IF(AN9>=Inputs!$B$38,AN9,MIN(AN9+'Dashboard (2)'!$N$2,Inputs!$B$38)) -> 0.82410232 | BA9: =SUM(BA6:BA8) -> 27364 | BB9: =SUM(BB6:BB8) -> 15559892 | BC9: =IF(AS9>=Inputs!$B$38,AS9,MIN(AS9+'Dashboard (2)'!$N$2,Inputs!$B$38)) -> 0.61634037 | BD9: =BB9*BC9 -> 9590189.6 | BF9: =SUM(BF6:BF8) -> 24282862 | BG9: =BF9*BH9 -> 20254391 | BH9: =IF(AX9>=Inputs!$B$38,AX9,MIN(AX9+'Dashboard (2)'!$N$2,Inputs!$B$38)) -> 0.83410232 | BK9: =SUM(BK6:BK8) -> 28209 | BL9: =SUM(BL6:BL8) -> 16534860 | BM9: =IF(BC9>=Inputs!$B$38,BC9,MIN(BC9+'Dashboard (2)'!$N$2,Inputs!$B$38)) -> 0.62634037 | BN9: =BL9*BM9 -> 10356450 | BP9: =SUM(BP6:BP8) -> 25804402 | BQ9: =BP9*BR9 -> 21781556 | BR9: =IF(BH9>=Inputs!$B$38,BH9,MIN(BH9+'Dashboard (2)'!$N$2,Inputs!$B$38)) -> 0.84410232
A10: UTI | B10: presented | C10: =Dashboard!C6 -> 3098113.5 | D10: =Dashboard!D6 -> 8485129 | E10: =Dashboard!E6 -> 0.36512274 | F10: =Dashboard!F6 -> 0 | G10: =Dashboard!G6 -> 159024.46 | H10: =Dashboard!H6 -> 0 | I10: =Dashboard!I6 -> 3257138 | J10: Max spend on IML data (2026 vehicles, +5%); target as presented in July | K10: CV | L10: =V10/(1+Inputs!$B$9) -> 751.02929 | M10: 10336 | N10: =L10*M10 -> 7762638.8 | O10: 3056797.1 | P10: =O10/N10 -> 0.39378324 | Q10: =IFERROR(R10/(Inputs!C29+Inputs!C30),0) -> 1212.6904 | R10: =Inputs!$C$14*Inputs!C29+Inputs!$C$15*Inputs!C30 -> 12534368 | S10: =IF(ISNUMBER(Dashboard!Q6),Dashboard!Q6,"no KPI data") -> no KPI data | T10: n/a | U10: CV | V10: =X10/W10 -> 788.58076 | W10: 10760 | X10: 8485129 | Y10: =Z10/X10 -> 0.38386428 | Z10: =Dashboard!I6 -> 3257138 | AA10: =IFERROR(AB10/(Inputs!D29+Inputs!D30),0) -> 1277.8399 | AB10: =Inputs!$C$14*(1+Inputs!$B$9)*Inputs!D29+Inputs!$C$15*(1+Inputs!$B$9)*Inputs!D30 -> 13749557 | AC10: =IF(ISNUMBER(S10),S10+Dashboard!G6/(1-Inputs!$B$18),"no KPI data") -> no KPI data | AD10: n/a | AE10: CV | AF10: =V10*(1+'Dashboard (2)'!$T$1) -> 812.23818 | AG10: =Inputs!E29+Inputs!E30 -> 10972 | AH10: =AF10*AG10 -> 8911877.3 | AI10: =IF(Y10>=Inputs!$B$38,Y10,MIN(Y10+'Dashboard (2)'!$N$2,Inputs!$B$38)) -> 0.39386428 | AJ10: =AH10*AI10 -> 3510070.2 | AK10: =IFERROR(AL10/(Inputs!E29+Inputs!E30),0) -> 1319.6461 | AL10: =Inputs!$C$14*(1+Inputs!$B$9)*(1+'Dashboard (2)'!$T$1)*Inputs!E29+Inputs!$C$15*(1+Inputs!$B$9)*(1+'Dashboard (2)'!$T$1)*Inputs!E30 -> 14479157 | AM10: =IF(ISNUMBER(AC10),AC10*AJ10/Z10,"no KPI data") -> no KPI data | AN10: n/a | AO10: CV | AP10: =AF10*(1+'Dashboard (2)'!$T$1) -> 836.60533 | AQ10: =Inputs!F29+Inputs!F30 -> 11280 | AR10: =AP10*AQ10 -> 9436908.1 | AS10: =IF(AI10>=Inputs!$B$38,AI10,MIN(AI10+'Dashboard (2)'!$N$2,Inputs!$B$38)) -> 0.40386428 | AT10: =AR10*AS10 -> 3811230.1 | AU10: =IFERROR(AV10/(Inputs!F29+Inputs!F30),0) -> 1362.3595 | AV10: =Inputs!$C$14*(1+Inputs!$B$9)*(1+'Dashboard (2)'!$T$1)*(1+'Dashboard (2)'!$T$1)*Inputs!F29+Inputs!$C$15*(1+Inputs!$B$9)*(1+'Dashboard (2)'!$T$1)*(1+'Dashboard (2)'!$T$1)*Inputs!F30 -> 15367415 | AW10: =IF(ISNUMBER(AM10),AM10*AT10/AJ10,"no KPI data") -> no KPI data | AX10: n/a | AY10: CV | AZ10: =AP10*(1+'Dashboard (2)'!$T$1) -> 861.70349 | BA10: =Inputs!G29+Inputs!G30 -> 11581 | BB10: =AZ10*BA10 -> 9979388.1 | BC10: =IF(AS10>=Inputs!$B$38,AS10,MIN(AS10+'Dashboard (2)'!$N$2,Inputs!$B$38)) -> 0.41386428 | BD10: =BB10*BC10 -> 4130112.3 | BE10: =IFERROR(BF10/(Inputs!G29+Inputs!G30),0) -> 1406.4612 | BF10: =Inputs!$C$14*(1+Inputs!$B$9)*(1+'Dashboard (2)'!$T$1)*(1+'Dashboard (2)'!$T$1)*(1+'Dashboard (2)'!$T$1)*Inputs!G29+Inputs!$C$15*(1+Inputs!$B$9)*(1+'Dashboard (2)'!$T$1)*(1+'Dashboard (2)'!$T$1)*(1+'Dashboard (2)'!$T$1)*Inputs!G30 -> 16288227 | BG10: =IF(ISNUMBER(AW10),AW10*BD10/AT10,"no KPI data") -> no KPI data | BH10: n/a | BI10: CV | BJ10: =AZ10*(1+'Dashboard (2)'!$T$1) -> 887.55459 | BK10: =Inputs!H29+Inputs!H30 -> 11882 | BL10: =BJ10*BK10 -> 10545924 | BM10: =IF(BC10>=Inputs!$B$38,BC10,MIN(BC10+'Dashboard (2)'!$N$2,Inputs!$B$38)) -> 0.42386428 | BN10: =BL10*BM10 -> 4470040.4 | BO10: =IFERROR(BP10/(Inputs!H29+Inputs!H30),0) -> 1451.8811 | BP10: =Inputs!$C$14*(1+Inputs!$B$9)*(1+'Dashboard (2)'!$T$1)*(1+'Dashboard (2)'!$T$1)*(1+'Dashboard (2)'!$T$1)*(1+'Dashboard (2)'!$T$1)*Inputs!H29+Inputs!$C$15*(1+Inputs!$B$9)*(1+'Dashboard (2)'!$T$1)*(1+'Dashboard (2)'!$T$1)*(1+'Dashboard (2)'!$T$1)*(1+'Dashboard (2)'!$T$1)*Inputs!H30 -> 17251252 | BQ10: =IF(ISNUMBER(BG10),BG10*BN10/BD10,"no KPI data") -> no KPI data | BR10: n/a
A11: IUK | B11: LCV | C11: =Dashboard!C7 -> 6062956.5 | D11: =Dashboard!D7 -> 12936000 | E11: =Dashboard!E7 -> 0.46868866 | F11: =Dashboard!F7 -> 0.018 | G11: =Dashboard!G7 -> 232848 | H11: =Dashboard!H7 -> 0.48668866 | I11: =Dashboard!I7 -> 6295804.5 | K11: LCV | L11: =IUK!D14 -> 250 | M11: =IUK!D9 -> 47783 | N11: =L11*M11 -> 11945750 | O11: =IUK!D20 -> 5895486.2 | P11: =O11/N11 -> 0.49352165 | Q11: =Inputs!$C$13 -> 448 | R11: =Q11*M11 -> 21406784 | S11: =IF(ISNUMBER(Dashboard!Q7),Dashboard!Q7,"no KPI data") -> 21418279 | T11: n/a | U11: LCV | V11: =IUK!E14 -> 262.5 | W11: =IUK!E9 -> 49280 | X11: =V11*W11 -> 12936000 | Y11: =Z11/X11 -> 0.48668866 | Z11: =IUK!E24 -> 6295804.5 | AA11: =Inputs!$C$13*(1+Inputs!$B$9) -> 470.4 | AB11: =AA11*W11 -> 23181312 | AC11: =IF(ISNUMBER(S11),S11+Dashboard!G7/(1-Inputs!$B$18),"no KPI data") -> 21776507 | AD11: n/a | AE11: LCV | AF11: =IUK!F14 -> 270.375 | AG11: =IUK!F9 -> 50202 | AH11: =AF11*AG11 -> 13573366 | AI11: =IF(Y11>=Inputs!$B$38,Y11,MIN(Y11+'Dashboard (2)'!$N$2,Inputs!$B$38)) -> 0.49668866 | AJ11: =AH11*AI11 -> 6741736.8 | AK11: =Inputs!$C$13*(1+Inputs!$B$9)*(1+'Dashboard (2)'!$T$1) -> 484.512 | AL11: =AK11*AG11 -> 24323471 | AM11: =IF(ISNUMBER(AC11),AC11*AJ11/Z11,"no KPI data") -> 23318938 | AN11: n/a | AO11: LCV | AP11: =IUK!G14 -> 278.48625 | AQ11: =IUK!G9 -> 51096 | AR11: =AP11*AQ11 -> 14229533 | AS11: =IF(AI11>=Inputs!$B$38,AI11,MIN(AI11+'Dashboard (2)'!$N$2,Inputs!$B$38)) -> 0.50668866 | AT11: =AR11*AS11 -> 7209943.2 | AU11: =Inputs!$C$13*(1+Inputs!$B$9)*(1+'Dashboard (2)'!$T$1)*(1+'Dashboard (2)'!$T$1) -> 499.04736 | AV11: =AU11*AQ11 -> 25499324 | AW11: =IF(ISNUMBER(AM11),AM11*AT11/AJ11,"no KPI data") -> 24938414 | AX11: n/a | AY11: LCV | AZ11: =IUK!H14 -> 286.84084 | BA11: =IUK!H9 -> 51963 | BB11: =AZ11*BA11 -> 14905110 | BC11: =IF(AS11>=Inputs!$B$38,AS11,MIN(AS11+'Dashboard (2)'!$N$2,Inputs!$B$38)) -> 0.51668866 | BD11: =BB11*BC11 -> 7701301.5 | BE11: =Inputs!$C$13*(1+Inputs!$B$9)*(1+'Dashboard (2)'!$T$1)*(1+'Dashboard (2)'!$T$1)*(1+'Dashboard (2)'!$T$1) -> 514.01878 | BF11: =BE11*BA11 -> 26709958 | BG11: =IF(ISNUMBER(AW11),AW11*BD11/AT11,"no KPI data") -> 26637969 | BH11: n/a | BI11: LCV | BJ11: =IUK!I14 -> 295.44606 | BK11: =IUK!I9 -> 52804 | BL11: =BJ11*BK11 -> 15600734 | BM11: =IF(BC11>=Inputs!$B$38,BC11,MIN(BC11+'Dashboard (2)'!$N$2,Inputs!$B$38)) -> 0.52668866 | BN11: =BL11*BM11 -> 8216729.6 | BO11: =Inputs!$C$13*(1+Inputs!$B$9)*(1+'Dashboard (2)'!$T$1)*(1+'Dashboard (2)'!$T$1)*(1+'Dashboard (2)'!$T$1)*(1+'Dashboard (2)'!$T$1) -> 529.43934 | BP11: =BO11*BK11 -> 27956515 | BQ11: =IF(ISNUMBER(BG11),BG11*BN11/BD11,"no KPI data") -> 28420779 | BR11: n/a
A12: UMI | B12: LCV | C12: =Dashboard!C8 -> 2973279.3 | D12: =Dashboard!D8 -> 4957575 | E12: =Dashboard!E8 -> 0.5997447 | F12: =Dashboard!F8 -> 0.018 | G12: =Dashboard!G8 -> 89236.35 | H12: =Dashboard!H8 -> 0.6177447 | I12: =Dashboard!I8 -> 3062515.7 | K12: LCV | L12: =UMI!D14 -> 250 | M12: =UMI!D9 -> 18542 | N12: =L12*M12 -> 4635500 | O12: =UMI!D20 -> 2445335.2 | P12: =O12/N12 -> 0.52752351 | Q12: =Inputs!$C$13 -> 448 | R12: =Q12*M12 -> 8306816 | S12: =IF(ISNUMBER(Dashboard!Q8),Dashboard!Q8,"no KPI data") -> no KPI data | T12: n/a | U12: LCV | V12: =UMI!E14 -> 262.5 | W12: =UMI!E9 -> 18886 | X12: =V12*W12 -> 4957575 | Y12: =Z12/X12 -> 0.6177447 | Z12: =UMI!E24 -> 3062515.7 | AA12: =Inputs!$C$13*(1+Inputs!$B$9) -> 470.4 | AB12: =AA12*W12 -> 8883974.4 | AC12: =IF(ISNUMBER(S12),S12+Dashboard!G8/(1-Inputs!$B$18),"no KPI data") -> no KPI data | AD12: n/a | AE12: LCV | AF12: =UMI!F14 -> 270.375 | AG12: =UMI!F9 -> 19319 | AH12: =AF12*AG12 -> 5223374.6 | AI12: =IF(Y12>=Inputs!$B$38,Y12,MIN(Y12+'Dashboard (2)'!$N$2,Inputs!$B$38)) -> 0.6277447 | AJ12: =AH12*AI12 -> 3278945.7 | AK12: =Inputs!$C$13*(1+Inputs!$B$9)*(1+'Dashboard (2)'!$T$1) -> 484.512 | AL12: =AK12*AG12 -> 9360287.3 | AM12: =IF(ISNUMBER(AC12),AC12*AJ12/Z12,"no KPI data") -> no KPI data | AN12: n/a | AO12: LCV | AP12: =UMI!G14 -> 278.48625 | AQ12: =UMI!G9 -> 19669 | AR12: =AP12*AQ12 -> 5477546.1 | AS12: =IF(AI12>=Inputs!$B$38,AI12,MIN(AI12+'Dashboard (2)'!$N$2,Inputs!$B$38)) -> 0.6377447 | AT12: =AR12*AS12 -> 3493276 | AU12: =Inputs!$C$13*(1+Inputs!$B$9)*(1+'Dashboard (2)'!$T$1)*(1+'Dashboard (2)'!$T$1) -> 499.04736 | AV12: =AU12*AQ12 -> 9815762.5 | AW12: =IF(ISNUMBER(AM12),AM12*AT12/AJ12,"no KPI data") -> no KPI data | AX12: n/a | AY12: LCV | AZ12: =UMI!H14 -> 286.84084 | BA12: =UMI!H9 -> 20009 | BB12: =AZ12*BA12 -> 5739398.3 | BC12: =IF(AS12>=Inputs!$B$38,AS12,MIN(AS12+'Dashboard (2)'!$N$2,Inputs!$B$38)) -> 0.6477447 | BD12: =BB12*BC12 -> 3717664.8 | BE12: =Inputs!$C$13*(1+Inputs!$B$9)*(1+'Dashboard (2)'!$T$1)*(1+'Dashboard (2)'!$T$1)*(1+'Dashboard (2)'!$T$1) -> 514.01878 | BF12: =BE12*BA12 -> 10285002 | BG12: =IF(ISNUMBER(AW12),AW12*BD12/AT12,"no KPI data") -> no KPI data | BH12: n/a | BI12: LCV | BJ12: =UMI!I14 -> 295.44606 | BK12: =UMI!I9 -> 20339 | BL12: =BJ12*BK12 -> 6009077.5 | BM12: =IF(BC12>=Inputs!$B$38,BC12,MIN(BC12+'Dashboard (2)'!$N$2,Inputs!$B$38)) -> 0.6577447 | BN12: =BL12*BM12 -> 3952438.9 | BO12: =Inputs!$C$13*(1+Inputs!$B$9)*(1+'Dashboard (2)'!$T$1)*(1+'Dashboard (2)'!$T$1)*(1+'Dashboard (2)'!$T$1)*(1+'Dashboard (2)'!$T$1) -> 529.43934 | BP12: =BO12*BK12 -> 10768267 | BQ12: =IF(ISNUMBER(BG12),BG12*BN12/BD12,"no KPI data") -> no KPI data | BR12: n/a
A13: NORWAY | B13: LCV | C13: =Dashboard!C9 -> 1764799.8 | D13: =Dashboard!D9 -> 2129137.5 | E13: =Dashboard!E9 -> 0.82888012 | F13: =Dashboard!F9 -> 0.018 | G13: =Dashboard!G9 -> 38324.475 | H13: =Dashboard!H9 -> 0.84688012 | I13: =Dashboard!I9 -> 1803124.2 | K13: LCV | L13: =NORWAY!D14 -> 250 | M13: =NORWAY!D9 -> 7929 | N13: =L13*M13 -> 1982250 | O13: =NORWAY!D20 -> 1471434.2 | P13: =O13/N13 -> 0.74230506 | Q13: =Inputs!$C$13 -> 448 | R13: =Q13*M13 -> 3552192 | S13: =IF(ISNUMBER(Dashboard!Q9),Dashboard!Q9,"no KPI data") -> 5248795 | T13: n/a | U13: LCV | V13: =NORWAY!E14 -> 262.5 | W13: =NORWAY!E9 -> 8111 | X13: =V13*W13 -> 2129137.5 | Y13: =Z13/X13 -> 0.84688012 | Z13: =NORWAY!E24 -> 1803124.2 | AA13: =Inputs!$C$13*(1+Inputs!$B$9) -> 470.4 | AB13: =AA13*W13 -> 3815414.4 | AC13: =IF(ISNUMBER(S13),S13+Dashboard!G9/(1-Inputs!$B$18),"no KPI data") -> 5307755.7 | AD13: n/a | AE13: LCV | AF13: =NORWAY!F14 -> 270.375 | AG13: =NORWAY!F9 -> 8218 | AH13: =AF13*AG13 -> 2221941.8 | AI13: =IF(Y13>=Inputs!$B$38,Y13,MIN(Y13+'Dashboard (2)'!$N$2,Inputs!$B$38)) -> 0.85688012 | AJ13: =AH13*AI13 -> 1903937.7 | AK13: =Inputs!$C$13*(1+Inputs!$B$9)*(1+'Dashboard (2)'!$T$1) -> 484.512 | AL13: =AK13*AG13 -> 3981719.6 | AM13: =IF(ISNUMBER(AC13),AC13*AJ13/Z13,"no KPI data") -> 5604514.8 | AN13: n/a | AO13: LCV | AP13: =NORWAY!G14 -> 278.48625 | AQ13: =NORWAY!G9 -> 8426 | AR13: =AP13*AQ13 -> 2346525.1 | AS13: =IF(AI13>=Inputs!$B$38,AI13,MIN(AI13+'Dashboard (2)'!$N$2,Inputs!$B$38)) -> 0.86688012 | AT13: =AR13*AS13 -> 2034156 | AU13: =Inputs!$C$13*(1+Inputs!$B$9)*(1+'Dashboard (2)'!$T$1)*(1+'Dashboard (2)'!$T$1) -> 499.04736 | AV13: =AU13*AQ13 -> 4204973.1 | AW13: =IF(ISNUMBER(AM13),AM13*AT13/AJ13,"no KPI data") -> 5987831 | AX13: n/a | AY13: LCV | AZ13: =NORWAY!H14 -> 286.84084 | BA13: =NORWAY!H9 -> 8628 | BB13: =AZ13*BA13 -> 2474862.7 | BC13: =IF(AS13>=Inputs!$B$38,AS13,MIN(AS13+'Dashboard (2)'!$N$2,Inputs!$B$38)) -> 0.87688012 | BD13: =BB13*BC13 -> 2170157.9 | BE13: =Inputs!$C$13*(1+Inputs!$B$9)*(1+'Dashboard (2)'!$T$1)*(1+'Dashboard (2)'!$T$1)*(1+'Dashboard (2)'!$T$1) -> 514.01878 | BF13: =BE13*BA13 -> 4434954 | BG13: =IF(ISNUMBER(AW13),AW13*BD13/AT13,"no KPI data") -> 6388172.3 | BH13: n/a | BI13: LCV | BJ13: =NORWAY!I14 -> 295.44606 | BK13: =NORWAY!I9 -> 8824 | BL13: =BJ13*BK13 -> 2607016.1 | BM13: =IF(BC13>=Inputs!$B$38,BC13,MIN(BC13+'Dashboard (2)'!$N$2,Inputs!$B$38)) -> 0.88688012 | BN13: =BL13*BM13 -> 2312110.7 | BO13: =Inputs!$C$13*(1+Inputs!$B$9)*(1+'Dashboard (2)'!$T$1)*(1+'Dashboard (2)'!$T$1)*(1+'Dashboard (2)'!$T$1)*(1+'Dashboard (2)'!$T$1) -> 529.43934 | BP13: =BO13*BK13 -> 4671772.8 | BQ13: =IF(ISNUMBER(BG13),BG13*BN13/BD13,"no KPI data") -> 6806030.7 | BR13: n/a
A14: SWEDEN | B14: LCV | C14: =Dashboard!C10 -> 1464302.3 | D14: =Dashboard!D10 -> 2386125 | E14: =Dashboard!E10 -> 0.61367377 | F14: =Dashboard!F10 -> 0.018 | G14: =Dashboard!G10 -> 42950.25 | H14: =Dashboard!H10 -> 0.63167377 | I14: =Dashboard!I10 -> 1507252.6 | K14: LCV | L14: =SWEDEN!D14 -> 250 | M14: =SWEDEN!D9 -> 8443 | N14: =L14*M14 -> 2110750 | O14: =SWEDEN!D20 -> 1298276 | P14: =O14/N14 -> 0.61507805 | Q14: =Inputs!$C$13 -> 448 | R14: =Q14*M14 -> 3782464 | S14: =IF(ISNUMBER(Dashboard!Q10),Dashboard!Q10,"no KPI data") -> 3154222 | T14: n/a | U14: LCV | V14: =SWEDEN!E14 -> 262.5 | W14: =SWEDEN!E9 -> 9090 | X14: =V14*W14 -> 2386125 | Y14: =Z14/X14 -> 0.63167377 | Z14: =SWEDEN!E24 -> 1507252.6 | AA14: =Inputs!$C$13*(1+Inputs!$B$9) -> 470.4 | AB14: =AA14*W14 -> 4275936 | AC14: =IF(ISNUMBER(S14),S14+Dashboard!G10/(1-Inputs!$B$18),"no KPI data") -> 3220299.3 | AD14: n/a | AE14: LCV | AF14: =SWEDEN!F14 -> 270.375 | AG14: =SWEDEN!F9 -> 9737 | AH14: =AF14*AG14 -> 2632641.4 | AI14: =IF(Y14>=Inputs!$B$38,Y14,MIN(Y14+'Dashboard (2)'!$N$2,Inputs!$B$38)) -> 0.64167377 | AJ14: =AH14*AI14 -> 1689296.9 | AK14: =Inputs!$C$13*(1+Inputs!$B$9)*(1+'Dashboard (2)'!$T$1) -> 484.512 | AL14: =AK14*AG14 -> 4717693.3 | AM14: =IF(ISNUMBER(AC14),AC14*AJ14/Z14,"no KPI data") -> 3609243.6 | AN14: n/a | AO14: LCV | AP14: =SWEDEN!G14 -> 278.48625 | AQ14: =SWEDEN!G9 -> 10320 | AR14: =AP14*AQ14 -> 2873978.1 | AS14: =IF(AI14>=Inputs!$B$38,AI14,MIN(AI14+'Dashboard (2)'!$N$2,Inputs!$B$38)) -> 0.65167377 | AT14: =AR14*AS14 -> 1872896.2 | AU14: =Inputs!$C$13*(1+Inputs!$B$9)*(1+'Dashboard (2)'!$T$1)*(1+'Dashboard (2)'!$T$1) -> 499.04736 | AV14: =AU14*AQ14 -> 5150168.8 | AW14: =IF(ISNUMBER(AM14),AM14*AT14/AJ14,"no KPI data") -> 4001509.9 | AX14: n/a | AY14: LCV | AZ14: =SWEDEN!H14 -> 286.84084 | BA14: =SWEDEN!H9 -> 10885 | BB14: =AZ14*BA14 -> 3122262.5 | BC14: =IF(AS14>=Inputs!$B$38,AS14,MIN(AS14+'Dashboard (2)'!$N$2,Inputs!$B$38)) -> 0.66167377 | BD14: =BB14*BC14 -> 2065919.2 | BE14: =Inputs!$C$13*(1+Inputs!$B$9)*(1+'Dashboard (2)'!$T$1)*(1+'Dashboard (2)'!$T$1)*(1+'Dashboard (2)'!$T$1) -> 514.01878 | BF14: =BE14*BA14 -> 5595094.4 | BG14: =IF(ISNUMBER(AW14),AW14*BD14/AT14,"no KPI data") -> 4413910.7 | BH14: n/a | BI14: LCV | BJ14: =SWEDEN!I14 -> 295.44606 | BK14: =SWEDEN!I9 -> 11433 | BL14: =BJ14*BK14 -> 3377834.8 | BM14: =IF(BC14>=Inputs!$B$38,BC14,MIN(BC14+'Dashboard (2)'!$N$2,Inputs!$B$38)) -> 0.67167377 | BN14: =BL14*BM14 -> 2268803.1 | BO14: =Inputs!$C$13*(1+Inputs!$B$9)*(1+'Dashboard (2)'!$T$1)*(1+'Dashboard (2)'!$T$1)*(1+'Dashboard (2)'!$T$1)*(1+'Dashboard (2)'!$T$1) -> 529.43934 | BP14: =BO14*BK14 -> 6053080 | BQ14: =IF(ISNUMBER(BG14),BG14*BN14/BD14,"no KPI data") -> 4847379.3 | BR14: n/a
A15: HUNGARY | B15: LCV | C15: =Dashboard!C11 -> 349600 | D15: =Dashboard!D11 -> 1047900 | E15: =Dashboard!E11 -> 0.33361962 | F15: =Dashboard!F11 -> 0.018 | G15: =Dashboard!G11 -> 18862.2 | H15: =Dashboard!H11 -> 0.35161962 | I15: =Dashboard!I11 -> 368462.2 | K15: LCV | L15: =HUNGARY!D14 -> 250 | M15: =HUNGARY!D9 -> 3734 | N15: =L15*M15 -> 933500 | O15: =HUNGARY!D20 -> 346246.24 | P15: =O15/N15 -> 0.37091188 | Q15: =Inputs!$C$13 -> 448 | R15: =Q15*M15 -> 1672832 | S15: =IF(ISNUMBER(Dashboard!Q11),Dashboard!Q11,"no KPI data") -> no KPI data | T15: n/a | U15: LCV | V15: =HUNGARY!E14 -> 262.5 | W15: =HUNGARY!E9 -> 3992 | X15: =V15*W15 -> 1047900 | Y15: =Z15/X15 -> 0.35161962 | Z15: =HUNGARY!E24 -> 368462.2 | AA15: =Inputs!$C$13*(1+Inputs!$B$9) -> 470.4 | AB15: =AA15*W15 -> 1877836.8 | AC15: =IF(ISNUMBER(S15),S15+Dashboard!G11/(1-Inputs!$B$18),"no KPI data") -> no KPI data | AD15: n/a | AE15: LCV | AF15: =HUNGARY!F14 -> 270.375 | AG15: =HUNGARY!F9 -> 4242 | AH15: =AF15*AG15 -> 1146930.8 | AI15: =IF(Y15>=Inputs!$B$38,Y15,MIN(Y15+'Dashboard (2)'!$N$2,Inputs!$B$38)) -> 0.36161962 | AJ15: =AH15*AI15 -> 414752.66 | AK15: =Inputs!$C$13*(1+Inputs!$B$9)*(1+'Dashboard (2)'!$T$1) -> 484.512 | AL15: =AK15*AG15 -> 2055299.9 | AM15: =IF(ISNUMBER(AC15),AC15*AJ15/Z15,"no KPI data") -> no KPI data | AN15: n/a | AO15: LCV | AP15: =HUNGARY!G14 -> 278.48625 | AQ15: =HUNGARY!G9 -> 4390 | AR15: =AP15*AQ15 -> 1222554.6 | AS15: =IF(AI15>=Inputs!$B$38,AI15,MIN(AI15+'Dashboard (2)'!$N$2,Inputs!$B$38)) -> 0.37161962 | AT15: =AR15*AS15 -> 454325.29 | AU15: =Inputs!$C$13*(1+Inputs!$B$9)*(1+'Dashboard (2)'!$T$1)*(1+'Dashboard (2)'!$T$1) -> 499.04736 | AV15: =AU15*AQ15 -> 2190817.9 | AW15: =IF(ISNUMBER(AM15),AM15*AT15/AJ15,"no KPI data") -> no KPI data | AX15: n/a | AY15: LCV | AZ15: =HUNGARY!H14 -> 286.84084 | BA15: =HUNGARY!H9 -> 4533 | BB15: =AZ15*BA15 -> 1300249.5 | BC15: =IF(AS15>=Inputs!$B$38,AS15,MIN(AS15+'Dashboard (2)'!$N$2,Inputs!$B$38)) -> 0.38161962 | BD15: =BB15*BC15 -> 496200.73 | BE15: =Inputs!$C$13*(1+Inputs!$B$9)*(1+'Dashboard (2)'!$T$1)*(1+'Dashboard (2)'!$T$1)*(1+'Dashboard (2)'!$T$1) -> 514.01878 | BF15: =BE15*BA15 -> 2330047.1 | BG15: =IF(ISNUMBER(AW15),AW15*BD15/AT15,"no KPI data") -> no KPI data | BH15: n/a | BI15: LCV | BJ15: =HUNGARY!I14 -> 295.44606 | BK15: =HUNGARY!I9 -> 4672 | BL15: =BJ15*BK15 -> 1380324 | BM15: =IF(BC15>=Inputs!$B$38,BC15,MIN(BC15+'Dashboard (2)'!$N$2,Inputs!$B$38)) -> 0.39161962 | BN15: =BL15*BM15 -> 540561.96 | BO15: =Inputs!$C$13*(1+Inputs!$B$9)*(1+'Dashboard (2)'!$T$1)*(1+'Dashboard (2)'!$T$1)*(1+'Dashboard (2)'!$T$1)*(1+'Dashboard (2)'!$T$1) -> 529.43934 | BP15: =BO15*BK15 -> 2473540.6 | BQ15: =IF(ISNUMBER(BG15),BG15*BN15/BD15,"no KPI data") -> no KPI data | BR15: n/a
A16: FINLAND | B16: LCV | C16: =Dashboard!C12 -> 360300 | D16: =Dashboard!D12 -> 343350 | E16: =Dashboard!E12 -> 1.0493665 | F16: =Dashboard!F12 -> 0.018 | G16: =Dashboard!G12 -> 6180.3 | H16: =Dashboard!H12 -> 1.0673665 | I16: =Dashboard!I12 -> 366480.3 | K16: LCV | L16: =FINLAND!D14 -> 250 | M16: =FINLAND!D9 -> 1204 | N16: =L16*M16 -> 301000 | O16: =FINLAND!D20 -> 279383.25 | P16: =O16/N16 -> 0.92818355 | Q16: =Inputs!$C$13 -> 448 | R16: =Q16*M16 -> 539392 | S16: =IF(ISNUMBER(Dashboard!Q12),Dashboard!Q12,"no KPI data") -> no KPI data | T16: n/a | U16: LCV | V16: =FINLAND!E14 -> 262.5 | W16: =FINLAND!E9 -> 1308 | X16: =V16*W16 -> 343350 | Y16: =Z16/X16 -> 1.0673665 | Z16: =FINLAND!E24 -> 366480.3 | AA16: =Inputs!$C$13*(1+Inputs!$B$9) -> 470.4 | AB16: =AA16*W16 -> 615283.2 | AC16: =IF(ISNUMBER(S16),S16+Dashboard!G12/(1-Inputs!$B$18),"no KPI data") -> no KPI data | AD16: n/a | AE16: LCV | AF16: =FINLAND!F14 -> 270.375 | AG16: =FINLAND!F9 -> 1409 | AH16: =AF16*AG16 -> 380958.38 | AI16: =IF(Y16>=Inputs!$B$38,Y16,MIN(Y16+'Dashboard (2)'!$N$2,Inputs!$B$38)) -> 1.0773665 | AJ16: =AH16*AI16 -> 410431.8 | AK16: =Inputs!$C$13*(1+Inputs!$B$9)*(1+'Dashboard (2)'!$T$1) -> 484.512 | AL16: =AK16*AG16 -> 682677.41 | AM16: =IF(ISNUMBER(AC16),AC16*AJ16/Z16,"no KPI data") -> no KPI data | AN16: n/a | AO16: LCV | AP16: =FINLAND!G14 -> 278.48625 | AQ16: =FINLAND!G9 -> 1522 | AR16: =AP16*AQ16 -> 423856.07 | AS16: =IF(AI16>=Inputs!$B$38,AI16,MIN(AI16+'Dashboard (2)'!$N$2,Inputs!$B$38)) -> 1.0873665 | AT16: =AR16*AS16 -> 460886.91 | AU16: =Inputs!$C$13*(1+Inputs!$B$9)*(1+'Dashboard (2)'!$T$1)*(1+'Dashboard (2)'!$T$1) -> 499.04736 | AV16: =AU16*AQ16 -> 759550.08 | AW16: =IF(ISNUMBER(AM16),AM16*AT16/AJ16,"no KPI data") -> no KPI data | AX16: n/a | AY16: LCV | AZ16: =FINLAND!H14 -> 286.84084 | BA16: =FINLAND!H9 -> 1631 | BB16: =AZ16*BA16 -> 467837.41 | BC16: =IF(AS16>=Inputs!$B$38,AS16,MIN(AS16+'Dashboard (2)'!$N$2,Inputs!$B$38)) -> 1.0973665 | BD16: =BB16*BC16 -> 513389.11 | BE16: =Inputs!$C$13*(1+Inputs!$B$9)*(1+'Dashboard (2)'!$T$1)*(1+'Dashboard (2)'!$T$1)*(1+'Dashboard (2)'!$T$1) -> 514.01878 | BF16: =BE16*BA16 -> 838364.63 | BG16: =IF(ISNUMBER(AW16),AW16*BD16/AT16,"no KPI data") -> no KPI data | BH16: n/a | BI16: LCV | BJ16: =FINLAND!I14 -> 295.44606 | BK16: =FINLAND!I9 -> 1737 | BL16: =BJ16*BK16 -> 513189.81 | BM16: =IF(BC16>=Inputs!$B$38,BC16,MIN(BC16+'Dashboard (2)'!$N$2,Inputs!$B$38)) -> 1.1073665 | BN16: =BL16*BM16 -> 568289.22 | BO16: =Inputs!$C$13*(1+Inputs!$B$9)*(1+'Dashboard (2)'!$T$1)*(1+'Dashboard (2)'!$T$1)*(1+'Dashboard (2)'!$T$1)*(1+'Dashboard (2)'!$T$1) -> 529.43934 | BP16: =BO16*BK16 -> 919636.14 | BQ16: =IF(ISNUMBER(BG16),BG16*BN16/BD16,"no KPI data") -> no KPI data | BR16: n/a
A17: ROMANIA | B17: LCV | C17: =Dashboard!C13 -> 199587.57 | D17: =Dashboard!D13 -> 317362.5 | E17: =Dashboard!E13 -> 0.62889462 | F17: =Dashboard!F13 -> 0.018 | G17: =Dashboard!G13 -> 5712.525 | H17: =Dashboard!H13 -> 0.64689462 | I17: =Dashboard!I13 -> 205300.1 | K17: LCV | L17: =ROMANIA!D14 -> 250 | M17: =ROMANIA!D9 -> 1071 | N17: =L17*M17 -> 267750 | O17: =ROMANIA!D20 -> 177897.87 | P17: =O17/N17 -> 0.66441782 | Q17: =Inputs!$C$13 -> 448 | R17: =Q17*M17 -> 479808 | S17: =IF(ISNUMBER(Dashboard!Q13),Dashboard!Q13,"no KPI data") -> 394597 | T17: n/a | U17: LCV | V17: =ROMANIA!E14 -> 262.5 | W17: =ROMANIA!E9 -> 1209 | X17: =V17*W17 -> 317362.5 | Y17: =Z17/X17 -> 0.64689462 | Z17: =ROMANIA!E24 -> 205300.1 | AA17: =Inputs!$C$13*(1+Inputs!$B$9) -> 470.4 | AB17: =AA17*W17 -> 568713.6 | AC17: =IF(ISNUMBER(S17),S17+Dashboard!G13/(1-Inputs!$B$18),"no KPI data") -> 403385.5 | AD17: n/a | AE17: LCV | AF17: =ROMANIA!F14 -> 270.375 | AG17: =ROMANIA!F9 -> 1343 | AH17: =AF17*AG17 -> 363113.62 | AI17: =IF(Y17>=Inputs!$B$38,Y17,MIN(Y17+'Dashboard (2)'!$N$2,Inputs!$B$38)) -> 0.65689462 | AJ17: =AH17*AI17 -> 238527.39 | AK17: =Inputs!$C$13*(1+Inputs!$B$9)*(1+'Dashboard (2)'!$T$1) -> 484.512 | AL17: =AK17*AG17 -> 650699.62 | AM17: =IF(ISNUMBER(AC17),AC17*AJ17/Z17,"no KPI data") -> 468672.41 | AN17: n/a | AO17: LCV | AP17: =ROMANIA!G14 -> 278.48625 | AQ17: =ROMANIA!G9 -> 1475 | AR17: =AP17*AQ17 -> 410767.22 | AS17: =IF(AI17>=Inputs!$B$38,AI17,MIN(AI17+'Dashboard (2)'!$N$2,Inputs!$B$38)) -> 0.66689462 | AT17: =AR17*AS17 -> 273938.45 | AU17: =Inputs!$C$13*(1+Inputs!$B$9)*(1+'Dashboard (2)'!$T$1)*(1+'Dashboard (2)'!$T$1) -> 499.04736 | AV17: =AU17*AQ17 -> 736094.86 | AW17: =IF(ISNUMBER(AM17),AM17*AT17/AJ17,"no KPI data") -> 538250.11 | AX17: n/a | AY17: LCV | AZ17: =ROMANIA!H14 -> 286.84084 | BA17: =ROMANIA!H9 -> 1603 | BB17: =AZ17*BA17 -> 459805.86 | BC17: =IF(AS17>=Inputs!$B$38,AS17,MIN(AS17+'Dashboard (2)'!$N$2,Inputs!$B$38)) -> 0.67689462 | BD17: =BB17*BC17 -> 311240.12 | BE17: =Inputs!$C$13*(1+Inputs!$B$9)*(1+'Dashboard (2)'!$T$1)*(1+'Dashboard (2)'!$T$1)*(1+'Dashboard (2)'!$T$1) -> 514.01878 | BF17: =BE17*BA17 -> 823972.11 | BG17: =IF(ISNUMBER(AW17),AW17*BD17/AT17,"no KPI data") -> 611542.58 | BH17: n/a | BI17: LCV | BJ17: =ROMANIA!I14 -> 295.44606 | BK17: =ROMANIA!I9 -> 1727 | BL17: =BJ17*BK17 -> 510235.35 | BM17: =IF(BC17>=Inputs!$B$38,BC17,MIN(BC17+'Dashboard (2)'!$N$2,Inputs!$B$38)) -> 0.68689462 | BN17: =BL17*BM17 -> 350477.92 | BO17: =Inputs!$C$13*(1+Inputs!$B$9)*(1+'Dashboard (2)'!$T$1)*(1+'Dashboard (2)'!$T$1)*(1+'Dashboard (2)'!$T$1)*(1+'Dashboard (2)'!$T$1) -> 529.43934 | BP17: =BO17*BK17 -> 914341.75 | BQ17: =IF(ISNUMBER(BG17),BG17*BN17/BD17,"no KPI data") -> 688639.28 | BR17: n/a
A18: DENMARK | B18: LCV | C18: =Dashboard!C14 -> 187600 | D18: =Dashboard!D14 -> 247800 | E18: =Dashboard!E14 -> 0.75706215 | F18: =Dashboard!F14 -> 0.018 | G18: =Dashboard!G14 -> 4460.4 | H18: =Dashboard!H14 -> 0.77506215 | I18: =Dashboard!I14 -> 192060.4 | K18: LCV | L18: =DENMARK!D14 -> 250 | M18: =DENMARK!D9 -> 850 | N18: =L18*M18 -> 212500 | O18: =DENMARK!D20 -> 154459.8 | P18: =O18/N18 -> 0.72686965 | Q18: =Inputs!$C$13 -> 448 | R18: =Q18*M18 -> 380800 | S18: =IF(ISNUMBER(Dashboard!Q14),Dashboard!Q14,"no KPI data") -> 572864 | T18: n/a | U18: LCV | V18: =DENMARK!E14 -> 262.5 | W18: =DENMARK!E9 -> 944 | X18: =V18*W18 -> 247800 | Y18: =Z18/X18 -> 0.77506215 | Z18: =DENMARK!E24 -> 192060.4 | AA18: =Inputs!$C$13*(1+Inputs!$B$9) -> 470.4 | AB18: =AA18*W18 -> 444057.6 | AC18: =IF(ISNUMBER(S18),S18+Dashboard!G14/(1-Inputs!$B$18),"no KPI data") -> 579726.15 | AD18: n/a | AE18: LCV | AF18: =DENMARK!F14 -> 270.375 | AG18: =DENMARK!F9 -> 1036 | AH18: =AF18*AG18 -> 280108.5 | AI18: =IF(Y18>=Inputs!$B$38,Y18,MIN(Y18+'Dashboard (2)'!$N$2,Inputs!$B$38)) -> 0.78506215 | AJ18: =AH18*AI18 -> 219902.58 | AK18: =Inputs!$C$13*(1+Inputs!$B$9)*(1+'Dashboard (2)'!$T$1) -> 484.512 | AL18: =AK18*AG18 -> 501954.43 | AM18: =IF(ISNUMBER(AC18),AC18*AJ18/Z18,"no KPI data") -> 663766.59 | AN18: n/a | AO18: LCV | AP18: =DENMARK!G14 -> 278.48625 | AQ18: =DENMARK!G9 -> 1140 | AR18: =AP18*AQ18 -> 317474.33 | AS18: =IF(AI18>=Inputs!$B$38,AI18,MIN(AI18+'Dashboard (2)'!$N$2,Inputs!$B$38)) -> 0.79506215 | AT18: =AR18*AS18 -> 252411.82 | AU18: =Inputs!$C$13*(1+Inputs!$B$9)*(1+'Dashboard (2)'!$T$1)*(1+'Dashboard (2)'!$T$1) -> 499.04736 | AV18: =AU18*AQ18 -> 568913.99 | AW18: =IF(ISNUMBER(AM18),AM18*AT18/AJ18,"no KPI data") -> 761894.35 | AX18: n/a | AY18: LCV | AZ18: =DENMARK!H14 -> 286.84084 | BA18: =DENMARK!H9 -> 1241 | BB18: =AZ18*BA18 -> 355969.48 | BC18: =IF(AS18>=Inputs!$B$38,AS18,MIN(AS18+'Dashboard (2)'!$N$2,Inputs!$B$38)) -> 0.80506215 | BD18: =BB18*BC18 -> 286577.55 | BE18: =Inputs!$C$13*(1+Inputs!$B$9)*(1+'Dashboard (2)'!$T$1)*(1+'Dashboard (2)'!$T$1)*(1+'Dashboard (2)'!$T$1) -> 514.01878 | BF18: =BE18*BA18 -> 637897.31 | BG18: =IF(ISNUMBER(AW18),AW18*BD18/AT18,"no KPI data") -> 865022.16 | BH18: n/a | BI18: LCV | BJ18: =DENMARK!I14 -> 295.44606 | BK18: =DENMARK!I9 -> 1339 | BL18: =BJ18*BK18 -> 395602.28 | BM18: =IF(BC18>=Inputs!$B$38,BC18,MIN(BC18+'Dashboard (2)'!$N$2,Inputs!$B$38)) -> 0.81506215 | BN18: =BL18*BM18 -> 322440.44 | BO18: =Inputs!$C$13*(1+Inputs!$B$9)*(1+'Dashboard (2)'!$T$1)*(1+'Dashboard (2)'!$T$1)*(1+'Dashboard (2)'!$T$1)*(1+'Dashboard (2)'!$T$1) -> 529.43934 | BP18: =BO18*BK18 -> 708919.28 | BQ18: =IF(ISNUMBER(BG18),BG18*BN18/BD18,"no KPI data") -> 973272.77 | BR18: n/a
A19: ICELAND | B19: LCV | C19: =Dashboard!C15 -> 104600 | D19: =Dashboard!D15 -> 115237.5 | E19: =Dashboard!E15 -> 0.90769064 | F19: =Dashboard!F15 -> 0.018 | G19: =Dashboard!G15 -> 2074.275 | H19: =Dashboard!H15 -> 0.92569064 | I19: =Dashboard!I15 -> 106674.27 | K19: LCV | L19: =ICELAND!D14 -> 250 | M19: =ICELAND!D9 -> 406 | N19: =L19*M19 -> 101500 | O19: =ICELAND!D20 -> 86604.51 | P19: =O19/N19 -> 0.8532464 | Q19: =Inputs!$C$13 -> 448 | R19: =Q19*M19 -> 181888 | S19: =IF(ISNUMBER(Dashboard!Q15),Dashboard!Q15,"no KPI data") -> 195849 | T19: n/a | U19: LCV | V19: =ICELAND!E14 -> 262.5 | W19: =ICELAND!E9 -> 439 | X19: =V19*W19 -> 115237.5 | Y19: =Z19/X19 -> 0.92569064 | Z19: =ICELAND!E24 -> 106674.27 | AA19: =Inputs!$C$13*(1+Inputs!$B$9) -> 470.4 | AB19: =AA19*W19 -> 206505.6 | AC19: =IF(ISNUMBER(S19),S19+Dashboard!G15/(1-Inputs!$B$18),"no KPI data") -> 199040.19 | AD19: n/a | AE19: LCV | AF19: =ICELAND!F14 -> 270.375 | AG19: =ICELAND!F9 -> 471 | AH19: =AF19*AG19 -> 127346.62 | AI19: =IF(Y19>=Inputs!$B$38,Y19,MIN(Y19+'Dashboard (2)'!$N$2,Inputs!$B$38)) -> 0.93569064 | AJ19: =AH19*AI19 -> 119157.04 | AK19: =Inputs!$C$13*(1+Inputs!$B$9)*(1+'Dashboard (2)'!$T$1) -> 484.512 | AL19: =AK19*AG19 -> 228205.15 | AM19: =IF(ISNUMBER(AC19),AC19*AJ19/Z19,"no KPI data") -> 222331.4 | AN19: n/a | AO19: LCV | AP19: =ICELAND!G14 -> 278.48625 | AQ19: =ICELAND!G9 -> 549 | AR19: =AP19*AQ19 -> 152888.95 | AS19: =IF(AI19>=Inputs!$B$38,AI19,MIN(AI19+'Dashboard (2)'!$N$2,Inputs!$B$38)) -> 0.94569064 | AT19: =AR19*AS19 -> 144585.65 | AU19: =Inputs!$C$13*(1+Inputs!$B$9)*(1+'Dashboard (2)'!$T$1)*(1+'Dashboard (2)'!$T$1) -> 499.04736 | AV19: =AU19*AQ19 -> 273977 | AW19: =IF(ISNUMBER(AM19),AM19*AT19/AJ19,"no KPI data") -> 269777.84 | AX19: n/a | AY19: LCV | AZ19: =ICELAND!H14 -> 286.84084 | BA19: =ICELAND!H9 -> 625 | BB19: =AZ19*BA19 -> 179275.52 | BC19: =IF(AS19>=Inputs!$B$38,AS19,MIN(AS19+'Dashboard (2)'!$N$2,Inputs!$B$38)) -> 0.95569064 | BD19: =BB19*BC19 -> 171331.94 | BE19: =Inputs!$C$13*(1+Inputs!$B$9)*(1+'Dashboard (2)'!$T$1)*(1+'Dashboard (2)'!$T$1)*(1+'Dashboard (2)'!$T$1) -> 514.01878 | BF19: =BE19*BA19 -> 321261.74 | BG19: =IF(ISNUMBER(AW19),AW19*BD19/AT19,"no KPI data") -> 319682.91 | BH19: n/a | BI19: LCV | BJ19: =ICELAND!I14 -> 295.44606 | BK19: =ICELAND!I9 -> 698 | BL19: =BJ19*BK19 -> 206221.35 | BM19: =IF(BC19>=Inputs!$B$38,BC19,MIN(BC19+'Dashboard (2)'!$N$2,Inputs!$B$38)) -> 0.96569064 | BN19: =BL19*BM19 -> 199146.03 | BO19: =Inputs!$C$13*(1+Inputs!$B$9)*(1+'Dashboard (2)'!$T$1)*(1+'Dashboard (2)'!$T$1)*(1+'Dashboard (2)'!$T$1)*(1+'Dashboard (2)'!$T$1) -> 529.43934 | BP19: =BO19*BK19 -> 369548.66 | BQ19: =IF(ISNUMBER(BG19),BG19*BN19/BD19,"no KPI data") -> 371580.34 | BR19: n/a
A20: GERMANY | B20: mixed | C20: =Dashboard!C16 -> 2913662.8 | D20: =Dashboard!D16 -> 4443791.1 | E20: =Dashboard!E16 -> 0.65567052 | F20: =Dashboard!F16 -> 0.018 | G20: =Dashboard!G16 -> 79988.24 | H20: =Dashboard!H16 -> 0.67367052 | I20: =Dashboard!I16 -> 2993651.1 | K20: CV LD | L20: =GERMANY!C17 -> 739 | M20: =GERMANY!D9 -> 697 | N20: =L20*M20 -> 515083 | Q20: =IFERROR(R20/M20,0) -> 1120 | R20: =Inputs!$C$14*GERMANY!D9 -> 780640 | U20: CV LD | V20: =GERMANY!D17 -> 775.95 | W20: =GERMANY!E9 -> 1066 | X20: =V20*W20 -> 827162.7 | AA20: =IFERROR(AB20/W20,0) -> 1176 | AB20: =Inputs!$C$14*(1+Inputs!$B$9)*GERMANY!E9 -> 1253616 | AE20: CV LD | AF20: =GERMANY!E17 -> 799.2285 | AG20: =GERMANY!F9 -> 1422 | AH20: =AF20*AG20 -> 1136502.9 | AK20: =IFERROR(AL20/AG20,0) -> 1211.28 | AL20: =Inputs!$C$14*(1+Inputs!$B$9)*(1+'Dashboard (2)'!$T$1)*GERMANY!F9 -> 1722440.2 | AO20: CV LD | AP20: =GERMANY!F17 -> 823.20536 | AQ20: =GERMANY!G9 -> 2003 | AR20: =AP20*AQ20 -> 1648880.3 | AU20: =IFERROR(AV20/AQ20,0) -> 1247.6184 | AV20: =Inputs!$C$14*(1+Inputs!$B$9)*(1+'Dashboard (2)'!$T$1)*(1+'Dashboard (2)'!$T$1)*GERMANY!G9 -> 2498979.7 | AY20: CV LD | AZ20: =GERMANY!G17 -> 847.90152 | BA20: =GERMANY!H9 -> 2841 | BB20: =AZ20*BA20 -> 2408888.2 | BE20: =IFERROR(BF20/BA20,0) -> 1285.047 | BF20: =Inputs!$C$14*(1+Inputs!$B$9)*(1+'Dashboard (2)'!$T$1)*(1+'Dashboard (2)'!$T$1)*(1+'Dashboard (2)'!$T$1)*GERMANY!H9 -> 3650818.4 | BI20: CV LD | BJ20: =GERMANY!H17 -> 873.33856 | BK20: =GERMANY!I9 -> 3756 | BL20: =BJ20*BK20 -> 3280259.6 | BO20: =IFERROR(BP20/BK20,0) -> 1323.5984 | BP20: =Inputs!$C$14*(1+Inputs!$B$9)*(1+'Dashboard (2)'!$T$1)*(1+'Dashboard (2)'!$T$1)*(1+'Dashboard (2)'!$T$1)*(1+'Dashboard (2)'!$T$1)*GERMANY!I9 -> 4971435.4
K21: CV MD | L21: =GERMANY!C18 -> 887 | M21: =GERMANY!D10 -> 35 | N21: =L21*M21 -> 31045 | Q21: =IFERROR(R21/M21,0) -> 1344 | R21: =Inputs!$C$15*GERMANY!D10 -> 47040 | U21: CV MD | V21: =GERMANY!D18 -> 931.35 | W21: =GERMANY!E10 -> 34 | X21: =V21*W21 -> 31665.9 | AA21: =IFERROR(AB21/W21,0) -> 1411.2 | AB21: =Inputs!$C$15*(1+Inputs!$B$9)*GERMANY!E10 -> 47980.8 | AE21: CV MD | AF21: =GERMANY!E18 -> 959.2905 | AG21: =GERMANY!F10 -> 33 | AH21: =AF21*AG21 -> 31656.587 | AK21: =IFERROR(AL21/AG21,0) -> 1453.536 | AL21: =Inputs!$C$15*(1+Inputs!$B$9)*(1+'Dashboard (2)'!$T$1)*GERMANY!F10 -> 47966.688 | AO21: CV MD | AP21: =GERMANY!F18 -> 988.06921 | AQ21: =GERMANY!G10 -> 32 | AR21: =AP21*AQ21 -> 31618.215 | AU21: =IFERROR(AV21/AQ21,0) -> 1497.1421 | AV21: =Inputs!$C$15*(1+Inputs!$B$9)*(1+'Dashboard (2)'!$T$1)*(1+'Dashboard (2)'!$T$1)*GERMANY!G10 -> 47908.547 | AY21: CV MD | AZ21: =GERMANY!G18 -> 1017.7113 | BA21: =GERMANY!H10 -> 31 | BB21: =AZ21*BA21 -> 31549.05 | BE21: =IFERROR(BF21/BA21,0) -> 1542.0563 | BF21: =Inputs!$C$15*(1+Inputs!$B$9)*(1+'Dashboard (2)'!$T$1)*(1+'Dashboard (2)'!$T$1)*(1+'Dashboard (2)'!$T$1)*GERMANY!H10 -> 47803.747 | BI21: CV MD | BJ21: =GERMANY!H18 -> 1048.2426 | BK21: =GERMANY!I10 -> 30 | BL21: =BJ21*BK21 -> 31447.279 | BO21: =IFERROR(BP21/BK21,0) -> 1588.318 | BP21: =Inputs!$C$15*(1+Inputs!$B$9)*(1+'Dashboard (2)'!$T$1)*(1+'Dashboard (2)'!$T$1)*(1+'Dashboard (2)'!$T$1)*(1+'Dashboard (2)'!$T$1)*GERMANY!I10 -> 47649.541
K22: LCV | L22: =GERMANY!C20 -> 250 | M22: =GERMANY!D12 -> 13048 | N22: =L22*M22 -> 3262000 | Q22: =IFERROR(R22/M22,0) -> 448 | R22: =Inputs!$C$13*GERMANY!D12 -> 5845504 | U22: LCV | V22: =GERMANY!D20 -> 262.5 | W22: =GERMANY!E12 -> 13657 | X22: =V22*W22 -> 3584962.5 | AA22: =IFERROR(AB22/W22,0) -> 470.4 | AB22: =Inputs!$C$13*(1+Inputs!$B$9)*GERMANY!E12 -> 6424252.8 | AE22: LCV | AF22: =GERMANY!E20 -> 270.375 | AG22: =GERMANY!F12 -> 14247 | AH22: =AF22*AG22 -> 3852032.6 | AK22: =IFERROR(AL22/AG22,0) -> 484.512 | AL22: =Inputs!$C$13*(1+Inputs!$B$9)*(1+'Dashboard (2)'!$T$1)*GERMANY!F12 -> 6902842.5 | AO22: LCV | AP22: =GERMANY!F20 -> 278.48625 | AQ22: =GERMANY!G12 -> 14820 | AR22: =AP22*AQ22 -> 4127166.2 | AU22: =IFERROR(AV22/AQ22,0) -> 499.04736 | AV22: =Inputs!$C$13*(1+Inputs!$B$9)*(1+'Dashboard (2)'!$T$1)*(1+'Dashboard (2)'!$T$1)*GERMANY!G12 -> 7395881.9 | AY22: LCV | AZ22: =GERMANY!G20 -> 286.84084 | BA22: =GERMANY!H12 -> 15375 | BB22: =AZ22*BA22 -> 4410177.9 | BE22: =IFERROR(BF22/BA22,0) -> 514.01878 | BF22: =Inputs!$C$13*(1+Inputs!$B$9)*(1+'Dashboard (2)'!$T$1)*(1+'Dashboard (2)'!$T$1)*(1+'Dashboard (2)'!$T$1)*GERMANY!H12 -> 7903038.8 | BI22: LCV | BJ22: =GERMANY!H20 -> 295.44606 | BK22: =GERMANY!I12 -> 15914 | BL22: =BJ22*BK22 -> 4701728.6 | BO22: =IFERROR(BP22/BK22,0) -> 529.43934 | BP22: =Inputs!$C$13*(1+Inputs!$B$9)*(1+'Dashboard (2)'!$T$1)*(1+'Dashboard (2)'!$T$1)*(1+'Dashboard (2)'!$T$1)*(1+'Dashboard (2)'!$T$1)*GERMANY!I12 -> 8425497.7
M23: =SUM(M20:M22) -> 13780 | N23: =SUM(N20:N22) -> 3808128 | O23: =GERMANY!D26 -> 2641885.1 | P23: =O23/N23 -> 0.69374904 | R23: =SUM(R20:R22) -> 6673184 | S23: =IF(ISNUMBER(Dashboard!Q16),Dashboard!Q16,"no KPI data") -> no KPI data | T23: n/a | W23: =SUM(W20:W22) -> 14757 | X23: =SUM(X20:X22) -> 4443791.1 | Y23: =Z23/X23 -> 0.67367052 | Z23: =GERMANY!E30 -> 2993651.1 | AB23: =SUM(AB20:AB22) -> 7725849.6 | AC23: =IF(ISNUMBER(S23),S23+Dashboard!G16/(1-Inputs!$B$18),"no KPI data") -> no KPI data | AD23: n/a | AG23: =SUM(AG20:AG22) -> 15702 | AH23: =SUM(AH20:AH22) -> 5020192.1 | AI23: =IF(Y23>=Inputs!$B$38,Y23,MIN(Y23+'Dashboard (2)'!$N$2,Inputs!$B$38)) -> 0.68367052 | AJ23: =AH23*AI23 -> 3432157.4 | AL23: =SUM(AL20:AL22) -> 8673249.3 | AM23: =IF(ISNUMBER(AC23),AC23*AJ23/Z23,"no KPI data") -> no KPI data | AN23: n/a | AQ23: =SUM(AQ20:AQ22) -> 16855 | AR23: =SUM(AR20:AR22) -> 5807664.8 | AS23: =IF(AI23>=Inputs!$B$38,AI23,MIN(AI23+'Dashboard (2)'!$N$2,Inputs!$B$38)) -> 0.69367052 | AT23: =AR23*AS23 -> 4028605.9 | AV23: =SUM(AV20:AV22) -> 9942770.1 | AW23: =IF(ISNUMBER(AM23),AM23*AT23/AJ23,"no KPI data") -> no KPI data | AX23: n/a | BA23: =SUM(BA20:BA22) -> 18247 | BB23: =SUM(BB20:BB22) -> 6850615.1 | BC23: =IF(AS23>=Inputs!$B$38,AS23,MIN(AS23+'Dashboard (2)'!$N$2,Inputs!$B$38)) -> 0.70367052 | BD23: =BB23*BC23 -> 4820575.9 | BF23: =SUM(BF20:BF22) -> 11601661 | BG23: =IF(ISNUMBER(AW23),AW23*BD23/AT23,"no KPI data") -> no KPI data | BH23: n/a | BK23: =SUM(BK20:BK22) -> 19700 | BL23: =SUM(BL20:BL22) -> 8013435.6 | BM23: =IF(BC23>=Inputs!$B$38,BC23,MIN(BC23+'Dashboard (2)'!$N$2,Inputs!$B$38)) -> 0.71367052 | BN23: =BL23*BM23 -> 5718952.8 | BP23: =SUM(BP20:BP22) -> 13444583 | BQ23: =IF(ISNUMBER(BG23),BG23*BN23/BD23,"no KPI data") -> no KPI data | BR23: n/a
A24: BELGIUM | B24: mixed | C24: =Dashboard!C17 -> 2296577.3 | D24: =Dashboard!D17 -> 2739612.8 | E24: =Dashboard!E17 -> 0.83828539 | F24: =Dashboard!F17 -> 0.018 | G24: =Dashboard!G17 -> 49313.029 | H24: =Dashboard!H17 -> 0.85628539 | I24: =Dashboard!I17 -> 2345890.4 | K24: CV LD | L24: =BELGIUM!C17 -> 739 | M24: =BELGIUM!D9 -> 113 | N24: =L24*M24 -> 83507 | Q24: =IFERROR(R24/M24,0) -> 1120 | R24: =Inputs!$C$14*BELGIUM!D9 -> 126560 | U24: CV LD | V24: =BELGIUM!D17 -> 775.95 | W24: =BELGIUM!E9 -> 145 | X24: =V24*W24 -> 112512.75 | AA24: =IFERROR(AB24/W24,0) -> 1176 | AB24: =Inputs!$C$14*(1+Inputs!$B$9)*BELGIUM!E9 -> 170520 | AE24: CV LD | AF24: =BELGIUM!E17 -> 799.2285 | AG24: =BELGIUM!F9 -> 176 | AH24: =AF24*AG24 -> 140664.22 | AK24: =IFERROR(AL24/AG24,0) -> 1211.28 | AL24: =Inputs!$C$14*(1+Inputs!$B$9)*(1+'Dashboard (2)'!$T$1)*BELGIUM!F9 -> 213185.28 | AO24: CV LD | AP24: =BELGIUM!F17 -> 823.20536 | AQ24: =BELGIUM!G9 -> 206 | AR24: =AP24*AQ24 -> 169580.3 | AU24: =IFERROR(AV24/AQ24,0) -> 1247.6184 | AV24: =Inputs!$C$14*(1+Inputs!$B$9)*(1+'Dashboard (2)'!$T$1)*(1+'Dashboard (2)'!$T$1)*BELGIUM!G9 -> 257009.39 | AY24: CV LD | AZ24: =BELGIUM!G17 -> 847.90152 | BA24: =BELGIUM!H9 -> 235 | BB24: =AZ24*BA24 -> 199256.86 | BE24: =IFERROR(BF24/BA24,0) -> 1285.047 | BF24: =Inputs!$C$14*(1+Inputs!$B$9)*(1+'Dashboard (2)'!$T$1)*(1+'Dashboard (2)'!$T$1)*(1+'Dashboard (2)'!$T$1)*BELGIUM!H9 -> 301986.03 | BI24: CV LD | BJ24: =BELGIUM!H17 -> 873.33856 | BK24: =BELGIUM!I9 -> 263 | BL24: =BJ24*BK24 -> 229688.04 | BO24: =IFERROR(BP24/BK24,0) -> 1323.5984 | BP24: =Inputs!$C$14*(1+Inputs!$B$9)*(1+'Dashboard (2)'!$T$1)*(1+'Dashboard (2)'!$T$1)*(1+'Dashboard (2)'!$T$1)*(1+'Dashboard (2)'!$T$1)*BELGIUM!I9 -> 348106.37
K25: LCV | L25: =BELGIUM!C20 -> 250 | M25: =BELGIUM!D12 -> 9452 | N25: =L25*M25 -> 2363000 | Q25: =IFERROR(R25/M25,0) -> 448 | R25: =Inputs!$C$13*BELGIUM!D12 -> 4234496 | U25: LCV | V25: =BELGIUM!D20 -> 262.5 | W25: =BELGIUM!E12 -> 10008 | X25: =V25*W25 -> 2627100 | AA25: =IFERROR(AB25/W25,0) -> 470.4 | AB25: =Inputs!$C$13*(1+Inputs!$B$9)*BELGIUM!E12 -> 4707763.2 | AE25: LCV | AF25: =BELGIUM!E20 -> 270.375 | AG25: =BELGIUM!F12 -> 10548 | AH25: =AF25*AG25 -> 2851915.5 | AK25: =IFERROR(AL25/AG25,0) -> 484.512 | AL25: =Inputs!$C$13*(1+Inputs!$B$9)*(1+'Dashboard (2)'!$T$1)*BELGIUM!F12 -> 5110632.6 | AO25: LCV | AP25: =BELGIUM!F20 -> 278.48625 | AQ25: =BELGIUM!G12 -> 11072 | AR25: =AP25*AQ25 -> 3083399.8 | AU25: =IFERROR(AV25/AQ25,0) -> 499.04736 | AV25: =Inputs!$C$13*(1+Inputs!$B$9)*(1+'Dashboard (2)'!$T$1)*(1+'Dashboard (2)'!$T$1)*BELGIUM!G12 -> 5525452.4 | AY25: LCV | AZ25: =BELGIUM!G20 -> 286.84084 | BA25: =BELGIUM!H12 -> 11580 | BB25: =AZ25*BA25 -> 3321616.9 | BE25: =IFERROR(BF25/BA25,0) -> 514.01878 | BF25: =Inputs!$C$13*(1+Inputs!$B$9)*(1+'Dashboard (2)'!$T$1)*(1+'Dashboard (2)'!$T$1)*(1+'Dashboard (2)'!$T$1)*BELGIUM!H12 -> 5952337.5 | BI25: LCV | BJ25: =BELGIUM!H20 -> 295.44606 | BK25: =BELGIUM!I12 -> 12073 | BL25: =BJ25*BK25 -> 3566920.3 | BO25: =IFERROR(BP25/BK25,0) -> 529.43934 | BP25: =Inputs!$C$13*(1+Inputs!$B$9)*(1+'Dashboard (2)'!$T$1)*(1+'Dashboard (2)'!$T$1)*(1+'Dashboard (2)'!$T$1)*(1+'Dashboard (2)'!$T$1)*BELGIUM!I12 -> 6391921.2
M26: =SUM(M24:M25) -> 9565 | N26: =SUM(N24:N25) -> 2446507 | O26: =BELGIUM!D26 -> 2110127.7 | P26: =O26/N26 -> 0.86250628 | R26: =SUM(R24:R25) -> 4361056 | S26: =IF(ISNUMBER(Dashboard!Q17),Dashboard!Q17,"no KPI data") -> 6834272 | T26: n/a | W26: =SUM(W24:W25) -> 10153 | X26: =SUM(X24:X25) -> 2739612.8 | Y26: =Z26/X26 -> 0.85628539 | Z26: =BELGIUM!E30 -> 2345890.4 | AB26: =SUM(AB24:AB25) -> 4878283.2 | AC26: =IF(ISNUMBER(S26),S26+Dashboard!G17/(1-Inputs!$B$18),"no KPI data") -> 6910138.2 | AD26: n/a | AG26: =SUM(AG24:AG25) -> 10724 | AH26: =SUM(AH24:AH25) -> 2992579.7 | AI26: =IF(Y26>=Inputs!$B$38,Y26,MIN(Y26+'Dashboard (2)'!$N$2,Inputs!$B$38)) -> 0.86628539 | AJ26: =AH26*AI26 -> 2592428.1 | AL26: =SUM(AL24:AL25) -> 5323817.9 | AM26: =IF(ISNUMBER(AC26),AC26*AJ26/Z26,"no KPI data") -> 7636348.5 | AN26: n/a | AQ26: =SUM(AQ24:AQ25) -> 11278 | AR26: =SUM(AR24:AR25) -> 3252980.1 | AS26: =IF(AI26>=Inputs!$B$38,AI26,MIN(AI26+'Dashboard (2)'!$N$2,Inputs!$B$38)) -> 0.87628539 | AT26: =AR26*AS26 -> 2850538.9 | AV26: =SUM(AV24:AV25) -> 5782461.8 | AW26: =IF(ISNUMBER(AM26),AM26*AT26/AJ26,"no KPI data") -> 8396648.9 | AX26: n/a | BA26: =SUM(BA24:BA25) -> 11815 | BB26: =SUM(BB24:BB25) -> 3520873.8 | BC26: =IF(AS26>=Inputs!$B$38,AS26,MIN(AS26+'Dashboard (2)'!$N$2,Inputs!$B$38)) -> 0.88628539 | BD26: =BB26*BC26 -> 3120499 | BF26: =SUM(BF24:BF25) -> 6254323.5 | BG26: =IF(ISNUMBER(AW26),AW26*BD26/AT26,"no KPI data") -> 9191852.9 | BH26: n/a | BK26: =SUM(BK24:BK25) -> 12336 | BL26: =SUM(BL24:BL25) -> 3796608.4 | BM26: =IF(BC26>=Inputs!$B$38,BC26,MIN(BC26+'Dashboard (2)'!$N$2,Inputs!$B$38)) -> 0.89628539 | BN26: =BL26*BM26 -> 3402844.6 | BP26: =SUM(BP24:BP25) -> 6740027.6 | BQ26: =IF(ISNUMBER(BG26),BG26*BN26/BD26,"no KPI data") -> 10023540 | BR26: n/a
A27: PORTUGAL | B27: mixed | C27: =Dashboard!C18 -> 1858269.4 | D27: =Dashboard!D18 -> 3788245.6 | E27: =Dashboard!E18 -> 0.49053561 | F27: =Dashboard!F18 -> 0.018 | G27: =Dashboard!G18 -> 68188.422 | H27: =Dashboard!H18 -> 0.50853561 | I27: =Dashboard!I18 -> 1926457.8 | K27: CV N | L27: =PORTUGAL!C17 -> 739 | M27: =PORTUGAL!D9 -> 2206 | N27: =L27*M27 -> 1630234 | Q27: =IFERROR(R27/M27,0) -> 1120 | R27: =Inputs!$C$14*PORTUGAL!D9 -> 2470720 | U27: CV N | V27: =PORTUGAL!D17 -> 775.95 | W27: =PORTUGAL!E9 -> 2596 | X27: =V27*W27 -> 2014366.2 | AA27: =IFERROR(AB27/W27,0) -> 1176 | AB27: =Inputs!$C$14*(1+Inputs!$B$9)*PORTUGAL!E9 -> 3052896 | AE27: CV N | AF27: =PORTUGAL!E17 -> 799.2285 | AG27: =PORTUGAL!F9 -> 2974 | AH27: =AF27*AG27 -> 2376905.6 | AK27: =IFERROR(AL27/AG27,0) -> 1211.28 | AL27: =Inputs!$C$14*(1+Inputs!$B$9)*(1+'Dashboard (2)'!$T$1)*PORTUGAL!F9 -> 3602346.7 | AO27: CV N | AP27: =PORTUGAL!F17 -> 823.20536 | AQ27: =PORTUGAL!G9 -> 3341 | AR27: =AP27*AQ27 -> 2750329.1 | AU27: =IFERROR(AV27/AQ27,0) -> 1247.6184 | AV27: =Inputs!$C$14*(1+Inputs!$B$9)*(1+'Dashboard (2)'!$T$1)*(1+'Dashboard (2)'!$T$1)*PORTUGAL!G9 -> 4168293.1 | AY27: CV N | AZ27: =PORTUGAL!G17 -> 847.90152 | BA27: =PORTUGAL!H9 -> 3697 | BB27: =AZ27*BA27 -> 3134691.9 | BE27: =IFERROR(BF27/BA27,0) -> 1285.047 | BF27: =Inputs!$C$14*(1+Inputs!$B$9)*(1+'Dashboard (2)'!$T$1)*(1+'Dashboard (2)'!$T$1)*(1+'Dashboard (2)'!$T$1)*PORTUGAL!H9 -> 4750818.6 | BI27: CV N | BJ27: =PORTUGAL!H17 -> 873.33856 | BK27: =PORTUGAL!I9 -> 4042 | BL27: =BJ27*BK27 -> 3530034.5 | BO27: =IFERROR(BP27/BK27,0) -> 1323.5984 | BP27: =Inputs!$C$14*(1+Inputs!$B$9)*(1+'Dashboard (2)'!$T$1)*(1+'Dashboard (2)'!$T$1)*(1+'Dashboard (2)'!$T$1)*(1+'Dashboard (2)'!$T$1)*PORTUGAL!I9 -> 5349984.6
K28: CV F | L28: =IFERROR(N28/M28,0) -> 887 | M28: =PORTUGAL!D10+PORTUGAL!D11 -> 269 | N28: =PORTUGAL!C18*PORTUGAL!D10+PORTUGAL!C19*PORTUGAL!D11 -> 238603 | Q28: =IFERROR(R28/M28,0) -> 1344 | R28: =Inputs!$C$15*PORTUGAL!D10+Inputs!$C$15*PORTUGAL!D11 -> 361536 | U28: CV F | V28: =IFERROR(X28/W28,0) -> 931.35 | W28: =PORTUGAL!E10+PORTUGAL!E11 -> 357 | X28: =PORTUGAL!D18*PORTUGAL!E10+PORTUGAL!D19*PORTUGAL!E11 -> 332491.95 | AA28: =IFERROR(AB28/W28,0) -> 1411.2 | AB28: =Inputs!$C$15*(1+Inputs!$B$9)*PORTUGAL!E10+Inputs!$C$15*(1+Inputs!$B$9)*PORTUGAL!E11 -> 503798.4 | AE28: CV F | AF28: =IFERROR(AH28/AG28,0) -> 959.2905 | AG28: =PORTUGAL!F10+PORTUGAL!F11 -> 454 | AH28: =PORTUGAL!E18*PORTUGAL!F10+PORTUGAL!E19*PORTUGAL!F11 -> 435517.89 | AK28: =IFERROR(AL28/AG28,0) -> 1453.536 | AL28: =Inputs!$C$15*(1+Inputs!$B$9)*(1+'Dashboard (2)'!$T$1)*PORTUGAL!F10+Inputs!$C$15*(1+Inputs!$B$9)*(1+'Dashboard (2)'!$T$1)*PORTUGAL!F11 -> 659905.34 | AO28: CV F | AP28: =IFERROR(AR28/AQ28,0) -> 988.06921 | AQ28: =PORTUGAL!G10+PORTUGAL!G11 -> 548 | AR28: =PORTUGAL!F18*PORTUGAL!G10+PORTUGAL!F19*PORTUGAL!G11 -> 541461.93 | AU28: =IFERROR(AV28/AQ28,0) -> 1497.1421 | AV28: =Inputs!$C$15*(1+Inputs!$B$9)*(1+'Dashboard (2)'!$T$1)*(1+'Dashboard (2)'!$T$1)*PORTUGAL!G10+Inputs!$C$15*(1+Inputs!$B$9)*(1+'Dashboard (2)'!$T$1)*(1+'Dashboard (2)'!$T$1)*PORTUGAL!G11 -> 820433.86 | AY28: CV F | AZ28: =IFERROR(BB28/BA28,0) -> 1017.7113 | BA28: =PORTUGAL!H10+PORTUGAL!H11 -> 640 | BB28: =PORTUGAL!G18*PORTUGAL!H10+PORTUGAL!G19*PORTUGAL!H11 -> 651335.23 | BE28: =IFERROR(BF28/BA28,0) -> 1542.0563 | BF28: =Inputs!$C$15*(1+Inputs!$B$9)*(1+'Dashboard (2)'!$T$1)*(1+'Dashboard (2)'!$T$1)*(1+'Dashboard (2)'!$T$1)*PORTUGAL!H10+Inputs!$C$15*(1+Inputs!$B$9)*(1+'Dashboard (2)'!$T$1)*(1+'Dashboard (2)'!$T$1)*(1+'Dashboard (2)'!$T$1)*PORTUGAL!H11 -> 986916.06 | BI28: CV F | BJ28: =IFERROR(BL28/BK28,0) -> 1048.2426 | BK28: =PORTUGAL!I10+PORTUGAL!I11 -> 729 | BL28: =PORTUGAL!H18*PORTUGAL!I10+PORTUGAL!H19*PORTUGAL!I11 -> 764168.88 | BO28: =IFERROR(BP28/BK28,0) -> 1588.318 | BP28: =Inputs!$C$15*(1+Inputs!$B$9)*(1+'Dashboard (2)'!$T$1)*(1+'Dashboard (2)'!$T$1)*(1+'Dashboard (2)'!$T$1)*(1+'Dashboard (2)'!$T$1)*PORTUGAL!I10+Inputs!$C$15*(1+Inputs!$B$9)*(1+'Dashboard (2)'!$T$1)*(1+'Dashboard (2)'!$T$1)*(1+'Dashboard (2)'!$T$1)*(1+'Dashboard (2)'!$T$1)*PORTUGAL!I11 -> 1157883.8
K29: LCV | L29: =PORTUGAL!C20 -> 250 | M29: =PORTUGAL!D12 -> 4733 | N29: =L29*M29 -> 1183250 | Q29: =IFERROR(R29/M29,0) -> 448 | R29: =Inputs!$C$13*PORTUGAL!D12 -> 2120384 | U29: LCV | V29: =PORTUGAL!D20 -> 262.5 | W29: =PORTUGAL!E12 -> 5491 | X29: =V29*W29 -> 1441387.5 | AA29: =IFERROR(AB29/W29,0) -> 470.4 | AB29: =Inputs!$C$13*(1+Inputs!$B$9)*PORTUGAL!E12 -> 2582966.4 | AE29: LCV | AF29: =PORTUGAL!E20 -> 270.375 | AG29: =PORTUGAL!F12 -> 6226 | AH29: =AF29*AG29 -> 1683354.8 | AK29: =IFERROR(AL29/AG29,0) -> 484.512 | AL29: =Inputs!$C$13*(1+Inputs!$B$9)*(1+'Dashboard (2)'!$T$1)*PORTUGAL!F12 -> 3016571.7 | AO29: LCV | AP29: =PORTUGAL!F20 -> 278.48625 | AQ29: =PORTUGAL!G12 -> 6879 | AR29: =AP29*AQ29 -> 1915706.9 | AU29: =IFERROR(AV29/AQ29,0) -> 499.04736 | AV29: =Inputs!$C$13*(1+Inputs!$B$9)*(1+'Dashboard (2)'!$T$1)*(1+'Dashboard (2)'!$T$1)*PORTUGAL!G12 -> 3432946.8 | AY29: LCV | AZ29: =PORTUGAL!G20 -> 286.84084 | BA29: =PORTUGAL!H12 -> 7513 | BB29: =AZ29*BA29 -> 2155035.2 | BE29: =IFERROR(BF29/BA29,0) -> 514.01878 | BF29: =Inputs!$C$13*(1+Inputs!$B$9)*(1+'Dashboard (2)'!$T$1)*(1+'Dashboard (2)'!$T$1)*(1+'Dashboard (2)'!$T$1)*PORTUGAL!H12 -> 3861823.1 | BI29: LCV | BJ29: =PORTUGAL!H20 -> 295.44606 | BK29: =PORTUGAL!I12 -> 8128 | BL29: =BJ29*BK29 -> 2401385.6 | BO29: =IFERROR(BP29/BK29,0) -> 529.43934 | BP29: =Inputs!$C$13*(1+Inputs!$B$9)*(1+'Dashboard (2)'!$T$1)*(1+'Dashboard (2)'!$T$1)*(1+'Dashboard (2)'!$T$1)*(1+'Dashboard (2)'!$T$1)*PORTUGAL!I12 -> 4303283
M30: =SUM(M27:M29) -> 7208 | N30: =SUM(N27:N29) -> 3052087 | O30: =PORTUGAL!D26 -> 1813146.9 | P30: =O30/N30 -> 0.59406788 | R30: =SUM(R27:R29) -> 4952640 | S30: =IF(ISNUMBER(Dashboard!Q18),Dashboard!Q18,"no KPI data") -> 4047903 | T30: n/a | W30: =SUM(W27:W29) -> 8444 | X30: =SUM(X27:X29) -> 3788245.6 | Y30: =Z30/X30 -> 0.50853561 | Z30: =PORTUGAL!E30 -> 1926457.8 | AB30: =SUM(AB27:AB29) -> 6139660.8 | AC30: =IF(ISNUMBER(S30),S30+Dashboard!G18/(1-Inputs!$B$18),"no KPI data") -> 4152808.3 | AD30: n/a | AG30: =SUM(AG27:AG29) -> 9654 | AH30: =SUM(AH27:AH29) -> 4495778.2 | AI30: =IF(Y30>=Inputs!$B$38,Y30,MIN(Y30+'Dashboard (2)'!$N$2,Inputs!$B$38)) -> 0.51853561 | AJ30: =AH30*AI30 -> 2331221.1 | AL30: =SUM(AL27:AL29) -> 7278823.8 | AM30: =IF(ISNUMBER(AC30),AC30*AJ30/Z30,"no KPI data") -> 5025344.5 | AN30: n/a | AQ30: =SUM(AQ27:AQ29) -> 10768 | AR30: =SUM(AR27:AR29) -> 5207497.9 | AS30: =IF(AI30>=Inputs!$B$38,AI30,MIN(AI30+'Dashboard (2)'!$N$2,Inputs!$B$38)) -> 0.52853561 | AT30: =AR30*AS30 -> 2752348.1 | AV30: =SUM(AV27:AV29) -> 8421673.7 | AW30: =IF(ISNUMBER(AM30),AM30*AT30/AJ30,"no KPI data") -> 5933155.6 | AX30: n/a | BA30: =SUM(BA27:BA29) -> 11850 | BB30: =SUM(BB27:BB29) -> 5941062.3 | BC30: =IF(AS30>=Inputs!$B$38,AS30,MIN(AS30+'Dashboard (2)'!$N$2,Inputs!$B$38)) -> 0.53853561 | BD30: =BB30*BC30 -> 3199473.6 | BF30: =SUM(BF27:BF29) -> 9599557.7 | BG30: =IF(ISNUMBER(AW30),AW30*BD30/AT30,"no KPI data") -> 6897010.9 | BH30: n/a | BK30: =SUM(BK27:BK29) -> 12899 | BL30: =SUM(BL27:BL29) -> 6695588.9 | BM30: =IF(BC30>=Inputs!$B$38,BC30,MIN(BC30+'Dashboard (2)'!$N$2,Inputs!$B$38)) -> 0.54853561 | BN30: =BL30*BM30 -> 3672769 | BP30: =SUM(BP27:BP29) -> 10811151 | BQ30: =IF(ISNUMBER(BG30),BG30*BN30/BD30,"no KPI data") -> 7917279.7 | BR30: n/a
A31: IRELAND | B31: mixed | C31: =Dashboard!C19 -> 1267443.4 | D31: =Dashboard!D19 -> 1287772.5 | E31: =Dashboard!E19 -> 0.98421371 | F31: =Dashboard!F19 -> 0.018 | G31: =Dashboard!G19 -> 23179.905 | H31: =Dashboard!H19 -> 1.0022137 | I31: =Dashboard!I19 -> 1290623.3 | K31: CV N | L31: =IRELAND!C17 -> 739 | M31: =IRELAND!D9 -> 731 | N31: =L31*M31 -> 540209 | Q31: =IFERROR(R31/M31,0) -> 1120 | R31: =Inputs!$C$14*IRELAND!D9 -> 818720 | U31: CV N | V31: =IRELAND!D17 -> 775.95 | W31: =IRELAND!E9 -> 925 | X31: =V31*W31 -> 717753.75 | AA31: =IFERROR(AB31/W31,0) -> 1176 | AB31: =Inputs!$C$14*(1+Inputs!$B$9)*IRELAND!E9 -> 1087800 | AE31: CV N | AF31: =IRELAND!E17 -> 799.2285 | AG31: =IRELAND!F9 -> 1113 | AH31: =AF31*AG31 -> 889541.32 | AK31: =IFERROR(AL31/AG31,0) -> 1211.28 | AL31: =Inputs!$C$14*(1+Inputs!$B$9)*(1+'Dashboard (2)'!$T$1)*IRELAND!F9 -> 1348154.6 | AO31: CV N | AP31: =IRELAND!F17 -> 823.20536 | AQ31: =IRELAND!G9 -> 1296 | AR31: =AP31*AQ31 -> 1066874.1 | AU31: =IFERROR(AV31/AQ31,0) -> 1247.6184 | AV31: =Inputs!$C$14*(1+Inputs!$B$9)*(1+'Dashboard (2)'!$T$1)*(1+'Dashboard (2)'!$T$1)*IRELAND!G9 -> 1616913.4 | AY31: CV N | AZ31: =IRELAND!G17 -> 847.90152 | BA31: =IRELAND!H9 -> 1473 | BB31: =AZ31*BA31 -> 1248958.9 | BE31: =IFERROR(BF31/BA31,0) -> 1285.047 | BF31: =Inputs!$C$14*(1+Inputs!$B$9)*(1+'Dashboard (2)'!$T$1)*(1+'Dashboard (2)'!$T$1)*(1+'Dashboard (2)'!$T$1)*IRELAND!H9 -> 1892874.2 | BI31: CV N | BJ31: =IRELAND!H17 -> 873.33856 | BK31: =IRELAND!I9 -> 1645 | BL31: =BJ31*BK31 -> 1436641.9 | BO31: =IFERROR(BP31/BK31,0) -> 1323.5984 | BP31: =Inputs!$C$14*(1+Inputs!$B$9)*(1+'Dashboard (2)'!$T$1)*(1+'Dashboard (2)'!$T$1)*(1+'Dashboard (2)'!$T$1)*(1+'Dashboard (2)'!$T$1)*IRELAND!I9 -> 2177319.3
K32: CV F | L32: =IFERROR(N32/M32,0) -> 887 | M32: =IRELAND!D10+IRELAND!D11 -> 92 | N32: =IRELAND!C18*IRELAND!D10+IRELAND!C19*IRELAND!D11 -> 81604 | Q32: =IFERROR(R32/M32,0) -> 1344 | R32: =Inputs!$C$15*IRELAND!D10+Inputs!$C$15*IRELAND!D11 -> 123648 | U32: CV F | V32: =IFERROR(X32/W32,0) -> 931.35 | W32: =IRELAND!E10+IRELAND!E11 -> 125 | X32: =IRELAND!D18*IRELAND!E10+IRELAND!D19*IRELAND!E11 -> 116418.75 | AA32: =IFERROR(AB32/W32,0) -> 1411.2 | AB32: =Inputs!$C$15*(1+Inputs!$B$9)*IRELAND!E10+Inputs!$C$15*(1+Inputs!$B$9)*IRELAND!E11 -> 176400 | AE32: CV F | AF32: =IFERROR(AH32/AG32,0) -> 959.2905 | AG32: =IRELAND!F10+IRELAND!F11 -> 157 | AH32: =IRELAND!E18*IRELAND!F10+IRELAND!E19*IRELAND!F11 -> 150608.61 | AK32: =IFERROR(AL32/AG32,0) -> 1453.536 | AL32: =Inputs!$C$15*(1+Inputs!$B$9)*(1+'Dashboard (2)'!$T$1)*IRELAND!F10+Inputs!$C$15*(1+Inputs!$B$9)*(1+'Dashboard (2)'!$T$1)*IRELAND!F11 -> 228205.15 | AO32: CV F | AP32: =IFERROR(AR32/AQ32,0) -> 988.06921 | AQ32: =IRELAND!G10+IRELAND!G11 -> 188 | AR32: =IRELAND!F18*IRELAND!G10+IRELAND!F19*IRELAND!G11 -> 185757.01 | AU32: =IFERROR(AV32/AQ32,0) -> 1497.1421 | AV32: =Inputs!$C$15*(1+Inputs!$B$9)*(1+'Dashboard (2)'!$T$1)*(1+'Dashboard (2)'!$T$1)*IRELAND!G10+Inputs!$C$15*(1+Inputs!$B$9)*(1+'Dashboard (2)'!$T$1)*(1+'Dashboard (2)'!$T$1)*IRELAND!G11 -> 281462.71 | AY32: CV F | AZ32: =IFERROR(BB32/BA32,0) -> 1017.7113 | BA32: =IRELAND!H10+IRELAND!H11 -> 219 | BB32: =IRELAND!G18*IRELAND!H10+IRELAND!G19*IRELAND!H11 -> 222878.77 | BE32: =IFERROR(BF32/BA32,0) -> 1542.0563 | BF32: =Inputs!$C$15*(1+Inputs!$B$9)*(1+'Dashboard (2)'!$T$1)*(1+'Dashboard (2)'!$T$1)*(1+'Dashboard (2)'!$T$1)*IRELAND!H10+Inputs!$C$15*(1+Inputs!$B$9)*(1+'Dashboard (2)'!$T$1)*(1+'Dashboard (2)'!$T$1)*(1+'Dashboard (2)'!$T$1)*IRELAND!H11 -> 337710.34 | BI32: CV F | BJ32: =IFERROR(BL32/BK32,0) -> 1048.2426 | BK32: =IRELAND!I10+IRELAND!I11 -> 249 | BL32: =IRELAND!H18*IRELAND!I10+IRELAND!H19*IRELAND!I11 -> 261012.41 | BO32: =IFERROR(BP32/BK32,0) -> 1588.318 | BP32: =Inputs!$C$15*(1+Inputs!$B$9)*(1+'Dashboard (2)'!$T$1)*(1+'Dashboard (2)'!$T$1)*(1+'Dashboard (2)'!$T$1)*(1+'Dashboard (2)'!$T$1)*IRELAND!I10+Inputs!$C$15*(1+Inputs!$B$9)*(1+'Dashboard (2)'!$T$1)*(1+'Dashboard (2)'!$T$1)*(1+'Dashboard (2)'!$T$1)*(1+'Dashboard (2)'!$T$1)*IRELAND!I11 -> 395491.19
K33: LCV | L33: =IRELAND!C20 -> 250 | M33: =IRELAND!D12 -> 1338 | N33: =L33*M33 -> 334500 | Q33: =IFERROR(R33/M33,0) -> 448 | R33: =Inputs!$C$13*IRELAND!D12 -> 599424 | U33: LCV | V33: =IRELAND!D20 -> 262.5 | W33: =IRELAND!E12 -> 1728 | X33: =V33*W33 -> 453600 | AA33: =IFERROR(AB33/W33,0) -> 470.4 | AB33: =Inputs!$C$13*(1+Inputs!$B$9)*IRELAND!E12 -> 812851.2 | AE33: LCV | AF33: =IRELAND!E20 -> 270.375 | AG33: =IRELAND!F12 -> 2106 | AH33: =AF33*AG33 -> 569409.75 | AK33: =IFERROR(AL33/AG33,0) -> 484.512 | AL33: =Inputs!$C$13*(1+Inputs!$B$9)*(1+'Dashboard (2)'!$T$1)*IRELAND!F12 -> 1020382.3 | AO33: LCV | AP33: =IRELAND!F20 -> 278.48625 | AQ33: =IRELAND!G12 -> 2473 | AR33: =AP33*AQ33 -> 688696.5 | AU33: =IFERROR(AV33/AQ33,0) -> 499.04736 | AV33: =Inputs!$C$13*(1+Inputs!$B$9)*(1+'Dashboard (2)'!$T$1)*(1+'Dashboard (2)'!$T$1)*IRELAND!G12 -> 1234144.1 | AY33: LCV | AZ33: =IRELAND!G20 -> 286.84084 | BA33: =IRELAND!H12 -> 2829 | BB33: =AZ33*BA33 -> 811472.73 | BE33: =IFERROR(BF33/BA33,0) -> 514.01878 | BF33: =Inputs!$C$13*(1+Inputs!$B$9)*(1+'Dashboard (2)'!$T$1)*(1+'Dashboard (2)'!$T$1)*(1+'Dashboard (2)'!$T$1)*IRELAND!H12 -> 1454159.1 | BI33: LCV | BJ33: =IRELAND!H20 -> 295.44606 | BK33: =IRELAND!I12 -> 3174 | BL33: =BJ33*BK33 -> 937745.8 | BO33: =IFERROR(BP33/BK33,0) -> 529.43934 | BP33: =Inputs!$C$13*(1+Inputs!$B$9)*(1+'Dashboard (2)'!$T$1)*(1+'Dashboard (2)'!$T$1)*(1+'Dashboard (2)'!$T$1)*(1+'Dashboard (2)'!$T$1)*IRELAND!I12 -> 1680440.5
M34: =SUM(M31:M33) -> 2161 | N34: =SUM(N31:N33) -> 956313 | O34: =IRELAND!D26 -> 1116861.5 | P34: =O34/N34 -> 1.1678828 | R34: =SUM(R31:R33) -> 1541792 | S34: =IF(ISNUMBER(Dashboard!Q19),Dashboard!Q19,"no KPI data") -> 2833637 | T34: n/a | W34: =SUM(W31:W33) -> 2778 | X34: =SUM(X31:X33) -> 1287772.5 | Y34: =Z34/X34 -> 1.0022137 | Z34: =IRELAND!E30 -> 1290623.3 | AB34: =SUM(AB31:AB33) -> 2077051.2 | AC34: =IF(ISNUMBER(S34),S34+Dashboard!G19/(1-Inputs!$B$18),"no KPI data") -> 2869298.4 | AD34: n/a | AG34: =SUM(AG31:AG33) -> 3376 | AH34: =SUM(AH31:AH33) -> 1609559.7 | AI34: =IF(Y34>=Inputs!$B$38,Y34,MIN(Y34+'Dashboard (2)'!$N$2,Inputs!$B$38)) -> 1.0122137 | AJ34: =AH34*AI34 -> 1629218.4 | AL34: =SUM(AL31:AL33) -> 2596742.1 | AM34: =IF(ISNUMBER(AC34),AC34*AJ34/Z34,"no KPI data") -> 3622059.1 | AN34: n/a | AQ34: =SUM(AQ31:AQ33) -> 3957 | AR34: =SUM(AR31:AR33) -> 1941327.6 | AS34: =IF(AI34>=Inputs!$B$38,AI34,MIN(AI34+'Dashboard (2)'!$N$2,Inputs!$B$38)) -> 1.0222137 | AT34: =AR34*AS34 -> 1984451.7 | AV34: =SUM(AV31:AV33) -> 3132520.3 | AW34: =IF(ISNUMBER(AM34),AM34*AT34/AJ34,"no KPI data") -> 4411809.7 | AX34: n/a | BA34: =SUM(BA31:BA33) -> 4521 | BB34: =SUM(BB31:BB33) -> 2283310.4 | BC34: =IF(AS34>=Inputs!$B$38,AS34,MIN(AS34+'Dashboard (2)'!$N$2,Inputs!$B$38)) -> 1.0322137 | BD34: =BB34*BC34 -> 2356864.3 | BF34: =SUM(BF31:BF33) -> 3684743.6 | BG34: =IF(ISNUMBER(AW34),AW34*BD34/AT34,"no KPI data") -> 5239753 | BH34: n/a | BK34: =SUM(BK31:BK33) -> 5068 | BL34: =SUM(BL31:BL33) -> 2635400.2 | BM34: =IF(BC34>=Inputs!$B$38,BC34,MIN(BC34+'Dashboard (2)'!$N$2,Inputs!$B$38)) -> 1.0422137 | BN34: =BL34*BM34 -> 2746650.2 | BP34: =SUM(BP31:BP33) -> 4253251 | BQ34: =IF(ISNUMBER(BG34),BG34*BN34/BD34,"no KPI data") -> 6106320.2 | BR34: n/a
A35: GREECE | B35: mixed | C35: =Dashboard!C20 -> 574400 | D35: =Dashboard!D20 -> 1156909.9 | E35: =Dashboard!E20 -> 0.496495 | F35: =Dashboard!F20 -> 0.018 | G35: =Dashboard!G20 -> 20824.379 | H35: =Dashboard!H20 -> 0.514495 | I35: =Dashboard!I20 -> 595224.38 | K35: CV N+MD | L35: =IFERROR(N35/M35,0) -> 739 | M35: =GREECE!D9+GREECE!D10 -> 37 | N35: =GREECE!C17*GREECE!D9+GREECE!C18*GREECE!D10 -> 27343 | Q35: =IFERROR(R35/M35,0) -> 1120 | R35: =Inputs!$C$14*GREECE!D9+Inputs!$C$15*GREECE!D10 -> 41440 | U35: CV N+MD | V35: =IFERROR(X35/W35,0) -> 788.6877 | W35: =GREECE!E9+GREECE!E10 -> 61 | X35: =GREECE!D17*GREECE!E9+GREECE!D18*GREECE!E10 -> 48109.95 | AA35: =IFERROR(AB35/W35,0) -> 1195.2787 | AB35: =Inputs!$C$14*(1+Inputs!$B$9)*GREECE!E9+Inputs!$C$15*(1+Inputs!$B$9)*GREECE!E10 -> 72912 | AE35: CV N+MD | AF35: =IFERROR(AH35/AG35,0) -> 818.2835 | AG35: =GREECE!F9+GREECE!F10 -> 84 | AH35: =GREECE!E17*GREECE!F9+GREECE!E18*GREECE!F10 -> 68735.814 | AK35: =IFERROR(AL35/AG35,0) -> 1240.12 | AL35: =Inputs!$C$14*(1+Inputs!$B$9)*(1+'Dashboard (2)'!$T$1)*GREECE!F9+Inputs!$C$15*(1+Inputs!$B$9)*(1+'Dashboard (2)'!$T$1)*GREECE!F10 -> 104170.08 | AO35: CV N+MD | AP35: =IFERROR(AR35/AQ35,0) -> 846.31711 | AQ35: =GREECE!G9+GREECE!G10 -> 107 | AR35: =GREECE!F17*GREECE!G9+GREECE!F18*GREECE!G10 -> 90555.931 | AU35: =IFERROR(AV35/AQ35,0) -> 1282.5984 | AV35: =Inputs!$C$14*(1+Inputs!$B$9)*(1+'Dashboard (2)'!$T$1)*(1+'Dashboard (2)'!$T$1)*GREECE!G9+Inputs!$C$15*(1+Inputs!$B$9)*(1+'Dashboard (2)'!$T$1)*(1+'Dashboard (2)'!$T$1)*GREECE!G10 -> 137238.02 | AY35: CV N+MD | AZ35: =IFERROR(BB35/BA35,0) -> 874.22861 | BA35: =GREECE!H9+GREECE!H10 -> 129 | BB35: =GREECE!G17*GREECE!H9+GREECE!G18*GREECE!H10 -> 112775.49 | BE35: =IFERROR(BF35/BA35,0) -> 1324.8934 | BF35: =Inputs!$C$14*(1+Inputs!$B$9)*(1+'Dashboard (2)'!$T$1)*(1+'Dashboard (2)'!$T$1)*(1+'Dashboard (2)'!$T$1)*GREECE!H9+Inputs!$C$15*(1+Inputs!$B$9)*(1+'Dashboard (2)'!$T$1)*(1+'Dashboard (2)'!$T$1)*(1+'Dashboard (2)'!$T$1)*GREECE!H10 -> 170911.24 | BI35: CV N+MD | BJ35: =IFERROR(BL35/BK35,0) -> 901.32321 | BK35: =GREECE!I9+GREECE!I10 -> 150 | BL35: =GREECE!H17*GREECE!I9+GREECE!H18*GREECE!I10 -> 135198.48 | BO35: =IFERROR(BP35/BK35,0) -> 1365.9535 | BP35: =Inputs!$C$14*(1+Inputs!$B$9)*(1+'Dashboard (2)'!$T$1)*(1+'Dashboard (2)'!$T$1)*(1+'Dashboard (2)'!$T$1)*(1+'Dashboard (2)'!$T$1)*GREECE!I9+Inputs!$C$15*(1+Inputs!$B$9)*(1+'Dashboard (2)'!$T$1)*(1+'Dashboard (2)'!$T$1)*(1+'Dashboard (2)'!$T$1)*(1+'Dashboard (2)'!$T$1)*GREECE!I10 -> 204893.03
K36: LCV | L36: =GREECE!C20 -> 250 | M36: =GREECE!D12 -> 3705 | N36: =L36*M36 -> 926250 | Q36: =IFERROR(R36/M36,0) -> 448 | R36: =Inputs!$C$13*GREECE!D12 -> 1659840 | U36: LCV | V36: =GREECE!D20 -> 262.5 | W36: =GREECE!E12 -> 4224 | X36: =V36*W36 -> 1108800 | AA36: =IFERROR(AB36/W36,0) -> 470.4 | AB36: =Inputs!$C$13*(1+Inputs!$B$9)*GREECE!E12 -> 1986969.6 | AE36: LCV | AF36: =GREECE!E20 -> 270.375 | AG36: =GREECE!F12 -> 4727 | AH36: =AF36*AG36 -> 1278062.6 | AK36: =IFERROR(AL36/AG36,0) -> 484.512 | AL36: =Inputs!$C$13*(1+Inputs!$B$9)*(1+'Dashboard (2)'!$T$1)*GREECE!F12 -> 2290288.2 | AO36: LCV | AP36: =GREECE!F20 -> 278.48625 | AQ36: =GREECE!G12 -> 5215 | AR36: =AP36*AQ36 -> 1452305.8 | AU36: =IFERROR(AV36/AQ36,0) -> 499.04736 | AV36: =Inputs!$C$13*(1+Inputs!$B$9)*(1+'Dashboard (2)'!$T$1)*(1+'Dashboard (2)'!$T$1)*GREECE!G12 -> 2602532 | AY36: LCV | AZ36: =GREECE!G20 -> 286.84084 | BA36: =GREECE!H12 -> 5689 | BB36: =AZ36*BA36 -> 1631837.5 | BE36: =IFERROR(BF36/BA36,0) -> 514.01878 | BF36: =Inputs!$C$13*(1+Inputs!$B$9)*(1+'Dashboard (2)'!$T$1)*(1+'Dashboard (2)'!$T$1)*(1+'Dashboard (2)'!$T$1)*GREECE!H12 -> 2924252.8 | BI36: LCV | BJ36: =GREECE!H20 -> 295.44606 | BK36: =GREECE!I12 -> 6148 | BL36: =BJ36*BK36 -> 1816402.4 | BO36: =IFERROR(BP36/BK36,0) -> 529.43934 | BP36: =Inputs!$C$13*(1+Inputs!$B$9)*(1+'Dashboard (2)'!$T$1)*(1+'Dashboard (2)'!$T$1)*(1+'Dashboard (2)'!$T$1)*(1+'Dashboard (2)'!$T$1)*GREECE!I12 -> 3254993.1
M37: =SUM(M35:M36) -> 3742 | N37: =SUM(N35:N36) -> 953593 | O37: =GREECE!D26 -> 460633.72 | P37: =O37/N37 -> 0.48305065 | R37: =SUM(R35:R36) -> 1701280 | S37: =IF(ISNUMBER(Dashboard!Q20),Dashboard!Q20,"no KPI data") -> no KPI data | T37: n/a | W37: =SUM(W35:W36) -> 4285 | X37: =SUM(X35:X36) -> 1156909.9 | Y37: =Z37/X37 -> 0.514495 | Z37: =GREECE!E30 -> 595224.38 | AB37: =SUM(AB35:AB36) -> 2059881.6 | AC37: =IF(ISNUMBER(S37),S37+Dashboard!G20/(1-Inputs!$B$18),"no KPI data") -> no KPI data | AD37: n/a | AG37: =SUM(AG35:AG36) -> 4811 | AH37: =SUM(AH35:AH36) -> 1346798.4 | AI37: =IF(Y37>=Inputs!$B$38,Y37,MIN(Y37+'Dashboard (2)'!$N$2,Inputs!$B$38)) -> 0.524495 | AJ37: =AH37*AI37 -> 706389.04 | AL37: =SUM(AL35:AL36) -> 2394458.3 | AM37: =IF(ISNUMBER(AC37),AC37*AJ37/Z37,"no KPI data") -> no KPI data | AN37: n/a | AQ37: =SUM(AQ35:AQ36) -> 5322 | AR37: =SUM(AR35:AR36) -> 1542861.7 | AS37: =IF(AI37>=Inputs!$B$38,AI37,MIN(AI37+'Dashboard (2)'!$N$2,Inputs!$B$38)) -> 0.534495 | AT37: =AR37*AS37 -> 824651.87 | AV37: =SUM(AV35:AV36) -> 2739770 | AW37: =IF(ISNUMBER(AM37),AM37*AT37/AJ37,"no KPI data") -> no KPI data | AX37: n/a | BA37: =SUM(BA35:BA36) -> 5818 | BB37: =SUM(BB35:BB36) -> 1744613 | BC37: =IF(AS37>=Inputs!$B$38,AS37,MIN(AS37+'Dashboard (2)'!$N$2,Inputs!$B$38)) -> 0.544495 | BD37: =BB37*BC37 -> 949933.06 | BF37: =SUM(BF35:BF36) -> 3095164.1 | BG37: =IF(ISNUMBER(AW37),AW37*BD37/AT37,"no KPI data") -> no KPI data | BH37: n/a | BK37: =SUM(BK35:BK36) -> 6298 | BL37: =SUM(BL35:BL36) -> 1951600.9 | BM37: =IF(BC37>=Inputs!$B$38,BC37,MIN(BC37+'Dashboard (2)'!$N$2,Inputs!$B$38)) -> 0.554495 | BN37: =BL37*BM37 -> 1082152.9 | BP37: =SUM(BP35:BP36) -> 3459886.1 | BQ37: =IF(ISNUMBER(BG37),BG37*BN37/BD37,"no KPI data") -> no KPI data | BR37: n/a
A38: CYPRUS | B38: mixed | C38: =Dashboard!C21 -> 539600 | D38: =Dashboard!D21 -> 811322.4 | E38: =Dashboard!E21 -> 0.66508702 | F38: =Dashboard!F21 -> 0.018 | G38: =Dashboard!G21 -> 14603.803 | H38: =Dashboard!H21 -> 0.68308702 | I38: =Dashboard!I21 -> 554203.8 | K38: CV N+MD | L38: =IFERROR(N38/M38,0) -> 739 | M38: =CYPRUS!D9+CYPRUS!D10 -> 203 | N38: =CYPRUS!C17*CYPRUS!D9+CYPRUS!C18*CYPRUS!D10 -> 150017 | Q38: =IFERROR(R38/M38,0) -> 1120 | R38: =Inputs!$C$14*CYPRUS!D9+Inputs!$C$15*CYPRUS!D10 -> 227360 | U38: CV N+MD | V38: =IFERROR(X38/W38,0) -> 779.29914 | W38: =CYPRUS!E9+CYPRUS!E10 -> 232 | X38: =CYPRUS!D17*CYPRUS!E9+CYPRUS!D18*CYPRUS!E10 -> 180797.4 | AA38: =IFERROR(AB38/W38,0) -> 1181.069 | AB38: =Inputs!$C$14*(1+Inputs!$B$9)*CYPRUS!E9+Inputs!$C$15*(1+Inputs!$B$9)*CYPRUS!E10 -> 274008 | AE38: CV N+MD | AF38: =IFERROR(AH38/AG38,0) -> 805.38473 | AG38: =CYPRUS!F9+CYPRUS!F10 -> 260 | AH38: =CYPRUS!E17*CYPRUS!F9+CYPRUS!E18*CYPRUS!F10 -> 209400.03 | AK38: =IFERROR(AL38/AG38,0) -> 1220.5975 | AL38: =Inputs!$C$14*(1+Inputs!$B$9)*(1+'Dashboard (2)'!$T$1)*CYPRUS!F9+Inputs!$C$15*(1+Inputs!$B$9)*(1+'Dashboard (2)'!$T$1)*CYPRUS!F10 -> 317355.36 | AO38: CV N+MD | AP38: =IFERROR(AR38/AQ38,0) -> 831.82193 | AQ38: =CYPRUS!G9+CYPRUS!G10 -> 287 | AR38: =CYPRUS!F17*CYPRUS!G9+CYPRUS!F18*CYPRUS!G10 -> 238732.89 | AU38: =IFERROR(AV38/AQ38,0) -> 1260.6597 | AV38: =Inputs!$C$14*(1+Inputs!$B$9)*(1+'Dashboard (2)'!$T$1)*(1+'Dashboard (2)'!$T$1)*CYPRUS!G9+Inputs!$C$15*(1+Inputs!$B$9)*(1+'Dashboard (2)'!$T$1)*(1+'Dashboard (2)'!$T$1)*CYPRUS!G10 -> 361809.34 | AY38: CV N+MD | AZ38: =IFERROR(BB38/BA38,0) -> 858.71742 | BA38: =CYPRUS!H9+CYPRUS!H10 -> 314 | BB38: =CYPRUS!G17*CYPRUS!H9+CYPRUS!G18*CYPRUS!H10 -> 269637.27 | BE38: =IFERROR(BF38/BA38,0) -> 1301.417 | BF38: =Inputs!$C$14*(1+Inputs!$B$9)*(1+'Dashboard (2)'!$T$1)*(1+'Dashboard (2)'!$T$1)*(1+'Dashboard (2)'!$T$1)*CYPRUS!H9+Inputs!$C$15*(1+Inputs!$B$9)*(1+'Dashboard (2)'!$T$1)*(1+'Dashboard (2)'!$T$1)*(1+'Dashboard (2)'!$T$1)*CYPRUS!H10 -> 408644.93 | BI38: CV N+MD | BJ38: =IFERROR(BL38/BK38,0) -> 885.72115 | BK38: =CYPRUS!I9+CYPRUS!I10 -> 339 | BL38: =CYPRUS!H17*CYPRUS!I9+CYPRUS!H18*CYPRUS!I10 -> 300259.47 | BO38: =IFERROR(BP38/BK38,0) -> 1342.3396 | BP38: =Inputs!$C$14*(1+Inputs!$B$9)*(1+'Dashboard (2)'!$T$1)*(1+'Dashboard (2)'!$T$1)*(1+'Dashboard (2)'!$T$1)*(1+'Dashboard (2)'!$T$1)*CYPRUS!I9+Inputs!$C$15*(1+Inputs!$B$9)*(1+'Dashboard (2)'!$T$1)*(1+'Dashboard (2)'!$T$1)*(1+'Dashboard (2)'!$T$1)*(1+'Dashboard (2)'!$T$1)*CYPRUS!I10 -> 455053.12
K39: LCV | L39: =CYPRUS!C20 -> 250 | M39: =CYPRUS!D12 -> 2105 | N39: =L39*M39 -> 526250 | Q39: =IFERROR(R39/M39,0) -> 448 | R39: =Inputs!$C$13*CYPRUS!D12 -> 943040 | U39: LCV | V39: =CYPRUS!D20 -> 262.5 | W39: =CYPRUS!E12 -> 2402 | X39: =V39*W39 -> 630525 | AA39: =IFERROR(AB39/W39,0) -> 470.4 | AB39: =Inputs!$C$13*(1+Inputs!$B$9)*CYPRUS!E12 -> 1129900.8 | AE39: LCV | AF39: =CYPRUS!E20 -> 270.375 | AG39: =CYPRUS!F12 -> 2730 | AH39: =AF39*AG39 -> 738123.75 | AK39: =IFERROR(AL39/AG39,0) -> 484.512 | AL39: =Inputs!$C$13*(1+Inputs!$B$9)*(1+'Dashboard (2)'!$T$1)*CYPRUS!F12 -> 1322717.8 | AO39: LCV | AP39: =CYPRUS!F20 -> 278.48625 | AQ39: =CYPRUS!G12 -> 3008 | AR39: =AP39*AQ39 -> 837686.64 | AU39: =IFERROR(AV39/AQ39,0) -> 499.04736 | AV39: =Inputs!$C$13*(1+Inputs!$B$9)*(1+'Dashboard (2)'!$T$1)*(1+'Dashboard (2)'!$T$1)*CYPRUS!G12 -> 1501134.5 | AY39: LCV | AZ39: =CYPRUS!G20 -> 286.84084 | BA39: =CYPRUS!H12 -> 3278 | BB39: =AZ39*BA39 -> 940264.27 | BE39: =IFERROR(BF39/BA39,0) -> 514.01878 | BF39: =Inputs!$C$13*(1+Inputs!$B$9)*(1+'Dashboard (2)'!$T$1)*(1+'Dashboard (2)'!$T$1)*(1+'Dashboard (2)'!$T$1)*CYPRUS!H12 -> 1684953.6 | BI39: LCV | BJ39: =CYPRUS!H20 -> 295.44606 | BK39: =CYPRUS!I12 -> 3540 | BL39: =BJ39*BK39 -> 1045879.1 | BO39: =IFERROR(BP39/BK39,0) -> 529.43934 | BP39: =Inputs!$C$13*(1+Inputs!$B$9)*(1+'Dashboard (2)'!$T$1)*(1+'Dashboard (2)'!$T$1)*(1+'Dashboard (2)'!$T$1)*(1+'Dashboard (2)'!$T$1)*CYPRUS!I12 -> 1874215.3
M40: =SUM(M38:M39) -> 2308 | N40: =SUM(N38:N39) -> 676267 | O40: =CYPRUS!D26 -> 401055.88 | P40: =O40/N40 -> 0.59304369 | R40: =SUM(R38:R39) -> 1170400 | S40: =IF(ISNUMBER(Dashboard!Q21),Dashboard!Q21,"no KPI data") -> no KPI data | T40: n/a | W40: =SUM(W38:W39) -> 2634 | X40: =SUM(X38:X39) -> 811322.4 | Y40: =Z40/X40 -> 0.68308702 | Z40: =CYPRUS!E30 -> 554203.8 | AB40: =SUM(AB38:AB39) -> 1403908.8 | AC40: =IF(ISNUMBER(S40),S40+Dashboard!G21/(1-Inputs!$B$18),"no KPI data") -> no KPI data | AD40: n/a | AG40: =SUM(AG38:AG39) -> 2990 | AH40: =SUM(AH38:AH39) -> 947523.78 | AI40: =IF(Y40>=Inputs!$B$38,Y40,MIN(Y40+'Dashboard (2)'!$N$2,Inputs!$B$38)) -> 0.69308702 | AJ40: =AH40*AI40 -> 656716.44 | AL40: =SUM(AL38:AL39) -> 1640073.1 | AM40: =IF(ISNUMBER(AC40),AC40*AJ40/Z40,"no KPI data") -> no KPI data | AN40: n/a | AQ40: =SUM(AQ38:AQ39) -> 3295 | AR40: =SUM(AR38:AR39) -> 1076419.5 | AS40: =IF(AI40>=Inputs!$B$38,AI40,MIN(AI40+'Dashboard (2)'!$N$2,Inputs!$B$38)) -> 0.70308702 | AT40: =AR40*AS40 -> 756816.61 | AV40: =SUM(AV38:AV39) -> 1862943.8 | AW40: =IF(ISNUMBER(AM40),AM40*AT40/AJ40,"no KPI data") -> no KPI data | AX40: n/a | BA40: =SUM(BA38:BA39) -> 3592 | BB40: =SUM(BB38:BB39) -> 1209901.5 | BC40: =IF(AS40>=Inputs!$B$38,AS40,MIN(AS40+'Dashboard (2)'!$N$2,Inputs!$B$38)) -> 0.71308702 | BD40: =BB40*BC40 -> 862765.09 | BF40: =SUM(BF38:BF39) -> 2093598.5 | BG40: =IF(ISNUMBER(AW40),AW40*BD40/AT40,"no KPI data") -> no KPI data | BH40: n/a | BK40: =SUM(BK38:BK39) -> 3879 | BL40: =SUM(BL38:BL39) -> 1346138.5 | BM40: =IF(BC40>=Inputs!$B$38,BC40,MIN(BC40+'Dashboard (2)'!$N$2,Inputs!$B$38)) -> 0.72308702 | BN40: =BL40*BM40 -> 973375.3 | BP40: =SUM(BP38:BP39) -> 2329268.4 | BQ40: =IF(ISNUMBER(BG40),BG40*BN40/BD40,"no KPI data") -> no KPI data | BR40: n/a
A41: MALTA | B41: mixed | C41: =Dashboard!C22 -> 233100 | D41: =Dashboard!D22 -> 424347 | E41: =Dashboard!E22 -> 0.54931459 | F41: =Dashboard!F22 -> 0.018 | G41: =Dashboard!G22 -> 7638.246 | H41: =Dashboard!H22 -> 0.56731459 | I41: =Dashboard!I22 -> 240738.25 | K41: CV N | L41: =MALTA!C17 -> 739 | M41: =MALTA!D9 -> 243 | N41: =L41*M41 -> 179577 | Q41: =IFERROR(R41/M41,0) -> 1120 | R41: =Inputs!$C$14*MALTA!D9 -> 272160 | U41: CV N | V41: =MALTA!D17 -> 775.95 | W41: =MALTA!E9 -> 260 | X41: =V41*W41 -> 201747 | AA41: =IFERROR(AB41/W41,0) -> 1176 | AB41: =Inputs!$C$14*(1+Inputs!$B$9)*MALTA!E9 -> 305760 | AE41: CV N | AF41: =MALTA!E17 -> 799.2285 | AG41: =MALTA!F9 -> 276 | AH41: =AF41*AG41 -> 220587.07 | AK41: =IFERROR(AL41/AG41,0) -> 1211.28 | AL41: =Inputs!$C$14*(1+Inputs!$B$9)*(1+'Dashboard (2)'!$T$1)*MALTA!F9 -> 334313.28 | AO41: CV N | AP41: =MALTA!F17 -> 823.20536 | AQ41: =MALTA!G9 -> 292 | AR41: =AP41*AQ41 -> 240375.96 | AU41: =IFERROR(AV41/AQ41,0) -> 1247.6184 | AV41: =Inputs!$C$14*(1+Inputs!$B$9)*(1+'Dashboard (2)'!$T$1)*(1+'Dashboard (2)'!$T$1)*MALTA!G9 -> 364304.57 | AY41: CV N | AZ41: =MALTA!G17 -> 847.90152 | BA41: =MALTA!H9 -> 307 | BB41: =AZ41*BA41 -> 260305.77 | BE41: =IFERROR(BF41/BA41,0) -> 1285.047 | BF41: =Inputs!$C$14*(1+Inputs!$B$9)*(1+'Dashboard (2)'!$T$1)*(1+'Dashboard (2)'!$T$1)*(1+'Dashboard (2)'!$T$1)*MALTA!H9 -> 394509.41 | BI41: CV N | BJ41: =MALTA!H17 -> 873.33856 | BK41: =MALTA!I9 -> 322 | BL41: =BJ41*BK41 -> 281215.02 | BO41: =IFERROR(BP41/BK41,0) -> 1323.5984 | BP41: =Inputs!$C$14*(1+Inputs!$B$9)*(1+'Dashboard (2)'!$T$1)*(1+'Dashboard (2)'!$T$1)*(1+'Dashboard (2)'!$T$1)*(1+'Dashboard (2)'!$T$1)*MALTA!I9 -> 426198.67
K42: LCV | L42: =MALTA!C20 -> 250 | M42: =MALTA!D12 -> 797 | N42: =L42*M42 -> 199250 | Q42: =IFERROR(R42/M42,0) -> 448 | R42: =Inputs!$C$13*MALTA!D12 -> 357056 | U42: LCV | V42: =MALTA!D20 -> 262.5 | W42: =MALTA!E12 -> 848 | X42: =V42*W42 -> 222600 | AA42: =IFERROR(AB42/W42,0) -> 470.4 | AB42: =Inputs!$C$13*(1+Inputs!$B$9)*MALTA!E12 -> 398899.2 | AE42: LCV | AF42: =MALTA!E20 -> 270.375 | AG42: =MALTA!F12 -> 948 | AH42: =AF42*AG42 -> 256315.5 | AK42: =IFERROR(AL42/AG42,0) -> 484.512 | AL42: =Inputs!$C$13*(1+Inputs!$B$9)*(1+'Dashboard (2)'!$T$1)*MALTA!F12 -> 459317.38 | AO42: LCV | AP42: =MALTA!F20 -> 278.48625 | AQ42: =MALTA!G12 -> 1025 | AR42: =AP42*AQ42 -> 285448.41 | AU42: =IFERROR(AV42/AQ42,0) -> 499.04736 | AV42: =Inputs!$C$13*(1+Inputs!$B$9)*(1+'Dashboard (2)'!$T$1)*(1+'Dashboard (2)'!$T$1)*MALTA!G12 -> 511523.54 | AY42: LCV | AZ42: =MALTA!G20 -> 286.84084 | BA42: =MALTA!H12 -> 1099 | BB42: =AZ42*BA42 -> 315238.08 | BE42: =IFERROR(BF42/BA42,0) -> 514.01878 | BF42: =Inputs!$C$13*(1+Inputs!$B$9)*(1+'Dashboard (2)'!$T$1)*(1+'Dashboard (2)'!$T$1)*(1+'Dashboard (2)'!$T$1)*MALTA!H12 -> 564906.64 | BI42: LCV | BJ42: =MALTA!H20 -> 295.44606 | BK42: =MALTA!I12 -> 1171 | BL42: =BJ42*BK42 -> 345967.34 | BO42: =IFERROR(BP42/BK42,0) -> 529.43934 | BP42: =Inputs!$C$13*(1+Inputs!$B$9)*(1+'Dashboard (2)'!$T$1)*(1+'Dashboard (2)'!$T$1)*(1+'Dashboard (2)'!$T$1)*(1+'Dashboard (2)'!$T$1)*MALTA!I12 -> 619973.47
M43: =SUM(M41:M42) -> 1040 | N43: =SUM(N41:N42) -> 378827 | O43: =MALTA!D26 -> 197021.69 | P43: =O43/N43 -> 0.52008355 | R43: =SUM(R41:R42) -> 629216 | S43: =IF(ISNUMBER(Dashboard!Q22),Dashboard!Q22,"no KPI data") -> 553873 | T43: n/a | W43: =SUM(W41:W42) -> 1108 | X43: =SUM(X41:X42) -> 424347 | Y43: =Z43/X43 -> 0.56731459 | Z43: =MALTA!E30 -> 240738.25 | AB43: =SUM(AB41:AB42) -> 704659.2 | AC43: =IF(ISNUMBER(S43),S43+Dashboard!G22/(1-Inputs!$B$18),"no KPI data") -> 565624.15 | AD43: n/a | AG43: =SUM(AG41:AG42) -> 1224 | AH43: =SUM(AH41:AH42) -> 476902.57 | AI43: =IF(Y43>=Inputs!$B$38,Y43,MIN(Y43+'Dashboard (2)'!$N$2,Inputs!$B$38)) -> 0.57731459 | AJ43: =AH43*AI43 -> 275322.81 | AL43: =SUM(AL41:AL42) -> 793630.66 | AM43: =IF(ISNUMBER(AC43),AC43*AJ43/Z43,"no KPI data") -> 646881.97 | AN43: n/a | AQ43: =SUM(AQ41:AQ42) -> 1317 | AR43: =SUM(AR41:AR42) -> 525824.37 | AS43: =IF(AI43>=Inputs!$B$38,AI43,MIN(AI43+'Dashboard (2)'!$N$2,Inputs!$B$38)) -> 0.58731459 | AT43: =AR43*AS43 -> 308824.33 | AV43: =SUM(AV41:AV42) -> 875828.12 | AW43: =IF(ISNUMBER(AM43),AM43*AT43/AJ43,"no KPI data") -> 725595.12 | AX43: n/a | BA43: =SUM(BA41:BA42) -> 1406 | BB43: =SUM(BB41:BB42) -> 575543.85 | BC43: =IF(AS43>=Inputs!$B$38,AS43,MIN(AS43+'Dashboard (2)'!$N$2,Inputs!$B$38)) -> 0.59731459 | BD43: =BB43*BC43 -> 343780.74 | BF43: =SUM(BF41:BF42) -> 959416.05 | BG43: =IF(ISNUMBER(AW43),AW43*BD43/AT43,"no KPI data") -> 807726.61 | BH43: n/a | BK43: =SUM(BK41:BK42) -> 1493 | BL43: =SUM(BL41:BL42) -> 627182.36 | BM43: =IF(BC43>=Inputs!$B$38,BC43,MIN(BC43+'Dashboard (2)'!$N$2,Inputs!$B$38)) -> 0.60731459 | BN43: =BL43*BM43 -> 380897 | BP43: =SUM(BP41:BP42) -> 1046172.1 | BQ43: =IF(ISNUMBER(BG43),BG43*BN43/BD43,"no KPI data") -> 894932.75 | BR43: n/a
A44: TOTAL | C44: =SUM(C6:C41) -> 33222362 | D44: =SUM(D6:D41) -> 60153415 | E44: =C44/D44 -> 0.55229386 | G44: =SUM(G6:G41) -> 1239483.2 | I44: =SUM(I6:I41) -> 34461845 | K44: TOTAL 18 | M44: =M9+M10+M11+M12+M13+M14+M15+M16+M17+M18+M19+M23+M26+M30+M34+M37+M40+M43 -> 163170 | N44: =N9+N10+N11+N12+N13+N14+N15+N16+N17+N18+N19+N23+N26+N30+N34+N37+N40+N43 -> 54054269 | O44: =O9+O10+O11+O12+O13+O14+O15+O16+O17+O18+O19+O23+O26+O30+O34+O37+O40+O43 -> 30758372 | P44: =O44/N44 -> 0.56902763 | R44: =R9+R10+R11+R12+R13+R14+R15+R16+R17+R18+R19+R23+R26+R30+R34+R37+R40+R43 -> 92209152 | S44: =N(S9)+N(S10)+N(S11)+N(S12)+N(S13)+N(S14)+N(S15)+N(S16)+N(S17)+N(S18)+N(S19)+N(S23)+N(S26)+N(S30)+N(S34)+N(S37)+N(S40)+N(S43) -> 59673168 | U44: TOTAL 18 | W44: =W9+W10+W11+W12+W13+W14+W15+W16+W17+W18+W19+W23+W26+W30+W34+W37+W40+W43 -> 172351 | X44: =X9+X10+X11+X12+X13+X14+X15+X16+X17+X18+X19+X23+X26+X30+X34+X37+X40+X43 -> 60153415 | Y44: =Z44/X44 -> 0.57289923 | Z44: =Z9+Z10+Z11+Z12+Z13+Z14+Z15+Z16+Z17+Z18+Z19+Z23+Z26+Z30+Z34+Z37+Z40+Z43 -> 34461845 | AB44: =AB9+AB10+AB11+AB12+AB13+AB14+AB15+AB16+AB17+AB18+AB19+AB23+AB26+AB30+AB34+AB37+AB40+AB43 -> 1.0217133e+08 | AC44: =N(AC9)+N(AC10)+N(AC11)+N(AC12)+N(AC13)+N(AC14)+N(AC15)+N(AC16)+N(AC17)+N(AC18)+N(AC19)+N(AC23)+N(AC26)+N(AC30)+N(AC34)+N(AC37)+N(AC40)+N(AC43) -> 61715591 | AE44: TOTAL 18 | AG44: =AG9+AG10+AG11+AG12+AG13+AG14+AG15+AG16+AG17+AG18+AG19+AG23+AG26+AG30+AG34+AG37+AG40+AG43 -> 180821 | AH44: =AH9+AH10+AH11+AH12+AH13+AH14+AH15+AH16+AH17+AH18+AH19+AH23+AH26+AH30+AH34+AH37+AH40+AH43 -> 65330591 | AI44: =AJ44/AH44 -> 0.58545735 | AJ44: =AJ9+AJ10+AJ11+AJ12+AJ13+AJ14+AJ15+AJ16+AJ17+AJ18+AJ19+AJ23+AJ26+AJ30+AJ34+AJ37+AJ40+AJ43 -> 38248275 | AL44: =AL9+AL10+AL11+AL12+AL13+AL14+AL15+AL16+AL17+AL18+AL19+AL23+AL26+AL30+AL34+AL37+AL40+AL43 -> 1.1087436e+08 | AM44: =N(AM9)+N(AM10)+N(AM11)+N(AM12)+N(AM13)+N(AM14)+N(AM15)+N(AM16)+N(AM17)+N(AM18)+N(AM19)+N(AM23)+N(AM26)+N(AM30)+N(AM34)+N(AM37)+N(AM40)+N(AM43) -> 68070885 | AO44: TOTAL 18 | AQ44: =AQ9+AQ10+AQ11+AQ12+AQ13+AQ14+AQ15+AQ16+AQ17+AQ18+AQ19+AQ23+AQ26+AQ30+AQ34+AQ37+AQ40+AQ43 -> 189094 | AR44: =AR9+AR10+AR11+AR12+AR13+AR14+AR15+AR16+AR17+AR18+AR19+AR23+AR26+AR30+AR34+AR37+AR40+AR43 -> 70826305 | AS44: =AT44/AR44 -> 0.59800022 | AT44: =AT9+AT10+AT11+AT12+AT13+AT14+AT15+AT16+AT17+AT18+AT19+AT23+AT26+AT30+AT34+AT37+AT40+AT43 -> 42354146 | AV44: =AV9+AV10+AV11+AV12+AV13+AV14+AV15+AV16+AV17+AV18+AV19+AV23+AV26+AV30+AV34+AV37+AV40+AV43 -> 1.2007813e+08 | AW44: =N(AW9)+N(AW10)+N(AW11)+N(AW12)+N(AW13)+N(AW14)+N(AW15)+N(AW16)+N(AW17)+N(AW18)+N(AW19)+N(AW23)+N(AW26)+N(AW30)+N(AW34)+N(AW37)+N(AW40)+N(AW43) -> 74715821 | AY44: TOTAL 18 | BA44: =BA9+BA10+BA11+BA12+BA13+BA14+BA15+BA16+BA17+BA18+BA19+BA23+BA26+BA30+BA34+BA37+BA40+BA43 -> 197312 | BB44: =BB9+BB10+BB11+BB12+BB13+BB14+BB15+BB16+BB17+BB18+BB19+BB23+BB26+BB30+BB34+BB37+BB40+BB43 -> 76669972 | BC44: =BD44/BB44 -> 0.61051251 | BD44: =BD9+BD10+BD11+BD12+BD13+BD14+BD15+BD16+BD17+BD18+BD19+BD23+BD26+BD30+BD34+BD37+BD40+BD43 -> 46807977 | BF44: =BF9+BF10+BF11+BF12+BF13+BF14+BF15+BF16+BF17+BF18+BF19+BF23+BF26+BF30+BF34+BF37+BF40+BF43 -> 1.298361e+08 | BG44: =N(BG9)+N(BG10)+N(BG11)+N(BG12)+N(BG13)+N(BG14)+N(BG15)+N(BG16)+N(BG17)+N(BG18)+N(BG19)+N(BG23)+N(BG26)+N(BG30)+N(BG34)+N(BG37)+N(BG40)+N(BG43) -> 81627034 | BI44: TOTAL 18 | BK44: =BK9+BK10+BK11+BK12+BK13+BK14+BK15+BK16+BK17+BK18+BK19+BK23+BK26+BK30+BK34+BK37+BK40+BK43 -> 205337 | BL44: =BL9+BL10+BL11+BL12+BL13+BL14+BL15+BL16+BL17+BL18+BL19+BL23+BL26+BL30+BL34+BL37+BL40+BL43 -> 82746973 | BM44: =BN44/BL44 -> 0.62280381 | BN44: =BN9+BN10+BN11+BN12+BN13+BN14+BN15+BN16+BN17+BN18+BN19+BN23+BN26+BN30+BN34+BN37+BN40+BN43 -> 51535130 | BP44: =BP9+BP10+BP11+BP12+BP13+BP14+BP15+BP16+BP17+BP18+BP19+BP23+BP26+BP30+BP34+BP37+BP40+BP43 -> 1.3997561e+08 | BQ44: =N(BQ9)+N(BQ10)+N(BQ11)+N(BQ12)+N(BQ13)+N(BQ14)+N(BQ15)+N(BQ16)+N(BQ17)+N(BQ18)+N(BQ19)+N(BQ23)+N(BQ26)+N(BQ30)+N(BQ34)+N(BQ37)+N(BQ40)+N(BQ43) -> 88831310
U45: + outside 18 (CIS/MIDI/KIMA/IMG, flat) | Z45: =Inputs!$D$23 -> 2062082.3 | AE45: + outside 18 (CIS/MIDI/KIMA/IMG, flat) | AJ45: =Inputs!$D$23 -> 2062082.3 | AO45: + outside 18 (CIS/MIDI/KIMA/IMG, flat) | AT45: =Inputs!$D$23 -> 2062082.3 | AY45: + outside 18 (CIS/MIDI/KIMA/IMG, flat) | BD45: =Inputs!$D$23 -> 2062082.3 | BI45: + outside 18 (CIS/MIDI/KIMA/IMG, flat) | BN45: =Inputs!$D$23 -> 2062082.3
A46: Remaining stretch BEFORE GPS | C46: 952037.42 | U46: Network BP (PL plan row 186) | Z46: =Inputs!D21 -> 35284444 | AE46: Network BP (PL plan row 186) | AJ46: =Inputs!E21 -> 37530000 | AO46: Network BP (PL plan row 186) | AT46: =Inputs!F21 -> 41530410 | AY46: Network BP (PL plan row 186) | BD46: =Inputs!G21 -> 46385705 | BI46: Network BP (PL plan row 186) | BN46: =Inputs!H21 -> 52096000
A47: GPS contribution (18 DBs) | C47: =G44 -> 1239483.2 | U47: Gap: target - BP (+ = above plan) | Z47: =Z44+Z45-Z46 -> 1239483.2 | AE47: Gap: target - BP (+ = above plan) | AJ47: =AJ44+AJ45-AJ46 -> 2780356.8 | AO47: Gap: target - BP (+ = above plan) | AT47: =AT44+AT45-AT46 -> 2885818.3 | AY47: Gap: target - BP (+ = above plan) | BD47: =BD44+BD45-BD46 -> 2484353.9 | BI47: Gap: target - BP (+ = above plan) | BN47: =BN44+BN45-BN46 -> 1501212.4
A48: Remaining stretch AFTER GPS | C48: =C46-C47 -> -287445.75 | E48: negative = over-covered = buffer | U48: Dealer totals (row 44) add only the distributors with KPI sales-to-dealer data.
A50: WATCH
A51: • Dealer level (販社): amounts only. The distributors' reported sales to dealers run 2.2 to 3.7 times ISZE billing, so a share would read above 100% for five distributors. FY2027 dealer target = FY2026 sales to dealers + ISZE stretch / 0.65; FY2028-FY2031 move with the ISZE target.
A52: • ITUK and UTI: targets and stretch as presented in July; maximum spend on IML data (2026 vehicles, +5%).
A53: • The same stretch for every distributor. Finland (104.9% on budget) and Ireland (100.2% after stretch) read above 100%: quote the amount, not the %. Ireland's fleet is national registration data.
A54: • Belgium: Isuzu Benelux also serves NL, PL and LU; only Belgian vehicles are counted.
A55: • Fleet: UIO V19 for all years. Sheets 'UIO V19' and 'UIO V20' explain the difference with the UIO V20 spec and its effect on FY2028-FY2031.
A56: • Blue numbers are inputs. Every other number is a formula; constants sit on the Inputs sheet or the distributor tabs.

Sheet Inputs
A1: Inputs — every constant the formulas use. Blue/yellow = edit here; everything else follows.
A3: ISZE-net parts spend per vehicle per year, FY2026 base (EUR)
A4: LCV / D-Max | B4: 250 | C4: pick-up rate per vehicle
A5: CV LD (N75/N50/N62) | B5: 739 | C5: truck rates, unchanged
A6: CV MD | B6: 887
A7: CV F-Series | B7: 887
A9: Price increase FY2027 | B9: 0.05
A10: Price increase FY2028-31 / yr | B10: ='Dashboard (2)'!T1 -> 0.03 | C10: set on Dashboard (2) T1
A11: Dealer price step FY27 (ITUK row as presented) | B11: 0.03
A12: Dealer-level spend per vehicle (GBP, ITUK convention) | C12: EUR
A13: LCV / N35 | B13: 400 | C13: =B13*$B$16 -> 448
A14: CV LD / N75 | B14: 1000 | C14: =B14*$B$16 -> 1120
A15: CV MD / F-Series | B15: 1200 | C15: =B15*$B$16 -> 1344
A16: GBP to EUR (as in the ITUK row) | B16: 1.12
A18: Distributor margin (dealer level = ISZE / (1 - margin)) | B18: 0.35
A20: Fiscal year | C20: FY2026 | D20: FY2027 | E20: FY2028 | F20: FY2029 | G20: FY2030 | H20: FY2031
A21: Network BP, PL plan row 186 (EUR) | D21: 35284444 | E21: 37530000 | F21: 41530410 | G21: 46385705 | H21: 52096000
A22: Sum of BP FY27, 18 distributors | D22: =Dashboard!C23 -> 33222362
A23: Customers outside the 18 (CIS, MIDI, KIMA, IMG), held flat | D23: =D21-D22 -> 2062082.3
A24: Fleet year used (fiscal year = calendar year + 1) | C24: CY2025 | D24: CY2026 | E24: CY2027 | F24: CY2028 | G24: CY2029 | H24: CY2030
A25: Fleet for ITUK and UTI (UIO V19)
A26: ITUK LD (N35 + N75) | C26: 22191 | D26: 23210 | E26: 24336 | F26: 25294 | G26: 26146 | H26: 26923
A27: ITUK F-Series | C27: 877 | D27: 963 | E27: 1055 | F27: 1141 | G27: 1218 | H27: 1286
A29: UTI LD | C29: 6059 | D29: 6101 | E29: 6064 | F29: 6093 | G29: 6110 | H29: 6124
A30: UTI MD | C30: 4277 | D30: 4659 | E30: 4908 | F30: 5187 | G30: 5471 | H30: 5758
A32: Other inputs: fleet and FY2025 / FY2026 billing on each distributor tab, stretch / cap / price on Dashboard (2) row 1-2, ITUK and UTI FY2027 figures as presented in July.
A34: ITUK sales to dealers FY26 (GBP, as presented) | B34: 12873998 | C34: x GBP->EUR B16 = Dashboard (2) S9
A36: Cap stretch at the share ceiling? (switch on Dashboard (2) Q1) | B36: ='Dashboard (2)'!Q1 -> NO | C36: Default NO: the same stretch for every distributor; above 100% we quote the amount, not the %.
A37: Share ceiling when the cap is on | B37: 1
A38: Effective ceiling used by the formulas (no cap = 999%) | B38: =IF(UPPER(B36)="YES",B37,9.99) -> 9.99
A40: UIO V19: share of the fleet leaving the road each year from 2026 (explanation on sheet 'UIO V19') | B40: 0.03

Sheet Checks
A1: Live checks — every row must read OK. Recalculate (F9) after changing an input.
A2: Overall | B2: =IF(COUNTIF(F5:F200,"CHECK")=0,"ALL OK",COUNTIF(F5:F200,"CHECK")&" CHECK") -> ALL OK
A4: # | B4: Check | C4: Value A | D4: Value B | E4: Difference | F4: Status
A5: 1 | B5: Waterfall closes to the FY27 plan | C5: ='Waterfall VP'!T5 -> 35284444 | D5: =Inputs!D21 -> 35284444 | E5: =C5-D5 -> 0 | F5: =IF(ABS(E5)<1,"OK","CHECK") -> OK
A6: 2 | B6: Waterfall GPS step = stretch total on Dashboard | C6: ='Waterfall VP'!P4 -> 1239483.2 | D6: =Dashboard!G23 -> 1239483.2 | E6: =C6-D6 -> 0 | F6: =IF(ABS(E6)<1,"OK","CHECK") -> OK
A7: 3 | B7: Waterfall: required 952K minus GPS step = Q4 | C7: ='Waterfall VP'!Q4 -> -287445.75 | D7: =Dashboard!C25-Dashboard!G23 -> -287445.75 | E7: =C7-D7 -> -4.2699394e-05 | F7: =IF(ABS(E7)<1,"OK","CHECK") -> OK
A8: 4 | B8: BP 18 distributors + outside 18 = network plan FY27 | C8: =Dashboard!C23+Inputs!D23 -> 35284444 | D8: =Inputs!D21 -> 35284444 | E8: =C8-D8 -> 0 | F8: =IF(ABS(E8)<1,"OK","CHECK") -> OK
A9: 5 | B9: Japanese view FY27 target total = Dashboard extended target total | C9: ='Dashboard (2)'!Z44 -> 34461845 | D9: =Dashboard!I23 -> 34461845 | E9: =C9-D9 -> 0 | F9: =IF(ABS(E9)<1,"OK","CHECK") -> OK
A10: 6 | B10: Japanese view FY27 potential (16) = Dashboard max spend (16) | C10: ='Dashboard (2)'!X44-'Dashboard (2)'!X9-'Dashboard (2)'!X10 -> 39132489 | D10: =Dashboard!D23-Dashboard!D5-Dashboard!D6 -> 39132489 | E10: =C10-D10 -> 0 | F10: =IF(ABS(E10)<1,"OK","CHECK") -> OK
A11: 7 | B11: Stretch total FY27 = sum over the 16 tabs + ITUK + UTI | C11: =Dashboard!G23 -> 1239483.2 | D11: =IUK!E23+UMI!E23+NORWAY!E23+SWEDEN!E23+HUNGARY!E23+FINLAND!E23+ROMANIA!E23+DENMARK!E23+ICELAND!E23+GERMANY!E29+BELGIUM!E29+PORTUGAL!E29+IRELAND!E29+GREECE!E29+CYPRUS!E29+MALTA!E29+Dashboard!G5+Dashboard!G6 -> 1239483.2 | E11: =C11-D11 -> 0 | F11: =IF(ABS(E11)<1,"OK","CHECK") -> OK
A12: 8 | B12: ITUK max spend: Dashboard = Dashboard (2) (IML data) | C12: =Dashboard!D5 -> 12535797 | D12: ='Dashboard (2)'!X9 -> 12535797 | E12: =C12-D12 -> 0 | F12: =IF(ABS(E12)<1,"OK","CHECK") -> OK
A13: 9 | B13: UTI max spend: Dashboard = Dashboard (2) (IML data) | C13: =Dashboard!D6 -> 8485129 | D13: ='Dashboard (2)'!X10 -> 8485129 | E13: =C13-D13 -> 0 | F13: =IF(ABS(E13)<1,"OK","CHECK") -> OK
A14: 10 | B14: Gap row FY31 = target + outside - BP | C14: ='Dashboard (2)'!BN47 -> 1501212.4 | D14: ='Dashboard (2)'!BN44+'Dashboard (2)'!BN45-'Dashboard (2)'!BN46 -> 1501212.4 | E14: =C14-D14 -> 0 | F14: =IF(ABS(E14)<1,"OK","CHECK") -> OK
A15: 11 | B15: Error cells on Dashboard (2) (must be 0) | C15: =SUMPRODUCT(--ISERROR('Dashboard (2)'!A1:BR60)) -> 0 | D15: =0 -> 0 | E15: =C15-D15 -> 0 | F15: =IF(ABS(E15)<1,"OK","CHECK") -> OK
A16: 12 | B16: Error cells on Dashboard (must be 0) | C16: =SUMPRODUCT(--ISERROR(Dashboard!A1:W40)) -> 0 | D16: =0 -> 0 | E16: =C16-D16 -> 0 | F16: =IF(ABS(E16)<1,"OK","CHECK") -> OK
A17: 13 | B17: IUK: tab extended target = Dashboard = Japanese view | C17: =IUK!E24 -> 6295804.5 | D17: =AVERAGE(Dashboard!I7,'Dashboard (2)'!Z11) -> 6295804.5 | E17: =C17-D17 -> 0 | F17: =IF(ABS(E17)<1,"OK","CHECK") -> OK
A18: 14 | B18: IUK: share after stretch within ceiling (or no stretch) | C18: =IF(OR(Dashboard!H7<=Inputs!$B$38+0.0000001,Dashboard!F7=0),1,0) -> 1 | D18: =1 -> 1 | E18: =C18-D18 -> 0 | F18: =IF(ABS(E18)<1,"OK","CHECK") -> OK
A19: 15 | B19: IUK: FY31 share within ceiling (or held flat) | C19: =IF(OR('Dashboard (2)'!BM11<=Inputs!$B$38+0.0000001,'Dashboard (2)'!BM11='Dashboard (2)'!Y11),1,0) -> 1 | D19: =1 -> 1 | E19: =C19-D19 -> 0 | F19: =IF(ABS(E19)<1,"OK","CHECK") -> OK
A20: 16 | B20: UMI: tab extended target = Dashboard = Japanese view | C20: =UMI!E24 -> 3062515.7 | D20: =AVERAGE(Dashboard!I8,'Dashboard (2)'!Z12) -> 3062515.7 | E20: =C20-D20 -> 0 | F20: =IF(ABS(E20)<1,"OK","CHECK") -> OK
A21: 17 | B21: UMI: share after stretch within ceiling (or no stretch) | C21: =IF(OR(Dashboard!H8<=Inputs!$B$38+0.0000001,Dashboard!F8=0),1,0) -> 1 | D21: =1 -> 1 | E21: =C21-D21 -> 0 | F21: =IF(ABS(E21)<1,"OK","CHECK") -> OK
A22: 18 | B22: UMI: FY31 share within ceiling (or held flat) | C22: =IF(OR('Dashboard (2)'!BM12<=Inputs!$B$38+0.0000001,'Dashboard (2)'!BM12='Dashboard (2)'!Y12),1,0) -> 1 | D22: =1 -> 1 | E22: =C22-D22 -> 0 | F22: =IF(ABS(E22)<1,"OK","CHECK") -> OK
A23: 19 | B23: NORWAY: tab extended target = Dashboard = Japanese view | C23: =NORWAY!E24 -> 1803124.2 | D23: =AVERAGE(Dashboard!I9,'Dashboard (2)'!Z13) -> 1803124.2 | E23: =C23-D23 -> 0 | F23: =IF(ABS(E23)<1,"OK","CHECK") -> OK
A24: 20 | B24: NORWAY: share after stretch within ceiling (or no stretch) | C24: =IF(OR(Dashboard!H9<=Inputs!$B$38+0.0000001,Dashboard!F9=0),1,0) -> 1 | D24: =1 -> 1 | E24: =C24-D24 -> 0 | F24: =IF(ABS(E24)<1,"OK","CHECK") -> OK
A25: 21 | B25: NORWAY: FY31 share within ceiling (or held flat) | C25: =IF(OR('Dashboard (2)'!BM13<=Inputs!$B$38+0.0000001,'Dashboard (2)'!BM13='Dashboard (2)'!Y13),1,0) -> 1 | D25: =1 -> 1 | E25: =C25-D25 -> 0 | F25: =IF(ABS(E25)<1,"OK","CHECK") -> OK
A26: 22 | B26: SWEDEN: tab extended target = Dashboard = Japanese view | C26: =SWEDEN!E24 -> 1507252.6 | D26: =AVERAGE(Dashboard!I10,'Dashboard (2)'!Z14) -> 1507252.6 | E26: =C26-D26 -> 0 | F26: =IF(ABS(E26)<1,"OK","CHECK") -> OK
A27: 23 | B27: SWEDEN: share after stretch within ceiling (or no stretch) | C27: =IF(OR(Dashboard!H10<=Inputs!$B$38+0.0000001,Dashboard!F10=0),1,0) -> 1 | D27: =1 -> 1 | E27: =C27-D27 -> 0 | F27: =IF(ABS(E27)<1,"OK","CHECK") -> OK
A28: 24 | B28: SWEDEN: FY31 share within ceiling (or held flat) | C28: =IF(OR('Dashboard (2)'!BM14<=Inputs!$B$38+0.0000001,'Dashboard (2)'!BM14='Dashboard (2)'!Y14),1,0) -> 1 | D28: =1 -> 1 | E28: =C28-D28 -> 0 | F28: =IF(ABS(E28)<1,"OK","CHECK") -> OK
A29: 25 | B29: HUNGARY: tab extended target = Dashboard = Japanese view | C29: =HUNGARY!E24 -> 368462.2 | D29: =AVERAGE(Dashboard!I11,'Dashboard (2)'!Z15) -> 368462.2 | E29: =C29-D29 -> 0 | F29: =IF(ABS(E29)<1,"OK","CHECK") -> OK
A30: 26 | B30: HUNGARY: share after stretch within ceiling (or no stretch) | C30: =IF(OR(Dashboard!H11<=Inputs!$B$38+0.0000001,Dashboard!F11=0),1,0) -> 1 | D30: =1 -> 1 | E30: =C30-D30 -> 0 | F30: =IF(ABS(E30)<1,"OK","CHECK") -> OK
A31: 27 | B31: HUNGARY: FY31 share within ceiling (or held flat) | C31: =IF(OR('Dashboard (2)'!BM15<=Inputs!$B$38+0.0000001,'Dashboard (2)'!BM15='Dashboard (2)'!Y15),1,0) -> 1 | D31: =1 -> 1 | E31: =C31-D31 -> 0 | F31: =IF(ABS(E31)<1,"OK","CHECK") -> OK
A32: 28 | B32: FINLAND: tab extended target = Dashboard = Japanese view | C32: =FINLAND!E24 -> 366480.3 | D32: =AVERAGE(Dashboard!I12,'Dashboard (2)'!Z16) -> 366480.3 | E32: =C32-D32 -> 0 | F32: =IF(ABS(E32)<1,"OK","CHECK") -> OK
A33: 29 | B33: FINLAND: share after stretch within ceiling (or no stretch) | C33: =IF(OR(Dashboard!H12<=Inputs!$B$38+0.0000001,Dashboard!F12=0),1,0) -> 1 | D33: =1 -> 1 | E33: =C33-D33 -> 0 | F33: =IF(ABS(E33)<1,"OK","CHECK") -> OK
A34: 30 | B34: FINLAND: FY31 share within ceiling (or held flat) | C34: =IF(OR('Dashboard (2)'!BM16<=Inputs!$B$38+0.0000001,'Dashboard (2)'!BM16='Dashboard (2)'!Y16),1,0) -> 1 | D34: =1 -> 1 | E34: =C34-D34 -> 0 | F34: =IF(ABS(E34)<1,"OK","CHECK") -> OK
A35: 31 | B35: ROMANIA: tab extended target = Dashboard = Japanese view | C35: =ROMANIA!E24 -> 205300.1 | D35: =AVERAGE(Dashboard!I13,'Dashboard (2)'!Z17) -> 205300.1 | E35: =C35-D35 -> 0 | F35: =IF(ABS(E35)<1,"OK","CHECK") -> OK
A36: 32 | B36: ROMANIA: share after stretch within ceiling (or no stretch) | C36: =IF(OR(Dashboard!H13<=Inputs!$B$38+0.0000001,Dashboard!F13=0),1,0) -> 1 | D36: =1 -> 1 | E36: =C36-D36 -> 0 | F36: =IF(ABS(E36)<1,"OK","CHECK") -> OK
A37: 33 | B37: ROMANIA: FY31 share within ceiling (or held flat) | C37: =IF(OR('Dashboard (2)'!BM17<=Inputs!$B$38+0.0000001,'Dashboard (2)'!BM17='Dashboard (2)'!Y17),1,0) -> 1 | D37: =1 -> 1 | E37: =C37-D37 -> 0 | F37: =IF(ABS(E37)<1,"OK","CHECK") -> OK
A38: 34 | B38: DENMARK: tab extended target = Dashboard = Japanese view | C38: =DENMARK!E24 -> 192060.4 | D38: =AVERAGE(Dashboard!I14,'Dashboard (2)'!Z18) -> 192060.4 | E38: =C38-D38 -> 0 | F38: =IF(ABS(E38)<1,"OK","CHECK") -> OK
A39: 35 | B39: DENMARK: share after stretch within ceiling (or no stretch) | C39: =IF(OR(Dashboard!H14<=Inputs!$B$38+0.0000001,Dashboard!F14=0),1,0) -> 1 | D39: =1 -> 1 | E39: =C39-D39 -> 0 | F39: =IF(ABS(E39)<1,"OK","CHECK") -> OK
A40: 36 | B40: DENMARK: FY31 share within ceiling (or held flat) | C40: =IF(OR('Dashboard (2)'!BM18<=Inputs!$B$38+0.0000001,'Dashboard (2)'!BM18='Dashboard (2)'!Y18),1,0) -> 1 | D40: =1 -> 1 | E40: =C40-D40 -> 0 | F40: =IF(ABS(E40)<1,"OK","CHECK") -> OK
A41: 37 | B41: ICELAND: tab extended target = Dashboard = Japanese view | C41: =ICELAND!E24 -> 106674.27 | D41: =AVERAGE(Dashboard!I15,'Dashboard (2)'!Z19) -> 106674.27 | E41: =C41-D41 -> 0 | F41: =IF(ABS(E41)<1,"OK","CHECK") -> OK
A42: 38 | B42: ICELAND: share after stretch within ceiling (or no stretch) | C42: =IF(OR(Dashboard!H15<=Inputs!$B$38+0.0000001,Dashboard!F15=0),1,0) -> 1 | D42: =1 -> 1 | E42: =C42-D42 -> 0 | F42: =IF(ABS(E42)<1,"OK","CHECK") -> OK
A43: 39 | B43: ICELAND: FY31 share within ceiling (or held flat) | C43: =IF(OR('Dashboard (2)'!BM19<=Inputs!$B$38+0.0000001,'Dashboard (2)'!BM19='Dashboard (2)'!Y19),1,0) -> 1 | D43: =1 -> 1 | E43: =C43-D43 -> 0 | F43: =IF(ABS(E43)<1,"OK","CHECK") -> OK
A44: 40 | B44: GERMANY: tab extended target = Dashboard = Japanese view | C44: =GERMANY!E30 -> 2993651.1 | D44: =AVERAGE(Dashboard!I16,'Dashboard (2)'!Z23) -> 2993651.1 | E44: =C44-D44 -> 0 | F44: =IF(ABS(E44)<1,"OK","CHECK") -> OK
A45: 41 | B45: GERMANY: share after stretch within ceiling (or no stretch) | C45: =IF(OR(Dashboard!H16<=Inputs!$B$38+0.0000001,Dashboard!F16=0),1,0) -> 1 | D45: =1 -> 1 | E45: =C45-D45 -> 0 | F45: =IF(ABS(E45)<1,"OK","CHECK") -> OK
A46: 42 | B46: GERMANY: FY31 share within ceiling (or held flat) | C46: =IF(OR('Dashboard (2)'!BM23<=Inputs!$B$38+0.0000001,'Dashboard (2)'!BM23='Dashboard (2)'!Y23),1,0) -> 1 | D46: =1 -> 1 | E46: =C46-D46 -> 0 | F46: =IF(ABS(E46)<1,"OK","CHECK") -> OK
A47: 43 | B47: BELGIUM: tab extended target = Dashboard = Japanese view | C47: =BELGIUM!E30 -> 2345890.4 | D47: =AVERAGE(Dashboard!I17,'Dashboard (2)'!Z26) -> 2345890.4 | E47: =C47-D47 -> 0 | F47: =IF(ABS(E47)<1,"OK","CHECK") -> OK
A48: 44 | B48: BELGIUM: share after stretch within ceiling (or no stretch) | C48: =IF(OR(Dashboard!H17<=Inputs!$B$38+0.0000001,Dashboard!F17=0),1,0) -> 1 | D48: =1 -> 1 | E48: =C48-D48 -> 0 | F48: =IF(ABS(E48)<1,"OK","CHECK") -> OK
A49: 45 | B49: BELGIUM: FY31 share within ceiling (or held flat) | C49: =IF(OR('Dashboard (2)'!BM26<=Inputs!$B$38+0.0000001,'Dashboard (2)'!BM26='Dashboard (2)'!Y26),1,0) -> 1 | D49: =1 -> 1 | E49: =C49-D49 -> 0 | F49: =IF(ABS(E49)<1,"OK","CHECK") -> OK
A50: 46 | B50: PORTUGAL: tab extended target = Dashboard = Japanese view | C50: =PORTUGAL!E30 -> 1926457.8 | D50: =AVERAGE(Dashboard!I18,'Dashboard (2)'!Z30) -> 1926457.8 | E50: =C50-D50 -> 0 | F50: =IF(ABS(E50)<1,"OK","CHECK") -> OK
A51: 47 | B51: PORTUGAL: share after stretch within ceiling (or no stretch) | C51: =IF(OR(Dashboard!H18<=Inputs!$B$38+0.0000001,Dashboard!F18=0),1,0) -> 1 | D51: =1 -> 1 | E51: =C51-D51 -> 0 | F51: =IF(ABS(E51)<1,"OK","CHECK") -> OK
A52: 48 | B52: PORTUGAL: FY31 share within ceiling (or held flat) | C52: =IF(OR('Dashboard (2)'!BM30<=Inputs!$B$38+0.0000001,'Dashboard (2)'!BM30='Dashboard (2)'!Y30),1,0) -> 1 | D52: =1 -> 1 | E52: =C52-D52 -> 0 | F52: =IF(ABS(E52)<1,"OK","CHECK") -> OK
A53: 49 | B53: IRELAND: tab extended target = Dashboard = Japanese view | C53: =IRELAND!E30 -> 1290623.3 | D53: =AVERAGE(Dashboard!I19,'Dashboard (2)'!Z34) -> 1290623.3 | E53: =C53-D53 -> 0 | F53: =IF(ABS(E53)<1,"OK","CHECK") -> OK
A54: 50 | B54: IRELAND: share after stretch within ceiling (or no stretch) | C54: =IF(OR(Dashboard!H19<=Inputs!$B$38+0.0000001,Dashboard!F19=0),1,0) -> 1 | D54: =1 -> 1 | E54: =C54-D54 -> 0 | F54: =IF(ABS(E54)<1,"OK","CHECK") -> OK
A55: 51 | B55: IRELAND: FY31 share within ceiling (or held flat) | C55: =IF(OR('Dashboard (2)'!BM34<=Inputs!$B$38+0.0000001,'Dashboard (2)'!BM34='Dashboard (2)'!Y34),1,0) -> 1 | D55: =1 -> 1 | E55: =C55-D55 -> 0 | F55: =IF(ABS(E55)<1,"OK","CHECK") -> OK
A56: 52 | B56: GREECE: tab extended target = Dashboard = Japanese view | C56: =GREECE!E30 -> 595224.38 | D56: =AVERAGE(Dashboard!I20,'Dashboard (2)'!Z37) -> 595224.38 | E56: =C56-D56 -> 0 | F56: =IF(ABS(E56)<1,"OK","CHECK") -> OK
A57: 53 | B57: GREECE: share after stretch within ceiling (or no stretch) | C57: =IF(OR(Dashboard!H20<=Inputs!$B$38+0.0000001,Dashboard!F20=0),1,0) -> 1 | D57: =1 -> 1 | E57: =C57-D57 -> 0 | F57: =IF(ABS(E57)<1,"OK","CHECK") -> OK
A58: 54 | B58: GREECE: FY31 share within ceiling (or held flat) | C58: =IF(OR('Dashboard (2)'!BM37<=Inputs!$B$38+0.0000001,'Dashboard (2)'!BM37='Dashboard (2)'!Y37),1,0) -> 1 | D58: =1 -> 1 | E58: =C58-D58 -> 0 | F58: =IF(ABS(E58)<1,"OK","CHECK") -> OK
A59: 55 | B59: CYPRUS: tab extended target = Dashboard = Japanese view | C59: =CYPRUS!E30 -> 554203.8 | D59: =AVERAGE(Dashboard!I21,'Dashboard (2)'!Z40) -> 554203.8 | E59: =C59-D59 -> 0 | F59: =IF(ABS(E59)<1,"OK","CHECK") -> OK
A60: 56 | B60: CYPRUS: share after stretch within ceiling (or no stretch) | C60: =IF(OR(Dashboard!H21<=Inputs!$B$38+0.0000001,Dashboard!F21=0),1,0) -> 1 | D60: =1 -> 1 | E60: =C60-D60 -> 0 | F60: =IF(ABS(E60)<1,"OK","CHECK") -> OK
A61: 57 | B61: CYPRUS: FY31 share within ceiling (or held flat) | C61: =IF(OR('Dashboard (2)'!BM40<=Inputs!$B$38+0.0000001,'Dashboard (2)'!BM40='Dashboard (2)'!Y40),1,0) -> 1 | D61: =1 -> 1 | E61: =C61-D61 -> 0 | F61: =IF(ABS(E61)<1,"OK","CHECK") -> OK
A62: 58 | B62: MALTA: tab extended target = Dashboard = Japanese view | C62: =MALTA!E30 -> 240738.25 | D62: =AVERAGE(Dashboard!I22,'Dashboard (2)'!Z43) -> 240738.25 | E62: =C62-D62 -> 0 | F62: =IF(ABS(E62)<1,"OK","CHECK") -> OK
A63: 59 | B63: MALTA: share after stretch within ceiling (or no stretch) | C63: =IF(OR(Dashboard!H22<=Inputs!$B$38+0.0000001,Dashboard!F22=0),1,0) -> 1 | D63: =1 -> 1 | E63: =C63-D63 -> 0 | F63: =IF(ABS(E63)<1,"OK","CHECK") -> OK
A64: 60 | B64: MALTA: FY31 share within ceiling (or held flat) | C64: =IF(OR('Dashboard (2)'!BM43<=Inputs!$B$38+0.0000001,'Dashboard (2)'!BM43='Dashboard (2)'!Y43),1,0) -> 1 | D64: =1 -> 1 | E64: =C64-D64 -> 0 | F64: =IF(ABS(E64)<1,"OK","CHECK") -> OK
A65: i | B65: INFO: distributors above 100% GPS share after the FY27 stretch (quote amount only) | C65: =COUNTIF(Dashboard!H7:H22,">1") -> 2 | F65: INFO
A66: 62 | B66: UIO V19 sheet: total potential FY31 = Dashboard (2) total | C66: ='UIO V19'!H79 -> 82746973 | D66: ='Dashboard (2)'!BL44 -> 82746973 | E66: =C66-D66 -> 0 | F66: =IF(ABS(E66)<1,"OK","CHECK") -> OK
A67: 63 | B67: UIO V19 sheet: total target FY31 = Dashboard (2) total | C67: ='UIO V19'!H122 -> 51535130 | D67: ='Dashboard (2)'!BN44 -> 51535130 | E67: =C67-D67 -> 0 | F67: =IF(ABS(E67)<1,"OK","CHECK") -> OK
A68: 64 | B68: UIO V20 sheet: FY27 target unchanged against the model | C68: ='UIO V20'!D120 -> 34461845 | D68: ='Dashboard (2)'!Z44 -> 34461845 | E68: =C68-D68 -> 0 | F68: =IF(ABS(E68)<1,"OK","CHECK") -> OK
A69: 65 | B69: UIO V20 sheet: ITUK and UTI potential FY31 unchanged | C69: ='UIO V20'!H59+'UIO V20'!H60 -> 27080783 | D69: ='Dashboard (2)'!BL9+'Dashboard (2)'!BL10 -> 27080783 | E69: =C69-D69 -> 0 | F69: =IF(ABS(E69)<1,"OK","CHECK") -> OK
B71: ITUK and UTI maximum spend use IML data on both dashboards (2026 vehicles, +5%); targets as presented in July.

Sheet UIO V19
A1: UIO V19: vehicles in use in this model
A3: What this sheet shows
A4: The vehicles in use per distributor and segment that every other sheet in this file uses. Fiscal year = calendar year + 1: FY2027 uses the fleet of calendar 2026, FY2031 the fleet of calendar 2030.
A5: How UIO V19 builds the fleet
A6: Up to 2025: registrations of each year, with an age curve for how many vehicles are still on the road. On that curve a pick-up stays on the road about 8 years on average and a truck about 10 years.
A7: From 2026: the forecast of new pick-up and truck sales is added each year, and only 3% of the fleet leaves the road each year. 3% a year means a vehicle stays on the road about 33 years, so the fleet keeps growing.
A8: Result: the fleet of these 18 distributors grows about 26% from FY2026 to FY2031, and the parts potential grows with it.
A10: Vehicles in use, UIO V19
A11: Distributor | B11: Segment | C11: FY26 (CY2025) | D11: FY27 (CY2026) | E11: FY28 (CY2027) | F11: FY29 (CY2028) | G11: FY30 (CY2029) | H11: FY31 (CY2030) | I11: Change FY26 to FY31
A12: ITUK | B12: Light truck (N35 + N75) | C12: =Inputs!C26 -> 22191 | D12: =Inputs!D26 -> 23210 | E12: =Inputs!E26 -> 24336 | F12: =Inputs!F26 -> 25294 | G12: =Inputs!G26 -> 26146 | H12: =Inputs!H26 -> 26923 | I12: =IF(C12=0,"",H12/C12-1) -> 0.2132396
A13: ITUK | B13: F-Series | C13: =Inputs!C27 -> 877 | D13: =Inputs!D27 -> 963 | E13: =Inputs!E27 -> 1055 | F13: =Inputs!F27 -> 1141 | G13: =Inputs!G27 -> 1218 | H13: =Inputs!H27 -> 1286 | I13: =IF(C13=0,"",H13/C13-1) -> 0.4663626
A14: UTI | B14: Light truck | C14: =Inputs!C29 -> 6059 | D14: =Inputs!D29 -> 6101 | E14: =Inputs!E29 -> 6064 | F14: =Inputs!F29 -> 6093 | G14: =Inputs!G29 -> 6110 | H14: =Inputs!H29 -> 6124 | I14: =IF(C14=0,"",H14/C14-1) -> 0.010727843
A15: UTI | B15: Medium truck | C15: =Inputs!C30 -> 4277 | D15: =Inputs!D30 -> 4659 | E15: =Inputs!E30 -> 4908 | F15: =Inputs!F30 -> 5187 | G15: =Inputs!G30 -> 5471 | H15: =Inputs!H30 -> 5758 | I15: =IF(C15=0,"",H15/C15-1) -> 0.34627075
A16: IUK | B16: Pick-up (D-Max) | C16: =IUK!D9 -> 47783 | D16: =IUK!E9 -> 49280 | E16: =IUK!F9 -> 50202 | F16: =IUK!G9 -> 51096 | G16: =IUK!H9 -> 51963 | H16: =IUK!I9 -> 52804 | I16: =IF(C16=0,"",H16/C16-1) -> 0.10507921
A17: UMI | B17: Pick-up (D-Max) | C17: =UMI!D9 -> 18542 | D17: =UMI!E9 -> 18886 | E17: =UMI!F9 -> 19319 | F17: =UMI!G9 -> 19669 | G17: =UMI!H9 -> 20009 | H17: =UMI!I9 -> 20339 | I17: =IF(C17=0,"",H17/C17-1) -> 0.096915112
A18: NORWAY | B18: Pick-up (D-Max) | C18: =NORWAY!D9 -> 7929 | D18: =NORWAY!E9 -> 8111 | E18: =NORWAY!F9 -> 8218 | F18: =NORWAY!G9 -> 8426 | G18: =NORWAY!H9 -> 8628 | H18: =NORWAY!I9 -> 8824 | I18: =IF(C18=0,"",H18/C18-1) -> 0.11287678
A19: SWEDEN | B19: Pick-up (D-Max) | C19: =SWEDEN!D9 -> 8443 | D19: =SWEDEN!E9 -> 9090 | E19: =SWEDEN!F9 -> 9737 | F19: =SWEDEN!G9 -> 10320 | G19: =SWEDEN!H9 -> 10885 | H19: =SWEDEN!I9 -> 11433 | I19: =IF(C19=0,"",H19/C19-1) -> 0.35413952
A20: HUNGARY | B20: Pick-up (D-Max) | C20: =HUNGARY!D9 -> 3734 | D20: =HUNGARY!E9 -> 3992 | E20: =HUNGARY!F9 -> 4242 | F20: =HUNGARY!G9 -> 4390 | G20: =HUNGARY!H9 -> 4533 | H20: =HUNGARY!I9 -> 4672 | I20: =IF(C20=0,"",H20/C20-1) -> 0.25120514
A21: FINLAND | B21: Pick-up (D-Max) | C21: =FINLAND!D9 -> 1204 | D21: =FINLAND!E9 -> 1308 | E21: =FINLAND!F9 -> 1409 | F21: =FINLAND!G9 -> 1522 | G21: =FINLAND!H9 -> 1631 | H21: =FINLAND!I9 -> 1737 | I21: =IF(C21=0,"",H21/C21-1) -> 0.44269103
A22: ROMANIA | B22: Pick-up (D-Max) | C22: =ROMANIA!D9 -> 1071 | D22: =ROMANIA!E9 -> 1209 | E22: =ROMANIA!F9 -> 1343 | F22: =ROMANIA!G9 -> 1475 | G22: =ROMANIA!H9 -> 1603 | H22: =ROMANIA!I9 -> 1727 | I22: =IF(C22=0,"",H22/C22-1) -> 0.61251167
A23: DENMARK | B23: Pick-up (D-Max) | C23: =DENMARK!D9 -> 850 | D23: =DENMARK!E9 -> 944 | E23: =DENMARK!F9 -> 1036 | F23: =DENMARK!G9 -> 1140 | G23: =DENMARK!H9 -> 1241 | H23: =DENMARK!I9 -> 1339 | I23: =IF(C23=0,"",H23/C23-1) -> 0.57529412
A24: ICELAND | B24: Pick-up (D-Max) | C24: =ICELAND!D9 -> 406 | D24: =ICELAND!E9 -> 439 | E24: =ICELAND!F9 -> 471 | F24: =ICELAND!G9 -> 549 | G24: =ICELAND!H9 -> 625 | H24: =ICELAND!I9 -> 698 | I24: =IF(C24=0,"",H24/C24-1) -> 0.71921182
A25: GERMANY | B25: Light truck | C25: =GERMANY!D9 -> 697 | D25: =GERMANY!E9 -> 1066 | E25: =GERMANY!F9 -> 1422 | F25: =GERMANY!G9 -> 2003 | G25: =GERMANY!H9 -> 2841 | H25: =GERMANY!I9 -> 3756 | I25: =IF(C25=0,"",H25/C25-1) -> 4.3888092
A26: GERMANY | B26: Medium truck | C26: =GERMANY!D10 -> 35 | D26: =GERMANY!E10 -> 34 | E26: =GERMANY!F10 -> 33 | F26: =GERMANY!G10 -> 32 | G26: =GERMANY!H10 -> 31 | H26: =GERMANY!I10 -> 30 | I26: =IF(C26=0,"",H26/C26-1) -> -0.14285714
A27: GERMANY | B27: Pick-up (D-Max) | C27: =GERMANY!D12 -> 13048 | D27: =GERMANY!E12 -> 13657 | E27: =GERMANY!F12 -> 14247 | F27: =GERMANY!G12 -> 14820 | G27: =GERMANY!H12 -> 15375 | H27: =GERMANY!I12 -> 15914 | I27: =IF(C27=0,"",H27/C27-1) -> 0.21965052
A28: BELGIUM | B28: Light truck | C28: =BELGIUM!D9 -> 113 | D28: =BELGIUM!E9 -> 145 | E28: =BELGIUM!F9 -> 176 | F28: =BELGIUM!G9 -> 206 | G28: =BELGIUM!H9 -> 235 | H28: =BELGIUM!I9 -> 263 | I28: =IF(C28=0,"",H28/C28-1) -> 1.3274336
A29: BELGIUM | B29: Pick-up (D-Max) | C29: =BELGIUM!D12 -> 9452 | D29: =BELGIUM!E12 -> 10008 | E29: =BELGIUM!F12 -> 10548 | F29: =BELGIUM!G12 -> 11072 | G29: =BELGIUM!H12 -> 11580 | H29: =BELGIUM!I12 -> 12073 | I29: =IF(C29=0,"",H29/C29-1) -> 0.27729581
A30: PORTUGAL | B30: Light truck | C30: =PORTUGAL!D9 -> 2206 | D30: =PORTUGAL!E9 -> 2596 | E30: =PORTUGAL!F9 -> 2974 | F30: =PORTUGAL!G9 -> 3341 | G30: =PORTUGAL!H9 -> 3697 | H30: =PORTUGAL!I9 -> 4042 | I30: =IF(C30=0,"",H30/C30-1) -> 0.83227561
A31: PORTUGAL | B31: Medium truck | C31: =PORTUGAL!D10 -> 0 | D31: =PORTUGAL!E10 -> 96 | E31: =PORTUGAL!F10 -> 201 | F31: =PORTUGAL!G10 -> 303 | G31: =PORTUGAL!H10 -> 402 | H31: =PORTUGAL!I10 -> 498 | I31: =IF(C31=0,"",H31/C31-1)
A32: PORTUGAL | B32: F-Series | C32: =PORTUGAL!D11 -> 269 | D32: =PORTUGAL!E11 -> 261 | E32: =PORTUGAL!F11 -> 253 | F32: =PORTUGAL!G11 -> 245 | G32: =PORTUGAL!H11 -> 238 | H32: =PORTUGAL!I11 -> 231 | I32: =IF(C32=0,"",H32/C32-1) -> -0.14126394
A33: PORTUGAL | B33: Pick-up (D-Max) | C33: =PORTUGAL!D12 -> 4733 | D33: =PORTUGAL!E12 -> 5491 | E33: =PORTUGAL!F12 -> 6226 | F33: =PORTUGAL!G12 -> 6879 | G33: =PORTUGAL!H12 -> 7513 | H33: =PORTUGAL!I12 -> 8128 | I33: =IF(C33=0,"",H33/C33-1) -> 0.71730404
A34: IRELAND | B34: Light truck | C34: =IRELAND!D9 -> 731 | D34: =IRELAND!E9 -> 925 | E34: =IRELAND!F9 -> 1113 | F34: =IRELAND!G9 -> 1296 | G34: =IRELAND!H9 -> 1473 | H34: =IRELAND!I9 -> 1645 | I34: =IF(C34=0,"",H34/C34-1) -> 1.250342
A35: IRELAND | B35: Medium truck | C35: =IRELAND!D10 -> 0 | D35: =IRELAND!E10 -> 36 | E35: =IRELAND!F10 -> 71 | F35: =IRELAND!G10 -> 105 | G35: =IRELAND!H10 -> 138 | H35: =IRELAND!I10 -> 170 | I35: =IF(C35=0,"",H35/C35-1)
A36: IRELAND | B36: F-Series | C36: =IRELAND!D11 -> 92 | D36: =IRELAND!E11 -> 89 | E36: =IRELAND!F11 -> 86 | F36: =IRELAND!G11 -> 83 | G36: =IRELAND!H11 -> 81 | H36: =IRELAND!I11 -> 79 | I36: =IF(C36=0,"",H36/C36-1) -> -0.14130435
A37: IRELAND | B37: Pick-up (D-Max) | C37: =IRELAND!D12 -> 1338 | D37: =IRELAND!E12 -> 1728 | E37: =IRELAND!F12 -> 2106 | F37: =IRELAND!G12 -> 2473 | G37: =IRELAND!H12 -> 2829 | H37: =IRELAND!I12 -> 3174 | I37: =IF(C37=0,"",H37/C37-1) -> 1.3721973
A38: GREECE | B38: Light truck | C38: =GREECE!D9 -> 37 | D38: =GREECE!E9 -> 56 | E38: =GREECE!F9 -> 74 | F38: =GREECE!G9 -> 92 | G38: =GREECE!H9 -> 109 | H38: =GREECE!I9 -> 126 | I38: =IF(C38=0,"",H38/C38-1) -> 2.4054054
A39: GREECE | B39: Medium truck | C39: =GREECE!D10 -> 0 | D39: =GREECE!E10 -> 5 | E39: =GREECE!F10 -> 10 | F39: =GREECE!G10 -> 15 | G39: =GREECE!H10 -> 20 | H39: =GREECE!I10 -> 24 | I39: =IF(C39=0,"",H39/C39-1)
A40: GREECE | B40: Pick-up (D-Max) | C40: =GREECE!D12 -> 3705 | D40: =GREECE!E12 -> 4224 | E40: =GREECE!F12 -> 4727 | F40: =GREECE!G12 -> 5215 | G40: =GREECE!H12 -> 5689 | H40: =GREECE!I12 -> 6148 | I40: =IF(C40=0,"",H40/C40-1) -> 0.65937922
A41: CYPRUS | B41: Light truck | C41: =CYPRUS!D9 -> 203 | D41: =CYPRUS!E9 -> 227 | E41: =CYPRUS!F9 -> 250 | F41: =CYPRUS!G9 -> 272 | G41: =CYPRUS!H9 -> 294 | H41: =CYPRUS!I9 -> 315 | I41: =IF(C41=0,"",H41/C41-1) -> 0.55172414
A42: CYPRUS | B42: Medium truck | C42: =CYPRUS!D10 -> 0 | D42: =CYPRUS!E10 -> 5 | E42: =CYPRUS!F10 -> 10 | F42: =CYPRUS!G10 -> 15 | G42: =CYPRUS!H10 -> 20 | H42: =CYPRUS!I10 -> 24 | I42: =IF(C42=0,"",H42/C42-1)
A43: CYPRUS | B43: Pick-up (D-Max) | C43: =CYPRUS!D12 -> 2105 | D43: =CYPRUS!E12 -> 2402 | E43: =CYPRUS!F12 -> 2730 | F43: =CYPRUS!G12 -> 3008 | G43: =CYPRUS!H12 -> 3278 | H43: =CYPRUS!I12 -> 3540 | I43: =IF(C43=0,"",H43/C43-1) -> 0.68171021
A44: MALTA | B44: Light truck | C44: =MALTA!D9 -> 243 | D44: =MALTA!E9 -> 260 | E44: =MALTA!F9 -> 276 | F44: =MALTA!G9 -> 292 | G44: =MALTA!H9 -> 307 | H44: =MALTA!I9 -> 322 | I44: =IF(C44=0,"",H44/C44-1) -> 0.32510288
A45: MALTA | B45: Pick-up (D-Max) | C45: =MALTA!D12 -> 797 | D45: =MALTA!E12 -> 848 | E45: =MALTA!F12 -> 948 | F45: =MALTA!G12 -> 1025 | G45: =MALTA!H12 -> 1099 | H45: =MALTA!I12 -> 1171 | I45: =IF(C45=0,"",H45/C45-1) -> 0.46925972
A46: Total | C46: =SUM(C12:C45) -> 163170 | D46: =SUM(D12:D45) -> 172351 | E46: =SUM(E12:E45) -> 180821 | F46: =SUM(F12:F45) -> 189094 | G46: =SUM(G12:G45) -> 197312 | H46: =SUM(H12:H45) -> 205337 | I46: =H46/C46-1 -> 0.25842373
A47: of which pick-ups | C47: =SUMIF($B$12:$B$45,"Pick-up (D-Max)",C12:C45) -> 125140 | D47: =SUMIF($B$12:$B$45,"Pick-up (D-Max)",D12:D45) -> 131617 | E47: =SUMIF($B$12:$B$45,"Pick-up (D-Max)",E12:E45) -> 137509 | F47: =SUMIF($B$12:$B$45,"Pick-up (D-Max)",F12:F45) -> 143079 | G47: =SUMIF($B$12:$B$45,"Pick-up (D-Max)",G12:G45) -> 148481 | H47: =SUMIF($B$12:$B$45,"Pick-up (D-Max)",H12:H45) -> 153721
A48: of which trucks | C48: =C46-C47 -> 38030 | D48: =D46-D47 -> 40734 | E48: =E46-E47 -> 43312 | F48: =F46-F47 -> 46015 | G48: =G46-G47 -> 48831 | H48: =H46-H47 -> 51616
A50: New pick-ups and pick-ups leaving the road per year (16 distributors and UMI, UIO V19)
C51: FY26 (CY2025) | D51: FY27 (CY2026) | E51: FY28 (CY2027) | F51: FY29 (CY2028) | G51: FY30 (CY2029) | H51: FY31 (CY2030)
A52: Pick-ups in use | C52: =C47 -> 125140 | D52: =D47 -> 131617 | E52: =E47 -> 137509 | F52: =F47 -> 143079 | G52: =G47 -> 148481 | H52: =H47 -> 153721
A53: Pick-ups leaving the road (3% a year) | D53: =C52*Inputs!$B$40 -> 3754.2 | E53: =D52*Inputs!$B$40 -> 3948.51 | F53: =E52*Inputs!$B$40 -> 4125.27 | G53: =F52*Inputs!$B$40 -> 4292.37 | H53: =G52*Inputs!$B$40 -> 4454.43
A54: New pick-ups in the forecast | D54: =D52-C52+D53 -> 10231.2 | E54: =E52-D52+E53 -> 9840.51 | F54: =F52-E52+F53 -> 9695.27 | G54: =G52-F52+G53 -> 9694.37 | H54: =H52-G52+H53 -> 9694.43
A55: New pick-ups = change in pick-ups in use + pick-ups leaving the road. The UIO V20 spec uses the same new pick-ups.
A57: Price index (FY2026 = 1) | C57: 1 | D57: =C57*(1+Inputs!$B$9) -> 1.05 | E57: =D57*(1+'Dashboard (2)'!$T$1) -> 1.0815 | F57: =E57*(1+'Dashboard (2)'!$T$1) -> 1.113945 | G57: =F57*(1+'Dashboard (2)'!$T$1) -> 1.1473634 | H57: =G57*(1+'Dashboard (2)'!$T$1) -> 1.1817843
A59: Parts potential (ISZE maximum spend, EUR)
A60: Distributor | C60: FY26 (CY2025) | D60: FY27 (CY2026) | E60: FY28 (CY2027) | F60: FY29 (CY2028) | G60: FY30 (CY2029) | H60: FY31 (CY2030)
A61: ITUK | C61: ='Dashboard (2)'!N9 -> 11529408 | D61: ='Dashboard (2)'!X9 -> 12535797 | E61: ='Dashboard (2)'!AH9 -> 13579598 | F61: ='Dashboard (2)'!AR9 -> 14579697 | G61: ='Dashboard (2)'!BB9 -> 15559892 | H61: ='Dashboard (2)'!BL9 -> 16534860
A62: UTI | C62: ='Dashboard (2)'!N10 -> 7762638.8 | D62: ='Dashboard (2)'!X10 -> 8485129 | E62: ='Dashboard (2)'!AH10 -> 8911877.3 | F62: ='Dashboard (2)'!AR10 -> 9436908.1 | G62: ='Dashboard (2)'!BB10 -> 9979388.1 | H62: ='Dashboard (2)'!BL10 -> 10545924
A63: IUK | C63: ='Dashboard (2)'!N11 -> 11945750 | D63: ='Dashboard (2)'!X11 -> 12936000 | E63: ='Dashboard (2)'!AH11 -> 13573366 | F63: ='Dashboard (2)'!AR11 -> 14229533 | G63: ='Dashboard (2)'!BB11 -> 14905110 | H63: ='Dashboard (2)'!BL11 -> 15600734
A64: UMI | C64: ='Dashboard (2)'!N12 -> 4635500 | D64: ='Dashboard (2)'!X12 -> 4957575 | E64: ='Dashboard (2)'!AH12 -> 5223374.6 | F64: ='Dashboard (2)'!AR12 -> 5477546.1 | G64: ='Dashboard (2)'!BB12 -> 5739398.3 | H64: ='Dashboard (2)'!BL12 -> 6009077.5
A65: NORWAY | C65: ='Dashboard (2)'!N13 -> 1982250 | D65: ='Dashboard (2)'!X13 -> 2129137.5 | E65: ='Dashboard (2)'!AH13 -> 2221941.8 | F65: ='Dashboard (2)'!AR13 -> 2346525.1 | G65: ='Dashboard (2)'!BB13 -> 2474862.7 | H65: ='Dashboard (2)'!BL13 -> 2607016.1
A66: SWEDEN | C66: ='Dashboard (2)'!N14 -> 2110750 | D66: ='Dashboard (2)'!X14 -> 2386125 | E66: ='Dashboard (2)'!AH14 -> 2632641.4 | F66: ='Dashboard (2)'!AR14 -> 2873978.1 | G66: ='Dashboard (2)'!BB14 -> 3122262.5 | H66: ='Dashboard (2)'!BL14 -> 3377834.8
A67: HUNGARY | C67: ='Dashboard (2)'!N15 -> 933500 | D67: ='Dashboard (2)'!X15 -> 1047900 | E67: ='Dashboard (2)'!AH15 -> 1146930.8 | F67: ='Dashboard (2)'!AR15 -> 1222554.6 | G67: ='Dashboard (2)'!BB15 -> 1300249.5 | H67: ='Dashboard (2)'!BL15 -> 1380324
A68: FINLAND | C68: ='Dashboard (2)'!N16 -> 301000 | D68: ='Dashboard (2)'!X16 -> 343350 | E68: ='Dashboard (2)'!AH16 -> 380958.38 | F68: ='Dashboard (2)'!AR16 -> 423856.07 | G68: ='Dashboard (2)'!BB16 -> 467837.41 | H68: ='Dashboard (2)'!BL16 -> 513189.81
A69: ROMANIA | C69: ='Dashboard (2)'!N17 -> 267750 | D69: ='Dashboard (2)'!X17 -> 317362.5 | E69: ='Dashboard (2)'!AH17 -> 363113.62 | F69: ='Dashboard (2)'!AR17 -> 410767.22 | G69: ='Dashboard (2)'!BB17 -> 459805.86 | H69: ='Dashboard (2)'!BL17 -> 510235.35
A70: DENMARK | C70: ='Dashboard (2)'!N18 -> 212500 | D70: ='Dashboard (2)'!X18 -> 247800 | E70: ='Dashboard (2)'!AH18 -> 280108.5 | F70: ='Dashboard (2)'!AR18 -> 317474.33 | G70: ='Dashboard (2)'!BB18 -> 355969.48 | H70: ='Dashboard (2)'!BL18 -> 395602.28
A71: ICELAND | C71: ='Dashboard (2)'!N19 -> 101500 | D71: ='Dashboard (2)'!X19 -> 115237.5 | E71: ='Dashboard (2)'!AH19 -> 127346.62 | F71: ='Dashboard (2)'!AR19 -> 152888.95 | G71: ='Dashboard (2)'!BB19 -> 179275.52 | H71: ='Dashboard (2)'!BL19 -> 206221.35
A72: GERMANY | C72: ='Dashboard (2)'!N23 -> 3808128 | D72: ='Dashboard (2)'!X23 -> 4443791.1 | E72: ='Dashboard (2)'!AH23 -> 5020192.1 | F72: ='Dashboard (2)'!AR23 -> 5807664.8 | G72: ='Dashboard (2)'!BB23 -> 6850615.1 | H72: ='Dashboard (2)'!BL23 -> 8013435.6
A73: BELGIUM | C73: ='Dashboard (2)'!N26 -> 2446507 | D73: ='Dashboard (2)'!X26 -> 2739612.8 | E73: ='Dashboard (2)'!AH26 -> 2992579.7 | F73: ='Dashboard (2)'!AR26 -> 3252980.1 | G73: ='Dashboard (2)'!BB26 -> 3520873.8 | H73: ='Dashboard (2)'!BL26 -> 3796608.4
A74: PORTUGAL | C74: ='Dashboard (2)'!N30 -> 3052087 | D74: ='Dashboard (2)'!X30 -> 3788245.6 | E74: ='Dashboard (2)'!AH30 -> 4495778.2 | F74: ='Dashboard (2)'!AR30 -> 5207497.9 | G74: ='Dashboard (2)'!BB30 -> 5941062.3 | H74: ='Dashboard (2)'!BL30 -> 6695588.9
A75: IRELAND | C75: ='Dashboard (2)'!N34 -> 956313 | D75: ='Dashboard (2)'!X34 -> 1287772.5 | E75: ='Dashboard (2)'!AH34 -> 1609559.7 | F75: ='Dashboard (2)'!AR34 -> 1941327.6 | G75: ='Dashboard (2)'!BB34 -> 2283310.4 | H75: ='Dashboard (2)'!BL34 -> 2635400.2
A76: GREECE | C76: ='Dashboard (2)'!N37 -> 953593 | D76: ='Dashboard (2)'!X37 -> 1156909.9 | E76: ='Dashboard (2)'!AH37 -> 1346798.4 | F76: ='Dashboard (2)'!AR37 -> 1542861.7 | G76: ='Dashboard (2)'!BB37 -> 1744613 | H76: ='Dashboard (2)'!BL37 -> 1951600.9
A77: CYPRUS | C77: ='Dashboard (2)'!N40 -> 676267 | D77: ='Dashboard (2)'!X40 -> 811322.4 | E77: ='Dashboard (2)'!AH40 -> 947523.78 | F77: ='Dashboard (2)'!AR40 -> 1076419.5 | G77: ='Dashboard (2)'!BB40 -> 1209901.5 | H77: ='Dashboard (2)'!BL40 -> 1346138.5
A78: MALTA | C78: ='Dashboard (2)'!N43 -> 378827 | D78: ='Dashboard (2)'!X43 -> 424347 | E78: ='Dashboard (2)'!AH43 -> 476902.57 | F78: ='Dashboard (2)'!AR43 -> 525824.37 | G78: ='Dashboard (2)'!BB43 -> 575543.85 | H78: ='Dashboard (2)'!BL43 -> 627182.36
A79: Total | C79: =SUM(C61:C78) -> 54054269 | D79: =SUM(D61:D78) -> 60153415 | E79: =SUM(E61:E78) -> 65330591 | F79: =SUM(F61:F78) -> 70826305 | G79: =SUM(G61:G78) -> 76669972 | H79: =SUM(H61:H78) -> 82746973
A81: GPS share (target)
A82: Distributor | C82: FY26 (CY2025) | D82: FY27 (CY2026) | E82: FY28 (CY2027) | F82: FY29 (CY2028) | G82: FY30 (CY2029) | H82: FY31 (CY2030)
A83: ITUK | D83: ='Dashboard (2)'!Y9 -> 0.58634037 | E83: ='Dashboard (2)'!AI9 -> 0.59634037 | F83: ='Dashboard (2)'!AS9 -> 0.60634037 | G83: ='Dashboard (2)'!BC9 -> 0.61634037 | H83: ='Dashboard (2)'!BM9 -> 0.62634037
A84: UTI | D84: ='Dashboard (2)'!Y10 -> 0.38386428 | E84: ='Dashboard (2)'!AI10 -> 0.39386428 | F84: ='Dashboard (2)'!AS10 -> 0.40386428 | G84: ='Dashboard (2)'!BC10 -> 0.41386428 | H84: ='Dashboard (2)'!BM10 -> 0.42386428
A85: IUK | D85: ='Dashboard (2)'!Y11 -> 0.48668866 | E85: ='Dashboard (2)'!AI11 -> 0.49668866 | F85: ='Dashboard (2)'!AS11 -> 0.50668866 | G85: ='Dashboard (2)'!BC11 -> 0.51668866 | H85: ='Dashboard (2)'!BM11 -> 0.52668866
A86: UMI | D86: ='Dashboard (2)'!Y12 -> 0.6177447 | E86: ='Dashboard (2)'!AI12 -> 0.6277447 | F86: ='Dashboard (2)'!AS12 -> 0.6377447 | G86: ='Dashboard (2)'!BC12 -> 0.6477447 | H86: ='Dashboard (2)'!BM12 -> 0.6577447
A87: NORWAY | D87: ='Dashboard (2)'!Y13 -> 0.84688012 | E87: ='Dashboard (2)'!AI13 -> 0.85688012 | F87: ='Dashboard (2)'!AS13 -> 0.86688012 | G87: ='Dashboard (2)'!BC13 -> 0.87688012 | H87: ='Dashboard (2)'!BM13 -> 0.88688012
A88: SWEDEN | D88: ='Dashboard (2)'!Y14 -> 0.63167377 | E88: ='Dashboard (2)'!AI14 -> 0.64167377 | F88: ='Dashboard (2)'!AS14 -> 0.65167377 | G88: ='Dashboard (2)'!BC14 -> 0.66167377 | H88: ='Dashboard (2)'!BM14 -> 0.67167377
A89: HUNGARY | D89: ='Dashboard (2)'!Y15 -> 0.35161962 | E89: ='Dashboard (2)'!AI15 -> 0.36161962 | F89: ='Dashboard (2)'!AS15 -> 0.37161962 | G89: ='Dashboard (2)'!BC15 -> 0.38161962 | H89: ='Dashboard (2)'!BM15 -> 0.39161962
A90: FINLAND | D90: ='Dashboard (2)'!Y16 -> 1.0673665 | E90: ='Dashboard (2)'!AI16 -> 1.0773665 | F90: ='Dashboard (2)'!AS16 -> 1.0873665 | G90: ='Dashboard (2)'!BC16 -> 1.0973665 | H90: ='Dashboard (2)'!BM16 -> 1.1073665
A91: ROMANIA | D91: ='Dashboard (2)'!Y17 -> 0.64689462 | E91: ='Dashboard (2)'!AI17 -> 0.65689462 | F91: ='Dashboard (2)'!AS17 -> 0.66689462 | G91: ='Dashboard (2)'!BC17 -> 0.67689462 | H91: ='Dashboard (2)'!BM17 -> 0.68689462
A92: DENMARK | D92: ='Dashboard (2)'!Y18 -> 0.77506215 | E92: ='Dashboard (2)'!AI18 -> 0.78506215 | F92: ='Dashboard (2)'!AS18 -> 0.79506215 | G92: ='Dashboard (2)'!BC18 -> 0.80506215 | H92: ='Dashboard (2)'!BM18 -> 0.81506215
A93: ICELAND | D93: ='Dashboard (2)'!Y19 -> 0.92569064 | E93: ='Dashboard (2)'!AI19 -> 0.93569064 | F93: ='Dashboard (2)'!AS19 -> 0.94569064 | G93: ='Dashboard (2)'!BC19 -> 0.95569064 | H93: ='Dashboard (2)'!BM19 -> 0.96569064
A94: GERMANY | D94: ='Dashboard (2)'!Y23 -> 0.67367052 | E94: ='Dashboard (2)'!AI23 -> 0.68367052 | F94: ='Dashboard (2)'!AS23 -> 0.69367052 | G94: ='Dashboard (2)'!BC23 -> 0.70367052 | H94: ='Dashboard (2)'!BM23 -> 0.71367052
A95: BELGIUM | D95: ='Dashboard (2)'!Y26 -> 0.85628539 | E95: ='Dashboard (2)'!AI26 -> 0.86628539 | F95: ='Dashboard (2)'!AS26 -> 0.87628539 | G95: ='Dashboard (2)'!BC26 -> 0.88628539 | H95: ='Dashboard (2)'!BM26 -> 0.89628539
A96: PORTUGAL | D96: ='Dashboard (2)'!Y30 -> 0.50853561 | E96: ='Dashboard (2)'!AI30 -> 0.51853561 | F96: ='Dashboard (2)'!AS30 -> 0.52853561 | G96: ='Dashboard (2)'!BC30 -> 0.53853561 | H96: ='Dashboard (2)'!BM30 -> 0.54853561
A97: IRELAND | D97: ='Dashboard (2)'!Y34 -> 1.0022137 | E97: ='Dashboard (2)'!AI34 -> 1.0122137 | F97: ='Dashboard (2)'!AS34 -> 1.0222137 | G97: ='Dashboard (2)'!BC34 -> 1.0322137 | H97: ='Dashboard (2)'!BM34 -> 1.0422137
A98: GREECE | D98: ='Dashboard (2)'!Y37 -> 0.514495 | E98: ='Dashboard (2)'!AI37 -> 0.524495 | F98: ='Dashboard (2)'!AS37 -> 0.534495 | G98: ='Dashboard (2)'!BC37 -> 0.544495 | H98: ='Dashboard (2)'!BM37 -> 0.554495
A99: CYPRUS | D99: ='Dashboard (2)'!Y40 -> 0.68308702 | E99: ='Dashboard (2)'!AI40 -> 0.69308702 | F99: ='Dashboard (2)'!AS40 -> 0.70308702 | G99: ='Dashboard (2)'!BC40 -> 0.71308702 | H99: ='Dashboard (2)'!BM40 -> 0.72308702
A100: MALTA | D100: ='Dashboard (2)'!Y43 -> 0.56731459 | E100: ='Dashboard (2)'!AI43 -> 0.57731459 | F100: ='Dashboard (2)'!AS43 -> 0.58731459 | G100: ='Dashboard (2)'!BC43 -> 0.59731459 | H100: ='Dashboard (2)'!BM43 -> 0.60731459
A102: ISZE parts sales target (EUR)
A103: Distributor | C103: FY26 (CY2025) | D103: FY27 (CY2026) | E103: FY28 (CY2027) | F103: FY29 (CY2028) | G103: FY30 (CY2029) | H103: FY31 (CY2030)
A104: ITUK | D104: ='Dashboard (2)'!Z9 -> 7350244 | E104: ='Dashboard (2)'!AJ9 -> 8098062.4 | F104: ='Dashboard (2)'!AT9 -> 8840259 | G104: ='Dashboard (2)'!BD9 -> 9590189.6 | H104: ='Dashboard (2)'!BN9 -> 10356450
A105: UTI | D105: ='Dashboard (2)'!Z10 -> 3257138 | E105: ='Dashboard (2)'!AJ10 -> 3510070.2 | F105: ='Dashboard (2)'!AT10 -> 3811230.1 | G105: ='Dashboard (2)'!BD10 -> 4130112.3 | H105: ='Dashboard (2)'!BN10 -> 4470040.4
A106: IUK | D106: ='Dashboard (2)'!Z11 -> 6295804.5 | E106: ='Dashboard (2)'!AJ11 -> 6741736.8 | F106: ='Dashboard (2)'!AT11 -> 7209943.2 | G106: ='Dashboard (2)'!BD11 -> 7701301.5 | H106: ='Dashboard (2)'!BN11 -> 8216729.6
A107: UMI | D107: ='Dashboard (2)'!Z12 -> 3062515.7 | E107: ='Dashboard (2)'!AJ12 -> 3278945.7 | F107: ='Dashboard (2)'!AT12 -> 3493276 | G107: ='Dashboard (2)'!BD12 -> 3717664.8 | H107: ='Dashboard (2)'!BN12 -> 3952438.9
...

Sheet UIO V20
A1: UIO V20 spec: the same fleet with the age curve also applied after 2025
A3: What is different in the UIO V20 spec
A4: Everything up to 2025 is the same as UIO V19, and the forecast of new pick-up and truck sales is the same. Only one thing changes: from 2026 vehicles leave the road on the same age curve as before 2026 (pick-up about 8 years, truck about 10 years) instead of 3% a year.
A5: Effect: each year about 10,000 new pick-ups are added for these distributors, while about 13,000 to 15,000 older pick-ups leave the road. The pick-up fleet therefore goes down instead of up.
A6: Medium trucks that UIO V19 shows from 2026 for Ireland, Portugal, Greece and Cyprus are planned vehicles, not registered vehicles; the UIO V20 spec leaves them out. ITUK and UTI are the same in both versions.
A7: Our reading: UIO V19 keeps vehicles too long (about 33 years); the UIO V20 curve takes pick-ups off the road early (almost all gone by year 12 to 13). The real fleet is most likely between the two. The UIO V20 spec is not yet approved, so this file uses UIO V19; this sheet shows what changes if UIO V20 is adopted.
A8: Targets on this sheet: FY2027 stays the same amount (budget + stretch). From FY2028 the same rule as the model: GPS share + the yearly stretch, applied to the smaller UIO V20 potential.
A10: Vehicles in use, UIO V20 spec
A11: Distributor | B11: Segment | C11: FY26 (CY2025) | D11: FY27 (CY2026) | E11: FY28 (CY2027) | F11: FY29 (CY2028) | G11: FY30 (CY2029) | H11: FY31 (CY2030) | I11: Change FY26 to FY31
A12: ITUK | B12: Light truck (N35 + N75) | C12: ='UIO V19'!C12 -> 22191 | D12: ='UIO V19'!D12 -> 23210 | E12: ='UIO V19'!E12 -> 24336 | F12: ='UIO V19'!F12 -> 25294 | G12: ='UIO V19'!G12 -> 26146 | H12: ='UIO V19'!H12 -> 26923 | I12: =IF(C12=0,"",H12/C12-1) -> 0.2132396
A13: ITUK | B13: F-Series | C13: ='UIO V19'!C13 -> 877 | D13: ='UIO V19'!D13 -> 963 | E13: ='UIO V19'!E13 -> 1055 | F13: ='UIO V19'!F13 -> 1141 | G13: ='UIO V19'!G13 -> 1218 | H13: ='UIO V19'!H13 -> 1286 | I13: =IF(C13=0,"",H13/C13-1) -> 0.4663626
A14: UTI | B14: Light truck | C14: ='UIO V19'!C14 -> 6059 | D14: ='UIO V19'!D14 -> 6101 | E14: ='UIO V19'!E14 -> 6064 | F14: ='UIO V19'!F14 -> 6093 | G14: ='UIO V19'!G14 -> 6110 | H14: ='UIO V19'!H14 -> 6124 | I14: =IF(C14=0,"",H14/C14-1) -> 0.010727843
A15: UTI | B15: Medium truck | C15: ='UIO V19'!C15 -> 4277 | D15: ='UIO V19'!D15 -> 4659 | E15: ='UIO V19'!E15 -> 4908 | F15: ='UIO V19'!F15 -> 5187 | G15: ='UIO V19'!G15 -> 5471 | H15: ='UIO V19'!H15 -> 5758 | I15: =IF(C15=0,"",H15/C15-1) -> 0.34627075
A16: IUK | B16: Pick-up (D-Max) | C16: ='UIO V19'!C16 -> 47783 | D16: 44926 | E16: 41800 | F16: 39058 | G16: 36654 | H16: 34546 | I16: =IF(C16=0,"",H16/C16-1) -> -0.27702321
A17: UMI | B17: Pick-up (D-Max) | C17: ='UIO V19'!C17 -> 18542 | D17: 17121 | E17: 15829 | F17: 14570 | G17: 13316 | H17: 12248 | I17: =IF(C17=0,"",H17/C17-1) -> -0.33944558
A18: NORWAY | B18: Pick-up (D-Max) | C18: ='UIO V19'!C18 -> 7929 | D18: 7251 | E18: 6647 | F18: 6003 | G18: 5523 | H18: 5068 | I18: =IF(C18=0,"",H18/C18-1) -> -0.36082734
A19: SWEDEN | B19: Pick-up (D-Max) | C19: ='UIO V19'!C19 -> 8443 | D19: 8643 | E19: 8772 | F19: 8837 | G19: 8926 | H19: 8886 | I19: =IF(C19=0,"",H19/C19-1) -> 0.052469501
A20: HUNGARY | B20: Pick-up (D-Max) | C20: ='UIO V19'!C20 -> 3734 | D20: 3603 | E20: 3467 | F20: 3319 | G20: 3168 | H20: 3040 | I20: =IF(C20=0,"",H20/C20-1) -> -0.18585967
A21: FINLAND | B21: Pick-up (D-Max) | C21: ='UIO V19'!C21 -> 1204 | D21: 1117 | E21: 1098 | F21: 1058 | G21: 1039 | H21: 1086 | I21: =IF(C21=0,"",H21/C21-1) -> -0.098006645
A22: ROMANIA | B22: Pick-up (D-Max) | C22: ='UIO V19'!C22 -> 1071 | D22: 1137 | E22: 1200 | F22: 1246 | G22: 1291 | H22: 1332 | I22: =IF(C22=0,"",H22/C22-1) -> 0.24369748
A23: DENMARK | B23: Pick-up (D-Max) | C23: ='UIO V19'!C23 -> 850 | D23: 890 | E23: 939 | F23: 973 | G23: 1003 | H23: 1038 | I23: =IF(C23=0,"",H23/C23-1) -> 0.22117647
A24: ICELAND | B24: Pick-up (D-Max) | C24: ='UIO V19'!C24 -> 406 | D24: 408 | E24: 419 | F24: 445 | G24: 500 | H24: 563 | I24: =IF(C24=0,"",H24/C24-1) -> 0.38669951
A25: GERMANY | B25: Light truck | C25: ='UIO V19'!C25 -> 697 | D25: 1025 | E25: 1400 | F25: 1917 | G25: 2639 | H25: 3493 | I25: =IF(C25=0,"",H25/C25-1) -> 4.0114778
A26: GERMANY | B26: Medium truck | C26: ='UIO V19'!C26 -> 35 | D26: 35 | E26: 30 | F26: 24 | G26: 18 | H26: 14 | I26: =IF(C26=0,"",H26/C26-1) -> -0.6
A27: GERMANY | B27: Pick-up (D-Max) | C27: ='UIO V19'!C27 -> 13048 | D27: 12578 | E27: 12156 | F27: 11631 | G27: 11141 | H27: 10597 | I27: =IF(C27=0,"",H27/C27-1) -> -0.18784488
... A45: MALTA | B45: Pick-up (D-Max) | C45: ='UIO V19'!C45 -> 797 | D45: 786 | E45: 774 | F45: 768 | G45: 767 | H45: 781 | I45: =IF(C45=0,"",H45/C45-1) -> -0.020075282
A46: Total | C46: =SUM(C12:C45) -> 163170 | D46: =SUM(D12:D45) -> 160938 | E46: =SUM(E12:E45) -> 158501 | F46: =SUM(F12:F45) -> 156308 | G46: =SUM(G12:G45) -> 154655 | H46: =SUM(H12:H45) -> 153516 | I46: =H46/C46-1 -> -0.059165288
A47: of which pick-ups | C47: =SUMIF($B$12:$B$45,"Pick-up (D-Max)",C12:C45) -> 125140 | D47: =SUMIF($B$12:$B$45,"Pick-up (D-Max)",D12:D45) -> 120562 | E47: =SUMIF($B$12:$B$45,"Pick-up (D-Max)",E12:E45) -> 115958 | F47: =SUMIF($B$12:$B$45,"Pick-up (D-Max)",F12:F45) -> 111581 | G47: =SUMIF($B$12:$B$45,"Pick-up (D-Max)",G12:G45) -> 107656 | H47: =SUMIF($B$12:$B$45,"Pick-up (D-Max)",H12:H45) -> 104185
A48: of which trucks | C48: =C46-C47 -> 38030 | D48: =D46-D47 -> 40376 | E48: =E46-E47 -> 42543 | F48: =F46-F47 -> 44727 | G48: =G46-G47 -> 46999 | H48: =H46-H47 -> 49331
A50: Difference with UIO V19
C51: FY26 (CY2025) | D51: FY27 (CY2026) | E51: FY28 (CY2027) | F51: FY29 (CY2028) | G51: FY30 (CY2029) | H51: FY31 (CY2030)
A52: Vehicles UIO V20 - UIO V19 | C52: =C46-'UIO V19'!C46 -> 0 | D52: =D46-'UIO V19'!D46 -> -11413 | E52: =E46-'UIO V19'!E46 -> -22320 | F52: =F46-'UIO V19'!F46 -> -32786 | G52: =G46-'UIO V19'!G46 -> -42657 | H52: =H46-'UIO V19'!H46 -> -51821
A53: in % | C53: =C46/'UIO V19'!C46-1 -> 0 | D53: =D46/'UIO V19'!D46-1 -> -0.066219517 | E53: =E46/'UIO V19'!E46-1 -> -0.12343699 | F53: =F46/'UIO V19'!F46-1 -> -0.17338467 | G53: =G46/'UIO V19'!G46-1 -> -0.2161906 | H53: =H46/'UIO V19'!H46-1 -> -0.25237049
A55: Price index (FY2026 = 1) | C55: 1 | D55: =C55*(1+Inputs!$B$9) -> 1.05 | E55: =D55*(1+'Dashboard (2)'!$T$1) -> 1.0815 | F55: =E55*(1+'Dashboard (2)'!$T$1) -> 1.113945 | G55: =F55*(1+'Dashboard (2)'!$T$1) -> 1.1473634 | H55: =G55*(1+'Dashboard (2)'!$T$1) -> 1.1817843
A57: Parts potential (ISZE maximum spend, EUR)
A58: Distributor | C58: FY26 (CY2025) | D58: FY27 (CY2026) | E58: FY28 (CY2027) | F58: FY29 (CY2028) | G58: FY30 (CY2029) | H58: FY31 (CY2030)
A59: ITUK | C59: ='Dashboard (2)'!N9 -> 11529408 | D59: ='Dashboard (2)'!X9 -> 12535797 | E59: ='Dashboard (2)'!AH9 -> 13579598 | F59: ='Dashboard (2)'!AR9 -> 14579697 | G59: ='Dashboard (2)'!BB9 -> 15559892 | H59: ='Dashboard (2)'!BL9 -> 16534860
A60: UTI | C60: ='Dashboard (2)'!N10 -> 7762638.8 | D60: ='Dashboard (2)'!X10 -> 8485129 | E60: ='Dashboard (2)'!AH10 -> 8911877.3 | F60: ='Dashboard (2)'!AR10 -> 9436908.1 | G60: ='Dashboard (2)'!BB10 -> 9979388.1 | H60: ='Dashboard (2)'!BL10 -> 10545924
A61: IUK | C61: =(C16*Inputs!$B$4)*C$55 -> 11945750 | D61: =(D16*Inputs!$B$4)*D$55 -> 11793075 | E61: =(E16*Inputs!$B$4)*E$55 -> 11301675 | F61: =(F16*Inputs!$B$4)*F$55 -> 10877116 | G61: =(G16*Inputs!$B$4)*G$55 -> 10513864 | H61: =(H16*Inputs!$B$4)*H$55 -> 10206480
A62: UMI | C62: =(C17*Inputs!$B$4)*C$55 -> 4635500 | D62: =(D17*Inputs!$B$4)*D$55 -> 4494262.5 | E62: =(E17*Inputs!$B$4)*E$55 -> 4279765.9 | F62: =(F17*Inputs!$B$4)*F$55 -> 4057544.7 | G62: =(G17*Inputs!$B$4)*G$55 -> 3819572.6 | H62: =(H17*Inputs!$B$4)*H$55 -> 3618623.4
A63: NORWAY | C63: =(C18*Inputs!$B$4)*C$55 -> 1982250 | D63: =(D18*Inputs!$B$4)*D$55 -> 1903387.5 | E63: =(E18*Inputs!$B$4)*E$55 -> 1797182.6 | F63: =(F18*Inputs!$B$4)*F$55 -> 1671753 | G63: =(G18*Inputs!$B$4)*G$55 -> 1584221.9 | H63: =(H18*Inputs!$B$4)*H$55 -> 1497320.6
A64: SWEDEN | C64: =(C19*Inputs!$B$4)*C$55 -> 2110750 | D64: =(D19*Inputs!$B$4)*D$55 -> 2268787.5 | E64: =(E19*Inputs!$B$4)*E$55 -> 2371729.5 | F64: =(F19*Inputs!$B$4)*F$55 -> 2460983 | G64: =(G19*Inputs!$B$4)*G$55 -> 2560341.3 | H64: =(H19*Inputs!$B$4)*H$55 -> 2625333.7
A65: HUNGARY | C65: =(C20*Inputs!$B$4)*C$55 -> 933500 | D65: =(D20*Inputs!$B$4)*D$55 -> 945787.5 | E65: =(E20*Inputs!$B$4)*E$55 -> 937390.12 | F65: =(F20*Inputs!$B$4)*F$55 -> 924295.86 | G65: =(G20*Inputs!$B$4)*G$55 -> 908711.77 | H65: =(H20*Inputs!$B$4)*H$55 -> 898156.03
A66: FINLAND | C66: =(C21*Inputs!$B$4)*C$55 -> 301000 | D66: =(D21*Inputs!$B$4)*D$55 -> 293212.5 | E66: =(E21*Inputs!$B$4)*E$55 -> 296871.75 | F66: =(F21*Inputs!$B$4)*F$55 -> 294638.45 | G66: =(G21*Inputs!$B$4)*G$55 -> 298027.63 | H66: =(H21*Inputs!$B$4)*H$55 -> 320854.42
A67: ROMANIA | C67: =(C22*Inputs!$B$4)*C$55 -> 267750 | D67: =(D22*Inputs!$B$4)*D$55 -> 298462.5 | E67: =(E22*Inputs!$B$4)*E$55 -> 324450 | F67: =(F22*Inputs!$B$4)*F$55 -> 346993.87 | G67: =(G22*Inputs!$B$4)*G$55 -> 370311.52 | H67: =(H22*Inputs!$B$4)*H$55 -> 393534.16
A68: DENMARK | C68: =(C23*Inputs!$B$4)*C$55 -> 212500 | D68: =(D23*Inputs!$B$4)*D$55 -> 233625 | E68: =(E23*Inputs!$B$4)*E$55 -> 253882.12 | F68: =(F23*Inputs!$B$4)*F$55 -> 270967.12 | G68: =(G23*Inputs!$B$4)*G$55 -> 287701.36 | H68: =(H23*Inputs!$B$4)*H$55 -> 306673.01
A69: ICELAND | C69: =(C24*Inputs!$B$4)*C$55 -> 101500 | D69: =(D24*Inputs!$B$4)*D$55 -> 107100 | E69: =(E24*Inputs!$B$4)*E$55 -> 113287.12 | F69: =(F24*Inputs!$B$4)*F$55 -> 123926.38 | G69: =(G24*Inputs!$B$4)*G$55 -> 143420.42 | H69: =(H24*Inputs!$B$4)*H$55 -> 166336.13
A70: GERMANY | C70: =(C25*Inputs!$B$5+C26*Inputs!$B$6+C27*Inputs!$B$4)*C$55 -> 3808128 | D70: =(D25*Inputs!$B$5+D26*Inputs!$B$6+D27*Inputs!$B$4)*D$55 -> 4129671 | E70: =(E25*Inputs!$B$5+E26*Inputs!$B$6+E27*Inputs!$B$4)*E$55 -> 4434377.1 | F70: =(F25*Inputs!$B$5+F26*Inputs!$B$6+F27*Inputs!$B$4)*F$55 -> 4840871.9 | G70: =(G25*Inputs!$B$5+G26*Inputs!$B$6+G27*Inputs!$B$4)*G$55 -> 5451624.7 | H70: =(H25*Inputs!$B$5+H26*Inputs!$B$6+H27*Inputs!$B$4)*H$55 -> 6196088.9
A71: BELGIUM | C71: =(C28*Inputs!$B$5+C29*Inputs!$B$4)*C$55 -> 2446507 | D71: =(D28*Inputs!$B$5+D29*Inputs!$B$4)*D$55 -> 2510280.1 | E71: =(E28*Inputs!$B$5+E29*Inputs!$B$4)*E$55 -> 2556925.6 | F71: =(F28*Inputs!$B$5+F29*Inputs!$B$4)*F$55 -> 2599388.4 | G71: =(G28*Inputs!$B$5+G29*Inputs!$B$4)*G$55 -> 2648695.2 | H71: =(H28*Inputs!$B$5+H29*Inputs!$B$4)*H$55 -> 2707805.7
A72: PORTUGAL | C72: =(C30*Inputs!$B$5+C31*Inputs!$B$6+C32*Inputs!$B$7+C33*Inputs!$B$4)*C$55 -> 3052087 | D72: =(D30*Inputs!$B$5+D31*Inputs!$B$6+D32*Inputs!$B$7+D33*Inputs!$B$4)*D$55 -> 3495203.2 | E72: =(E30*Inputs!$B$5+E31*Inputs!$B$6+E32*Inputs!$B$7+E33*Inputs!$B$4)*E$55 -> 3864201.7 | F72: =(F30*Inputs!$B$5+F31*Inputs!$B$6+F32*Inputs!$B$7+F33*Inputs!$B$4)*F$55 -> 4209859.9 | G72: =(G30*Inputs!$B$5+G31*Inputs!$B$6+G32*Inputs!$B$7+G33*Inputs!$B$4)*G$55 -> 4554977.4 | H72: =(H30*Inputs!$B$5+H31*Inputs!$B$6+H32*Inputs!$B$7+H33*Inputs!$B$4)*H$55 -> 4925916.7
A73: IRELAND | C73: =(C34*Inputs!$B$5+C35*Inputs!$B$6+C36*Inputs!$B$7+C37*Inputs!$B$4)*C$55 -> 956313 | D73: =(D34*Inputs!$B$5+D35*Inputs!$B$6+D36*Inputs!$B$7+D37*Inputs!$B$4)*D$55 -> 1218539.7 | E73: =(E34*Inputs!$B$5+E35*Inputs!$B$6+E36*Inputs!$B$7+E37*Inputs!$B$4)*E$55 -> 1409064.7 | F73: =(F34*Inputs!$B$5+F35*Inputs!$B$6+F36*Inputs!$B$7+F37*Inputs!$B$4)*F$55 -> 1613530.4 | G73: =(G34*Inputs!$B$5+G35*Inputs!$B$6+G36*Inputs!$B$7+G37*Inputs!$B$4)*G$55 -> 1807435.7 | H73: =(H34*Inputs!$B$5+H35*Inputs!$B$6+H36*Inputs!$B$7+H37*Inputs!$B$4)*H$55 -> 2013233.3
A74: GREECE | C74: =(C38*Inputs!$B$5+C39*Inputs!$B$6+C40*Inputs!$B$4)*C$55 -> 953593 | D74: =(D38*Inputs!$B$5+D39*Inputs!$B$6+D40*Inputs!$B$4)*D$55 -> 1084060.9 | E74: =(E38*Inputs!$B$5+E39*Inputs!$B$6+E40*Inputs!$B$4)*E$55 -> 1194554.6 | F74: =(F38*Inputs!$B$5+F39*Inputs!$B$6+F40*Inputs!$B$4)*F$55 -> 1332702.6 | G74: =(G38*Inputs!$B$5+G39*Inputs!$B$6+G40*Inputs!$B$4)*G$55 -> 1473761.8 | H74: =(H38*Inputs!$B$5+H39*Inputs!$B$6+H40*Inputs!$B$4)*H$55 -> 1610845.2
A75: CYPRUS | C75: =(C41*Inputs!$B$5+C42*Inputs!$B$6+C43*Inputs!$B$4)*C$55 -> 676267 | D75: =(D41*Inputs!$B$5+D42*Inputs!$B$6+D43*Inputs!$B$4)*D$55 -> 746544.75 | E75: =(E41*Inputs!$B$5+E42*Inputs!$B$6+E43*Inputs!$B$4)*E$55 -> 798646.65 | F75: =(F41*Inputs!$B$5+F42*Inputs!$B$6+F43*Inputs!$B$4)*F$55 -> 853772.01 | G75: =(G41*Inputs!$B$5+G42*Inputs!$B$6+G43*Inputs!$B$4)*G$55 -> 904576.68 | H75: =(H41*Inputs!$B$5+H42*Inputs!$B$6+H43*Inputs!$B$4)*H$55 -> 964430.49
A76: MALTA | C76: =(C44*Inputs!$B$5+C45*Inputs!$B$4)*C$55 -> 378827 | D76: =(D44*Inputs!$B$5+D45*Inputs!$B$4)*D$55 -> 407296.05 | E76: =(E44*Inputs!$B$5+E45*Inputs!$B$4)*E$55 -> 413073.52 | F76: =(F44*Inputs!$B$5+F45*Inputs!$B$4)*F$55 -> 419678.78 | G76: =(G44*Inputs!$B$5+G45*Inputs!$B$4)*G$55 -> 429438.6 | H76: =(H44*Inputs!$B$5+H45*Inputs!$B$4)*H$55 -> 442091.31
A77: Total | C77: =SUM(C59:C76) -> 54054269 | D77: =SUM(D59:D76) -> 56950222 | E77: =SUM(E59:E76) -> 58838553 | F77: =SUM(F59:F76) -> 60914628 | G77: =SUM(G59:G76) -> 63295963 | H77: =SUM(H59:H76) -> 65974506
A79: GPS share (target)
A80: Distributor | C80: FY26 (CY2025) | D80: FY27 (CY2026) | E80: FY28 (CY2027) | F80: FY29 (CY2028) | G80: FY30 (CY2029) | H80: FY31 (CY2030)
A81: ITUK | D81: =IFERROR('Dashboard (2)'!Z9/D59,0) -> 0.58634037 | E81: =IF(D81>=Inputs!$B$38,D81,MIN(D81+'Dashboard (2)'!$N$2,Inputs!$B$38)) -> 0.59634037 | F81: =IF(E81>=Inputs!$B$38,E81,MIN(E81+'Dashboard (2)'!$N$2,Inputs!$B$38)) -> 0.60634037 | G81: =IF(F81>=Inputs!$B$38,F81,MIN(F81+'Dashboard (2)'!$N$2,Inputs!$B$38)) -> 0.61634037 | H81: =IF(G81>=Inputs!$B$38,G81,MIN(G81+'Dashboard (2)'!$N$2,Inputs!$B$38)) -> 0.62634037
A82: UTI | D82: =IFERROR('Dashboard (2)'!Z10/D60,0) -> 0.38386428 | E82: =IF(D82>=Inputs!$B$38,D82,MIN(D82+'Dashboard (2)'!$N$2,Inputs!$B$38)) -> 0.39386428 | F82: =IF(E82>=Inputs!$B$38,E82,MIN(E82+'Dashboard (2)'!$N$2,Inputs!$B$38)) -> 0.40386428 | G82: =IF(F82>=Inputs!$B$38,F82,MIN(F82+'Dashboard (2)'!$N$2,Inputs!$B$38)) -> 0.41386428 | H82: =IF(G82>=Inputs!$B$38,G82,MIN(G82+'Dashboard (2)'!$N$2,Inputs!$B$38)) -> 0.42386428
A83: IUK | D83: =IFERROR('Dashboard (2)'!Z11/D61,0) -> 0.53385605 | E83: =IF(D83>=Inputs!$B$38,D83,MIN(D83+'Dashboard (2)'!$N$2,Inputs!$B$38)) -> 0.54385605 | F83: =IF(E83>=Inputs!$B$38,E83,MIN(E83+'Dashboard (2)'!$N$2,Inputs!$B$38)) -> 0.55385605 | G83: =IF(F83>=Inputs!$B$38,F83,MIN(F83+'Dashboard (2)'!$N$2,Inputs!$B$38)) -> 0.56385605 | H83: =IF(G83>=Inputs!$B$38,G83,MIN(G83+'Dashboard (2)'!$N$2,Inputs!$B$38)) -> 0.57385605
A84: UMI | D84: =IFERROR('Dashboard (2)'!Z12/D62,0) -> 0.68142786 | E84: =IF(D84>=Inputs!$B$38,D84,MIN(D84+'Dashboard (2)'!$N$2,Inputs!$B$38)) -> 0.69142786 | F84: =IF(E84>=Inputs!$B$38,E84,MIN(E84+'Dashboard (2)'!$N$2,Inputs!$B$38)) -> 0.70142786 | G84: =IF(F84>=Inputs!$B$38,F84,MIN(F84+'Dashboard (2)'!$N$2,Inputs!$B$38)) -> 0.71142786 | H84: =IF(G84>=Inputs!$B$38,G84,MIN(G84+'Dashboard (2)'!$N$2,Inputs!$B$38)) -> 0.72142786
A85: NORWAY | D85: =IFERROR('Dashboard (2)'!Z13/D63,0) -> 0.94732377 | E85: =IF(D85>=Inputs!$B$38,D85,MIN(D85+'Dashboard (2)'!$N$2,Inputs!$B$38)) -> 0.95732377 | F85: =IF(E85>=Inputs!$B$38,E85,MIN(E85+'Dashboard (2)'!$N$2,Inputs!$B$38)) -> 0.96732377 | G85: =IF(F85>=Inputs!$B$38,F85,MIN(F85+'Dashboard (2)'!$N$2,Inputs!$B$38)) -> 0.97732377 | H85: =IF(G85>=Inputs!$B$38,G85,MIN(G85+'Dashboard (2)'!$N$2,Inputs!$B$38)) -> 0.98732377
A86: SWEDEN | D86: =IFERROR('Dashboard (2)'!Z14/D64,0) -> 0.66434277 | E86: =IF(D86>=Inputs!$B$38,D86,MIN(D86+'Dashboard (2)'!$N$2,Inputs!$B$38)) -> 0.67434277 | F86: =IF(E86>=Inputs!$B$38,E86,MIN(E86+'Dashboard (2)'!$N$2,Inputs!$B$38)) -> 0.68434277 | G86: =IF(F86>=Inputs!$B$38,F86,MIN(F86+'Dashboard (2)'!$N$2,Inputs!$B$38)) -> 0.69434277 | H86: =IF(G86>=Inputs!$B$38,G86,MIN(G86+'Dashboard (2)'!$N$2,Inputs!$B$38)) -> 0.70434277
A87: HUNGARY | D87: =IFERROR('Dashboard (2)'!Z15/D65,0) -> 0.38958244 | E87: =IF(D87>=Inputs!$B$38,D87,MIN(D87+'Dashboard (2)'!$N$2,Inputs!$B$38)) -> 0.39958244 | F87: =IF(E87>=Inputs!$B$38,E87,MIN(E87+'Dashboard (2)'!$N$2,Inputs!$B$38)) -> 0.40958244 | G87: =IF(F87>=Inputs!$B$38,F87,MIN(F87+'Dashboard (2)'!$N$2,Inputs!$B$38)) -> 0.41958244 | H87: =IF(G87>=Inputs!$B$38,G87,MIN(G87+'Dashboard (2)'!$N$2,Inputs!$B$38)) -> 0.42958244
A88: FINLAND | D88: =IFERROR('Dashboard (2)'!Z16/D66,0) -> 1.2498795 | E88: =IF(D88>=Inputs!$B$38,D88,MIN(D88+'Dashboard (2)'!$N$2,Inputs!$B$38)) -> 1.2598795 | F88: =IF(E88>=Inputs!$B$38,E88,MIN(E88+'Dashboard (2)'!$N$2,Inputs!$B$38)) -> 1.2698795 | G88: =IF(F88>=Inputs!$B$38,F88,MIN(F88+'Dashboard (2)'!$N$2,Inputs!$B$38)) -> 1.2798795 | H88: =IF(G88>=Inputs!$B$38,G88,MIN(G88+'Dashboard (2)'!$N$2,Inputs!$B$38)) -> 1.2898795
A89: ROMANIA | D89: =IFERROR('Dashboard (2)'!Z17/D67,0) -> 0.68785893 | E89: =IF(D89>=Inputs!$B$38,D89,MIN(D89+'Dashboard (2)'!$N$2,Inputs!$B$38)) -> 0.69785893 | F89: =IF(E89>=Inputs!$B$38,E89,MIN(E89+'Dashboard (2)'!$N$2,Inputs!$B$38)) -> 0.70785893 | G89: =IF(F89>=Inputs!$B$38,F89,MIN(F89+'Dashboard (2)'!$N$2,Inputs!$B$38)) -> 0.71785893 | H89: =IF(G89>=Inputs!$B$38,G89,MIN(G89+'Dashboard (2)'!$N$2,Inputs!$B$38)) -> 0.72785893
A90: DENMARK | D90: =IFERROR('Dashboard (2)'!Z18/D68,0) -> 0.82208839 | E90: =IF(D90>=Inputs!$B$38,D90,MIN(D90+'Dashboard (2)'!$N$2,Inputs!$B$38)) -> 0.83208839 | F90: =IF(E90>=Inputs!$B$38,E90,MIN(E90+'Dashboard (2)'!$N$2,Inputs!$B$38)) -> 0.84208839 | G90: =IF(F90>=Inputs!$B$38,F90,MIN(F90+'Dashboard (2)'!$N$2,Inputs!$B$38)) -> 0.85208839 | H90: =IF(G90>=Inputs!$B$38,G90,MIN(G90+'Dashboard (2)'!$N$2,Inputs!$B$38)) -> 0.86208839
A91: ICELAND | D91: =IFERROR('Dashboard (2)'!Z19/D69,0) -> 0.99602498 | E91: =IF(D91>=Inputs!$B$38,D91,MIN(D91+'Dashboard (2)'!$N$2,Inputs!$B$38)) -> 1.006025 | F91: =IF(E91>=Inputs!$B$38,E91,MIN(E91+'Dashboard (2)'!$N$2,Inputs!$B$38)) -> 1.016025 | G91: =IF(F91>=Inputs!$B$38,F91,MIN(F91+'Dashboard (2)'!$N$2,Inputs!$B$38)) -> 1.026025 | H91: =IF(G91>=Inputs!$B$38,G91,MIN(G91+'Dashboard (2)'!$N$2,Inputs!$B$38)) -> 1.036025
A92: GERMANY | D92: =IFERROR('Dashboard (2)'!Z23/D70,0) -> 0.72491273 | E92: =IF(D92>=Inputs!$B$38,D92,MIN(D92+'Dashboard (2)'!$N$2,Inputs!$B$38)) -> 0.73491273 | F92: =IF(E92>=Inputs!$B$38,E92,MIN(E92+'Dashboard (2)'!$N$2,Inputs!$B$38)) -> 0.74491273 | G92: =IF(F92>=Inputs!$B$38,F92,MIN(F92+'Dashboard (2)'!$N$2,Inputs!$B$38)) -> 0.75491273 | H92: =IF(G92>=Inputs!$B$38,G92,MIN(G92+'Dashboard (2)'!$N$2,Inputs!$B$38)) -> 0.76491273
A93: BELGIUM | D93: =IFERROR('Dashboard (2)'!Z26/D71,0) -> 0.93451337 | E93: =IF(D93>=Inputs!$B$38,D93,MIN(D93+'Dashboard (2)'!$N$2,Inputs!$B$38)) -> 0.94451337 | F93: =IF(E93>=Inputs!$B$38,E93,MIN(E93+'Dashboard (2)'!$N$2,Inputs!$B$38)) -> 0.95451337 | G93: =IF(F93>=Inputs!$B$38,F93,MIN(F93+'Dashboard (2)'!$N$2,Inputs!$B$38)) -> 0.96451337 | H93: =IF(G93>=Inputs!$B$38,G93,MIN(G93+'Dashboard (2)'!$N$2,Inputs!$B$38)) -> 0.97451337
A94: PORTUGAL | D94: =IFERROR('Dashboard (2)'!Z30/D72,0) -> 0.5511719 | E94: =IF(D94>=Inputs!$B$38,D94,MIN(D94+'Dashboard (2)'!$N$2,Inputs!$B$38)) -> 0.5611719 | F94: =IF(E94>=Inputs!$B$38,E94,MIN(E94+'Dashboard (2)'!$N$2,Inputs!$B$38)) -> 0.5711719 | G94: =IF(F94>=Inputs!$B$38,F94,MIN(F94+'Dashboard (2)'!$N$2,Inputs!$B$38)) -> 0.5811719 | H94: =IF(G94>=Inputs!$B$38,G94,MIN(G94+'Dashboard (2)'!$N$2,Inputs!$B$38)) -> 0.5911719
A95: IRELAND | D95: =IFERROR('Dashboard (2)'!Z34/D73,0) -> 1.0591557 | E95: =IF(D95>=Inputs!$B$38,D95,MIN(D95+'Dashboard (2)'!$N$2,Inputs!$B$38)) -> 1.0691557 | F95: =IF(E95>=Inputs!$B$38,E95,MIN(E95+'Dashboard (2)'!$N$2,Inputs!$B$38)) -> 1.0791557 | G95: =IF(F95>=Inputs!$B$38,F95,MIN(F95+'Dashboard (2)'!$N$2,Inputs!$B$38)) -> 1.0891557 | H95: =IF(G95>=Inputs!$B$38,G95,MIN(G95+'Dashboard (2)'!$N$2,Inputs!$B$38)) -> 1.0991557
A96: GREECE | D96: =IFERROR('Dashboard (2)'!Z37/D74,0) -> 0.54906911 | E96: =IF(D96>=Inputs!$B$38,D96,MIN(D96+'Dashboard (2)'!$N$2,Inputs!$B$38)) -> 0.55906911 | F96: =IF(E96>=Inputs!$B$38,E96,MIN(E96+'Dashboard (2)'!$N$2,Inputs!$B$38)) -> 0.56906911 | G96: =IF(F96>=Inputs!$B$38,F96,MIN(F96+'Dashboard (2)'!$N$2,Inputs!$B$38)) -> 0.57906911 | H96: =IF(G96>=Inputs!$B$38,G96,MIN(G96+'Dashboard (2)'!$N$2,Inputs!$B$38)) -> 0.58906911
A97: CYPRUS | D97: =IFERROR('Dashboard (2)'!Z40/D75,0) -> 0.74235845 | E97: =IF(D97>=Inputs!$B$38,D97,MIN(D97+'Dashboard (2)'!$N$2,Inputs!$B$38)) -> 0.75235845 | F97: =IF(E97>=Inputs!$B$38,E97,MIN(E97+'Dashboard (2)'!$N$2,Inputs!$B$38)) -> 0.76235845 | G97: =IF(F97>=Inputs!$B$38,F97,MIN(F97+'Dashboard (2)'!$N$2,Inputs!$B$38)) -> 0.77235845 | H97: =IF(G97>=Inputs!$B$38,G97,MIN(G97+'Dashboard (2)'!$N$2,Inputs!$B$38)) -> 0.78235845
A98: MALTA | D98: =IFERROR('Dashboard (2)'!Z43/D76,0) -> 0.59106452 | E98: =IF(D98>=Inputs!$B$38,D98,MIN(D98+'Dashboard (2)'!$N$2,Inputs!$B$38)) -> 0.60106452 | F98: =IF(E98>=Inputs!$B$38,E98,MIN(E98+'Dashboard (2)'!$N$2,Inputs!$B$38)) -> 0.61106452 | G98: =IF(F98>=Inputs!$B$38,F98,MIN(F98+'Dashboard (2)'!$N$2,Inputs!$B$38)) -> 0.62106452 | H98: =IF(G98>=Inputs!$B$38,G98,MIN(G98+'Dashboard (2)'!$N$2,Inputs!$B$38)) -> 0.63106452
A100: ISZE parts sales target (EUR)
A101: Distributor | C101: FY26 (CY2025) | D101: FY27 (CY2026) | E101: FY28 (CY2027) | F101: FY29 (CY2028) | G101: FY30 (CY2029) | H101: FY31 (CY2030)
A102: ITUK | D102: =D81*D59 -> 7350244 | E102: =E81*E59 -> 8098062.4 | F102: =F81*F59 -> 8840259 | G102: =G81*G59 -> 9590189.6 | H102: =H81*H59 -> 10356450
A103: UTI | D103: =D82*D60 -> 3257138 | E103: =E82*E60 -> 3510070.2 | F103: =F82*F60 -> 3811230.1 | G103: =G82*G60 -> 4130112.3 | H103: =H82*H60 -> 4470040.4
A104: IUK | D104: =D83*D61 -> 6295804.5 | E104: =E83*E61 -> 6146484.4 | F104: =F83*F61 -> 6024356.5 | G104: =G83*G61 -> 5928305.9 | H104: =H83*H61 -> 5857050.2
A105: UMI | D105: =D84*D62 -> 3062515.7 | E105: =E84*E62 -> 2959149.4 | F105: =F84*F62 -> 2846074.9 | G105: =G84*G62 -> 2717350.4 | H105: =H84*H62 -> 2610575.7
A106: NORWAY | D106: =D85*D63 -> 1803124.2 | E106: =E85*E63 -> 1720485.6 | F106: =F85*F63 -> 1617126.4 | G106: =G85*G63 -> 1548297.8 | H106: =H85*H63 -> 1478340.3
A107: SWEDEN | D107: =D86*D64 -> 1507252.6 | E107: =E86*E64 -> 1599358.6 | F107: =F86*F64 -> 1684155.9 | G107: =G86*G64 -> 1777754.5 | H107: =H86*H64 -> 1849134.8
A108: HUNGARY | D108: =D87*D65 -> 368462.2 | E108: =E87*E65 -> 374564.63 | F108: =F87*F65 -> 378575.35 | G108: =G87*G65 -> 381279.5 | H108: =H87*H65 -> 385832.06
A109: FINLAND | D109: =D88*D66 -> 366480.3 | E109: =E88*E66 -> 374022.64 | F109: =F88*F66 -> 374155.34 | G109: =G88*G66 -> 381439.46 | H109: =H88*H66 -> 413863.55
A110: ROMANIA | D110: =D89*D67 -> 205300.1 | E110: =E89*E67 -> 226420.33 | F110: =F89*F67 -> 245622.71 | G110: =G89*G67 -> 265831.43 | H110: =H89*H67 -> 286437.35
A111: DENMARK | D111: =D90*D68 -> 192060.4 | E111: =E90*E68 -> 211252.37 | F111: =F90*F68 -> 228178.27 | G111: =G90*G68 -> 245146.99 | H111: =H90*H68 -> 264379.24
A112: ICELAND | D112: =D91*D69 -> 106674.27 | E112: =E91*E69 -> 113969.68 | F112: =F91*F69 -> 125912.3 | G112: =G91*G69 -> 147152.93 | H112: =H91*H69 -> 172328.39
A113: GERMANY | D113: =D92*D70 -> 2993651.1 | E113: =E92*E70 -> 3258880.2 | F113: =F92*F70 -> 3606027.1 | G113: =G92*G70 -> 4115500.9 | H113: =H92*H70 -> 4739467.3
... A119: MALTA | D119: =D98*D76 -> 240738.25 | E119: =E98*E76 -> 248283.84 | F119: =F98*F76 -> 256450.81 | G119: =G98*G76 -> 266709.08 | H119: =H98*H76 -> 278988.14
A120: Total 18 distributors | D120: =SUM(D102:D119) -> 34461845 | E120: =SUM(E102:E119) -> 36199753 | F120: =SUM(F102:F119) -> 38074360 | G120: =SUM(G102:G119) -> 40217644 | H120: =SUM(H102:H119) -> 42630030
A121: Customers outside the 18 (held flat) | D121: =Inputs!$D$23 -> 2062082.3 | E121: =Inputs!$D$23 -> 2062082.3 | F121: =Inputs!$D$23 -> 2062082.3 | G121: =Inputs!$D$23 -> 2062082.3 | H121: =Inputs!$D$23 -> 2062082.3
A122: Total ISZE | D122: =D120+D121 -> 36523927 | E122: =E120+E121 -> 38261835 | F122: =F120+F121 -> 40136442 | G122: =G120+G121 -> 42279726 | H122: =H120+H121 -> 44692113
A123: Network plan | D123: =Inputs!D21 -> 35284444 | E123: =Inputs!E21 -> 37530000 | F123: =Inputs!F21 -> 41530410 | G123: =Inputs!G21 -> 46385705 | H123: =Inputs!H21 -> 52096000
A124: Above (+) / below (-) plan | D124: =D122-D123 -> 1239483.2 | E124: =E122-E123 -> 731835.07 | F124: =F122-F123 -> -1393967.6 | G124: =G122-G123 -> -4105978.9 | H124: =H122-H123 -> -7403887.5
A125: GPS share, 18 distributors | D125: =D120/D77 -> 0.60512223 | E125: =E120/E77 -> 0.61523866 | F125: =F120/F77 -> 0.62504462 | G125: =G120/G77 -> 0.63539035 | H125: =H120/H77 -> 0.64615914
A127: Summary: UIO V19 (this model) against the UIO V20 spec
C128: FY26 (CY2025) | D128: FY27 (CY2026) | E128: FY28 (CY2027) | F128: FY29 (CY2028) | G128: FY30 (CY2029) | H128: FY31 (CY2030)
A129: Vehicles, UIO V19 | D129: ='UIO V19'!D46 -> 172351 | E129: ='UIO V19'!E46 -> 180821 | F129: ='UIO V19'!F46 -> 189094 | G129: ='UIO V19'!G46 -> 197312 | H129: ='UIO V19'!H46 -> 205337
A130: Vehicles, UIO V20 | D130: =D46 -> 160938 | E130: =E46 -> 158501 | F130: =F46 -> 156308 | G130: =G46 -> 154655 | H130: =H46 -> 153516
...

Sheet Dashboard
A1: ISZE — FY2027 GPS Extended Target
A2: ISZE to distributor level. Stretch inputs on Dashboard (2) row 1. Every number on this sheet is live.
A3: ISZE to distributor (billing and GPS %) | M3: ISZE billing (reference) | P3: Distributor sales to dealers (distributor KPI)
A4: DB | B4: Segment | C4: BP FY27 | D4: Max spend | E4: GPS % | F4: Stretch% | G4: Stretch EUR | H4: New GPS | I4: EXT TARGET | J4: Note | M4: ISZE billing FY25 (EUR) | N4: ISZE billing FY26 (EUR) | P4: Sales to dealers FY25 (EUR) | Q4: Sales to dealers FY26 (EUR) | V4: Data coverage
A5: ITUK | B5: presented | C5: 6974170.1 | D5: ='Dashboard (2)'!X9 -> 12535797 | E5: =C5/D5 -> 0.55634037 | G5: 376073.91 | I5: =C5+G5 -> 7350244 | J5: Max spend on IML data (2026 vehicles, +5%); target as presented in July | L5: =G5*0.33/2 -> 62052.196 | M5: 5668549 | N5: 6658172 | P5: Not used (ITUK / UTI as presented)
A6: UTI | B6: presented | C6: 3098113.5 | D6: ='Dashboard (2)'!X10 -> 8485129 | E6: =C6/D6 -> 0.36512274 | G6: 159024.46 | I6: =C6+G6 -> 3257138 | J6: Max spend on IML data (2026 vehicles, +5%); target as presented in July | L6: =G6*0.33/2 -> 26239.035 | P6: Not used (ITUK / UTI as presented)
A7: IUK | B7: LCV | C7: =IUK!E20 -> 6062956.5 | D7: =IUK!E19 -> 12936000 | E7: =IUK!E21 -> 0.46868866 | F7: =IUK!E22 -> 0.018 | G7: =IUK!E23 -> 232848 | H7: =IUK!E25 -> 0.48668866 | I7: =IUK!E24 -> 6295804.5 | L7: =G7*0.33/2 -> 38419.92 | M7: 7154801 | N7: 5682505 | P7: 18843293 | Q7: 21418279 | V7: full 12/12 monthly coverage both FY25 and FY26
A8: UMI | B8: LCV | C8: =UMI!E20 -> 2973279.3 | D8: =UMI!E19 -> 4957575 | E8: =UMI!E21 -> 0.5997447 | F8: =UMI!E22 -> 0.018 | G8: =UMI!E23 -> 89236.35 | H8: =UMI!E25 -> 0.6177447 | I8: =UMI!E24 -> 3062515.7 | L8: =G8*0.33/2 -> 14723.998 | M8: 5755871 | N8: 5546944 | P8: Insufficient data | V8: Insufficient data — KPI marks UMI sales to dealers "Internal only", no figures.
A9: NORWAY | B9: LCV | C9: =NORWAY!E20 -> 1764799.8 | D9: =NORWAY!E19 -> 2129137.5 | E9: =NORWAY!E21 -> 0.82888012 | F9: =NORWAY!E22 -> 0.018 | G9: =NORWAY!E23 -> 38324.475 | H9: =NORWAY!E25 -> 0.84688012 | I9: =NORWAY!E24 -> 1803124.2 | L9: =G9*0.33/2 -> 6323.5384 | M9: 1156859 | N9: 1454525 | P9: 3367988 | Q9: 5248795 | V9: FY26 annualized from 11/12 months
A10: SWEDEN | B10: LCV | C10: =SWEDEN!E20 -> 1464302.3 | D10: =SWEDEN!E19 -> 2386125 | E10: =SWEDEN!E21 -> 0.61367377 | F10: =SWEDEN!E22 -> 0.018 | G10: =SWEDEN!E23 -> 42950.25 | H10: =SWEDEN!E25 -> 0.63167377 | I10: =SWEDEN!E24 -> 1507252.6 | L10: =G10*0.33/2 -> 7086.7913 | M10: 1233980 | N10: 1282687 | P10: 2482560 | Q10: 3154222 | V10: full 12/12 monthly coverage both FY25 and FY26
A11: HUNGARY | B11: LCV | C11: =HUNGARY!E20 -> 349600 | D11: =HUNGARY!E19 -> 1047900 | E11: =HUNGARY!E21 -> 0.33361962 | F11: =HUNGARY!E22 -> 0.018 | G11: =HUNGARY!E23 -> 18862.2 | H11: =HUNGARY!E25 -> 0.35161962 | I11: =HUNGARY!E24 -> 368462.2 | L11: =G11*0.33/2 -> 3112.263 | M11: 365622 | N11: 347456 | P11: Insufficient data | V11: Insufficient data — no Hungary/AutoWallis row in the distributor KPI block.
A12: FINLAND | B12: LCV | C12: =FINLAND!E20 -> 360300 | D12: =FINLAND!E19 -> 343350 | E12: =FINLAND!E21 -> 1.0493665 | F12: =FINLAND!E22 -> 0.018 | G12: =FINLAND!E23 -> 6180.3 | H12: =FINLAND!E25 -> 1.0673665 | I12: =FINLAND!E24 -> 366480.3 | J12: Above 100% at BP: quote the amount, not the % | L12: =G12*0.33/2 -> 1019.7495 | M12: 267986 | N12: 280753 | P12: Insufficient data | V12: Insufficient data — distributor KPI (IMF/Nordic Auto.) stopped reporting Oct'25, 9 months stale.
A13: ROMANIA | B13: LCV | C13: =ROMANIA!E20 -> 199587.57 | D13: =ROMANIA!E19 -> 317362.5 | E13: =ROMANIA!E21 -> 0.62889462 | F13: =ROMANIA!E22 -> 0.018 | G13: =ROMANIA!E23 -> 5712.525 | H13: =ROMANIA!E25 -> 0.64689462 | I13: =ROMANIA!E24 -> 205300.1 | L13: =G13*0.33/2 -> 942.56663 | M13: 155162 | N13: 180500 | P13: 382258 | Q13: 394597 | V13: full 12/12 monthly coverage both FY25 and FY26
A14: DENMARK | B14: LCV | C14: =DENMARK!E20 -> 187600 | D14: =DENMARK!E19 -> 247800 | E14: =DENMARK!E21 -> 0.75706215 | F14: =DENMARK!E22 -> 0.018 | G14: =DENMARK!E23 -> 4460.4 | H14: =DENMARK!E25 -> 0.77506215 | I14: =DENMARK!E24 -> 192060.4 | L14: =G14*0.33/2 -> 735.966 | M14: 125038 | N14: 155945 | P14: 356680 | Q14: 572864 | V14: full 12/12 monthly coverage both FY25 and FY26
A15: ICELAND | B15: LCV | C15: =ICELAND!E20 -> 104600 | D15: =ICELAND!E19 -> 115237.5 | E15: =ICELAND!E21 -> 0.90769064 | F15: =ICELAND!E22 -> 0.018 | G15: =ICELAND!E23 -> 2074.275 | H15: =ICELAND!E25 -> 0.92569064 | I15: =ICELAND!E24 -> 106674.27 | L15: =G15*0.33/2 -> 342.25538 | M15: 76214 | N15: 89209 | P15: 209944 | Q15: 195849 | V15: full 12/12 monthly coverage both FY25 and FY26
A16: GERMANY | B16: mixed | C16: =GERMANY!E26 -> 2913662.8 | D16: =GERMANY!E25 -> 4443791.1 | E16: =GERMANY!E27 -> 0.65567052 | F16: =GERMANY!E28 -> 0.018 | G16: =GERMANY!E29 -> 79988.24 | H16: =GERMANY!E31 -> 0.67367052 | I16: =GERMANY!E30 -> 2993651.1 | L16: =G16*0.33/2 -> 13198.06 | M16: 2614731 | N16: 2661850 | P16: Insufficient data | V16: Insufficient data — distributor KPI (ISD) stopped reporting Mar'25, 15+ months stale.
A17: BELGIUM | B17: mixed | C17: =BELGIUM!E26 -> 2296577.3 | D17: =BELGIUM!E25 -> 2739612.8 | E17: =BELGIUM!E27 -> 0.83828539 | F17: =BELGIUM!E28 -> 0.018 | G17: =BELGIUM!E29 -> 49313.029 | H17: =BELGIUM!E31 -> 0.85628539 | I17: =BELGIUM!E30 -> 2345890.4 | J17: Belgian vehicles only (IBX also serves NL/PL/LU) | L17: =G17*0.33/2 -> 8136.6499 | M17: 2286742 | N17: 2152712 | P17: 4867562 | Q17: 6834272 | V17: FY25 annualized from 10/12 months
A18: PORTUGAL | B18: mixed | C18: =PORTUGAL!E26 -> 1858269.4 | D18: =PORTUGAL!E25 -> 3788245.6 | E18: =PORTUGAL!E27 -> 0.49053561 | F18: =PORTUGAL!E28 -> 0.018 | G18: =PORTUGAL!E29 -> 68188.422 | H18: =PORTUGAL!E31 -> 0.50853561 | I18: =PORTUGAL!E30 -> 1926457.8 | L18: =G18*0.33/2 -> 11251.09 | M18: 1551256 | N18: 1795020 | P18: 3821463 | Q18: 4047903 | V18: FY25 annualized from 7/12 months
A19: IRELAND | B19: mixed | C19: =IRELAND!E26 -> 1267443.4 | D19: =IRELAND!E25 -> 1287772.5 | E19: =IRELAND!E27 -> 0.98421371 | F19: =IRELAND!E28 -> 0.018 | G19: =IRELAND!E29 -> 23179.905 | H19: =IRELAND!E31 -> 1.0022137 | I19: =IRELAND!E30 -> 1290623.3 | J19: Above 100% after stretch: quote the amount, not the % | L19: =G19*0.33/2 -> 3824.6843 | M19: 1201537 | N19: 1118453 | P19: 2687539 | Q19: 2833637 | V19: full 12/12 monthly coverage both FY25 and FY26
A20: GREECE | B20: mixed | C20: =GREECE!E26 -> 574400 | D20: =GREECE!E25 -> 1156909.9 | E20: =GREECE!E27 -> 0.496495 | F20: =GREECE!E28 -> 0.018 | G20: =GREECE!E29 -> 20824.379 | H20: =GREECE!E31 -> 0.514495 | I20: =GREECE!E30 -> 595224.38 | L20: =G20*0.33/2 -> 3436.0226 | M20: 467826 | N20: 471586 | P20: Insufficient data | V20: Insufficient data — Petros Petropoulos stale since Jun'25 (12+ months).
A21: CYPRUS | B21: mixed | C21: =CYPRUS!E26 -> 539600 | D21: =CYPRUS!E25 -> 811322.4 | E21: =CYPRUS!E27 -> 0.66508702 | F21: =CYPRUS!E28 -> 0.018 | G21: =CYPRUS!E29 -> 14603.803 | H21: =CYPRUS!E31 -> 0.68308702 | I21: =CYPRUS!E30 -> 554203.8 | L21: =G21*0.33/2 -> 2409.6275 | P21: Insufficient data | V21: Insufficient data — Cyprus's real distributor (Loutsios & Sons) has zero KPI data. KPI's 'MIDI' row is Italy's, not Cyprus's — excluded.
A22: MALTA | B22: mixed | C22: =MALTA!E26 -> 233100 | D22: =MALTA!E25 -> 424347 | E22: =MALTA!E27 -> 0.54931459 | F22: =MALTA!E28 -> 0.018 | G22: =MALTA!E29 -> 7638.246 | H22: =MALTA!E31 -> 0.56731459 | I22: =MALTA!E30 -> 240738.25 | L22: =G22*0.33/2 -> 1260.3106 | M22: 209033 | N22: 196245 | P22: 555482 | Q22: 553873 | V22: full 12/12 monthly coverage both FY25 and FY26
A23: TOTAL | C23: =SUM(C5:C22) -> 33222362 | D23: =SUM(D5:D22) -> 60153415 | E23: =C23/D23 -> 0.55229386 | G23: =SUM(G5:G22) -> 1239483.2 | I23: =SUM(I5:I22) -> 34461845 | M23: =SUM(M5:M22) -> 30291207 | N23: =SUM(N5:N22) -> 30074562 | P23: =SUM(P5:P22) -> 37574769 | Q23: =SUM(Q5:Q22) -> 45254291
A25: Remaining stretch BEFORE GPS | C25: 952037.42
A26: GPS contribution (18 DBs) | C26: =G23 -> 1239483.2
A27: Remaining stretch AFTER GPS | C27: =C25-C26 -> -287445.75 | E27: negative = over-covered = buffer
A29: WATCH
A30: • Dealer level (販社): amounts only. The distributors' reported sales to dealers run 2.2 to 3.7 times ISZE billing, so a share would read above 100% for five distributors. FY2027 dealer target = FY2026 sales to dealers + ISZE stretch / 0.65; FY2028-FY2031 move with the ISZE target.
A31: • ITUK and UTI: targets and stretch as presented in July; maximum spend on IML data (2026 vehicles, +5%).
A32: • The same stretch for every distributor. Finland (104.9% on budget) and Ireland (100.2% after stretch) read above 100%: quote the amount, not the %. Ireland's fleet is national registration data.
A33: • Belgium: Isuzu Benelux also serves NL, PL and LU; only Belgian vehicles are counted.
A34: • Fleet: UIO V19 for all years. Sheets 'UIO V19' and 'UIO V20' explain the difference with the UIO V20 spec and its effect on FY2028-FY2031.
A35: • Blue numbers are inputs. Every other number is a formula; constants sit on the Inputs sheet or the distributor tabs.

Sheet Waterfall VP
P4: =SUM(V13:V30) -> 1239483.2 | Q4: =T7-C16-SUM(D5:S16)-P4 -> -287445.75 | T4: check:
O5: 210000 | P5: GPS extended target | Q5: remaining stretch / SURPLUS if negative | R5: -260000 | T5: =SUM(C3:S16) -> 35284444
O6: MOS ISA+RSA | S6: -350000
N7: =71575+307333 -> 378908 | R7: Shell oil decrease | T7: 35284444
K8: 93000 | N8: SPA | S8: negative impact on volume from price increase
M9: 55000 | U9: SURPLUS vs FY2027 Plan (GPS exceeds the gap) | V9: =-Q4 -> 287445.75
J10: 280000 | K10: local DPD | M10: Overstock campaign | N10: # Original: 1,015k | U10: The remaining stretch is negative because the GPS stretch is larger than the gap: that amount is the surplus above the plan.
H11: 46000 | I11: 11940 | J11: local brake | M11: All DB's 55K€ | N11: -> IUK 71,575
G12: 75000 | H12: Genuine Share | I12: PMS | N12: -> UTI 307333 | U12: GPS extended target — per customer
F13: 60000 | G13: L/B | H13: # Original: 46,000 | I13: # Original: 11,940 | N13: -> | U13: -> ITUK (as presented in July) | V13: 376073.91
E14: 96664.198 | F14: Cab | H14: -> ITUK 376,074 | I14: -> ITUK 8,000 | N14: -> | U14: -> UTI (as presented in July) | V14: 159024.46
D15: 691851.85 | E15: UIO up | H15: -> Ireland | I15: -> Portugal | U15: -> IUK | V15: =IUK!E23 -> 232848
C16: 32944043 | D16: Price up 2% | H16: -> Portugal | I16: -> Ireland | U16: -> UMI | V16: =UMI!E23 -> 89236.35
H17: -> | I17: -> IUK | U17: -> NORWAY | V17: =NORWAY!E23 -> 38324.475
H18: -> | I18: -> | U18: -> SWEDEN | V18: =SWEDEN!E23 -> 42950.25
H19: -> | I19: -> | U19: -> HUNGARY | V19: =HUNGARY!E23 -> 18862.2
U20: -> FINLAND | V20: =FINLAND!E23 -> 6180.3
U21: -> ROMANIA | V21: =ROMANIA!E23 -> 5712.525
U22: -> DENMARK | V22: =DENMARK!E23 -> 4460.4
U23: -> ICELAND | V23: =ICELAND!E23 -> 2074.275
U24: -> GERMANY | V24: =GERMANY!E29 -> 79988.24
C25: FY2026 Actual | T25: FY2027 Plan | U25: -> BELGIUM | V25: =BELGIUM!E29 -> 49313.029
U26: -> PORTUGAL | V26: =PORTUGAL!E29 -> 68188.422
U27: -> IRELAND | V27: =IRELAND!E29 -> 23179.905
U28: -> GREECE | V28: =GREECE!E29 -> 20824.379
U29: -> CYPRUS | V29: =CYPRUS!E29 -> 14603.803
U30: -> MALTA | V30: =MALTA!E29 -> 7638.246
U31: GPS total | V31: =SUM(V13:V30) -> 1239483.2

Sheet IUK
A1: IUK — GPS Extended Target FY2027 · I.M. PARTS & SERVICE Limited [LCV only]
A2: ISZE to distributor target is set here. Blue = input. FY2028-FY2031 in columns F:I. The dealer block at the bottom uses the IML method (ISZE stretch / (1 - distributor margin)) and is an amount only, never a share.
F3: Colours
F4: Firm / actual
F5: Stretch
A7: IUK UIO (LCV)
C8: FY25 (Apr'24-Mar'25) | D8: FY26 (Apr'25-Mar'26) | E8: FY27 (Apr'26-Mar'27) | F8: FY28 (CY2027F) | G8: FY29 (CY2028F) | H8: FY30 (CY2029F) | I8: FY31 (CY2030F)
A9: LCV | C9: 48876 | D9: 47783 | E9: 49280 | F9: 50202 | G9: 51096 | H9: 51963 | I9: 52804
A10: TTL | C10: =C9 -> 48876 | D10: =D9 -> 47783 | E10: =E9 -> 49280 | F10: =F9 -> 50202 | G10: =G9 -> 51096 | H10: =H9 -> 51963 | I10: =I9 -> 52804
A11: Source: UIO V19. Fiscal year = calendar year + 1 (FY2027 uses the fleet of calendar 2026). Compare with the UIO V20 spec on sheet 'UIO V20'.
A13: Parts spend per vehicle (EUR) | B13: FY26 base | D13: FY26 | E13: FY27 (+5%) | F13: FY28 (+price) | G13: FY29 (+price) | H13: FY30 (+price) | I13: FY31 (+price)
A14: ISZE net EUR per pick-up | B14: =Inputs!$B$4 -> 250 | D14: =B14 -> 250 | E14: =D14*(1+Inputs!$B$9) -> 262.5 | F14: =E14*(1+'Dashboard (2)'!$T$1) -> 270.375 | G14: =F14*(1+'Dashboard (2)'!$T$1) -> 278.48625 | H14: =G14*(1+'Dashboard (2)'!$T$1) -> 286.84084 | I14: =H14*(1+'Dashboard (2)'!$T$1) -> 295.44606
A15: Pick-up rate EUR 250 per vehicle (FY2026, ISZE net), +5% in FY2027 = EUR 262.50, then + yearly price input (Dashboard (2) T1). Replaces the earlier EUR 219.56.
A17: ISZE -> IUK wholesale (ISZE-net EUR) << EXTENDED TARGET IS SET HERE
C18: FY25 (Apr'24-Mar'25) | D18: FY26 (Apr'25-Mar'26) | E18: FY27 (Apr'26-Mar'27) | F18: FY28 | G18: FY29 | H18: FY30 | I18: FY31
A19: Max spend / potential (= UIO x ISZE-net rate) | C19: =C9*$D$14 -> 12219000 | D19: =D9*$D$14 -> 11945750 | E19: =E9*$E$14 -> 12936000 | F19: =F9*F14 -> 13573366 | G19: =G9*G14 -> 14229533 | H19: =H9*H14 -> 14905110 | I19: =I9*I14 -> 15600734
A20: Actual (ISZE billing) · FY27 = BP target | C20: 7297065.7 | D20: 5895486.2 | E20: 6062956.5
A21: Share (GPS, ISZE level) | C21: =C20/C19 -> 0.59719009 | D21: =D20/D19 -> 0.49352165 | E21: =E20/E19 -> 0.46868866
A22: Stretch (%) = global input, capped at ceiling | C22: 0 | D22: 0 | E22: =MAX(0,MIN('Dashboard (2)'!$N$1,Inputs!$B$38-E21)) -> 0.018
A23: Stretch amount (= max spend x stretch%) | C23: =C19*C22 -> 0 | D23: =D19*D22 -> 0 | E23: =E19*E22 -> 232848
A24: TTL amount (= actual + stretch) << EXTENDED TARGET | C24: =C20+C23 -> 7297065.7 | D24: =D20+D23 -> 5895486.2 | E24: =E20+E23 -> 6295804.5
A25: Share (new) | C25: =C24/C19 -> 0.59719009 | D25: =D24/D19 -> 0.49352165 | E25: =E24/E19 -> 0.48668866
A26: Source: ISZE billing to the distributor, GPS basis, lubricants included. FY2027 = budget reviewed April 2026.
A27: FY28-FY31 max spend (row 19, cols F:I) feeds Dashboard (2). FY27 actual cell E20 = BP reviewed 24-04-2026.
A28: IUK to dealer level
C29: FY25 (Apr'24-Mar'25) | D29: FY26 (Apr'25-Mar'26) | E29: FY27 (Apr'26-Mar'27)
A30: Sales to dealers (actual, distributor KPI June 2026) | C30: 18843293 | D30: 21418279 | F30: FY25 12/12 mo · FY26 12/12 mo
A31: Distributor margin % | B31: 0.35
A32: Stretch at dealer level (= ISZE stretch / (1 - margin)) | E32: =-E23/(B31-1) -> 358227.69
A33: FY27 AMOUNT TO REACH at dealer (= FY26 actual + dealer stretch) | E33: =IF(OR(D30="",D30="no KPI data"),"no KPI data",D30+E32) -> 21776507
A34: Dealer level: the ISZE stretch is converted to dealer prices by dividing by (1 - 35% distributor margin). FY2027 amount = FY2026 sales to dealers + that stretch. Amount only, never a share: the distributors' reported sales to dealers run 2.2 to 3.7 times ISZE billing.
A37: Notes
A38: 1. Pick-up rate EUR 250 per vehicle (FY2026, ISZE net), +5% in FY2027 = EUR 262.50. Replaces the earlier EUR 219.56.

Sheet UMI
A1: UMI — GPS Extended Target FY2027 · UNIVERSAL MOTORS ISRAEL LTD [LCV only]
A2: ISZE to distributor target is set here. Blue = input. FY2028-FY2031 in columns F:I. The dealer block at the bottom uses the IML method (ISZE stretch / (1 - distributor margin)) and is an amount only, never a share.
F3: Colours
F4: Firm / actual
F5: Stretch
A7: UMI UIO (LCV)
C8: FY25 (Apr'24-Mar'25) | D8: FY26 (Apr'25-Mar'26) | E8: FY27 (Apr'26-Mar'27) | F8: FY28 (CY2027F) | G8: FY29 (CY2028F) | H8: FY30 (CY2029F) | I8: FY31 (CY2030F)
A9: LCV | C9: 18349 | D9: 18542 | E9: 18886 | F9: 19319 | G9: 19669 | H9: 20009 | I9: 20339
A10: TTL | C10: =C9 -> 18349 | D10: =D9 -> 18542 | E10: =E9 -> 18886 | F10: =F9 -> 19319 | G10: =G9 -> 19669 | H10: =H9 -> 20009 | I10: =I9 -> 20339
A11: Source: UIO V19. Fiscal year = calendar year + 1 (FY2027 uses the fleet of calendar 2026). Compare with the UIO V20 spec on sheet 'UIO V20'.
A13: Parts spend per vehicle (EUR) | B13: FY26 base | D13: FY26 | E13: FY27 (+5%) | F13: FY28 (+price) | G13: FY29 (+price) | H13: FY30 (+price) | I13: FY31 (+price)
A14: ISZE net EUR per pick-up | B14: =Inputs!$B$4 -> 250 | D14: =B14 -> 250 | E14: =D14*(1+Inputs!$B$9) -> 262.5 | F14: =E14*(1+'Dashboard (2)'!$T$1) -> 270.375 | G14: =F14*(1+'Dashboard (2)'!$T$1) -> 278.48625 | H14: =G14*(1+'Dashboard (2)'!$T$1) -> 286.84084 | I14: =H14*(1+'Dashboard (2)'!$T$1) -> 295.44606
A15: Pick-up rate EUR 250 per vehicle (FY2026, ISZE net), +5% in FY2027 = EUR 262.50, then + yearly price input (Dashboard (2) T1). Replaces the earlier EUR 219.56.
A17: ISZE -> UMI wholesale (ISZE-net EUR) << EXTENDED TARGET IS SET HERE
C18: FY25 (Apr'24-Mar'25) | D18: FY26 (Apr'25-Mar'26) | E18: FY27 (Apr'26-Mar'27) | F18: FY28 | G18: FY29 | H18: FY30 | I18: FY31
A19: Max spend / potential (= UIO x ISZE-net rate) | C19: =C9*$D$14 -> 4587250 | D19: =D9*$D$14 -> 4635500 | E19: =E9*$E$14 -> 4957575 | F19: =F9*F14 -> 5223374.6 | G19: =G9*G14 -> 5477546.1 | H19: =H9*H14 -> 5739398.3 | I19: =I9*I14 -> 6009077.5
A20: Actual (ISZE billing) · FY27 = BP target | C20: 2739215.7 | D20: 2445335.2 | E20: 2973279.3
A21: Share (GPS, ISZE level) | C21: =C20/C19 -> 0.59713678 | D21: =D20/D19 -> 0.52752351 | E21: =E20/E19 -> 0.5997447
A22: Stretch (%) = global input, capped at ceiling | C22: 0 | D22: 0 | E22: =MAX(0,MIN('Dashboard (2)'!$N$1,Inputs!$B$38-E21)) -> 0.018
A23: Stretch amount (= max spend x stretch%) | C23: =C19*C22 -> 0 | D23: =D19*D22 -> 0 | E23: =E19*E22 -> 89236.35
A24: TTL amount (= actual + stretch) << EXTENDED TARGET | C24: =C20+C23 -> 2739215.7 | D24: =D20+D23 -> 2445335.2 | E24: =E20+E23 -> 3062515.7
A25: Share (new) | C25: =C24/C19 -> 0.59713678 | D25: =D24/D19 -> 0.52752351 | E25: =E24/E19 -> 0.6177447
A26: Source: ISZE billing to the distributor, GPS basis, lubricants included. FY2027 = budget reviewed April 2026.
A27: FY28-FY31 max spend (row 19, cols F:I) feeds Dashboard (2). FY27 actual cell E20 = BP reviewed 24-04-2026.
A28: UMI to dealer level
C29: FY25 (Apr'24-Mar'25) | D29: FY26 (Apr'25-Mar'26) | E29: FY27 (Apr'26-Mar'27)
A30: Sales to dealers (actual, distributor KPI June 2026) | F30: FY25 0/12 mo · FY26 0/12 mo
A31: Distributor margin % | B31: 0.35
A32: Stretch at dealer level (= ISZE stretch / (1 - margin)) | E32: =-E23/(B31-1) -> 137286.69
A33: FY27 AMOUNT TO REACH at dealer (= FY26 actual + dealer stretch) | E33: =IF(OR(D30="",D30="no KPI data"),"no KPI data",D30+E32) -> no KPI data
A34: Dealer level: the ISZE stretch is converted to dealer prices by dividing by (1 - 35% distributor margin). FY2027 amount = FY2026 sales to dealers + that stretch. Amount only, never a share: the distributors' reported sales to dealers run 2.2 to 3.7 times ISZE billing.
A37: Notes
A38: 1. Pick-up rate EUR 250 per vehicle (FY2026, ISZE net), +5% in FY2027 = EUR 262.50. Replaces the earlier EUR 219.56.
A39: 2. UMI reports no sales to dealers, so the dealer target shows 'no KPI data'.

Sheet NORWAY
A1: NORWAY — GPS Extended Target FY2027 · RUTEBILEIERNES STANDARDISERING AS [LCV only]
A2: ISZE to distributor target is set here. Blue = input. FY2028-FY2031 in columns F:I. The dealer block at the bottom uses the IML method (ISZE stretch / (1 - distributor margin)) and is an amount only, never a share.
F3: Colours
F4: Firm / actual
F5: Stretch
A7: NORWAY UIO (LCV)
C8: FY25 (Apr'24-Mar'25) | D8: FY26 (Apr'25-Mar'26) | E8: FY27 (Apr'26-Mar'27) | F8: FY28 (CY2027F) | G8: FY29 (CY2028F) | H8: FY30 (CY2029F) | I8: FY31 (CY2030F)
A9: LCV | C9: 8237 | D9: 7929 | E9: 8111 | F9: 8218 | G9: 8426 | H9: 8628 | I9: 8824
A10: TTL | C10: =C9 -> 8237 | D10: =D9 -> 7929 | E10: =E9 -> 8111 | F10: =F9 -> 8218 | G10: =G9 -> 8426 | H10: =H9 -> 8628 | I10: =I9 -> 8824
A11: Source: UIO V19. Fiscal year = calendar year + 1 (FY2027 uses the fleet of calendar 2026). Compare with the UIO V20 spec on sheet 'UIO V20'.
A13: Parts spend per vehicle (EUR) | B13: FY26 base | D13: FY26 | E13: FY27 (+5%) | F13: FY28 (+price) | G13: FY29 (+price) | H13: FY30 (+price) | I13: FY31 (+price)
A14: ISZE net EUR per pick-up | B14: =Inputs!$B$4 -> 250 | D14: =B14 -> 250 | E14: =D14*(1+Inputs!$B$9) -> 262.5 | F14: =E14*(1+'Dashboard (2)'!$T$1) -> 270.375 | G14: =F14*(1+'Dashboard (2)'!$T$1) -> 278.48625 | H14: =G14*(1+'Dashboard (2)'!$T$1) -> 286.84084 | I14: =H14*(1+'Dashboard (2)'!$T$1) -> 295.44606
A15: Pick-up rate EUR 250 per vehicle (FY2026, ISZE net), +5% in FY2027 = EUR 262.50, then + yearly price input (Dashboard (2) T1). Replaces the earlier EUR 219.56.
A17: ISZE -> NORWAY wholesale (ISZE-net EUR) << EXTENDED TARGET IS SET HERE
C18: FY25 (Apr'24-Mar'25) | D18: FY26 (Apr'25-Mar'26) | E18: FY27 (Apr'26-Mar'27) | F18: FY28 | G18: FY29 | H18: FY30 | I18: FY31
A19: Max spend / potential (= UIO x ISZE-net rate) | C19: =C9*$D$14 -> 2059250 | D19: =D9*$D$14 -> 1982250 | E19: =E9*$E$14 -> 2129137.5 | F19: =F9*F14 -> 2221941.8 | G19: =G9*G14 -> 2346525.1 | H19: =H9*H14 -> 2474862.7 | I19: =I9*I14 -> 2607016.1
A20: Actual (ISZE billing) · FY27 = BP target | C20: 1162750.7 | D20: 1471434.2 | E20: 1764799.8
A21: Share (GPS, ISZE level) | C21: =C20/C19 -> 0.56464765 | D21: =D20/D19 -> 0.74230506 | E21: =E20/E19 -> 0.82888012
A22: Stretch (%) = global input, capped at ceiling | C22: 0 | D22: 0 | E22: =MAX(0,MIN('Dashboard (2)'!$N$1,Inputs!$B$38-E21)) -> 0.018
A23: Stretch amount (= max spend x stretch%) | C23: =C19*C22 -> 0 | D23: =D19*D22 -> 0 | E23: =E19*E22 -> 38324.475
A24: TTL amount (= actual + stretch) << EXTENDED TARGET | C24: =C20+C23 -> 1162750.7 | D24: =D20+D23 -> 1471434.2 | E24: =E20+E23 -> 1803124.2
A25: Share (new) | C25: =C24/C19 -> 0.56464765 | D25: =D24/D19 -> 0.74230506 | E25: =E24/E19 -> 0.84688012
A26: Source: ISZE billing to the distributor, GPS basis, lubricants included. FY2027 = budget reviewed April 2026.
A27: FY28-FY31 max spend (row 19, cols F:I) feeds Dashboard (2). FY27 actual cell E20 = BP reviewed 24-04-2026.
A28: NORWAY to dealer level
C29: FY25 (Apr'24-Mar'25) | D29: FY26 (Apr'25-Mar'26) | E29: FY27 (Apr'26-Mar'27)
A30: Sales to dealers (actual, distributor KPI June 2026) | C30: 3367988 | D30: 4811395 | F30: FY25 12/12 mo · FY26 11/12 mo
A31: Distributor margin % | B31: 0.35
A32: Stretch at dealer level (= ISZE stretch / (1 - margin)) | E32: =-E23/(B31-1) -> 58960.731
A33: FY27 AMOUNT TO REACH at dealer (= FY26 actual + dealer stretch) | E33: =IF(OR(D30="",D30="no KPI data"),"no KPI data",D30+E32) -> 4870355.7
A34: Dealer level: the ISZE stretch is converted to dealer prices by dividing by (1 - 35% distributor margin). FY2027 amount = FY2026 sales to dealers + that stretch. Amount only, never a share: the distributors' reported sales to dealers run 2.2 to 3.7 times ISZE billing.
A37: Notes
A38: 1. Pick-up rate EUR 250 per vehicle (FY2026, ISZE net), +5% in FY2027 = EUR 262.50. Replaces the earlier EUR 219.56.

Sheet SWEDEN
A1: SWEDEN — GPS Extended Target FY2027 · ISUZU SVERIGE AB [LCV only]
A2: ISZE to distributor target is set here. Blue = input. FY2028-FY2031 in columns F:I. The dealer block at the bottom uses the IML method (ISZE stretch / (1 - distributor margin)) and is an amount only, never a share.
F3: Colours
F4: Firm / actual
F5: Stretch
A7: SWEDEN UIO (LCV)
C8: FY25 (Apr'24-Mar'25) | D8: FY26 (Apr'25-Mar'26) | E8: FY27 (Apr'26-Mar'27) | F8: FY28 (CY2027F) | G8: FY29 (CY2028F) | H8: FY30 (CY2029F) | I8: FY31 (CY2030F)
A9: LCV | C9: 7221 | D9: 8443 | E9: 9090 | F9: 9737 | G9: 10320 | H9: 10885 | I9: 11433
A10: TTL | C10: =C9 -> 7221 | D10: =D9 -> 8443 | E10: =E9 -> 9090 | F10: =F9 -> 9737 | G10: =G9 -> 10320 | H10: =H9 -> 10885 | I10: =I9 -> 11433
A11: Source: UIO V19. Fiscal year = calendar year + 1 (FY2027 uses the fleet of calendar 2026). Compare with the UIO V20 spec on sheet 'UIO V20'.
A13: Parts spend per vehicle (EUR) | B13: FY26 base | D13: FY26 | E13: FY27 (+5%) | F13: FY28 (+price) | G13: FY29 (+price) | H13: FY30 (+price) | I13: FY31 (+price)
A14: ISZE net EUR per pick-up | B14: =Inputs!$B$4 -> 250 | D14: =B14 -> 250 | E14: =D14*(1+Inputs!$B$9) -> 262.5 | F14: =E14*(1+'Dashboard (2)'!$T$1) -> 270.375 | G14: =F14*(1+'Dashboard (2)'!$T$1) -> 278.48625 | H14: =G14*(1+'Dashboard (2)'!$T$1) -> 286.84084 | I14: =H14*(1+'Dashboard (2)'!$T$1) -> 295.44606
A15: Pick-up rate EUR 250 per vehicle (FY2026, ISZE net), +5% in FY2027 = EUR 262.50, then + yearly price input (Dashboard (2) T1). Replaces the earlier EUR 219.56.
A17: ISZE -> SWEDEN wholesale (ISZE-net EUR) << EXTENDED TARGET IS SET HERE
C18: FY25 (Apr'24-Mar'25) | D18: FY26 (Apr'25-Mar'26) | E18: FY27 (Apr'26-Mar'27) | F18: FY28 | G18: FY29 | H18: FY30 | I18: FY31
A19: Max spend / potential (= UIO x ISZE-net rate) | C19: =C9*$D$14 -> 1805250 | D19: =D9*$D$14 -> 2110750 | E19: =E9*$E$14 -> 2386125 | F19: =F9*F14 -> 2632641.4 | G19: =G9*G14 -> 2873978.1 | H19: =H9*H14 -> 3122262.5 | I19: =I9*I14 -> 3377834.8
A20: Actual (ISZE billing) · FY27 = BP target | C20: 1215958.3 | D20: 1298276 | E20: 1464302.3
A21: Share (GPS, ISZE level) | C21: =C20/C19 -> 0.67356783 | D21: =D20/D19 -> 0.61507805 | E21: =E20/E19 -> 0.61367377
A22: Stretch (%) = global input, capped at ceiling | C22: 0 | D22: 0 | E22: =MAX(0,MIN('Dashboard (2)'!$N$1,Inputs!$B$38-E21)) -> 0.018
A23: Stretch amount (= max spend x stretch%) | C23: =C19*C22 -> 0 | D23: =D19*D22 -> 0 | E23: =E19*E22 -> 42950.25
A24: TTL amount (= actual + stretch) << EXTENDED TARGET | C24: =C20+C23 -> 1215958.3 | D24: =D20+D23 -> 1298276 | E24: =E20+E23 -> 1507252.6
A25: Share (new) | C25: =C24/C19 -> 0.67356783 | D25: =D24/D19 -> 0.61507805 | E25: =E24/E19 -> 0.63167377
A26: Source: ISZE billing to the distributor, GPS basis, lubricants included. FY2027 = budget reviewed April 2026.
A27: FY28-FY31 max spend (row 19, cols F:I) feeds Dashboard (2). FY27 actual cell E20 = BP reviewed 24-04-2026.
A28: SWEDEN to dealer level
C29: FY25 (Apr'24-Mar'25) | D29: FY26 (Apr'25-Mar'26) | E29: FY27 (Apr'26-Mar'27)
A30: Sales to dealers (actual, distributor KPI June 2026) | C30: 2482560 | D30: 3154221.5 | F30: FY25 12/12 mo · FY26 12/12 mo
A31: Distributor margin % | B31: 0.35
A32: Stretch at dealer level (= ISZE stretch / (1 - margin)) | E32: =-E23/(B31-1) -> 66077.308
A33: FY27 AMOUNT TO REACH at dealer (= FY26 actual + dealer stretch) | E33: =IF(OR(D30="",D30="no KPI data"),"no KPI data",D30+E32) -> 3220298.8
A34: Dealer level: the ISZE stretch is converted to dealer prices by dividing by (1 - 35% distributor margin). FY2027 amount = FY2026 sales to dealers + that stretch. Amount only, never a share: the distributors' reported sales to dealers run 2.2 to 3.7 times ISZE billing.
A37: Notes
A38: 1. Pick-up rate EUR 250 per vehicle (FY2026, ISZE net), +5% in FY2027 = EUR 262.50. Replaces the earlier EUR 219.56.

Sheet HUNGARY
A1: HUNGARY — GPS Extended Target FY2027 · AW Distribution Kft. [LCV only]
A2: ISZE to distributor target is set here. Blue = input. FY2028-FY2031 in columns F:I. The dealer block at the bottom uses the IML method (ISZE stretch / (1 - distributor margin)) and is an amount only, never a share.
F3: Colours
F4: Firm / actual
F5: Stretch
A7: HUNGARY UIO (LCV)
C8: FY25 (Apr'24-Mar'25) | D8: FY26 (Apr'25-Mar'26) | E8: FY27 (Apr'26-Mar'27) | F8: FY28 (CY2027F) | G8: FY29 (CY2028F) | H8: FY30 (CY2029F) | I8: FY31 (CY2030F)
A9: LCV | C9: 3714 | D9: 3734 | E9: 3992 | F9: 4242 | G9: 4390 | H9: 4533 | I9: 4672
A10: TTL | C10: =C9 -> 3714 | D10: =D9 -> 3734 | E10: =E9 -> 3992 | F10: =F9 -> 4242 | G10: =G9 -> 4390 | H10: =H9 -> 4533 | I10: =I9 -> 4672
A11: Source: UIO V19. Fiscal year = calendar year + 1 (FY2027 uses the fleet of calendar 2026). Compare with the UIO V20 spec on sheet 'UIO V20'.
A13: Parts spend per vehicle (EUR) | B13: FY26 base | D13: FY26 | E13: FY27 (+5%) | F13: FY28 (+price) | G13: FY29 (+price) | H13: FY30 (+price) | I13: FY31 (+price)
A14: ISZE net EUR per pick-up | B14: =Inputs!$B$4 -> 250 | D14: =B14 -> 250 | E14: =D14*(1+Inputs!$B$9) -> 262.5 | F14: =E14*(1+'Dashboard (2)'!$T$1) -> 270.375 | G14: =F14*(1+'Dashboard (2)'!$T$1) -> 278.48625 | H14: =G14*(1+'Dashboard (2)'!$T$1) -> 286.84084 | I14: =H14*(1+'Dashboard (2)'!$T$1) -> 295.44606
A15: Pick-up rate EUR 250 per vehicle (FY2026, ISZE net), +5% in FY2027 = EUR 262.50, then + yearly price input (Dashboard (2) T1). Replaces the earlier EUR 219.56.
A17: ISZE -> HUNGARY wholesale (ISZE-net EUR) << EXTENDED TARGET IS SET HERE
C18: FY25 (Apr'24-Mar'25) | D18: FY26 (Apr'25-Mar'26) | E18: FY27 (Apr'26-Mar'27) | F18: FY28 | G18: FY29 | H18: FY30 | I18: FY31
A19: Max spend / potential (= UIO x ISZE-net rate) | C19: =C9*$D$14 -> 928500 | D19: =D9*$D$14 -> 933500 | E19: =E9*$E$14 -> 1047900 | F19: =F9*F14 -> 1146930.8 | G19: =G9*G14 -> 1222554.6 | H19: =H9*H14 -> 1300249.5 | I19: =I9*I14 -> 1380324
A20: Actual (ISZE billing) · FY27 = BP target | C20: 365817.37 | D20: 346246.24 | E20: 349600
A21: Share (GPS, ISZE level) | C21: =C20/C19 -> 0.39398747 | D21: =D20/D19 -> 0.37091188 | E21: =E20/E19 -> 0.33361962
A22: Stretch (%) = global input, capped at ceiling | C22: 0 | D22: 0 | E22: =MAX(0,MIN('Dashboard (2)'!$N$1,Inputs!$B$38-E21)) -> 0.018
A23: Stretch amount (= max spend x stretch%) | C23: =C19*C22 -> 0 | D23: =D19*D22 -> 0 | E23: =E19*E22 -> 18862.2
A24: TTL amount (= actual + stretch) << EXTENDED TARGET | C24: =C20+C23 -> 365817.37 | D24: =D20+D23 -> 346246.24 | E24: =E20+E23 -> 368462.2
A25: Share (new) | C25: =C24/C19 -> 0.39398747 | D25: =D24/D19 -> 0.37091188 | E25: =E24/E19 -> 0.35161962
A26: Source: ISZE billing to the distributor, GPS basis, lubricants included. FY2027 = budget reviewed April 2026.
A27: FY28-FY31 max spend (row 19, cols F:I) feeds Dashboard (2). FY27 actual cell E20 = BP reviewed 24-04-2026.
A28: HUNGARY to dealer level
C29: FY25 (Apr'24-Mar'25) | D29: FY26 (Apr'25-Mar'26) | E29: FY27 (Apr'26-Mar'27)
A30: Sales to dealers (actual, distributor KPI June 2026) | C30: 934209 | D30: 871455 | F30: FY25 12/12 mo · FY26 12/12 mo
A31: Distributor margin % | B31: 0.35
A32: Stretch at dealer level (= ISZE stretch / (1 - margin)) | E32: =-E23/(B31-1) -> 29018.769
A33: FY27 AMOUNT TO REACH at dealer (= FY26 actual + dealer stretch) | E33: =IF(OR(D30="",D30="no KPI data"),"no KPI data",D30+E32) -> 900473.77
A34: Dealer level: the ISZE stretch is converted to dealer prices by dividing by (1 - 35% distributor margin). FY2027 amount = FY2026 sales to dealers + that stretch. Amount only, never a share: the distributors' reported sales to dealers run 2.2 to 3.7 times ISZE billing.
A37: Notes
A38: 1. Pick-up rate EUR 250 per vehicle (FY2026, ISZE net), +5% in FY2027 = EUR 262.50. Replaces the earlier EUR 219.56.

Sheet FINLAND
A1: FINLAND — GPS Extended Target FY2027 · Nordic Automotive trading oy. [LCV only]
A2: ISZE to distributor target is set here. Blue = input. FY2028-FY2031 in columns F:I. The dealer block at the bottom uses the IML method (ISZE stretch / (1 - distributor margin)) and is an amount only, never a share.
F3: Colours
F4: Firm / actual
F5: Stretch
A7: FINLAND UIO (LCV)
C8: FY25 (Apr'24-Mar'25) | D8: FY26 (Apr'25-Mar'26) | E8: FY27 (Apr'26-Mar'27) | F8: FY28 (CY2027F) | G8: FY29 (CY2028F) | H8: FY30 (CY2029F) | I8: FY31 (CY2030F)
A9: LCV | C9: 1259 | D9: 1204 | E9: 1308 | F9: 1409 | G9: 1522 | H9: 1631 | I9: 1737
A10: TTL | C10: =C9 -> 1259 | D10: =D9 -> 1204 | E10: =E9 -> 1308 | F10: =F9 -> 1409 | G10: =G9 -> 1522 | H10: =H9 -> 1631 | I10: =I9 -> 1737
A11: Source: UIO V19. Fiscal year = calendar year + 1 (FY2027 uses the fleet of calendar 2026). Compare with the UIO V20 spec on sheet 'UIO V20'.
A13: Parts spend per vehicle (EUR) | B13: FY26 base | D13: FY26 | E13: FY27 (+5%) | F13: FY28 (+price) | G13: FY29 (+price) | H13: FY30 (+price) | I13: FY31 (+price)
A14: ISZE net EUR per pick-up | B14: =Inputs!$B$4 -> 250 | D14: =B14 -> 250 | E14: =D14*(1+Inputs!$B$9) -> 262.5 | F14: =E14*(1+'Dashboard (2)'!$T$1) -> 270.375 | G14: =F14*(1+'Dashboard (2)'!$T$1) -> 278.48625 | H14: =G14*(1+'Dashboard (2)'!$T$1) -> 286.84084 | I14: =H14*(1+'Dashboard (2)'!$T$1) -> 295.44606
A15: Pick-up rate EUR 250 per vehicle (FY2026, ISZE net), +5% in FY2027 = EUR 262.50, then + yearly price input (Dashboard (2) T1). Replaces the earlier EUR 219.56.
A17: ISZE -> FINLAND wholesale (ISZE-net EUR) << EXTENDED TARGET IS SET HERE
C18: FY25 (Apr'24-Mar'25) | D18: FY26 (Apr'25-Mar'26) | E18: FY27 (Apr'26-Mar'27) | F18: FY28 | G18: FY29 | H18: FY30 | I18: FY31
A19: Max spend / potential (= UIO x ISZE-net rate) | C19: =C9*$D$14 -> 314750 | D19: =D9*$D$14 -> 301000 | E19: =E9*$E$14 -> 343350 | F19: =F9*F14 -> 380958.38 | G19: =G9*G14 -> 423856.07 | H19: =H9*H14 -> 467837.41 | I19: =I9*I14 -> 513189.81
A20: Actual (ISZE billing) · FY27 = BP target | C20: 266204.48 | D20: 279383.25 | E20: 360300
A21: Share (GPS, ISZE level) | C21: =C20/C19 -> 0.84576483 | D21: =D20/D19 -> 0.92818355 | E21: =E20/E19 -> 1.0493665
A22: Stretch (%) = global input, capped at ceiling | C22: 0 | D22: 0 | E22: =MAX(0,MIN('Dashboard (2)'!$N$1,Inputs!$B$38-E21)) -> 0.018
A23: Stretch amount (= max spend x stretch%) | C23: =C19*C22 -> 0 | D23: =D19*D22 -> 0 | E23: =E19*E22 -> 6180.3
A24: TTL amount (= actual + stretch) << EXTENDED TARGET | C24: =C20+C23 -> 266204.48 | D24: =D20+D23 -> 279383.25 | E24: =E20+E23 -> 366480.3
A25: Share (new) | C25: =C24/C19 -> 0.84576483 | D25: =D24/D19 -> 0.92818355 | E25: =E24/E19 -> 1.0673665
A26: Source: ISZE billing to the distributor, GPS basis, lubricants included. FY2027 = budget reviewed April 2026.
A27: FY28-FY31 max spend (row 19, cols F:I) feeds Dashboard (2). FY27 actual cell E20 = BP reviewed 24-04-2026.
A28: FINLAND to dealer level
C29: FY25 (Apr'24-Mar'25) | D29: FY26 (Apr'25-Mar'26) | E29: FY27 (Apr'26-Mar'27)
A30: Sales to dealers (actual, distributor KPI June 2026) | C30: 576758 | D30: 350854 | F30: FY25 12/12 mo · FY26 6/12 mo
A31: Distributor margin % | B31: 0.35
A32: Stretch at dealer level (= ISZE stretch / (1 - margin)) | E32: =-E23/(B31-1) -> 9508.1538
A33: FY27 AMOUNT TO REACH at dealer (= FY26 actual + dealer stretch) | E33: =IF(OR(D30="",D30="no KPI data"),"no KPI data",D30+E32) -> 360362.15
A34: Dealer level: the ISZE stretch is converted to dealer prices by dividing by (1 - 35% distributor margin). FY2027 amount = FY2026 sales to dealers + that stretch. Amount only, never a share: the distributors' reported sales to dealers run 2.2 to 3.7 times ISZE billing.
A37: Notes
A38: 1. Pick-up rate EUR 250 per vehicle (FY2026, ISZE net), +5% in FY2027 = EUR 262.50. Replaces the earlier EUR 219.56.
A39: 2. GPS share is above 100% on budget (104.9%); the stretch applies as for every distributor. Discuss the amount with the distributor, not the %.

Sheet ROMANIA
A1: ROMANIA — GPS Extended Target FY2027 · Isuzu Rom Auto [LCV only]
A2: ISZE to distributor target is set here. Blue = input. FY2028-FY2031 in columns F:I. The dealer block at the bottom uses the IML method (ISZE stretch / (1 - distributor margin)) and is an amount only, never a share.
F3: Colours
F4: Firm / actual
F5: Stretch
A7: ROMANIA UIO (LCV)
C8: FY25 (Apr'24-Mar'25) | D8: FY26 (Apr'25-Mar'26) | E8: FY27 (Apr'26-Mar'27) | F8: FY28 (CY2027F) | G8: FY29 (CY2028F) | H8: FY30 (CY2029F) | I8: FY31 (CY2030F)
A9: LCV | C9: 986 | D9: 1071 | E9: 1209 | F9: 1343 | G9: 1475 | H9: 1603 | I9: 1727
A10: TTL | C10: =C9 -> 986 | D10: =D9 -> 1071 | E10: =E9 -> 1209 | F10: =F9 -> 1343 | G10: =G9 -> 1475 | H10: =H9 -> 1603 | I10: =I9 -> 1727
A11: Source: UIO V19. Fiscal year = calendar year + 1 (FY2027 uses the fleet of calendar 2026). Compare with the UIO V20 spec on sheet 'UIO V20'.
A13: Parts spend per vehicle (EUR) | B13: FY26 base | D13: FY26 | E13: FY27 (+5%) | F13: FY28 (+price) | G13: FY29 (+price) | H13: FY30 (+price) | I13: FY31 (+price)
A14: ISZE net EUR per pick-up | B14: =Inputs!$B$4 -> 250 | D14: =B14 -> 250 | E14: =D14*(1+Inputs!$B$9) -> 262.5 | F14: =E14*(1+'Dashboard (2)'!$T$1) -> 270.375 | G14: =F14*(1+'Dashboard (2)'!$T$1) -> 278.48625 | H14: =G14*(1+'Dashboard (2)'!$T$1) -> 286.84084 | I14: =H14*(1+'Dashboard (2)'!$T$1) -> 295.44606
A15: Pick-up rate EUR 250 per vehicle (FY2026, ISZE net), +5% in FY2027 = EUR 262.50, then + yearly price input (Dashboard (2) T1). Replaces the earlier EUR 219.56.
A17: ISZE -> ROMANIA wholesale (ISZE-net EUR) << EXTENDED TARGET IS SET HERE
C18: FY25 (Apr'24-Mar'25) | D18: FY26 (Apr'25-Mar'26) | E18: FY27 (Apr'26-Mar'27) | F18: FY28 | G18: FY29 | H18: FY30 | I18: FY31
A19: Max spend / potential (= UIO x ISZE-net rate) | C19: =C9*$D$14 -> 246500 | D19: =D9*$D$14 -> 267750 | E19: =E9*$E$14 -> 317362.5 | F19: =F9*F14 -> 363113.62 | G19: =G9*G14 -> 410767.22 | H19: =H9*H14 -> 459805.86 | I19: =I9*I14 -> 510235.35
A20: Actual (ISZE billing) · FY27 = BP target | C20: 151600.22 | D20: 177897.87 | E20: 199587.57
A21: Share (GPS, ISZE level) | C21: =C20/C19 -> 0.61501103 | D21: =D20/D19 -> 0.66441782 | E21: =E20/E19 -> 0.62889462
A22: Stretch (%) = global input, capped at ceiling | C22: 0 | D22: 0 | E22: =MAX(0,MIN('Dashboard (2)'!$N$1,Inputs!$B$38-E21)) -> 0.018
A23: Stretch amount (= max spend x stretch%) | C23: =C19*C22 -> 0 | D23: =D19*D22 -> 0 | E23: =E19*E22 -> 5712.525
A24: TTL amount (= actual + stretch) << EXTENDED TARGET | C24: =C20+C23 -> 151600.22 | D24: =D20+D23 -> 177897.87 | E24: =E20+E23 -> 205300.1
A25: Share (new) | C25: =C24/C19 -> 0.61501103 | D25: =D24/D19 -> 0.66441782 | E25: =E24/E19 -> 0.64689462
A26: Source: ISZE billing to the distributor, GPS basis, lubricants included. FY2027 = budget reviewed April 2026.
A27: FY28-FY31 max spend (row 19, cols F:I) feeds Dashboard (2). FY27 actual cell E20 = BP reviewed 24-04-2026.
A28: ROMANIA to dealer level
C29: FY25 (Apr'24-Mar'25) | D29: FY26 (Apr'25-Mar'26) | E29: FY27 (Apr'26-Mar'27)
A30: Sales to dealers (actual, distributor KPI June 2026) | C30: 382258 | D30: 394596.63 | F30: FY25 12/12 mo · FY26 12/12 mo
A31: Distributor margin % | B31: 0.35
A32: Stretch at dealer level (= ISZE stretch / (1 - margin)) | E32: =-E23/(B31-1) -> 8788.5
A33: FY27 AMOUNT TO REACH at dealer (= FY26 actual + dealer stretch) | E33: =IF(OR(D30="",D30="no KPI data"),"no KPI data",D30+E32) -> 403385.13
A34: Dealer level: the ISZE stretch is converted to dealer prices by dividing by (1 - 35% distributor margin). FY2027 amount = FY2026 sales to dealers + that stretch. Amount only, never a share: the distributors' reported sales to dealers run 2.2 to 3.7 times ISZE billing.
A37: Notes
A38: 1. Pick-up rate EUR 250 per vehicle (FY2026, ISZE net), +5% in FY2027 = EUR 262.50. Replaces the earlier EUR 219.56.

Sheet DENMARK
A1: DENMARK — GPS Extended Target FY2027 · ISUZU DANMARK A/S [LCV only]
A2: ISZE to distributor target is set here. Blue = input. FY2028-FY2031 in columns F:I. The dealer block at the bottom uses the IML method (ISZE stretch / (1 - distributor margin)) and is an amount only, never a share.
F3: Colours
F4: Firm / actual
F5: Stretch
A7: DENMARK UIO (LCV)
C8: FY25 (Apr'24-Mar'25) | D8: FY26 (Apr'25-Mar'26) | E8: FY27 (Apr'26-Mar'27) | F8: FY28 (CY2027F) | G8: FY29 (CY2028F) | H8: FY30 (CY2029F) | I8: FY31 (CY2030F)
A9: LCV | C9: 829 | D9: 850 | E9: 944 | F9: 1036 | G9: 1140 | H9: 1241 | I9: 1339
A10: TTL | C10: =C9 -> 829 | D10: =D9 -> 850 | E10: =E9 -> 944 | F10: =F9 -> 1036 | G10: =G9 -> 1140 | H10: =H9 -> 1241 | I10: =I9 -> 1339
A11: Source: UIO V19. Fiscal year = calendar year + 1 (FY2027 uses the fleet of calendar 2026). Compare with the UIO V20 spec on sheet 'UIO V20'.
A13: Parts spend per vehicle (EUR) | B13: FY26 base | D13: FY26 | E13: FY27 (+5%) | F13: FY28 (+price) | G13: FY29 (+price) | H13: FY30 (+price) | I13: FY31 (+price)
A14: ISZE net EUR per pick-up | B14: =Inputs!$B$4 -> 250 | D14: =B14 -> 250 | E14: =D14*(1+Inputs!$B$9) -> 262.5 | F14: =E14*(1+'Dashboard (2)'!$T$1) -> 270.375 | G14: =F14*(1+'Dashboard (2)'!$T$1) -> 278.48625 | H14: =G14*(1+'Dashboard (2)'!$T$1) -> 286.84084 | I14: =H14*(1+'Dashboard (2)'!$T$1) -> 295.44606
A15: Pick-up rate EUR 250 per vehicle (FY2026, ISZE net), +5% in FY2027 = EUR 262.50, then + yearly price input (Dashboard (2) T1). Replaces the earlier EUR 219.56.
A17: ISZE -> DENMARK wholesale (ISZE-net EUR) << EXTENDED TARGET IS SET HERE
C18: FY25 (Apr'24-Mar'25) | D18: FY26 (Apr'25-Mar'26) | E18: FY27 (Apr'26-Mar'27) | F18: FY28 | G18: FY29 | H18: FY30 | I18: FY31
A19: Max spend / potential (= UIO x ISZE-net rate) | C19: =C9*$D$14 -> 207250 | D19: =D9*$D$14 -> 212500 | E19: =E9*$E$14 -> 247800 | F19: =F9*F14 -> 280108.5 | G19: =G9*G14 -> 317474.33 | H19: =H9*H14 -> 355969.48 | I19: =I9*I14 -> 395602.28
A20: Actual (ISZE billing) · FY27 = BP target | C20: 122628.72 | D20: 154459.8 | E20: 187600
A21: Share (GPS, ISZE level) | C21: =C20/C19 -> 0.59169467 | D21: =D20/D19 -> 0.72686965 | E21: =E20/E19 -> 0.75706215
A22: Stretch (%) = global input, capped at ceiling | C22: 0 | D22: 0 | E22: =MAX(0,MIN('Dashboard (2)'!$N$1,Inputs!$B$38-E21)) -> 0.018
A23: Stretch amount (= max spend x stretch%) | C23: =C19*C22 -> 0 | D23: =D19*D22 -> 0 | E23: =E19*E22 -> 4460.4
A24: TTL amount (= actual + stretch) << EXTENDED TARGET | C24: =C20+C23 -> 122628.72 | D24: =D20+D23 -> 154459.8 | E24: =E20+E23 -> 192060.4
A25: Share (new) | C25: =C24/C19 -> 0.59169467 | D25: =D24/D19 -> 0.72686965 | E25: =E24/E19 -> 0.77506215
A26: Source: ISZE billing to the distributor, GPS basis, lubricants included. FY2027 = budget reviewed April 2026.
A27: FY28-FY31 max spend (row 19, cols F:I) feeds Dashboard (2). FY27 actual cell E20 = BP reviewed 24-04-2026.
A28: DENMARK to dealer level
C29: FY25 (Apr'24-Mar'25) | D29: FY26 (Apr'25-Mar'26) | E29: FY27 (Apr'26-Mar'27)
A30: Sales to dealers (actual, distributor KPI June 2026) | C30: 356680.16 | D30: 572863.67 | F30: FY25 12/12 mo · FY26 12/12 mo
A31: Distributor margin % | B31: 0.35
A32: Stretch at dealer level (= ISZE stretch / (1 - margin)) | E32: =-E23/(B31-1) -> 6862.1538
A33: FY27 AMOUNT TO REACH at dealer (= FY26 actual + dealer stretch) | E33: =IF(OR(D30="",D30="no KPI data"),"no KPI data",D30+E32) -> 579725.82
A34: Dealer level: the ISZE stretch is converted to dealer prices by dividing by (1 - 35% distributor margin). FY2027 amount = FY2026 sales to dealers + that stretch. Amount only, never a share: the distributors' reported sales to dealers run 2.2 to 3.7 times ISZE billing.
A37: Notes
A38: 1. Pick-up rate EUR 250 per vehicle (FY2026, ISZE net), +5% in FY2027 = EUR 262.50. Replaces the earlier EUR 219.56.

Sheet ICELAND
A1: ICELAND — GPS Extended Target FY2027 · BL. EHF. [LCV only]
A2: ISZE to distributor target is set here. Blue = input. FY2028-FY2031 in columns F:I. The dealer block at the bottom uses the IML method (ISZE stretch / (1 - distributor margin)) and is an amount only, never a share.
F3: Colours
F4: Firm / actual
F5: Stretch
A7: ICELAND UIO (LCV)
C8: FY25 (Apr'24-Mar'25) | D8: FY26 (Apr'25-Mar'26) | E8: FY27 (Apr'26-Mar'27) | F8: FY28 (CY2027F) | G8: FY29 (CY2028F) | H8: FY30 (CY2029F) | I8: FY31 (CY2030F)
A9: LCV | C9: 342 | D9: 406 | E9: 439 | F9: 471 | G9: 549 | H9: 625 | I9: 698
A10: TTL | C10: =C9 -> 342 | D10: =D9 -> 406 | E10: =E9 -> 439 | F10: =F9 -> 471 | G10: =G9 -> 549 | H10: =H9 -> 625 | I10: =I9 -> 698
A11: Source: UIO V19. Fiscal year = calendar year + 1 (FY2027 uses the fleet of calendar 2026). Compare with the UIO V20 spec on sheet 'UIO V20'.
A13: Parts spend per vehicle (EUR) | B13: FY26 base | D13: FY26 | E13: FY27 (+5%) | F13: FY28 (+price) | G13: FY29 (+price) | H13: FY30 (+price) | I13: FY31 (+price)
A14: ISZE net EUR per pick-up | B14: =Inputs!$B$4 -> 250 | D14: =B14 -> 250 | E14: =D14*(1+Inputs!$B$9) -> 262.5 | F14: =E14*(1+'Dashboard (2)'!$T$1) -> 270.375 | G14: =F14*(1+'Dashboard (2)'!$T$1) -> 278.48625 | H14: =G14*(1+'Dashboard (2)'!$T$1) -> 286.84084 | I14: =H14*(1+'Dashboard (2)'!$T$1) -> 295.44606
A15: Pick-up rate EUR 250 per vehicle (FY2026, ISZE net), +5% in FY2027 = EUR 262.50, then + yearly price input (Dashboard (2) T1). Replaces the earlier EUR 219.56.
A17: ISZE -> ICELAND wholesale (ISZE-net EUR) << EXTENDED TARGET IS SET HERE
C18: FY25 (Apr'24-Mar'25) | D18: FY26 (Apr'25-Mar'26) | E18: FY27 (Apr'26-Mar'27) | F18: FY28 | G18: FY29 | H18: FY30 | I18: FY31
A19: Max spend / potential (= UIO x ISZE-net rate) | C19: =C9*$D$14 -> 85500 | D19: =D9*$D$14 -> 101500 | E19: =E9*$E$14 -> 115237.5 | F19: =F9*F14 -> 127346.62 | G19: =G9*G14 -> 152888.95 | H19: =H9*H14 -> 179275.52 | I19: =I9*I14 -> 206221.35
A20: Actual (ISZE billing) · FY27 = BP target | C20: 73673.52 | D20: 86604.51 | E20: 104600
A21: Share (GPS, ISZE level) | C21: =C20/C19 -> 0.8616786 | D21: =D20/D19 -> 0.8532464 | E21: =E20/E19 -> 0.90769064
A22: Stretch (%) = global input, capped at ceiling | C22: 0 | D22: 0 | E22: =MAX(0,MIN('Dashboard (2)'!$N$1,Inputs!$B$38-E21)) -> 0.018
A23: Stretch amount (= max spend x stretch%) | C23: =C19*C22 -> 0 | D23: =D19*D22 -> 0 | E23: =E19*E22 -> 2074.275
A24: TTL amount (= actual + stretch) << EXTENDED TARGET | C24: =C20+C23 -> 73673.52 | D24: =D20+D23 -> 86604.51 | E24: =E20+E23 -> 106674.27
A25: Share (new) | C25: =C24/C19 -> 0.8616786 | D25: =D24/D19 -> 0.8532464 | E25: =E24/E19 -> 0.92569064
A26: Source: ISZE billing to the distributor, GPS basis, lubricants included. FY2027 = budget reviewed April 2026.
A27: FY28-FY31 max spend (row 19, cols F:I) feeds Dashboard (2). FY27 actual cell E20 = BP reviewed 24-04-2026.
A28: ICELAND to dealer level
C29: FY25 (Apr'24-Mar'25) | D29: FY26 (Apr'25-Mar'26) | E29: FY27 (Apr'26-Mar'27)
A30: Sales to dealers (actual, distributor KPI June 2026) | C30: 209944 | D30: 195849 | F30: FY25 12/12 mo · FY26 12/12 mo
A31: Distributor margin % | B31: 0.35
A32: Stretch at dealer level (= ISZE stretch / (1 - margin)) | E32: =-E23/(B31-1) -> 3191.1923
A33: FY27 AMOUNT TO REACH at dealer (= FY26 actual + dealer stretch) | E33: =IF(OR(D30="",D30="no KPI data"),"no KPI data",D30+E32) -> 199040.19
A34: Dealer level: the ISZE stretch is converted to dealer prices by dividing by (1 - 35% distributor margin). FY2027 amount = FY2026 sales to dealers + that stretch. Amount only, never a share: the distributors' reported sales to dealers run 2.2 to 3.7 times ISZE billing.
A37: Notes
A38: 1. Pick-up rate EUR 250 per vehicle (FY2026, ISZE net), +5% in FY2027 = EUR 262.50. Replaces the earlier EUR 219.56.

Sheet GERMANY
A1: GERMANY — GPS Extended Target FY2027 · ISUZU SALES DEUTSCHLAND GMBH [mixed CV+LCV]
A2: ISZE to distributor target is set here. Blue = input. FY2028-FY2031 in columns F:I. The dealer block at the bottom uses the IML method (ISZE stretch / (1 - distributor margin)) and is an amount only, never a share.
F3: Colours
F4: Firm / actual
F5: Stretch
A7: GERMANY UIO by segment
C8: FY25 (Apr'24-Mar'25) | D8: FY26 (Apr'25-Mar'26) | E8: FY27 (Apr'26-Mar'27) | F8: FY28 (CY2027F) | G8: FY29 (CY2028F) | H8: FY30 (CY2029F) | I8: FY31 (CY2030F)
A9: LD (N75/N50/N62) | C9: 719 | D9: 697 | E9: 1066 | F9: 1422 | G9: 2003 | H9: 2841 | I9: 3756
A10: MD | C10: 36 | D10: 35 | E10: 34 | F10: 33 | G10: 32 | H10: 31 | I10: 30
A11: F-Series | C11: 0 | D11: 0 | E11: 0 | F11: 0 | G11: 0 | H11: 0 | I11: 0
A12: LCV / D-Max | C12: 12709 | D12: 13048 | E12: 13657 | F12: 14247 | G12: 14820 | H12: 15375 | I12: 15914
A13: TTL | C13: =SUM(C9:C12) -> 13464 | D13: =SUM(D9:D12) -> 13780 | E13: =SUM(E9:E12) -> 14757 | F13: =SUM(F9:F12) -> 15702 | G13: =SUM(G9:G12) -> 16855 | H13: =SUM(H9:H12) -> 18247 | I13: =SUM(I9:I12) -> 19700
A14: Source: UIO V19. Fiscal year = calendar year + 1 (FY2027 uses the fleet of calendar 2026). Compare with the UIO V20 spec on sheet 'UIO V20'.
A16: Max spend per unit (EUR, ISZE-net) | C16: base | D16: FY27 (+5%) | E16: FY28 | F16: FY29 | G16: FY30 | H16: FY31
A17: Light truck (LD) rate | C17: =Inputs!$B$5 -> 739 | D17: =C17*(1+Inputs!$B$9) -> 775.95 | E17: =D17*(1+'Dashboard (2)'!$T$1) -> 799.2285 | F17: =E17*(1+'Dashboard (2)'!$T$1) -> 823.20536 | G17: =F17*(1+'Dashboard (2)'!$T$1) -> 847.90152 | H17: =G17*(1+'Dashboard (2)'!$T$1) -> 873.33856
A18: Medium truck (MD) rate | C18: =Inputs!$B$6 -> 887 | D18: =C18*(1+Inputs!$B$9) -> 931.35 | E18: =D18*(1+'Dashboard (2)'!$T$1) -> 959.2905 | F18: =E18*(1+'Dashboard (2)'!$T$1) -> 988.06921 | G18: =F18*(1+'Dashboard (2)'!$T$1) -> 1017.7113 | H18: =G18*(1+'Dashboard (2)'!$T$1) -> 1048.2426
A19: F-Series rate | C19: =Inputs!$B$7 -> 887 | D19: =C19*(1+Inputs!$B$9) -> 931.35 | E19: =D19*(1+'Dashboard (2)'!$T$1) -> 959.2905 | F19: =E19*(1+'Dashboard (2)'!$T$1) -> 988.06921 | G19: =F19*(1+'Dashboard (2)'!$T$1) -> 1017.7113 | H19: =G19*(1+'Dashboard (2)'!$T$1) -> 1048.2426
A20: Pick-up (D-Max) rate, EUR 250 base | C20: =Inputs!$B$4 -> 250 | D20: =C20*(1+Inputs!$B$9) -> 262.5 | E20: =D20*(1+'Dashboard (2)'!$T$1) -> 270.375 | F20: =E20*(1+'Dashboard (2)'!$T$1) -> 278.48625 | G20: =F20*(1+'Dashboard (2)'!$T$1) -> 286.84084 | H20: =G20*(1+'Dashboard (2)'!$T$1) -> 295.44606
A21: Truck rates 739 / 887 and pick-up rate EUR 250 per vehicle (FY2026, ISZE net), +5% in FY2027, then + yearly price input. All rates sit on the Inputs sheet.
A23: ISZE -> GERMANY wholesale (ISZE-net EUR) << EXTENDED TARGET IS SET HERE
C24: FY25 (Apr'24-Mar'25) | D24: FY26 (Apr'25-Mar'26) | E24: FY27 (Apr'26-Mar'27) | F24: FY28 | G24: FY29 | H24: FY30 | I24: FY31
A25: Max spend / potential (= UIO x ISZE-net rate) | C25: =C9*$C$17+C10*$C$18+C11*$C$19+C12*$C$20 -> 3740523 | D25: =D9*$C$17+D10*$C$18+D11*$C$19+D12*$C$20 -> 3808128 | E25: =E9*$D$17+E10*$D$18+E11*$D$19+E12*$D$20 -> 4443791.1 | F25: =F9*E17+F10*E18+F11*E19+F12*E20 -> 5020192.1 | G25: =G9*F17+G10*F18+G11*F19+G12*F20 -> 5807664.8 | H25: =H9*G17+H10*G18+H11*G19+H12*G20 -> 6850615.1 | I25: =I9*H17+I10*H18+I11*H19+I12*H20 -> 8013435.6
A26: Actual (ISZE billing) · FY27 = BP target | C26: 2589331.9 | D26: 2641885.1 | E26: 2913662.8
A27: Share (GPS, ISZE level) | C27: =C26/C25 -> 0.69223794 | D27: =D26/D25 -> 0.69374904 | E27: =E26/E25 -> 0.65567052
