Workbook

Sheet How to Use
A1: SPA OPTIMIZER V3 — HOW TO USE
A2: Isuzu Motors Europe · Parts & Aftersales · Special Pricing Agreement Tool
A4: PURPOSE
A5: Compares L12 SAP actuals versus a proposed SPA price and volume commitment. Quantifies profit impact, break-even conditions, and IML/IMIT purchase support required. V3 adds customer-safe output (Customer View), IML brief, management business case, scenario modelling, and SPA Health Check.
A7: TAB GUIDE — WHO USES WHAT
A8: Tab | B8: Audience | C8: Colour | D8: Purpose
A9: How to Use | B9: Everyone | C9: Blue | D9: This page. Start here before opening anything else.
A10: Assumptions | B10: ISZE internal | C10: Green | D10: Set all inputs. Read the SPA Health Check at bottom before sharing anything.
A11: SPA Optimizer | B11: ISZE internal | C11: Green | D11: Core engine. Blue cells = inputs. All other cells are formulas — do not edit.
A12: Customer View | B12: Share with Distributor | C12: Red | D12: Customer-safe: list price, SPA price, saving %, GBP. No ISZE cost/margin data. Safe to email.
A13: IML_IMIT Brief | B13: IML / IMIT only | C13: Orange | D13: Confidential. Full cost data, required cut %, €-sacrifice, volume upside, 6-section rationale. Never share with distributors.
A14: SPA Rationale | B14: ISZE management | C14: Green | D14: 9-section business case for Management Approvers. Retention risk, financials, recommendation pre-populated.
A15: Scenario Planner | B15: ISZE internal | C15: Green | D15: Four scenarios: Partial / Full / Full+IML (★) / Enhanced. Use to frame approval requests.
A17: STEP-BY-STEP WORKFLOW
A18: STEP 1 Assumptions | B18: Set customer name, market, SPA ref, validity dates, IML cut %, GBP/EUR, retention risk score, volume growth assumption. Then read the SPA Health Check — it tells you whether the SPA is approvable, needs IML support, or needs renegotiation before you go further.
A19: STEP 2 SPA Optimizer inputs | B19: Blue cells are your inputs: Purchase Price (€), ISZE Sales Price (€), L12 Qty and Revenue (from SAP), SPA Price (€), and SPA Qty committed by Distributor. Everything else calculates automatically.
A20: STEP 3 Review results | B20: Status (no cut) = viable without IML. Status w/ Cut = viable with IML cut from Assumptions. Min Qty and Min Price = your floor conditions. Req IML Cut % (col AA) = what you take to Japan.
A21: STEP 4 Scenario Planner | B21: Four scenarios. Full+IML = recommended (green). Use to frame your internal approval request to Director and Management Approver.
A22: STEP 5 SPA Rationale | B22: Your management narrative. Retention risk, financial impact, recommendation pre-populated. Adapt the Recommendation section before sharing if needed.
A23: STEP 6 Share with Distributor | B23: Export or print Customer View tab ONLY. No ISZE cost or margin. Shows list price, SPA price, savings in € and GBP, volume commitment. Safe to email directly.
A24: STEP 7 Brief IML/IMIT | B24: Send IML_IMIT Brief to Japan — contains full cost data, required cut %, €-sacrifice, volume upside. Verify red-highlighted Column C (purchase price) is NEVER visible to distributors.
A26: CELL COLOUR CODE (SPA Optimizer tab)
A27: Blue text / blue bg | B27: Manual input — you edit these
A28: Black text | B28: Formula / auto-calculated — do not edit
A29: Green text | B29: Cross-sheet link from Assumptions tab
A30: Red/orange highlight | B30: Flagged issue or anomaly — needs review
A31: ▲ BETTER | B31: SPA scenario generates more profit than L12
A32: ▼ WORSE | B32: SPA scenario generates less profit than L12

Sheet Assumptions
B1: SPA OPTIMIZER — ASSUMPTIONS
B3: PARAMETER | C3: VALUE | D3: NOTES
B4: IML / IMIT Purchase Price Cut % | C4: 0.07 | D4: % of purchase price that IML/IMIT reduces for ISZE. 0%=ISZE absorbs all. 0.05=IML gives 5% off.
B5: Minimum GM% Floor (ISZE reference) | C5: 0.25 | D5: Reference floor — does NOT block calculations. Used to highlight margin erosion.
B6: FX Rate (JPY / EUR) — reference only | C6: 163.7 | D6: Current FX context. Not used in EUR-EUR calculations.
A8: CUSTOMER & SPA CONTEXT
A9: Customer / Distributor Name | B9: Distributor | C9: ← edit as needed
A10: Market | B10: [Market] | C10: ← edit as needed
A11: SPA Reference | B11: SPA Distributor | C11: ← edit as needed
A12: SPA Valid From | B12: 01/05/2026 | C12: ← edit as needed
A13: SPA Valid To | B13: 30/04/2027 | C13: ← edit as needed
A14: Prepared by | B14: [Name] | C14: ← edit as needed
A15: Currency display (customer) | B15: EUR | C15: ← edit as needed
A16: GBP/EUR FX Rate | B16: N#/A | C16: ← edit as needed
A17: Retention Risk Score (1–5) | B17: 4 | C17: ← edit as needed
A18: Competitor Threat | B18: IAM Competitors | C18: ← edit as needed
A19: Volume Growth Assumption % | B19: 0.1 | C19: ← edit as needed
A21: SPA HEALTH CHECK — READ BEFORE SHARING
A22: Auto-calculated from SPA Optimizer. Updates whenever you change inputs above.
A23: KPI | B23: Current value | C23: Status
A24: SPA revenue delta vs L12 | B24: =TEXT(ABS('SPA Optimizer'!P60),"€#,##0")&IF('SPA Optimizer'!P60>=0," ▲"," ▼") -> €39735,470 ▼ | C24: =IF('SPA Optimizer'!P60>=-50000,IF('SPA Optimizer'!P60>=0,"✔ Revenue maintained or grown","⚠ Revenue decline within tolerance (<€50K)"),"✖ Revenue decline exceeds €50K — review") -> ⚠ Revenue decline within tolerance (<€50K)
A25: ISZE profit w/ IML cut vs L12 | B25: =TEXT(ABS('SPA Optimizer'!Y60),"€#,##0")&IF('SPA Optimizer'!Y60>=0," ▲"," ▼") -> €85594,263 ▼ | C25: =IF('SPA Optimizer'!Y60>=0,"✔ Profit neutral or better with IML support",IF('SPA Optimizer'!Y60>=-40000,"⚠ Profit decline with IML — still submittable","✖ Profit decline too large — renegotiate")) -> ✖ Profit decline too large — renegotiate
A26: IML sacrifice required | B26: =TEXT('SPA Optimizer'!Z60,"€#,##0") -> €37134,528 | C26: =IF('SPA Optimizer'!Z60<=20000,"✔ IML sacrifice reasonable (≤€20K)",IF('SPA Optimizer'!Z60<=40000,"⚠ Elevated — escalation likely needed","✖ Too high — review pricing")) -> ⚠ Elevated — escalation likely needed
A27: Lines viable without IML | B27: =COUNTIF('SPA Optimizer'!R6:R58,"▲ BETTER")&" of 12" -> 16 of 12 | C27: =IF(COUNTIF('SPA Optimizer'!R6:R58,"▲ BETTER")>=6,"✔ Majority viable standalone",IF(COUNTIF('SPA Optimizer'!R6:R58,"▲ BETTER")>=2,"⚠ Few viable standalone — IML needed for most","✖ None viable without IML")) -> ✔ Majority viable standalone
A28: Lines viable WITH IML support | B28: =COUNTIF('SPA Optimizer'!AB6:AB58,"▲ BETTER")&" of 12" -> 21 of 12 | C28: =IF(COUNTIF('SPA Optimizer'!AB6:AB58,"▲ BETTER")>=10,"✔ SPA approvable with IML support",IF(COUNTIF('SPA Optimizer'!AB6:AB58,"▲ BETTER")>=6,"⚠ Partial approval possible — review weak lines","✖ Not viable even with IML — renegotiate")) -> ✔ SPA approvable with IML support
A29: Average SPA gross margin | B29: =TEXT(AVERAGE('SPA Optimizer'!O6:O58),"0.0%")&" (L12: "&TEXT(AVERAGE('SPA Optimizer'!I6:I58),"0.0%")&")" -> 27% (L12: 42%) | C29: =IF(AVERAGE('SPA Optimizer'!O6:O58)>=0.3,"✔ Avg GM% above 30% floor",IF(AVERAGE('SPA Optimizer'!O6:O58)>=0.25,"⚠ Near 25% floor — Management Approver flag","✖ Below 25% minimum — approval at risk")) -> ⚠ Near 25% floor — Management Approver flag
A30: Net volume uplift vs L12 | B30: =TEXT(SUM('SPA Optimizer'!K6:K58)-SUM('SPA Optimizer'!E6:E58),"+#,##0;-#,##0;0")&" units" -> +715,0 units | C30: =IF(SUM('SPA Optimizer'!K6:K58)>=SUM('SPA Optimizer'!E6:E58),"✔ Committed volume exceeds L12 — SPA justified","⚠ Below L12 — strengthen ask or add justification") -> ✔ Committed volume exceeds L12 — SPA justified
A31: ★ OVERALL SPA VERDICT | B31: " " | C31: =IF(COUNTIF('SPA Optimizer'!AB6:AB58,"▲ BETTER")>=10,IF('SPA Optimizer'!Z60<=25000,"✔ APPROVABLE — Submit with IML brief. All key metrics within range.","⚠ APPROVABLE WITH ESCALATION — IML sacrifice elevated. Needs Management Approver sign-off."),IF(COUNTIF('SPA Optimizer'!AB6:AB58,"▲ BETTER")>=6,"⚠ PARTIAL APPROVAL — Submit viable lines only. Review weak lines first.","✖ NOT READY — Revise SPA prices or volumes before submission.")) -> ⚠ APPROVABLE WITH ESCALATION — IML sacrifice elevated. Needs Management Approver sign-off.
A33: GM% FLOOR CHECK — PER LINE (Management Approver 25% minimum / 10% alarm)
A34: Live formulas. Green = above 30% | Amber = 25–30% (caution) | Red = below 25% (Management Approver alarm threshold)
A35: P/N | B35: Description | C35: SPA GM% | D35: Status vs 25% floor
A36: ='SPA Optimizer'!A6 -> 1443803030 | B36: ='SPA Optimizer'!B6 -> LINK; DRAG | C36: ='SPA Optimizer'!O6 -> 0.34618182 | D36: =IF('SPA Optimizer'!O6>=0.3,"✔ OK",IF('SPA Optimizer'!O6>=0.25,"⚠ Caution — below 30% — explain to Management Approver","✖ ALARM — below 25% — Management Approver will flag this")) -> ✔ OK
A37: ='SPA Optimizer'!A7 -> 1443803050 | B37: ='SPA Optimizer'!B7 -> LINK; DRAG | C37: ='SPA Optimizer'!O7 -> 0.31763636 | D37: =IF('SPA Optimizer'!O7>=0.3,"✔ OK",IF('SPA Optimizer'!O7>=0.25,"⚠ Caution — below 30% — explain to Management Approver","✖ ALARM — below 25% — Management Approver will flag this")) -> ✔ OK
A38: ='SPA Optimizer'!A8 -> 1476010870 | B38: ='SPA Optimizer'!B8 -> EXPANDER | C38: ='SPA Optimizer'!O8 -> 0.3102 | D38: =IF('SPA Optimizer'!O8>=0.3,"✔ OK",IF('SPA Optimizer'!O8>=0.25,"⚠ Caution — below 30% — explain to Management Approver","✖ ALARM — below 25% — Management Approver will flag this")) -> ✔ OK
A39: ='SPA Optimizer'!A9 -> 1476012180 | B39: ='SPA Optimizer'!B9 -> CYLINDER; WHEEL,RR BRK | C39: ='SPA Optimizer'!O9 -> 0.2376 | D39: =IF('SPA Optimizer'!O9>=0.3,"✔ OK",IF('SPA Optimizer'!O9>=0.25,"⚠ Caution — below 30% — explain to Management Approver","✖ ALARM — below 25% — Management Approver will flag this")) -> ✖ ALARM — below 25% — Management Approver will flag this
A40: ='SPA Optimizer'!A10 -> 1476012190 | B40: ='SPA Optimizer'!B10 -> CYLINDER; WHEEL,RR BRK | C40: ='SPA Optimizer'!O10 -> 0.2376 | D40: =IF('SPA Optimizer'!O10>=0.3,"✔ OK",IF('SPA Optimizer'!O10>=0.25,"⚠ Caution — below 30% — explain to Management Approver","✖ ALARM — below 25% — Management Approver will flag this")) -> ✖ ALARM — below 25% — Management Approver will flag this
A41: ='SPA Optimizer'!A11 -> 1876101141 | B41: ='SPA Optimizer'!B11 -> FILTER; ACL,INNER | C41: ='SPA Optimizer'!O11 -> 0.21166667 | D41: =IF('SPA Optimizer'!O11>=0.3,"✔ OK",IF('SPA Optimizer'!O11>=0.25,"⚠ Caution — below 30% — explain to Management Approver","✖ ALARM — below 25% — Management Approver will flag this")) -> ✖ ALARM — below 25% — Management Approver will flag this
A42: ='SPA Optimizer'!A12 -> 5876100891 | B42: ='SPA Optimizer'!B12 -> PUMP ASM; WATER | C42: ='SPA Optimizer'!O12 -> 0.508 | D42: =IF('SPA Optimizer'!O12>=0.3,"✔ OK",IF('SPA Optimizer'!O12>=0.25,"⚠ Caution — below 30% — explain to Management Approver","✖ ALARM — below 25% — Management Approver will flag this")) -> ✔ OK
A43: ='SPA Optimizer'!A13 -> 5876102200 | B43: ='SPA Optimizer'!B13 -> ELEMENT KIT;FUEL FILTER | C43: ='SPA Optimizer'!O13 -> 0.20285714 | D43: =IF('SPA Optimizer'!O13>=0.3,"✔ OK",IF('SPA Optimizer'!O13>=0.25,"⚠ Caution — below 30% — explain to Management Approver","✖ ALARM — below 25% — Management Approver will flag this")) -> ✖ ALARM — below 25% — Management Approver will flag this
A44: ='SPA Optimizer'!A14 -> 5876102320 | B44: ='SPA Optimizer'!B14 -> CLUTCH KIT | C44: ='SPA Optimizer'!O14 -> 0.10766667 | D44: =IF('SPA Optimizer'!O14>=0.3,"✔ OK",IF('SPA Optimizer'!O14>=0.25,"⚠ Caution — below 30% — explain to Management Approver","✖ ALARM — below 25% — Management Approver will flag this")) -> ✖ ALARM — below 25% — Management Approver will flag this
A45: ='SPA Optimizer'!A15 -> 5876102820 | B45: ='SPA Optimizer'!B15 -> STARTER ASM | C45: ='SPA Optimizer'!O15 -> 0.35259259 | D45: =IF('SPA Optimizer'!O15>=0.3,"✔ OK",IF('SPA Optimizer'!O15>=0.25,"⚠ Caution — below 30% — explain to Management Approver","✖ ALARM — below 25% — Management Approver will flag this")) -> ✔ OK
A46: ='SPA Optimizer'!A16 -> 5876102850 | B46: ='SPA Optimizer'!B16 -> ABSORBER ASM; SHOCK,FRT | C46: ='SPA Optimizer'!O16 -> 0.12 | D46: =IF('SPA Optimizer'!O16>=0.3,"✔ OK",IF('SPA Optimizer'!O16>=0.25,"⚠ Caution — below 30% — explain to Management Approver","✖ ALARM — below 25% — Management Approver will flag this")) -> ✖ ALARM — below 25% — Management Approver will flag this
A47: ='SPA Optimizer'!A17 -> 5878323991 | B47: ='SPA Optimizer'!B17 -> KING PIN KIT | C47: ='SPA Optimizer'!O17 -> 0.2004 | D47: =IF('SPA Optimizer'!O17>=0.3,"✔ OK",IF('SPA Optimizer'!O17>=0.25,"⚠ Caution — below 30% — explain to Management Approver","✖ ALARM — below 25% — Management Approver will flag this")) -> ✖ ALARM — below 25% — Management Approver will flag this
... A88: ='SPA Optimizer'!A58 -> 8983528481 | B88: ='SPA Optimizer'!B58 -> SENSOR; NOX | C88: ='SPA Optimizer'!O58 -> 0.40770732 | D88: =IF('SPA Optimizer'!O58>=0.3,"✔ OK",IF('SPA Optimizer'!O58>=0.25,"⚠ Caution — below 30% — explain to Management Approver","✖ ALARM — below 25% — Management Approver will flag this")) -> ✔ OK

Sheet SPA Optimizer
A1: SPA OPTIMIZER · Distributor · ISZE
A2: Compare L12 actual vs SPA scenario | Profit impact | Break-even | Entity sharing | O2: Blue cells = inputs | Black = formulas | Green = from Assumptions sheet
A4: PART INFO | C4: ◀ L12 BASELINE — ACTUAL (SAP) ▶ | J4: ◀ SPA AS REQUESTED ▶ | P4: ◀ DELTA vs L12 ▶ | S4: ◀ BREAK-EVEN ▶ | V4: ◀ ENTITY SHARING — IML / IMIT CUT ▶
A5: P/N | B5: Description | C5: Purchase Price (€) | D5: ISZE Sales Price (€) | E5: L12 Qty | F5: L12 Revenue (€) | G5: L12 Cost (€) | H5: L12 Profit (€) | I5: L12 GM% | J5: SPA Price (€) | K5: SPA Qty Committed | L5: SPA Revenue (€) | M5: Unit Margin (€) | N5: SPA Profit (€) | O5: SPA GM% | P5: Δ Revenue (€) | Q5: Δ Profit (€) | R5: Status (no cut) | S5: Min Qty @ SPA Price | T5: Min Price @ SPA Qty | U5: Extra Qty Needed | V5: IML Cut % | W5: ISZE Cost w/ Cut (€) | X5: SPA Profit w/ Cut (€) | Y5: Δ Profit w/ Cut (€) | Z5: IML € Sacrifice | AA5: Req IML Cut % | AB5: Status w/ Cut
A6: 1443803030 | B6: LINK; DRAG | C6: 71.92 | D6: 131.66 | E6: 68 | F6: 8952.88 | G6: 4890.56 | H6: =F6-G6 -> 4062.32 | I6: =IFERROR(H6/F6,0) -> 0.45374449 | J6: 110 | K6: 60 | L6: =J6*K6 -> 6600 | M6: =J6-C6 -> 38.08 | N6: =M6*K6 -> 2284.8 | O6: =IFERROR(N6/L6,0) -> 0.34618182 | P6: =L6-F6 -> -2352.88 | Q6: =N6-H6 -> -1777.52 | R6: =IF(Q6>=0,"▲ BETTER","▼ WORSE") -> ▼ WORSE | S6: =IFERROR(IF(J6-C6<=0,"BELOW COST",CEILING(H6/(J6-C6),1)),"N/A") -> 107 | T6: =IFERROR(H6/K6+C6,"N/A") -> 139.62533 | U6: =IFERROR(MAX(0,S6-K6),0) -> 47 | V6: =Assumptions!$C$4 -> 0.07 | W6: =IFERROR(C6*(1-Assumptions!$C$4),C6) -> 66.8856 | X6: =IFERROR((J6-C6*(1-Assumptions!$C$4))*K6,N6) -> 2586.864 | Y6: =IFERROR(X6-H6,N6-H6) -> -1475.456 | Z6: =IFERROR(C6*Assumptions!$C$4*K6,0) -> 302.064 | AA6: =IFERROR(MAX(0,1-(J6-H6/K6)/C6),"N/A") -> 0.41192065 | AB6: =IFERROR(IF(Y6>=0,"▲ BETTER","▼ WORSE"),"N/A") -> ▼ WORSE
A7: 1443803050 | B7: LINK; DRAG | C7: 75.06 | D7: 137.41 | E7: 44 | F7: 6046.04 | G7: 3302.64 | H7: =F7-G7 -> 2743.4 | I7: =IFERROR(H7/F7,0) -> 0.45375155 | J7: 110 | K7: 55 | L7: =J7*K7 -> 6050 | M7: =J7-C7 -> 34.94 | N7: =M7*K7 -> 1921.7 | O7: =IFERROR(N7/L7,0) -> 0.31763636 | P7: =L7-F7 -> 3.96 | Q7: =N7-H7 -> -821.7 | R7: =IF(Q7>=0,"▲ BETTER","▼ WORSE") -> ▼ WORSE | S7: =IFERROR(IF(J7-C7<=0,"BELOW COST",CEILING(H7/(J7-C7),1)),"N/A") -> 79 | T7: =IFERROR(H7/K7+C7,"N/A") -> 124.94 | U7: =IFERROR(MAX(0,S7-K7),0) -> 24 | V7: =Assumptions!$C$4 -> 0.07 | W7: =IFERROR(C7*(1-Assumptions!$C$4),C7) -> 69.8058 | X7: =IFERROR((J7-C7*(1-Assumptions!$C$4))*K7,N7) -> 2210.681 | Y7: =IFERROR(X7-H7,N7-H7) -> -532.719 | Z7: =IFERROR(C7*Assumptions!$C$4*K7,0) -> 288.981 | AA7: =IFERROR(MAX(0,1-(J7-H7/K7)/C7),"N/A") -> 0.19904077 | AB7: =IFERROR(IF(Y7>=0,"▲ BETTER","▼ WORSE"),"N/A") -> ▼ WORSE
A8: 1476010870 | B8: EXPANDER | C8: 137.96 | D8: 252.56 | E8: 49 | F8: 12375.44 | G8: 6760.04 | H8: =F8-G8 -> 5615.4 | I8: =IFERROR(H8/F8,0) -> 0.45375356 | J8: 200 | K8: 90 | L8: =J8*K8 -> 18000 | M8: =J8-C8 -> 62.04 | N8: =M8*K8 -> 5583.6 | O8: =IFERROR(N8/L8,0) -> 0.3102 | P8: =L8-F8 -> 5624.56 | Q8: =N8-H8 -> -31.8 | R8: =IF(Q8>=0,"▲ BETTER","▼ WORSE") -> ▼ WORSE | S8: =IFERROR(IF(J8-C8<=0,"BELOW COST",CEILING(H8/(J8-C8),1)),"N/A") -> 91 | T8: =IFERROR(H8/K8+C8,"N/A") -> 200.35333 | U8: =IFERROR(MAX(0,S8-K8),0) -> 1 | V8: =Assumptions!$C$4 -> 0.07 | W8: =IFERROR(C8*(1-Assumptions!$C$4),C8) -> 128.3028 | X8: =IFERROR((J8-C8*(1-Assumptions!$C$4))*K8,N8) -> 6452.748 | Y8: =IFERROR(X8-H8,N8-H8) -> 837.348 | Z8: =IFERROR(C8*Assumptions!$C$4*K8,0) -> 869.148 | AA8: =IFERROR(MAX(0,1-(J8-H8/K8)/C8),"N/A") -> 0.0025611288 | AB8: =IFERROR(IF(Y8>=0,"▲ BETTER","▼ WORSE"),"N/A") -> ▲ BETTER
A9: 1476012180 | B9: CYLINDER; WHEEL,RR BRK | C9: 114.36 | D9: 193.68 | E9: 77 | F9: 14913.36 | G9: 8805.72 | H9: =F9-G9 -> 6107.64 | I9: =IFERROR(H9/F9,0) -> 0.40954151 | J9: 150 | K9: 80 | L9: =J9*K9 -> 12000 | M9: =J9-C9 -> 35.64 | N9: =M9*K9 -> 2851.2 | O9: =IFERROR(N9/L9,0) -> 0.2376 | P9: =L9-F9 -> -2913.36 | Q9: =N9-H9 -> -3256.44 | R9: =IF(Q9>=0,"▲ BETTER","▼ WORSE") -> ▼ WORSE | S9: =IFERROR(IF(J9-C9<=0,"BELOW COST",CEILING(H9/(J9-C9),1)),"N/A") -> 172 | T9: =IFERROR(H9/K9+C9,"N/A") -> 190.7055 | U9: =IFERROR(MAX(0,S9-K9),0) -> 92 | V9: =Assumptions!$C$4 -> 0.07 | W9: =IFERROR(C9*(1-Assumptions!$C$4),C9) -> 106.3548 | X9: =IFERROR((J9-C9*(1-Assumptions!$C$4))*K9,N9) -> 3491.616 | Y9: =IFERROR(X9-H9,N9-H9) -> -2616.024 | Z9: =IFERROR(C9*Assumptions!$C$4*K9,0) -> 640.416 | AA9: =IFERROR(MAX(0,1-(J9-H9/K9)/C9),"N/A") -> 0.35594176 | AB9: =IFERROR(IF(Y9>=0,"▲ BETTER","▼ WORSE"),"N/A") -> ▼ WORSE
A10: 1476012190 | B10: CYLINDER; WHEEL,RR BRK | C10: 114.36 | D10: 193.68 | E10: 101 | F10: 19561.68 | G10: 11550.36 | H10: =F10-G10 -> 8011.32 | I10: =IFERROR(H10/F10,0) -> 0.40954151 | J10: 150 | K10: 70 | L10: =J10*K10 -> 10500 | M10: =J10-C10 -> 35.64 | N10: =M10*K10 -> 2494.8 | O10: =IFERROR(N10/L10,0) -> 0.2376 | P10: =L10-F10 -> -9061.68 | Q10: =N10-H10 -> -5516.52 | R10: =IF(Q10>=0,"▲ BETTER","▼ WORSE") -> ▼ WORSE | S10: =IFERROR(IF(J10-C10<=0,"BELOW COST",CEILING(H10/(J10-C10),1)),"N/A") -> 225 | T10: =IFERROR(H10/K10+C10,"N/A") -> 228.80743 | U10: =IFERROR(MAX(0,S10-K10),0) -> 155 | V10: =Assumptions!$C$4 -> 0.07 | W10: =IFERROR(C10*(1-Assumptions!$C$4),C10) -> 106.3548 | X10: =IFERROR((J10-C10*(1-Assumptions!$C$4))*K10,N10) -> 3055.164 | Y10: =IFERROR(X10-H10,N10-H10) -> -4956.156 | Z10: =IFERROR(C10*Assumptions!$C$4*K10,0) -> 560.364 | AA10: =IFERROR(MAX(0,1-(J10-H10/K10)/C10),"N/A") -> 0.68911707 | AB10: =IFERROR(IF(Y10>=0,"▲ BETTER","▼ WORSE"),"N/A") -> ▼ WORSE
A11: 1876101141 | B11: FILTER; ACL,INNER | C11: 9.46 | D11: 14.8 | E11: 890 | F11: 13172 | G11: 8419.4 | H11: =F11-G11 -> 4752.6 | I11: =IFERROR(H11/F11,0) -> 0.36081081 | J11: 12 | K11: 1200 | L11: =J11*K11 -> 14400 | M11: =J11-C11 -> 2.54 | N11: =M11*K11 -> 3048 | O11: =IFERROR(N11/L11,0) -> 0.21166667 | P11: =L11-F11 -> 1228 | Q11: =N11-H11 -> -1704.6 | R11: =IF(Q11>=0,"▲ BETTER","▼ WORSE") -> ▼ WORSE | S11: =IFERROR(IF(J11-C11<=0,"BELOW COST",CEILING(H11/(J11-C11),1)),"N/A") -> 1872 | T11: =IFERROR(H11/K11+C11,"N/A") -> 13.4205 | U11: =IFERROR(MAX(0,S11-K11),0) -> 672 | V11: =Assumptions!$C$4 -> 0.07 | W11: =IFERROR(C11*(1-Assumptions!$C$4),C11) -> 8.7978 | X11: =IFERROR((J11-C11*(1-Assumptions!$C$4))*K11,N11) -> 3842.64 | Y11: =IFERROR(X11-H11,N11-H11) -> -909.96 | Z11: =IFERROR(C11*Assumptions!$C$4*K11,0) -> 794.64 | AA11: =IFERROR(MAX(0,1-(J11-H11/K11)/C11),"N/A") -> 0.15015856 | AB11: =IFERROR(IF(Y11>=0,"▲ BETTER","▼ WORSE"),"N/A") -> ▼ WORSE
A12: 5876100891 | B12: PUMP ASM; WATER | C12: 24.6 | D12: 41.66 | E12: 43 | F12: 1791.38 | G12: 1057.8 | H12: =F12-G12 -> 733.58 | I12: =IFERROR(H12/F12,0) -> 0.40950552 | J12: 50 | K12: 35 | L12: =J12*K12 -> 1750 | M12: =J12-C12 -> 25.4 | N12: =M12*K12 -> 889 | O12: =IFERROR(N12/L12,0) -> 0.508 | P12: =L12-F12 -> -41.38 | Q12: =N12-H12 -> 155.42 | R12: =IF(Q12>=0,"▲ BETTER","▼ WORSE") -> ▲ BETTER | S12: =IFERROR(IF(J12-C12<=0,"BELOW COST",CEILING(H12/(J12-C12),1)),"N/A") -> 29 | T12: =IFERROR(H12/K12+C12,"N/A") -> 45.559429 | U12: =IFERROR(MAX(0,S12-K12),0) -> 0 | V12: =Assumptions!$C$4 -> 0.07 | W12: =IFERROR(C12*(1-Assumptions!$C$4),C12) -> 22.878 | X12: =IFERROR((J12-C12*(1-Assumptions!$C$4))*K12,N12) -> 949.27 | Y12: =IFERROR(X12-H12,N12-H12) -> 215.69 | Z12: =IFERROR(C12*Assumptions!$C$4*K12,0) -> 60.27 | AA12: =IFERROR(MAX(0,1-(J12-H12/K12)/C12),"N/A") -> 0 | AB12: =IFERROR(IF(Y12>=0,"▲ BETTER","▼ WORSE"),"N/A") -> ▲ BETTER
A13: 5876102200 | B13: ELEMENT KIT;FUEL FILTER | C13: 11.16 | D13: 17.46 | E13: 2039 | F13: 35600.94 | G13: 22755.24 | H13: =F13-G13 -> 12845.7 | I13: =IFERROR(H13/F13,0) -> 0.36082474 | J13: 14 | K13: 2300 | L13: =J13*K13 -> 32200 | M13: =J13-C13 -> 2.84 | N13: =M13*K13 -> 6532 | O13: =IFERROR(N13/L13,0) -> 0.20285714 | P13: =L13-F13 -> -3400.94 | Q13: =N13-H13 -> -6313.7 | R13: =IF(Q13>=0,"▲ BETTER","▼ WORSE") -> ▼ WORSE | S13: =IFERROR(IF(J13-C13<=0,"BELOW COST",CEILING(H13/(J13-C13),1)),"N/A") -> 4524 | T13: =IFERROR(H13/K13+C13,"N/A") -> 16.745087 | U13: =IFERROR(MAX(0,S13-K13),0) -> 2224 | V13: =Assumptions!$C$4 -> 0.07 | W13: =IFERROR(C13*(1-Assumptions!$C$4),C13) -> 10.3788 | X13: =IFERROR((J13-C13*(1-Assumptions!$C$4))*K13,N13) -> 8328.76 | Y13: =IFERROR(X13-H13,N13-H13) -> -4516.94 | Z13: =IFERROR(C13*Assumptions!$C$4*K13,0) -> 1796.76 | AA13: =IFERROR(MAX(0,1-(J13-H13/K13)/C13),"N/A") -> 0.24597553 | AB13: =IFERROR(IF(Y13>=0,"▲ BETTER","▼ WORSE"),"N/A") -> ▼ WORSE
A14: 5876102320 | B14: CLUTCH KIT | C14: 107.08 | D14: 167.52 | E14: 325 | F14: 54444 | G14: 34801 | H14: =F14-G14 -> 19643 | I14: =IFERROR(H14/F14,0) -> 0.36079274 | J14: 120 | K14: 400 | L14: =J14*K14 -> 48000 | M14: =J14-C14 -> 12.92 | N14: =M14*K14 -> 5168 | O14: =IFERROR(N14/L14,0) -> 0.10766667 | P14: =L14-F14 -> -6444 | Q14: =N14-H14 -> -14475 | R14: =IF(Q14>=0,"▲ BETTER","▼ WORSE") -> ▼ WORSE | S14: =IFERROR(IF(J14-C14<=0,"BELOW COST",CEILING(H14/(J14-C14),1)),"N/A") -> 1521 | T14: =IFERROR(H14/K14+C14,"N/A") -> 156.1875 | U14: =IFERROR(MAX(0,S14-K14),0) -> 1121 | V14: =Assumptions!$C$4 -> 0.07 | W14: =IFERROR(C14*(1-Assumptions!$C$4),C14) -> 99.5844 | X14: =IFERROR((J14-C14*(1-Assumptions!$C$4))*K14,N14) -> 8166.24 | Y14: =IFERROR(X14-H14,N14-H14) -> -11476.76 | Z14: =IFERROR(C14*Assumptions!$C$4*K14,0) -> 2998.24 | AA14: =IFERROR(MAX(0,1-(J14-H14/K14)/C14),"N/A") -> 0.33794826 | AB14: =IFERROR(IF(Y14>=0,"▲ BETTER","▼ WORSE"),"N/A") -> ▼ WORSE
A15: 5876102820 | B15: STARTER ASM | C15: 87.4 | D15: 148.01 | E15: 10 | F15: 1480.1 | G15: 874 | H15: =F15-G15 -> 606.1 | I15: =IFERROR(H15/F15,0) -> 0.40949936 | J15: 135 | K15: 45 | L15: =J15*K15 -> 6075 | M15: =J15-C15 -> 47.6 | N15: =M15*K15 -> 2142 | O15: =IFERROR(N15/L15,0) -> 0.35259259 | P15: =L15-F15 -> 4594.9 | Q15: =N15-H15 -> 1535.9 | R15: =IF(Q15>=0,"▲ BETTER","▼ WORSE") -> ▲ BETTER | S15: =IFERROR(IF(J15-C15<=0,"BELOW COST",CEILING(H15/(J15-C15),1)),"N/A") -> 13 | T15: =IFERROR(H15/K15+C15,"N/A") -> 100.86889 | U15: =IFERROR(MAX(0,S15-K15),0) -> 0 | V15: =Assumptions!$C$4 -> 0.07 | W15: =IFERROR(C15*(1-Assumptions!$C$4),C15) -> 81.282 | X15: =IFERROR((J15-C15*(1-Assumptions!$C$4))*K15,N15) -> 2417.31 | Y15: =IFERROR(X15-H15,N15-H15) -> 1811.21 | Z15: =IFERROR(C15*Assumptions!$C$4*K15,0) -> 275.31 | AA15: =IFERROR(MAX(0,1-(J15-H15/K15)/C15),"N/A") -> 0 | AB15: =IFERROR(IF(Y15>=0,"▲ BETTER","▼ WORSE"),"N/A") -> ▲ BETTER
A16: 5876102850 | B16: ABSORBER ASM; SHOCK,FRT | C16: 10.56 | D16: 17.88 | E16: 260 | F16: 4648.8 | G16: 2745.6 | H16: =F16-G16 -> 1903.2 | I16: =IFERROR(H16/F16,0) -> 0.40939597 | J16: 12 | K16: 300 | L16: =J16*K16 -> 3600 | M16: =J16-C16 -> 1.44 | N16: =M16*K16 -> 432 | O16: =IFERROR(N16/L16,0) -> 0.12 | P16: =L16-F16 -> -1048.8 | Q16: =N16-H16 -> -1471.2 | R16: =IF(Q16>=0,"▲ BETTER","▼ WORSE") -> ▼ WORSE | S16: =IFERROR(IF(J16-C16<=0,"BELOW COST",CEILING(H16/(J16-C16),1)),"N/A") -> 1322 | T16: =IFERROR(H16/K16+C16,"N/A") -> 16.904 | U16: =IFERROR(MAX(0,S16-K16),0) -> 1022 | V16: =Assumptions!$C$4 -> 0.07 | W16: =IFERROR(C16*(1-Assumptions!$C$4),C16) -> 9.8208 | X16: =IFERROR((J16-C16*(1-Assumptions!$C$4))*K16,N16) -> 653.76 | Y16: =IFERROR(X16-H16,N16-H16) -> -1249.44 | Z16: =IFERROR(C16*Assumptions!$C$4*K16,0) -> 221.76 | AA16: =IFERROR(MAX(0,1-(J16-H16/K16)/C16),"N/A") -> 0.46439394 | AB16: =IFERROR(IF(Y16>=0,"▲ BETTER","▼ WORSE"),"N/A") -> ▼ WORSE
A17: 5878323991 | B17: KING PIN KIT | C17: 39.98 | D17: 62.55 | E17: 70 | F17: 4378.5 | G17: 2798.6 | H17: =F17-G17 -> 1579.9 | I17: =IFERROR(H17/F17,0) -> 0.36083133 | J17: 50 | K17: 270 | L17: =J17*K17 -> 13500 | M17: =J17-C17 -> 10.02 | N17: =M17*K17 -> 2705.4 | O17: =IFERROR(N17/L17,0) -> 0.2004 | P17: =L17-F17 -> 9121.5 | Q17: =N17-H17 -> 1125.5 | R17: =IF(Q17>=0,"▲ BETTER","▼ WORSE") -> ▲ BETTER | S17: =IFERROR(IF(J17-C17<=0,"BELOW COST",CEILING(H17/(J17-C17),1)),"N/A") -> 158 | T17: =IFERROR(H17/K17+C17,"N/A") -> 45.831481 | U17: =IFERROR(MAX(0,S17-K17),0) -> 0 | V17: =Assumptions!$C$4 -> 0.07 | W17: =IFERROR(C17*(1-Assumptions!$C$4),C17) -> 37.1814 | X17: =IFERROR((J17-C17*(1-Assumptions!$C$4))*K17,N17) -> 3461.022 | Y17: =IFERROR(X17-H17,N17-H17) -> 1881.122 | Z17: =IFERROR(C17*Assumptions!$C$4*K17,0) -> 755.622 | AA17: =IFERROR(MAX(0,1-(J17-H17/K17)/C17),"N/A") -> 0 | AB17: =IFERROR(IF(Y17>=0,"▲ BETTER","▼ WORSE"),"N/A") -> ▲ BETTER
... A58: 8983528481 | B58: SENSOR; NOX | C58: 121.42 | D58: 222.27 | E58: 630 | F58: 140030.1 | G58: 76494.6 | H58: =F58-G58 -> 63535.5 | I58: =IFERROR(H58/F58,0) -> 0.45372745 | J58: 205 | K58: 450 | L58: =J58*K58 -> 92250 | M58: =J58-C58 -> 83.58 | N58: =M58*K58 -> 37611 | O58: =IFERROR(N58/L58,0) -> 0.40770732 | P58: =L58-F58 -> -47780.1 | Q58: =N58-H58 -> -25924.5 | R58: =IF(Q58>=0,"▲ BETTER","▼ WORSE") -> ▼ WORSE | S58: =IFERROR(IF(J58-C58<=0,"BELOW COST",CEILING(H58/(J58-C58),1)),"N/A") -> 761 | T58: =IFERROR(H58/K58+C58,"N/A") -> 262.61 | U58: =IFERROR(MAX(0,S58-K58),0) -> 311 | V58: =Assumptions!$C$4 -> 0.07 | W58: =IFERROR(C58*(1-Assumptions!$C$4),C58) -> 112.9206 | X58: =IFERROR((J58-C58*(1-Assumptions!$C$4))*K58,N58) -> 41435.73 | Y58: =IFERROR(X58-H58,N58-H58) -> -22099.77 | Z58: =IFERROR(C58*Assumptions!$C$4*K58,0) -> 3824.73 | AA58: =IFERROR(MAX(0,1-(J58-H58/K58)/C58),"N/A") -> 0.47446879 | AB58: =IFERROR(IF(Y58>=0,"▲ BETTER","▼ WORSE"),"N/A") -> ▼ WORSE
A60: TOTAL | B60: 53 part numbers | E60: =SUM(E6:E58) -> 17395 | F60: =SUM(F6:F58) -> 768615.47 | G60: =SUM(G6:G58) -> 447499.93 | H60: =SUM(H6:H58) -> 321115.54 | I60: =IFERROR(H60/F60,0) -> 0.41778438 | K60: =SUM(K6:K58) -> 18110 | L60: =SUM(L6:L58) -> 728880 | N60: =SUM(N6:N58) -> 198386.75 | O60: =IFERROR(N60/L60,0) -> 0.27218026 | P60: =SUM(P6:P58) -> -39735.47 | Q60: =SUM(Q6:Q58) -> -122728.79 | R60: =IF(Q60>=0,"▲ BETTER","▼ WORSE") -> ▼ WORSE | X60: =SUM(X6:X58) -> 235521.28 | Y60: =SUM(Y6:Y58) -> -85594.262 | Z60: =SUM(Z6:Z58) -> 37134.528 | AB60: =IF(Y60>=0,"▲ BETTER","▼ WORSE") -> ▼ WORSE
A62: FORMULA NOTES
A63: Min Qty @ SPA Price | B63: Minimum units Distributor must commit at the SPA price for ISZE to match L12 profit (assuming no IML/IMIT price support). Formula: L12 Profit ÷ (SPA Price − Purchase Price).
A64: Min Price @ SPA Qty | B64: Lowest acceptable SPA price at the committed SPA qty, for ISZE to match L12 profit (no IML cut). Formula: L12 Profit ÷ SPA Qty + Purchase Price.
A65: Required IML Cut % | B65: % by which IML/IMIT must reduce their sell price to ISZE so that ISZE matches L12 profit at the agreed SPA price & qty. 0% = SPA already better than L12, no IML help needed. >100% = not feasible. Formula: MAX(0, 1 − (SPA Price − L12 Profit/SPA Qty) ÷ Purchase Price).
A66: Entity Sharing logic | B66: When IML gives a cut (Assumptions!B3), ISZE's effective cost drops. IML Sacrifice = (Purchase Price − ISZE Cost w/ cut) × SPA Qty. Split the required cut between ISZE margin compression and IML price support to reach profit neutrality.

Sheet Customer View
A1: SPECIAL PRICING AGREEMENT — CUSTOMER SUMMARY
A2: =Assumptions!B9 & " | Market: " & Assumptions!B10 & " | Ref: " & Assumptions!B11 -> Distributor | Market: [Market] | Ref: SPA Distributor
A4: P/N | B4: Description | C4: Current List Price (€) | D4: Proposed SPA Price (€) | E4: Saving per Unit (€) | F4: Saving % | G4: Volume Commitment | H4: Projected Annual Spend (€) | I4: Savings vs List Spend (€) | J4: Vol. Uplift vs L12 | K4: Annual Saving (€) | L4: SPA Status
A5: ='SPA Optimizer'!A6 -> 1443803030 | B5: ='SPA Optimizer'!B6 -> LINK; DRAG | C5: ='SPA Optimizer'!D6 -> 131.66 | D5: ='SPA Optimizer'!J6 -> 110 | E5: ='SPA Optimizer'!D6-'SPA Optimizer'!J6 -> 21.66 | F5: =IFERROR(IF('SPA Optimizer'!D6>0,('SPA Optimizer'!D6-'SPA Optimizer'!J6)/'SPA Optimizer'!D6,0),0) -> 0.16451466 | G5: ='SPA Optimizer'!K6 -> 60 | H5: ='SPA Optimizer'!L6 -> 6600 | I5: =IFERROR('SPA Optimizer'!D6*'SPA Optimizer'!K6-'SPA Optimizer'!L6,0) -> 1299.6 | J5: =IFERROR(IF('SPA Optimizer'!E6>0,('SPA Optimizer'!K6-'SPA Optimizer'!E6)/'SPA Optimizer'!E6,0),0) -> -0.11764706 | K5: =IFERROR(('SPA Optimizer'!D6-'SPA Optimizer'!J6)*'SPA Optimizer'!K6,0) -> 1299.6 | L5: =IF('SPA Optimizer'!R6="▲ BETTER","✔ Viable",IF(AND('SPA Optimizer'!AB6="▲ BETTER",'SPA Optimizer'!AA6<=1),"✔ w/ IML support",IF(OR('SPA Optimizer'!AA6>1,'SPA Optimizer'!O6<0),"✖ Not feasible","⚠ Review"))) -> ⚠ Review
A6: ='SPA Optimizer'!A7 -> 1443803050 | B6: ='SPA Optimizer'!B7 -> LINK; DRAG | C6: ='SPA Optimizer'!D7 -> 137.41 | D6: ='SPA Optimizer'!J7 -> 110 | E6: ='SPA Optimizer'!D7-'SPA Optimizer'!J7 -> 27.41 | F6: =IFERROR(IF('SPA Optimizer'!D7>0,('SPA Optimizer'!D7-'SPA Optimizer'!J7)/'SPA Optimizer'!D7,0),0) -> 0.19947602 | G6: ='SPA Optimizer'!K7 -> 55 | H6: ='SPA Optimizer'!L7 -> 6050 | I6: =IFERROR('SPA Optimizer'!D7*'SPA Optimizer'!K7-'SPA Optimizer'!L7,0) -> 1507.55 | J6: =IFERROR(IF('SPA Optimizer'!E7>0,('SPA Optimizer'!K7-'SPA Optimizer'!E7)/'SPA Optimizer'!E7,0),0) -> 0.25 | K6: =IFERROR(('SPA Optimizer'!D7-'SPA Optimizer'!J7)*'SPA Optimizer'!K7,0) -> 1507.55 | L6: =IF('SPA Optimizer'!R7="▲ BETTER","✔ Viable",IF(AND('SPA Optimizer'!AB7="▲ BETTER",'SPA Optimizer'!AA7<=1),"✔ w/ IML support",IF(OR('SPA Optimizer'!AA7>1,'SPA Optimizer'!O7<0),"✖ Not feasible","⚠ Review"))) -> ⚠ Review
A7: ='SPA Optimizer'!A8 -> 1476010870 | B7: ='SPA Optimizer'!B8 -> EXPANDER | C7: ='SPA Optimizer'!D8 -> 252.56 | D7: ='SPA Optimizer'!J8 -> 200 | E7: ='SPA Optimizer'!D8-'SPA Optimizer'!J8 -> 52.56 | F7: =IFERROR(IF('SPA Optimizer'!D8>0,('SPA Optimizer'!D8-'SPA Optimizer'!J8)/'SPA Optimizer'!D8,0),0) -> 0.20810896 | G7: ='SPA Optimizer'!K8 -> 90 | H7: ='SPA Optimizer'!L8 -> 18000 | I7: =IFERROR('SPA Optimizer'!D8*'SPA Optimizer'!K8-'SPA Optimizer'!L8,0) -> 4730.4 | J7: =IFERROR(IF('SPA Optimizer'!E8>0,('SPA Optimizer'!K8-'SPA Optimizer'!E8)/'SPA Optimizer'!E8,0),0) -> 0.83673469 | K7: =IFERROR(('SPA Optimizer'!D8-'SPA Optimizer'!J8)*'SPA Optimizer'!K8,0) -> 4730.4 | L7: =IF('SPA Optimizer'!R8="▲ BETTER","✔ Viable",IF(AND('SPA Optimizer'!AB8="▲ BETTER",'SPA Optimizer'!AA8<=1),"✔ w/ IML support",IF(OR('SPA Optimizer'!AA8>1,'SPA Optimizer'!O8<0),"✖ Not feasible","⚠ Review"))) -> ✔ w/ IML support
A8: ='SPA Optimizer'!A9 -> 1476012180 | B8: ='SPA Optimizer'!B9 -> CYLINDER; WHEEL,RR BRK | C8: ='SPA Optimizer'!D9 -> 193.68 | D8: ='SPA Optimizer'!J9 -> 150 | E8: ='SPA Optimizer'!D9-'SPA Optimizer'!J9 -> 43.68 | F8: =IFERROR(IF('SPA Optimizer'!D9>0,('SPA Optimizer'!D9-'SPA Optimizer'!J9)/'SPA Optimizer'!D9,0),0) -> 0.22552664 | G8: ='SPA Optimizer'!K9 -> 80 | H8: ='SPA Optimizer'!L9 -> 12000 | I8: =IFERROR('SPA Optimizer'!D9*'SPA Optimizer'!K9-'SPA Optimizer'!L9,0) -> 3494.4 | J8: =IFERROR(IF('SPA Optimizer'!E9>0,('SPA Optimizer'!K9-'SPA Optimizer'!E9)/'SPA Optimizer'!E9,0),0) -> 0.038961039 | K8: =IFERROR(('SPA Optimizer'!D9-'SPA Optimizer'!J9)*'SPA Optimizer'!K9,0) -> 3494.4 | L8: =IF('SPA Optimizer'!R9="▲ BETTER","✔ Viable",IF(AND('SPA Optimizer'!AB9="▲ BETTER",'SPA Optimizer'!AA9<=1),"✔ w/ IML support",IF(OR('SPA Optimizer'!AA9>1,'SPA Optimizer'!O9<0),"✖ Not feasible","⚠ Review"))) -> ⚠ Review
A9: ='SPA Optimizer'!A10 -> 1476012190 | B9: ='SPA Optimizer'!B10 -> CYLINDER; WHEEL,RR BRK | C9: ='SPA Optimizer'!D10 -> 193.68 | D9: ='SPA Optimizer'!J10 -> 150 | E9: ='SPA Optimizer'!D10-'SPA Optimizer'!J10 -> 43.68 | F9: =IFERROR(IF('SPA Optimizer'!D10>0,('SPA Optimizer'!D10-'SPA Optimizer'!J10)/'SPA Optimizer'!D10,0),0) -> 0.22552664 | G9: ='SPA Optimizer'!K10 -> 70 | H9: ='SPA Optimizer'!L10 -> 10500 | I9: =IFERROR('SPA Optimizer'!D10*'SPA Optimizer'!K10-'SPA Optimizer'!L10,0) -> 3057.6 | J9: =IFERROR(IF('SPA Optimizer'!E10>0,('SPA Optimizer'!K10-'SPA Optimizer'!E10)/'SPA Optimizer'!E10,0),0) -> -0.30693069 | K9: =IFERROR(('SPA Optimizer'!D10-'SPA Optimizer'!J10)*'SPA Optimizer'!K10,0) -> 3057.6 | L9: =IF('SPA Optimizer'!R10="▲ BETTER","✔ Viable",IF(AND('SPA Optimizer'!AB10="▲ BETTER",'SPA Optimizer'!AA10<=1),"✔ w/ IML support",IF(OR('SPA Optimizer'!AA10>1,'SPA Optimizer'!O10<0),"✖ Not feasible","⚠ Review"))) -> ⚠ Review
A10: ='SPA Optimizer'!A11 -> 1876101141 | B10: ='SPA Optimizer'!B11 -> FILTER; ACL,INNER | C10: ='SPA Optimizer'!D11 -> 14.8 | D10: ='SPA Optimizer'!J11 -> 12 | E10: ='SPA Optimizer'!D11-'SPA Optimizer'!J11 -> 2.8 | F10: =IFERROR(IF('SPA Optimizer'!D11>0,('SPA Optimizer'!D11-'SPA Optimizer'!J11)/'SPA Optimizer'!D11,0),0) -> 0.18918919 | G10: ='SPA Optimizer'!K11 -> 1200 | H10: ='SPA Optimizer'!L11 -> 14400 | I10: =IFERROR('SPA Optimizer'!D11*'SPA Optimizer'!K11-'SPA Optimizer'!L11,0) -> 3360 | J10: =IFERROR(IF('SPA Optimizer'!E11>0,('SPA Optimizer'!K11-'SPA Optimizer'!E11)/'SPA Optimizer'!E11,0),0) -> 0.34831461 | K10: =IFERROR(('SPA Optimizer'!D11-'SPA Optimizer'!J11)*'SPA Optimizer'!K11,0) -> 3360 | L10: =IF('SPA Optimizer'!R11="▲ BETTER","✔ Viable",IF(AND('SPA Optimizer'!AB11="▲ BETTER",'SPA Optimizer'!AA11<=1),"✔ w/ IML support",IF(OR('SPA Optimizer'!AA11>1,'SPA Optimizer'!O11<0),"✖ Not feasible","⚠ Review"))) -> ⚠ Review
A11: ='SPA Optimizer'!A12 -> 5876100891 | B11: ='SPA Optimizer'!B12 -> PUMP ASM; WATER | C11: ='SPA Optimizer'!D12 -> 41.66 | D11: ='SPA Optimizer'!J12 -> 50 | E11: ='SPA Optimizer'!D12-'SPA Optimizer'!J12 -> -8.34 | F11: =IFERROR(IF('SPA Optimizer'!D12>0,('SPA Optimizer'!D12-'SPA Optimizer'!J12)/'SPA Optimizer'!D12,0),0) -> -0.20019203 | G11: ='SPA Optimizer'!K12 -> 35 | H11: ='SPA Optimizer'!L12 -> 1750 | I11: =IFERROR('SPA Optimizer'!D12*'SPA Optimizer'!K12-'SPA Optimizer'!L12,0) -> -291.9 | J11: =IFERROR(IF('SPA Optimizer'!E12>0,('SPA Optimizer'!K12-'SPA Optimizer'!E12)/'SPA Optimizer'!E12,0),0) -> -0.18604651 | K11: =IFERROR(('SPA Optimizer'!D12-'SPA Optimizer'!J12)*'SPA Optimizer'!K12,0) -> -291.9 | L11: =IF('SPA Optimizer'!R12="▲ BETTER","✔ Viable",IF(AND('SPA Optimizer'!AB12="▲ BETTER",'SPA Optimizer'!AA12<=1),"✔ w/ IML support",IF(OR('SPA Optimizer'!AA12>1,'SPA Optimizer'!O12<0),"✖ Not feasible","⚠ Review"))) -> ✔ Viable
A12: ='SPA Optimizer'!A13 -> 5876102200 | B12: ='SPA Optimizer'!B13 -> ELEMENT KIT;FUEL FILTER | C12: ='SPA Optimizer'!D13 -> 17.46 | D12: ='SPA Optimizer'!J13 -> 14 | E12: ='SPA Optimizer'!D13-'SPA Optimizer'!J13 -> 3.46 | F12: =IFERROR(IF('SPA Optimizer'!D13>0,('SPA Optimizer'!D13-'SPA Optimizer'!J13)/'SPA Optimizer'!D13,0),0) -> 0.19816724 | G12: ='SPA Optimizer'!K13 -> 2300 | H12: ='SPA Optimizer'!L13 -> 32200 | I12: =IFERROR('SPA Optimizer'!D13*'SPA Optimizer'!K13-'SPA Optimizer'!L13,0) -> 7958 | J12: =IFERROR(IF('SPA Optimizer'!E13>0,('SPA Optimizer'!K13-'SPA Optimizer'!E13)/'SPA Optimizer'!E13,0),0) -> 0.12800392 | K12: =IFERROR(('SPA Optimizer'!D13-'SPA Optimizer'!J13)*'SPA Optimizer'!K13,0) -> 7958 | L12: =IF('SPA Optimizer'!R13="▲ BETTER","✔ Viable",IF(AND('SPA Optimizer'!AB13="▲ BETTER",'SPA Optimizer'!AA13<=1),"✔ w/ IML support",IF(OR('SPA Optimizer'!AA13>1,'SPA Optimizer'!O13<0),"✖ Not feasible","⚠ Review"))) -> ⚠ Review
A13: ='SPA Optimizer'!A14 -> 5876102320 | B13: ='SPA Optimizer'!B14 -> CLUTCH KIT | C13: ='SPA Optimizer'!D14 -> 167.52 | D13: ='SPA Optimizer'!J14 -> 120 | E13: ='SPA Optimizer'!D14-'SPA Optimizer'!J14 -> 47.52 | F13: =IFERROR(IF('SPA Optimizer'!D14>0,('SPA Optimizer'!D14-'SPA Optimizer'!J14)/'SPA Optimizer'!D14,0),0) -> 0.28366762 | G13: ='SPA Optimizer'!K14 -> 400 | H13: ='SPA Optimizer'!L14 -> 48000 | I13: =IFERROR('SPA Optimizer'!D14*'SPA Optimizer'!K14-'SPA Optimizer'!L14,0) -> 19008 | J13: =IFERROR(IF('SPA Optimizer'!E14>0,('SPA Optimizer'!K14-'SPA Optimizer'!E14)/'SPA Optimizer'!E14,0),0) -> 0.23076923 | K13: =IFERROR(('SPA Optimizer'!D14-'SPA Optimizer'!J14)*'SPA Optimizer'!K14,0) -> 19008 | L13: =IF('SPA Optimizer'!R14="▲ BETTER","✔ Viable",IF(AND('SPA Optimizer'!AB14="▲ BETTER",'SPA Optimizer'!AA14<=1),"✔ w/ IML support",IF(OR('SPA Optimizer'!AA14>1,'SPA Optimizer'!O14<0),"✖ Not feasible","⚠ Review"))) -> ⚠ Review
A14: ='SPA Optimizer'!A15 -> 5876102820 | B14: ='SPA Optimizer'!B15 -> STARTER ASM | C14: ='SPA Optimizer'!D15 -> 148.01 | D14: ='SPA Optimizer'!J15 -> 135 | E14: ='SPA Optimizer'!D15-'SPA Optimizer'!J15 -> 13.01 | F14: =IFERROR(IF('SPA Optimizer'!D15>0,('SPA Optimizer'!D15-'SPA Optimizer'!J15)/'SPA Optimizer'!D15,0),0) -> 0.087899466 | G14: ='SPA Optimizer'!K15 -> 45 | H14: ='SPA Optimizer'!L15 -> 6075 | I14: =IFERROR('SPA Optimizer'!D15*'SPA Optimizer'!K15-'SPA Optimizer'!L15,0) -> 585.45 | J14: =IFERROR(IF('SPA Optimizer'!E15>0,('SPA Optimizer'!K15-'SPA Optimizer'!E15)/'SPA Optimizer'!E15,0),0) -> 3.5 | K14: =IFERROR(('SPA Optimizer'!D15-'SPA Optimizer'!J15)*'SPA Optimizer'!K15,0) -> 585.45 | L14: =IF('SPA Optimizer'!R15="▲ BETTER","✔ Viable",IF(AND('SPA Optimizer'!AB15="▲ BETTER",'SPA Optimizer'!AA15<=1),"✔ w/ IML support",IF(OR('SPA Optimizer'!AA15>1,'SPA Optimizer'!O15<0),"✖ Not feasible","⚠ Review"))) -> ✔ Viable
A15: ='SPA Optimizer'!A16 -> 5876102850 | B15: ='SPA Optimizer'!B16 -> ABSORBER ASM; SHOCK,FRT | C15: ='SPA Optimizer'!D16 -> 17.88 | D15: ='SPA Optimizer'!J16 -> 12 | E15: ='SPA Optimizer'!D16-'SPA Optimizer'!J16 -> 5.88 | F15: =IFERROR(IF('SPA Optimizer'!D16>0,('SPA Optimizer'!D16-'SPA Optimizer'!J16)/'SPA Optimizer'!D16,0),0) -> 0.32885906 | G15: ='SPA Optimizer'!K16 -> 300 | H15: ='SPA Optimizer'!L16 -> 3600 | I15: =IFERROR('SPA Optimizer'!D16*'SPA Optimizer'!K16-'SPA Optimizer'!L16,0) -> 1764 | J15: =IFERROR(IF('SPA Optimizer'!E16>0,('SPA Optimizer'!K16-'SPA Optimizer'!E16)/'SPA Optimizer'!E16,0),0) -> 0.15384615 | K15: =IFERROR(('SPA Optimizer'!D16-'SPA Optimizer'!J16)*'SPA Optimizer'!K16,0) -> 1764 | L15: =IF('SPA Optimizer'!R16="▲ BETTER","✔ Viable",IF(AND('SPA Optimizer'!AB16="▲ BETTER",'SPA Optimizer'!AA16<=1),"✔ w/ IML support",IF(OR('SPA Optimizer'!AA16>1,'SPA Optimizer'!O16<0),"✖ Not feasible","⚠ Review"))) -> ⚠ Review
A16: ='SPA Optimizer'!A17 -> 5878323991 | B16: ='SPA Optimizer'!B17 -> KING PIN KIT | C16: ='SPA Optimizer'!D17 -> 62.55 | D16: ='SPA Optimizer'!J17 -> 50 | E16: ='SPA Optimizer'!D17-'SPA Optimizer'!J17 -> 12.55 | F16: =IFERROR(IF('SPA Optimizer'!D17>0,('SPA Optimizer'!D17-'SPA Optimizer'!J17)/'SPA Optimizer'!D17,0),0) -> 0.20063949 | G16: ='SPA Optimizer'!K17 -> 270 | H16: ='SPA Optimizer'!L17 -> 13500 | I16: =IFERROR('SPA Optimizer'!D17*'SPA Optimizer'!K17-'SPA Optimizer'!L17,0) -> 3388.5 | J16: =IFERROR(IF('SPA Optimizer'!E17>0,('SPA Optimizer'!K17-'SPA Optimizer'!E17)/'SPA Optimizer'!E17,0),0) -> 2.8571429 | K16: =IFERROR(('SPA Optimizer'!D17-'SPA Optimizer'!J17)*'SPA Optimizer'!K17,0) -> 3388.5 | L16: =IF('SPA Optimizer'!R17="▲ BETTER","✔ Viable",IF(AND('SPA Optimizer'!AB17="▲ BETTER",'SPA Optimizer'!AA17<=1),"✔ w/ IML support",IF(OR('SPA Optimizer'!AA17>1,'SPA Optimizer'!O17<0),"✖ Not feasible","⚠ Review"))) -> ✔ Viable
... A57: ='SPA Optimizer'!A58 -> 8983528481 | B57: ='SPA Optimizer'!B58 -> SENSOR; NOX | C57: ='SPA Optimizer'!D58 -> 222.27 | D57: ='SPA Optimizer'!J58 -> 205 | E57: ='SPA Optimizer'!D58-'SPA Optimizer'!J58 -> 17.27 | F57: =IFERROR(IF('SPA Optimizer'!D58>0,('SPA Optimizer'!D58-'SPA Optimizer'!J58)/'SPA Optimizer'!D58,0),0) -> 0.077698295 | G57: ='SPA Optimizer'!K58 -> 450 | H57: ='SPA Optimizer'!L58 -> 92250 | I57: =IFERROR('SPA Optimizer'!D58*'SPA Optimizer'!K58-'SPA Optimizer'!L58,0) -> 7771.5 | J57: =IFERROR(IF('SPA Optimizer'!E58>0,('SPA Optimizer'!K58-'SPA Optimizer'!E58)/'SPA Optimizer'!E58,0),0) -> -0.28571429 | K57: =IFERROR(('SPA Optimizer'!D58-'SPA Optimizer'!J58)*'SPA Optimizer'!K58,0) -> 7771.5 | L57: =IF('SPA Optimizer'!R58="▲ BETTER","✔ Viable",IF(AND('SPA Optimizer'!AB58="▲ BETTER",'SPA Optimizer'!AA58<=1),"✔ w/ IML support",IF(OR('SPA Optimizer'!AA58>1,'SPA Optimizer'!O58<0),"✖ Not feasible","⚠ Review"))) -> ⚠ Review
A58: TOTAL | B58: 53 part numbers | H58: =SUM(H5:H57) -> 728880 | I58: =SUM(I5:I57) -> 179979.5 | K58: =SUM(K5:K57) -> 179979.5
A60: SUMMARY FOR CUSTOMER
A61: What this SPA does: | B61: This agreement offers volume-linked pricing on selected Genuine Isuzu parts lines. By committing to the agreed purchase volumes, your business benefits from reduced unit costs while securing priority supply continuity — all parts fully covered by OEM warranty.
A62: Why Genuine parts? | B62: Genuine Isuzu parts are engineered to OEM specification, carry full warranty coverage, and reduce total R&M lifecycle cost — protecting your customers' uptime SLAs, your workshop reputation, and eligibility for extended warranty programmes.
A63: Volume commitment: | B63: The quantities shown reflect realistic demand based on your fleet profile and historical purchase data. ISZE commits to priority availability and lead-time performance on all SPA lines for the duration of the agreement.
A64: Next step: | B64: Return the signed SPA confirmation with agreed quantities. Pricing activates from the agreed start date and is reviewed at 6 and 12 months against volume performance targets.

Sheet IML_IMIT Brief
A1: IML / IMIT — PURCHASE SUPPORT BRIEF
A2: ⚠ CONFIDENTIAL — FOR INTERNAL USE ONLY | Do NOT share with distributors
A4: P/N | B4: Description | C4: ISZE Purchase Price (€) ⚠ | D4: ISZE Sales Price (€) | E4: Current ISZE GM% | F4: SPA Price (€) | G4: SPA GM% | H4: Req IML Cut % | I4: IML € Sacrifice | J4: SPA Qty Committed | K4: L12 Qty | L4: Volume Uplift (units) | M4: IML Revenue Upside (€)
A5: ='SPA Optimizer'!A6 -> 1443803030 | B5: ='SPA Optimizer'!B6 -> LINK; DRAG | C5: ='SPA Optimizer'!C6 -> 71.92 | D5: ='SPA Optimizer'!D6 -> 131.66 | E5: ='SPA Optimizer'!I6 -> 0.45374449 | F5: ='SPA Optimizer'!J6 -> 110 | G5: ='SPA Optimizer'!O6 -> 0.34618182 | H5: ='SPA Optimizer'!AA6 -> 0.41192065 | I5: ='SPA Optimizer'!Z6 -> 302.064 | J5: ='SPA Optimizer'!K6 -> 60 | K5: ='SPA Optimizer'!E6 -> 68 | L5: =IFERROR('SPA Optimizer'!K6-'SPA Optimizer'!E6,0) -> -8 | M5: =IFERROR(MAX(0,'SPA Optimizer'!K6-'SPA Optimizer'!E6)*'SPA Optimizer'!C6*(1-'SPA Optimizer'!AA6),0) -> 0
A6: ='SPA Optimizer'!A7 -> 1443803050 | B6: ='SPA Optimizer'!B7 -> LINK; DRAG | C6: ='SPA Optimizer'!C7 -> 75.06 | D6: ='SPA Optimizer'!D7 -> 137.41 | E6: ='SPA Optimizer'!I7 -> 0.45375155 | F6: ='SPA Optimizer'!J7 -> 110 | G6: ='SPA Optimizer'!O7 -> 0.31763636 | H6: ='SPA Optimizer'!AA7 -> 0.19904077 | I6: ='SPA Optimizer'!Z7 -> 288.981 | J6: ='SPA Optimizer'!K7 -> 55 | K6: ='SPA Optimizer'!E7 -> 44 | L6: =IFERROR('SPA Optimizer'!K7-'SPA Optimizer'!E7,0) -> 11 | M6: =IFERROR(MAX(0,'SPA Optimizer'!K7-'SPA Optimizer'!E7)*'SPA Optimizer'!C7*(1-'SPA Optimizer'!AA7),0) -> 661.32
A7: ='SPA Optimizer'!A8 -> 1476010870 | B7: ='SPA Optimizer'!B8 -> EXPANDER | C7: ='SPA Optimizer'!C8 -> 137.96 | D7: ='SPA Optimizer'!D8 -> 252.56 | E7: ='SPA Optimizer'!I8 -> 0.45375356 | F7: ='SPA Optimizer'!J8 -> 200 | G7: ='SPA Optimizer'!O8 -> 0.3102 | H7: ='SPA Optimizer'!AA8 -> 0.0025611288 | I7: ='SPA Optimizer'!Z8 -> 869.148 | J7: ='SPA Optimizer'!K8 -> 90 | K7: ='SPA Optimizer'!E8 -> 49 | L7: =IFERROR('SPA Optimizer'!K8-'SPA Optimizer'!E8,0) -> 41 | M7: =IFERROR(MAX(0,'SPA Optimizer'!K8-'SPA Optimizer'!E8)*'SPA Optimizer'!C8*(1-'SPA Optimizer'!AA8),0) -> 5641.8733
A8: ='SPA Optimizer'!A9 -> 1476012180 | B8: ='SPA Optimizer'!B9 -> CYLINDER; WHEEL,RR BRK | C8: ='SPA Optimizer'!C9 -> 114.36 | D8: ='SPA Optimizer'!D9 -> 193.68 | E8: ='SPA Optimizer'!I9 -> 0.40954151 | F8: ='SPA Optimizer'!J9 -> 150 | G8: ='SPA Optimizer'!O9 -> 0.2376 | H8: ='SPA Optimizer'!AA9 -> 0.35594176 | I8: ='SPA Optimizer'!Z9 -> 640.416 | J8: ='SPA Optimizer'!K9 -> 80 | K8: ='SPA Optimizer'!E9 -> 77 | L8: =IFERROR('SPA Optimizer'!K9-'SPA Optimizer'!E9,0) -> 3 | M8: =IFERROR(MAX(0,'SPA Optimizer'!K9-'SPA Optimizer'!E9)*'SPA Optimizer'!C9*(1-'SPA Optimizer'!AA9),0) -> 220.9635
A9: ='SPA Optimizer'!A10 -> 1476012190 | B9: ='SPA Optimizer'!B10 -> CYLINDER; WHEEL,RR BRK | C9: ='SPA Optimizer'!C10 -> 114.36 | D9: ='SPA Optimizer'!D10 -> 193.68 | E9: ='SPA Optimizer'!I10 -> 0.40954151 | F9: ='SPA Optimizer'!J10 -> 150 | G9: ='SPA Optimizer'!O10 -> 0.2376 | H9: ='SPA Optimizer'!AA10 -> 0.68911707 | I9: ='SPA Optimizer'!Z10 -> 560.364 | J9: ='SPA Optimizer'!K10 -> 70 | K9: ='SPA Optimizer'!E10 -> 101 | L9: =IFERROR('SPA Optimizer'!K10-'SPA Optimizer'!E10,0) -> -31 | M9: =IFERROR(MAX(0,'SPA Optimizer'!K10-'SPA Optimizer'!E10)*'SPA Optimizer'!C10*(1-'SPA Optimizer'!AA10),0) -> 0
A10: ='SPA Optimizer'!A11 -> 1876101141 | B10: ='SPA Optimizer'!B11 -> FILTER; ACL,INNER | C10: ='SPA Optimizer'!C11 -> 9.46 | D10: ='SPA Optimizer'!D11 -> 14.8 | E10: ='SPA Optimizer'!I11 -> 0.36081081 | F10: ='SPA Optimizer'!J11 -> 12 | G10: ='SPA Optimizer'!O11 -> 0.21166667 | H10: ='SPA Optimizer'!AA11 -> 0.15015856 | I10: ='SPA Optimizer'!Z11 -> 794.64 | J10: ='SPA Optimizer'!K11 -> 1200 | K10: ='SPA Optimizer'!E11 -> 890 | L10: =IFERROR('SPA Optimizer'!K11-'SPA Optimizer'!E11,0) -> 310 | M10: =IFERROR(MAX(0,'SPA Optimizer'!K11-'SPA Optimizer'!E11)*'SPA Optimizer'!C11*(1-'SPA Optimizer'!AA11),0) -> 2492.245
A11: ='SPA Optimizer'!A12 -> 5876100891 | B11: ='SPA Optimizer'!B12 -> PUMP ASM; WATER | C11: ='SPA Optimizer'!C12 -> 24.6 | D11: ='SPA Optimizer'!D12 -> 41.66 | E11: ='SPA Optimizer'!I12 -> 0.40950552 | F11: ='SPA Optimizer'!J12 -> 50 | G11: ='SPA Optimizer'!O12 -> 0.508 | H11: ='SPA Optimizer'!AA12 -> 0 | I11: ='SPA Optimizer'!Z12 -> 60.27 | J11: ='SPA Optimizer'!K12 -> 35 | K11: ='SPA Optimizer'!E12 -> 43 | L11: =IFERROR('SPA Optimizer'!K12-'SPA Optimizer'!E12,0) -> -8 | M11: =IFERROR(MAX(0,'SPA Optimizer'!K12-'SPA Optimizer'!E12)*'SPA Optimizer'!C12*(1-'SPA Optimizer'!AA12),0) -> 0
A12: ='SPA Optimizer'!A13 -> 5876102200 | B12: ='SPA Optimizer'!B13 -> ELEMENT KIT;FUEL FILTER | C12: ='SPA Optimizer'!C13 -> 11.16 | D12: ='SPA Optimizer'!D13 -> 17.46 | E12: ='SPA Optimizer'!I13 -> 0.36082474 | F12: ='SPA Optimizer'!J13 -> 14 | G12: ='SPA Optimizer'!O13 -> 0.20285714 | H12: ='SPA Optimizer'!AA13 -> 0.24597553 | I12: ='SPA Optimizer'!Z13 -> 1796.76 | J12: ='SPA Optimizer'!K13 -> 2300 | K12: ='SPA Optimizer'!E13 -> 2039 | L12: =IFERROR('SPA Optimizer'!K13-'SPA Optimizer'!E13,0) -> 261 | M12: =IFERROR(MAX(0,'SPA Optimizer'!K13-'SPA Optimizer'!E13)*'SPA Optimizer'!C13*(1-'SPA Optimizer'!AA13),0) -> 2196.2923
A13: ='SPA Optimizer'!A14 -> 5876102320 | B13: ='SPA Optimizer'!B14 -> CLUTCH KIT | C13: ='SPA Optimizer'!C14 -> 107.08 | D13: ='SPA Optimizer'!D14 -> 167.52 | E13: ='SPA Optimizer'!I14 -> 0.36079274 | F13: ='SPA Optimizer'!J14 -> 120 | G13: ='SPA Optimizer'!O14 -> 0.10766667 | H13: ='SPA Optimizer'!AA14 -> 0.33794826 | I13: ='SPA Optimizer'!Z14 -> 2998.24 | J13: ='SPA Optimizer'!K14 -> 400 | K13: ='SPA Optimizer'!E14 -> 325 | L13: =IFERROR('SPA Optimizer'!K14-'SPA Optimizer'!E14,0) -> 75 | M13: =IFERROR(MAX(0,'SPA Optimizer'!K14-'SPA Optimizer'!E14)*'SPA Optimizer'!C14*(1-'SPA Optimizer'!AA14),0) -> 5316.9375
A14: ='SPA Optimizer'!A15 -> 5876102820 | B14: ='SPA Optimizer'!B15 -> STARTER ASM | C14: ='SPA Optimizer'!C15 -> 87.4 | D14: ='SPA Optimizer'!D15 -> 148.01 | E14: ='SPA Optimizer'!I15 -> 0.40949936 | F14: ='SPA Optimizer'!J15 -> 135 | G14: ='SPA Optimizer'!O15 -> 0.35259259 | H14: ='SPA Optimizer'!AA15 -> 0 | I14: ='SPA Optimizer'!Z15 -> 275.31 | J14: ='SPA Optimizer'!K15 -> 45 | K14: ='SPA Optimizer'!E15 -> 10 | L14: =IFERROR('SPA Optimizer'!K15-'SPA Optimizer'!E15,0) -> 35 | M14: =IFERROR(MAX(0,'SPA Optimizer'!K15-'SPA Optimizer'!E15)*'SPA Optimizer'!C15*(1-'SPA Optimizer'!AA15),0) -> 3059
A15: ='SPA Optimizer'!A16 -> 5876102850 | B15: ='SPA Optimizer'!B16 -> ABSORBER ASM; SHOCK,FRT | C15: ='SPA Optimizer'!C16 -> 10.56 | D15: ='SPA Optimizer'!D16 -> 17.88 | E15: ='SPA Optimizer'!I16 -> 0.40939597 | F15: ='SPA Optimizer'!J16 -> 12 | G15: ='SPA Optimizer'!O16 -> 0.12 | H15: ='SPA Optimizer'!AA16 -> 0.46439394 | I15: ='SPA Optimizer'!Z16 -> 221.76 | J15: ='SPA Optimizer'!K16 -> 300 | K15: ='SPA Optimizer'!E16 -> 260 | L15: =IFERROR('SPA Optimizer'!K16-'SPA Optimizer'!E16,0) -> 40 | M15: =IFERROR(MAX(0,'SPA Optimizer'!K16-'SPA Optimizer'!E16)*'SPA Optimizer'!C16*(1-'SPA Optimizer'!AA16),0) -> 226.24
A16: ='SPA Optimizer'!A17 -> 5878323991 | B16: ='SPA Optimizer'!B17 -> KING PIN KIT | C16: ='SPA Optimizer'!C17 -> 39.98 | D16: ='SPA Optimizer'!D17 -> 62.55 | E16: ='SPA Optimizer'!I17 -> 0.36083133 | F16: ='SPA Optimizer'!J17 -> 50 | G16: ='SPA Optimizer'!O17 -> 0.2004 | H16: ='SPA Optimizer'!AA17 -> 0 | I16: ='SPA Optimizer'!Z17 -> 755.622 | J16: ='SPA Optimizer'!K17 -> 270 | K16: ='SPA Optimizer'!E17 -> 70 | L16: =IFERROR('SPA Optimizer'!K17-'SPA Optimizer'!E17,0) -> 200 | M16: =IFERROR(MAX(0,'SPA Optimizer'!K17-'SPA Optimizer'!E17)*'SPA Optimizer'!C17*(1-'SPA Optimizer'!AA17),0) -> 7996
... A26: ='SPA Optimizer'!A27 -> 8980023462 | B26: ='SPA Optimizer'!B27 -> ELEMENT KIT; PCV | C26: ='SPA Optimizer'!C27 -> 6.15 | D26: ='SPA Optimizer'!D27 -> 11.25 | E26: ='SPA Optimizer'!I27 -> 0.45333333 | F26: ='SPA Optimizer'!J27 -> 5 | G26: ='SPA Optimizer'!O27 -> -0.23 | H26: ='SPA Optimizer'!AA27 -> 0.60162602 | I26: ='SPA Optimizer'!Z27 -> 516.6 | J26: ='SPA Optimizer'!K27 -> 1200 | K26: ='SPA Optimizer'!E27 -> 600 | L26: =IFERROR('SPA Optimizer'!K27-'SPA Optimizer'!E27,0) -> 600 | M26: =IFERROR(MAX(0,'SPA Optimizer'!K27-'SPA Optimizer'!E27)*'SPA Optimizer'!C27*(1-'SPA Optimizer'!AA27),0) -> 1470
A27: ='SPA Optimizer'!A28 -> 8980067942
A28: ='SPA Optimizer'!A29 -> 8980252486 | B28: ='SPA Optimizer'!B29 -> COOLER ASM; EGR | C28: ='SPA Optimizer'!C29 -> 121.61 | D28: ='SPA Optimizer'!D29 -> 222.62 | E28: ='SPA Optimizer'!I29 -> 0.45373282 | F28: ='SPA Optimizer'!J29 -> 145 | G28: ='SPA Optimizer'!O29 -> 0.16131034 | H28: ='SPA Optimizer'!AA29 -> 0.40985322 | I28: ='SPA Optimizer'!Z29 -> 1702.54 | J28: ='SPA Optimizer'!K29 -> 200 | K28: ='SPA Optimizer'!E29 -> 145 | L28: =IFERROR('SPA Optimizer'!K29-'SPA Optimizer'!E29,0) -> 55 | M28: =IFERROR(MAX(0,'SPA Optimizer'!K29-'SPA Optimizer'!E29)*'SPA Optimizer'!C29*(1-'SPA Optimizer'!AA29),0) -> 3947.2263
A29: ='SPA Optimizer'!A30 -> 8980253080 | B29: ='SPA Optimizer'!B30 -> CYLINDER ASM; CLUTCH MASTER | C29: ='SPA Optimizer'!C30 -> 19.05 | D29: ='SPA Optimizer'!D30 -> 32.26 | E29: ='SPA Optimizer'!I30 -> 0.40948543 | F29: ='SPA Optimizer'!J30 -> 25 | G29: ='SPA Optimizer'!O30 -> 0.238 | H29: ='SPA Optimizer'!AA30 -> 0 | I29: ='SPA Optimizer'!Z30 -> 66.675 | J29: ='SPA Optimizer'!K30 -> 50 | K29: ='SPA Optimizer'!E30 -> 10 | L29: =IFERROR('SPA Optimizer'!K30-'SPA Optimizer'!E30,0) -> 40 | M29: =IFERROR(MAX(0,'SPA Optimizer'!K30-'SPA Optimizer'!E30)*'SPA Optimizer'!C30*(1-'SPA Optimizer'!AA30),0) -> 762
A30: ='SPA Optimizer'!A31 -> 8980435960 | B30: ='SPA Optimizer'!B31 -> CHAMBER; POWER | C30: ='SPA Optimizer'!C31 -> 20.19 | D30: ='SPA Optimizer'!D31 -> 36.96 | E30: ='SPA Optimizer'!I31 -> 0.45373377 | F30: ='SPA Optimizer'!J31 -> 26 | G30: ='SPA Optimizer'!O31 -> 0.22346154 | H30: ='SPA Optimizer'!AA31 -> 0.41825161 | I30: ='SPA Optimizer'!Z31 -> 141.33 | J30: ='SPA Optimizer'!K31 -> 100 | K30: ='SPA Optimizer'!E31 -> 85 | L30: =IFERROR('SPA Optimizer'!K31-'SPA Optimizer'!E31,0) -> 15 | M30: =IFERROR(MAX(0,'SPA Optimizer'!K31-'SPA Optimizer'!E31)*'SPA Optimizer'!C31*(1-'SPA Optimizer'!AA31),0) -> 176.1825
A31: ='SPA Optimizer'!A32 -> 8980896771 | B31: ='SPA Optimizer'!B32 -> CYLINDER; SLAVE,CLU | C31: ='SPA Optimizer'!C32 -> 14.92 | D31: ='SPA Optimizer'!D32 -> 25.27 | E31: ='SPA Optimizer'!I32 -> 0.40957657 | F31: ='SPA Optimizer'!J32 -> 20 | G31: ='SPA Optimizer'!O32 -> 0.254 | H31: ='SPA Optimizer'!AA32 -> 0.29540885 | I31: ='SPA Optimizer'!Z32 -> 125.328 | J31: ='SPA Optimizer'!K32 -> 120 | K31: ='SPA Optimizer'!E32 -> 110 | L31: =IFERROR('SPA Optimizer'!K32-'SPA Optimizer'!E32,0) -> 10 | M31: =IFERROR(MAX(0,'SPA Optimizer'!K32-'SPA Optimizer'!E32)*'SPA Optimizer'!C32*(1-'SPA Optimizer'!AA32),0) -> 105.125
A32: ='SPA Optimizer'!A33 -> 8980982575 | B32: ='SPA Optimizer'!B33 -> VALVE; EGR | C32: ='SPA Optimizer'!C33 -> 40.42 | D32: ='SPA Optimizer'!D33 -> 73.99 | E32: ='SPA Optimizer'!I33 -> 0.45370996 | F32: ='SPA Optimizer'!J33 -> 68 | G32: ='SPA Optimizer'!O33 -> 0.40558824 | H32: ='SPA Optimizer'!AA33 -> 0.065141019 | I32: ='SPA Optimizer'!Z33 -> 565.88 | J32: ='SPA Optimizer'!K33 -> 200 | K32: ='SPA Optimizer'!E33 -> 180 | L32: =IFERROR('SPA Optimizer'!K33-'SPA Optimizer'!E33,0) -> 20 | M32: =IFERROR(MAX(0,'SPA Optimizer'!K33-'SPA Optimizer'!E33)*'SPA Optimizer'!C33*(1-'SPA Optimizer'!AA33),0) -> 755.74
A33: ='SPA Optimizer'!A34 -> 8981065790 | B33: ='SPA Optimizer'!B34 -> ELEMENT KIT; PCV | C33: ='SPA Optimizer'!C34 -> 4.23 | D33: ='SPA Optimizer'!D34 -> 7.74 | E33: ='SPA Optimizer'!I34 -> 0.45348837 | F33: ='SPA Optimizer'!J34 -> 4.9 | G33: ='SPA Optimizer'!O34 -> 0.13673469 | H33: ='SPA Optimizer'!AA34 -> 1.1884161 | I33: ='SPA Optimizer'!Z34 -> 769.86 | J33: ='SPA Optimizer'!K34 -> 2600 | K33: ='SPA Optimizer'!E34 -> 4220 | L33: =IFERROR('SPA Optimizer'!K34-'SPA Optimizer'!E34,0) -> -1620 | M33: =IFERROR(MAX(0,'SPA Optimizer'!K34-'SPA Optimizer'!E34)*'SPA Optimizer'!C34*(1-'SPA Optimizer'!AA34),0) -> 0
A34: ='SPA Optimizer'!A35 -> 8981454841 | B34: ='SPA Optimizer'!B35 -> OVERHAUL KIT; SUPPLY PUMP | C34: ='SPA Optimizer'!C35 -> 44.34 | D34: ='SPA Optimizer'!D35 -> 81.17 | E34: ='SPA Optimizer'!I35 -> 0.45373907 | F34: ='SPA Optimizer'!J35 -> 70 | G34: ='SPA Optimizer'!O35 -> 0.36657143 | H34: ='SPA Optimizer'!AA35 -> 0 | I34: ='SPA Optimizer'!Z35 -> 124.152 | J34: ='SPA Optimizer'!K35 -> 40 | K34: ='SPA Optimizer'!E35 -> 4 | L34: =IFERROR('SPA Optimizer'!K35-'SPA Optimizer'!E35,0) -> 36 | M34: =IFERROR(MAX(0,'SPA Optimizer'!K35-'SPA Optimizer'!E35)*'SPA Optimizer'!C35*(1-'SPA Optimizer'!AA35),0) -> 1596.24
A35: ='SPA Optimizer'!A36 -> 8981455011 | B35: ='SPA Optimizer'!B36 -> OVERHAUL KIT; SUPPLY PUMP | C35: ='SPA Optimizer'!C36 -> 27.78 | D35: ='SPA Optimizer'!D36 -> 50.86 | E35: ='SPA Optimizer'!I36 -> 0.45379473 | F35: ='SPA Optimizer'!J36 -> 40 | G35: ='SPA Optimizer'!O36 -> 0.3055 | H35: ='SPA Optimizer'!AA36 -> 0.25692654 | I35: ='SPA Optimizer'!Z36 -> 602.826 | J35: ='SPA Optimizer'!K36 -> 310 | K35: ='SPA Optimizer'!E36 -> 260 | L35: =IFERROR('SPA Optimizer'!K36-'SPA Optimizer'!E36,0) -> 50 | M35: =IFERROR(MAX(0,'SPA Optimizer'!K36-'SPA Optimizer'!E36)*'SPA Optimizer'!C36*(1-'SPA Optimizer'!AA36),0) -> 1032.129
A36: ='SPA Optimizer'!A37 -> 8982127181 | B36: ='SPA Optimizer'!B37 -> COOLER ASM; EGR | C36: ='SPA Optimizer'!C37 -> 121.61 | D36: ='SPA Optimizer'!D37 -> 222.62 | E36: ='SPA Optimizer'!I37 -> 0.45373282 | F36: ='SPA Optimizer'!J37 -> 145 | G36: ='SPA Optimizer'!O37 -> 0.16131034 | H36: ='SPA Optimizer'!AA37 -> 0.036080503 | I36: ='SPA Optimizer'!Z37 -> 1702.54 | J36: ='SPA Optimizer'!K37 -> 200 | K36: ='SPA Optimizer'!E37 -> 55 | L36: =IFERROR('SPA Optimizer'!K37-'SPA Optimizer'!E37,0) -> 145 | M36: =IFERROR(MAX(0,'SPA Optimizer'!K37-'SPA Optimizer'!E37)*'SPA Optimizer'!C37*(1-'SPA Optimizer'!AA37),0) -> 16997.226
A37: ='SPA Optimizer'!A38 -> 8982236150 | B37: ='SPA Optimizer'!B38 -> LAMP ASM; RR COMB | C37: ='SPA Optimizer'!C38 -> 19.51 | D37: ='SPA Optimizer'!D38 -> 33.03 | E37: ='SPA Optimizer'!I38 -> 0.40932486 | F37: ='SPA Optimizer'!J38 -> 25 | G37: ='SPA Optimizer'!O38 -> 0.2196 | H37: ='SPA Optimizer'!AA38 -> 0.60057779 | I37: ='SPA Optimizer'!Z38 -> 150.227 | J37: ='SPA Optimizer'!K38 -> 110 | K37: ='SPA Optimizer'!E38 -> 140 | L37: =IFERROR('SPA Optimizer'!K38-'SPA Optimizer'!E38,0) -> -30 | M37: =IFERROR(MAX(0,'SPA Optimizer'!K38-'SPA Optimizer'!E38)*'SPA Optimizer'!C38*(1-'SPA Optimizer'!AA38),0) -> 0
A38: ='SPA Optimizer'!A39 -> 8982236160 | B38: ='SPA Optimizer'!B39 -> LAMP ASM; RR COMB | C38: ='SPA Optimizer'!C39 -> 19.51 | D38: ='SPA Optimizer'!D39 -> 33.03 | E38: ='SPA Optimizer'!I39 -> 0.40932486 | F38: ='SPA Optimizer'!J39 -> 25 | G38: ='SPA Optimizer'!O39 -> 0.2196 | H38: ='SPA Optimizer'!AA39 -> 0.42544336 | I38: ='SPA Optimizer'!Z39 -> 136.57 | J38: ='SPA Optimizer'!K39 -> 100 | K38: ='SPA Optimizer'!E39 -> 102 | L38: =IFERROR('SPA Optimizer'!K39-'SPA Optimizer'!E39,0) -> -2 | M38: =IFERROR(MAX(0,'SPA Optimizer'!K39-'SPA Optimizer'!E39)*'SPA Optimizer'!C39*(1-'SPA Optimizer'!AA39),0) -> 0
A39: ='SPA Optimizer'!A40 -> 8982263230 | B39: ='SPA Optimizer'!B40 -> REPAIR KIT; AIR DRYER | C39: ='SPA Optimizer'!C40 -> 51.54 | D39: ='SPA Optimizer'!D40 -> 87.29 | E39: ='SPA Optimizer'!I40 -> 0.40955436 | F39: ='SPA Optimizer'!J40 -> 78 | G39: ='SPA Optimizer'!O40 -> 0.33923077 | H39: ='SPA Optimizer'!AA40 -> 0 | I39: ='SPA Optimizer'!Z40 -> 1190.574 | J39: ='SPA Optimizer'!K40 -> 330 | K39: ='SPA Optimizer'!E40 -> 115 | L39: =IFERROR('SPA Optimizer'!K40-'SPA Optimizer'!E40,0) -> 215 | M39: =IFERROR(MAX(0,'SPA Optimizer'!K40-'SPA Optimizer'!E40)*'SPA Optimizer'!C40*(1-'SPA Optimizer'!AA40),0) -> 11081.1
... A57: ='SPA Optimizer'!A58 -> 8983528481 | B57: ='SPA Optimizer'!B58 -> SENSOR; NOX | C57: ='SPA Optimizer'!C58 -> 121.42 | D57: ='SPA Optimizer'!D58 -> 222.27 | E57: ='SPA Optimizer'!I58 -> 0.45372745 | F57: ='SPA Optimizer'!J58 -> 205 | G57: ='SPA Optimizer'!O58 -> 0.40770732 | H57: ='SPA Optimizer'!AA58 -> 0.47446879 | I57: ='SPA Optimizer'!Z58 -> 3824.73 | J57: ='SPA Optimizer'!K58 -> 450 | K57: ='SPA Optimizer'!E58 -> 630 | L57: =IFERROR('SPA Optimizer'!K58-'SPA Optimizer'!E58,0) -> -180 | M57: =IFERROR(MAX(0,'SPA Optimizer'!K58-'SPA Optimizer'!E58)*'SPA Optimizer'!C58*(1-'SPA Optimizer'!AA58),0) -> 0
A58: TOTAL | B58: 53 lines | I58: =SUM(I5:I57) -> 36121.838 | J58: =SUM(J5:J57) -> 17650 | K58: =SUM(K5:K57) -> 17015 | L58: =SUM(L5:L57) -> 635 | M58: =SUM(M5:M57) -> 112981.7
A60: RATIONALE FOR IML / IMIT PURCHASE SUPPORT
A61: Strategic context: | B61: The distributor is a key ISZE market by genuine parts turnover. The distributor market has a confirmed UIO of [X] Isuzu trucks ([Fleet Register], [Date]). Genuine parts capture rate on critical wear lines is estimated below 20% — the remainder goes to IAM competitors. This SPA is a direct counter-measure to prevent further volume erosion.
A62: Why IML/IMIT support is justified: | B62: IAM competitors systematically undercut Genuine Isuzu on price. Without SPA pricing relief, the distributor will continue routing to IAM for the lines listed above — meaning IML/IMIT loses the downstream volume permanently, not just the short-term margin. Every unit the distributor buys from IAM is a unit IML/IMIT does not ship.
A63: Volume argument: | B63: The committed SPA volumes represent a net uplift over L12 actuals (column L vs column K). At the requested IML cut %, the incremental volume more than compensates IML/IMIT for the unit price sacrifice. Net IML revenue upside per line is shown in column M above.
A64: Retention risk: | B64: Distributor retention risk is rated [X]/5 (see Assumptions tab). Loss of this distributor as a genuine parts customer would put significant annualised genuine parts revenue at risk across all categories — not just the lines in this SPA. The cost of recovering a disengaged distributor is 3–5× the cost of this SPA.
A65: Proposed split: | B65: ISZE proposes IML/IMIT absorbs the Required IML Cut % (column H above) to bring ISZE to profit-neutrality vs L12 baseline. ISZE accepts margin compression on incremental volume. This is a shared investment in market recovery, not a unilateral discount request.
A66: Request: | B66: Approval of the purchase price reductions listed in column H, effective from the SPA start date. ISZE commits to monthly volume compliance tracking and a formal Q3 [Year] review report to IML/IMIT.
A68: ⚠ Column C (Purchase Price) highlighted in red = ISZE cost data — CONFIDENTIAL. Share 'Customer View' tab only with Distributor/distributors.

Sheet SPA Rationale
A1: SPA APPROVAL REQUEST — MANAGEMENT APPROVER
A2: Customer: Distributor · 53 part lines · [Date] · Prepared by: [Name]
A4: A. PROCESS — IN LINE WITH AGREED APPROVAL PROCEDURE
A5: In your earlier instruction, you instructed that all future support be explained to you before any agreement is reached with the distributor. This submission follows that process: 1. ROI study completed in full before approaching Distributor (see Section C below). 2. No commitment made to Distributor pending your approval. 3. IML/IMIT purchase support requirement quantified and presented for your consideration before any bilateral discussion with Japan. We are presenting this to you first. Distributor has not been given a price commitment.
A7: B. THE THREE KEY FIGURES
A8: The figures below answer the three questions you typically require before approving support.
A9: 1. What is the purpose of this support?
A10: Price support on 53 part lines where IAM competitors undercut ISZE genuine prices by 25–40%. Without SPA pricing, Distributor routes to aftermarket and ISZE loses the upstream volume entirely. This SPA is a structured defence — price relief linked to volume commitment, time-bounded at 12 months.
A11: 2. What does ISZE earn from it — GP (€) and GP (%)?
A12: Refer to the SPA Optimizer TOTAL row for live figures. • L12 baseline (no SPA): L12 Profit TOTAL | L12 GM% • SPA scenario (with IML support): SPA Profit w/ Cut TOTAL | SPA GM% • Delta: Δ Profit w/ Cut TOTAL GM% floor compliance per line is detailed in Section D and the Assumptions tab. Without this SPA, if the distributor migrates to IAM, ISZE gross profit on these lines trends toward €0.
A13: 3. What is the rationale behind the support amount?
A14: IML/IMIT purchase price reduction required: average 16.7% on lines needing support Total IML sacrifice (all 53 lines): → SPA Optimizer: IML € Sacrifice TOTAL This is the minimum IML reduction needed to bring ISZE to profit-neutrality vs L12 at SPA prices and committed volumes. It is not a lump subsidy — it is a unit cost adjustment that scales with actual volume shipped.
... A17: Investment / return framing:
A18: IML investment (sacrifice) | C18: GP defended (ISZE, w/ IML) | F18: Return on IML investment | H18: Revenue at risk if SPA declined
A19: → SPA Optimizer: IML € Sacrifice TOTAL | C19: → SPA Optimizer: SPA Profit w/ Cut TOTAL | F19: GP defended ÷ IML sacrifice (calculate from TOTAL row) | H19: [Total at-risk revenue — fill from distributor analysis]
A20: IML/IMIT investment (sacrifice) | C20: ISZE GP defended at SPA + IML | F20: Return ratio: GP per € of IML sacrifice | H20: Total genuine parts revenue at risk if distributor migrates to IAM
A22: D. GROSS MARGIN FLOOR CHECK — ALL LINES
A23: You have indicated that GM% falling to ~10% requires scrutiny. All lines are checked in the Assumptions tab (GM% Floor Check) against a 25% floor (caution) and 10% floor (alarm). Lines below 30% require explanation — update the table below after reviewing the Assumptions tab output.
A24: P/N | B24: Description | C24: L12 GM% | D24: SPA GM% | E24: vs 25% floor | F24: vs 30% floor | G24: Explanation
A25: [P/N — from Assumptions GM check] | B25: [Description] | C25: [L12 GM%] | D25: [SPA GM%] | E25: [vs 25% floor] | F25: [vs 30% floor] | G25: [Explanation — required for any line below 30% GM]
A38: E. THE ASK — TWO DECISIONS REQUIRED
A39: We are requesting two approvals: DECISION 1: Approve the SPA with Distributor at the prices and volumes shown in the SPA Optimizer tab. This commits ISZE to offer SPA pricing conditional on Distributor meeting volume commitments. No cost to ISZE beyond the GM reduction already quantified. DECISION 2: Authorise ISZE to present the required IML/IMIT purchase price reduction (average 16.7%, total IML sacrifice → SPA Optimizer: IML € Sacrifice TOTAL) to IML as part of the normal bilateral commercial discussion. This is not a request to commit IML — it is a request to open the conversation with Japan on our behalf. Both decisions are bounded: 12-month SPA, reviewed at Q3 [Year] against volume targets. If Distributor does not meet 80% of committed volumes at 6 months, ISZE reserves the right to withdraw SPA pricing without penalty.
A41: F. BACKGROUND — COMMERCIAL CONTEXT
A42: Why Distributor?
A43: The distributor is ISZE's largest distributor by genuine parts turnover. Distributor UIO is [X] trucks (confirmed, [Date]). Genuine brake parts capture rate is below 15% — the remainder is lost to IAM competitors at prices 25–40% below current ISZE SP.
A45: Why an SPA and not a general price reduction?
A46: An SPA links price relief to volume commitment. Distributor commits to specific quantities — ISZE only offers the reduced price if volumes are met. A general price reduction gives the same discount with no volume guarantee. The SPA is the fiscally responsible instrument.
A48: Why now?
A49: Distributor is actively reviewing its parts supply chain. A decision delayed risks Distributor formalising IAM supply contracts that will be structurally harder to dislodge. Workshop staff begin recommending alternative brands once genuine is structurally unavailable at competitive price points — recovery then requires active re-engagement campaigns, not just price correction.
A51: What happens if the SPA is declined?
A52: ISZE continues at current SP levels. Distributor continues routing to IAM for these 53 lines. L12 volume on these lines will erode at an estimated 10–15% per year based on current trend. Within 3 years, genuine parts revenue on part lines at Distributor trends toward €0. The total at-risk genuine parts revenue across Distributor (all categories) is €400K–€600K annualised if Distributor formally disengages from genuine parts.
A54: Additional benefits not captured in the GP figures above
... A58: • UIO: [X trucks] (confirmed, [Date] — fill from fleet register) • L12 volumes: SAP actuals • IML cut scenario: [X]% (editable in Assumptions tab) • FX: [X] JPY/EUR (editable in Assumptions tab) • Volume growth assumption: [X]% (editable in Assumptions tab) • Counterfactual: without SPA, L12 volumes erode 10–15%/year based on current IAM trend

Sheet Scenario Planner
A1: SPA SCENARIO PLANNER — OUTCOME MODELLING
A2: Models three SPA scenarios: Partial (lines with ▲ BETTER only) | Full (all 53 lines) | Enhanced (Full + volume growth assumption)
A5: SCENARIO INPUTS
A6: Volume Growth Assumption | B6: 0.05 | C6: % additional volume vs committed qty
A7: IML Cut Applied | B7: =Assumptions!B3 -> PARAMETER | C7: From Assumptions tab
A8: GBP/EUR Rate | B8: =Assumptions!B19 -> 0.1 | C8: For GBP output
A10: SCENARIO COMPARISON
A11: Scenario | B11: Lines Included | C11: SPA Revenue (€) | D11: ISZE Profit vs L12 (€) | E11: IML Sacrifice (€) | F11: Net Revenue to ISZE (€) | G11: Assessment
A12: Partial — ▲ BETTER lines only | B12: 2 of 53 | C12: =SUMIF('SPA Optimizer'!R4:R58,"▲ BETTER",'SPA Optimizer'!L4:L58) -> 120635 | D12: =SUMIF('SPA Optimizer'!R4:R58,"▲ BETTER",'SPA Optimizer'!P4:P58) -> 79028.88 | E12: 0 | F12: =SUMIF('SPA Optimizer'!R4:R58,"▲ BETTER",'SPA Optimizer'!L4:L58) -> 120635 | G12: Low risk — supports Distributor on viable lines only. Limited revenue recovery.
A13: Full — All 53 lines (no IML cut) | B13: 12 of 53 | C13: ='SPA Optimizer'!L60 -> 728880 | D13: ='SPA Optimizer'!Q60 -> -122728.79 | E13: 0 | F13: ='SPA Optimizer'!L60 -> 728880 | G13: Maximum Distributor support. Significant ISZE margin impact without IML help.
A14: Full + IML Support (recommended) | B14: 12 of 53 | C14: ='SPA Optimizer'!L60 -> 728880 | D14: ='SPA Optimizer'!Y60 -> -85594.262 | E14: ='SPA Optimizer'!Z60 -> 37134.528 | F14: ='SPA Optimizer'!L60 -> 728880 | G14: ★ RECOMMENDED — All SPA lines with IML purchase price cut
A15: Enhanced — Full + Volume Growth | B15: 12 of 53 | C15: ='SPA Optimizer'!L60*(1+Assumptions!B21) -> 728880 | D15: ='SPA Optimizer'!Y60*1.1 -> -94153.689 | E15: ='SPA Optimizer'!Z60*1.05 -> 38991.254 | F15: ='SPA Optimizer'!L60*(1+Assumptions!B21) -> 728880 | G15: Upside scenario. Volume growth assumption realised. Strong ROI for all parties.

Sheet MD Approval Request
B1: ISUZU MOTORS EUROPE NV | J1: ISUZU
B2: Requested by | E2: Approved by
B3: Applicant | E3: Manager | H3: Director | K3: Managing Director
B4: =Assumptions!B14 -> [Name] | E4: [Manager Name] | H4: Masumi Hayakawa | K4: Norihiro Yoshimoto
B5: Date: | C5: =TODAY() -> 46141 | E5: Date: | H5: Date: | K5: Date:
B7: Promotional Parts Price Change Request
B8: PARTS CAMPAIGN
B10: Customer
B11: Name | C11: =Assumptions!B9 -> Distributor | I11: Sold To Party | J11: [SAP Customer Code]
B12: Country / Market | C12: =Assumptions!B10 -> [Market] | I12: SAP Branch | J12: [SAP Branch Code]
B14: Financial Overview — Current vs SPA Proposal
B15: CURRENT (L12 Baseline) | H15: SPA PROPOSAL (with IML support)
B16: =IFERROR("SPA Ref: "&Assumptions!B11,"") -> SPA Ref: SPA Distributor | H16: =IFERROR("Validity: "&TEXT(Assumptions!B12,"dd-mmm-yyyy")&" to "&TEXT(Assumptions!B13,"dd-mmm-yyyy"),"") -> Validity: 01-May-2026 to 30-Apr-2027
B17: TOTALS
B18: Total Revenue (€) | D18: ='SPA Optimizer'!F60 -> 768615.47 | H18: Total SPA Revenue (€) | J18: ='SPA Optimizer'!L60 -> 728880
B19: Purchase Cost (€) | D19: ='SPA Optimizer'!G60 -> 447499.93 | H19: Purchase Cost (€) | J19: ='SPA Optimizer'!L60-'SPA Optimizer'!X60 -> 493358.72
B20: Gross Margin % | D20: ='SPA Optimizer'!I60 -> 0.41778438 | H20: Gross Margin % | J20: ='SPA Optimizer'!O60 -> 0.27218026
B21: Gross Profit (€) | D21: ='SPA Optimizer'!H60 -> 321115.54 | H21: Gross Profit (€) | J21: ='SPA Optimizer'!X60 -> 235521.28
B23: Validity | C23: From: | D23: =Assumptions!B12 -> 01/05/2026 | F23: To: | G23: =Assumptions!B13 -> 30/04/2027 | J23: Repetition | K23: No
B25: Background & Justification
B26: =IFERROR("Special Pricing Agreement — "&Assumptions!B9&" | Market: "&Assumptions!B10,"[Fill in justification]")&CHAR(10)&CHAR(10)&"This SPA covers "&COUNTA('SPA Optimizer'!A6:A58)&" part lines with a total SPA revenue commitment of "&TEXT('SPA Optimizer'!L60,"#,##0")&" € vs a L12 baseline of "&TEXT('SPA Optimizer'!F60,"#,##0")&" €."&CHAR(10)&"Gross margin moves from "&TEXT('SPA Optimizer'!I60,"0.0%")&" (L12) to "&TEXT('SPA Optimizer'!O60,"0.0%")&" (SPA), with an IML sacrifice of "&TEXT('SPA Optimizer'!Z60,"#,##0")&" €."&CHAR(10)&CHAR(10)&"Objective: defend genuine parts volume against IAM price competition. SPA pricing is conditional on volume commitments. Retention risk score: "&Assumptions!B20&"/5." -> Special Pricing Agreement — Distributor | Market: [Market] This SPA covers 53 part lines with a total SPA revenue commitment of 728880,0 € vs a L12 baseline of 768615,470 €. Gross margin moves from 42% (L12) to 27% (SPA), with an IML sacrifice of 37134,528 €. Objective: defend genuine parts volume against IAM price competition. SPA pricing is conditional on volume commitments. Retention risk score: /5.
L31: (Unit: €)
B32: 【Business Impact】 | D32: L12 Baseline | F32: Budget / Target | H32: After SPA (with IML support) | J32: Δ Impact vs L12
D33: SAP Actuals | F33: [Fill] | H33: SPA Year 1 | J33: SPA vs L12
B34: Revenue (€) | D34: ='SPA Optimizer'!F60 -> 768615.47 | F34: [Target] | H34: ='SPA Optimizer'!L60 -> 728880 | J34: =H34-D34 -> -39735.47
B35: Purchase Cost (€) | D35: ='SPA Optimizer'!G60 -> 447499.93 | F35: [Target] | H35: =D34-H36 -> 533094.19 | J35: =H35-D35 -> 85594.263
B36: Gross Profit (€) | D36: ='SPA Optimizer'!H60 -> 321115.54 | F36: [Target] | H36: ='SPA Optimizer'!X60 -> 235521.28 | J36: =H36-D36 -> -85594.263
B37: Gross Margin % | D37: ='SPA Optimizer'!I60 -> 0.41778438 | F37: [Target] | H37: ='SPA Optimizer'!O60 -> 0.27218026 | J37: ='SPA Optimizer'!O60-'SPA Optimizer'!I60 -> -0.14560412
J39: 1 EUR = | L39: Not applicable — EUR
B41: Comments from Approver, if any
